Workbook

Sheet Lançamentos
A1: Data | B1: Descrição Extrato | C1: Categoria | D1: Tipo | E1: Grupo DRE | F1: Valor | G1: Banco | H1: Mês
A2: 01/06/2026 | B2: PIX CREDITO DE: POLLYANA ROCHA DA SILVA | C2: Vendas de Produtos | D2: =IF(C2="","",VLOOKUP(C2,Categorias!$A$2:$C$54,2,FALSE)) -> Entrada | E2: =IF(C2="","",VLOOKUP(C2,Categorias!$A$2:$C$54,3,FALSE)) -> Receita Bruta | F2: 16.99 | G2: Cresol | H2: =IF(A2="","",DATE(YEAR(A2),MONTH(A2),1)) -> 46174
A3: 01/06/2026 | B3: PIX CREDITO DE: LUCINEIA COSTA SARAIVA DE AM | C3: Vendas de Produtos | D3: =IF(C3="","",VLOOKUP(C3,Categorias!$A$2:$C$54,2,FALSE)) -> Entrada | E3: =IF(C3="","",VLOOKUP(C3,Categorias!$A$2:$C$54,3,FALSE)) -> Receita Bruta | F3: 25.98 | G3: Cresol | H3: =IF(A3="","",DATE(YEAR(A3),MONTH(A3),1)) -> 46174
A4: 01/06/2026 | B4: TED CRÉDITO 082 0000 07679404000100 BANCO | C4: Vendas de Produtos | D4: =IF(C4="","",VLOOKUP(C4,Categorias!$A$2:$C$54,2,FALSE)) -> Entrada | E4: =IF(C4="","",VLOOKUP(C4,Categorias!$A$2:$C$54,3,FALSE)) -> Receita Bruta | F4: 19.39 | G4: Cresol | H4: =IF(A4="","",DATE(YEAR(A4),MONTH(A4),1)) -> 46174
A5: 01/06/2026 | B5: PIX CREDITO DE: ANTONIO DONIZETI BIN - 31/05 | C5: Vendas de Produtos | D5: =IF(C5="","",VLOOKUP(C5,Categorias!$A$2:$C$54,2,FALSE)) -> Entrada | E5: =IF(C5="","",VLOOKUP(C5,Categorias!$A$2:$C$54,3,FALSE)) -> Receita Bruta | F5: 13.99 | G5: Cresol | H5: =IF(A5="","",DATE(YEAR(A5),MONTH(A5),1)) -> 46174
A6: 01/06/2026 | B6: PIX DEBITO INTERCOOPERATIVO PARA: CONDOMINIO RESIDENCIAL SPA | C6: Aluguel | D6: =IF(C6="","",VLOOKUP(C6,Categorias!$A$2:$C$54,2,FALSE)) -> Saída | E6: =IF(C6="","",VLOOKUP(C6,Categorias!$A$2:$C$54,3,FALSE)) -> Despesas Operacionais | F6: -1532.31 | G6: Cresol | H6: =IF(A6="","",DATE(YEAR(A6),MONTH(A6),1)) -> 46174
A7: 01/06/2026 | B7: PAGAMENTO DE TÍTULOS - IB SPAL IND BRAS DE BEBIDAS SA | C7: Pagamento de Fornecedores | D7: =IF(C7="","",VLOOKUP(C7,Categorias!$A$2:$C$54,2,FALSE)) -> Saída | E7: =IF(C7="","",VLOOKUP(C7,Categorias!$A$2:$C$54,3,FALSE)) -> CMV | F7: -709.94 | G7: Cresol | H7: =IF(A7="","",DATE(YEAR(A7),MONTH(A7),1)) -> 46174
A8: 01/06/2026 | B8: PAGAMENTO DE TÍTULOS - IB PENNACCHI CIA LTDA | C8: Pagamento de Fornecedores | D8: =IF(C8="","",VLOOKUP(C8,Categorias!$A$2:$C$54,2,FALSE)) -> Saída | E8: =IF(C8="","",VLOOKUP(C8,Categorias!$A$2:$C$54,3,FALSE)) -> CMV | F8: -1048.92 | G8: Cresol | H8: =IF(A8="","",DATE(YEAR(A8),MONTH(A8),1)) -> 46174
A9: 01/06/2026 | B9: PIX DEBITO PARA: WYLLAMY SANTOS DA SILVA | C9: Pagamento de Fornecedores | D9: =IF(C9="","",VLOOKUP(C9,Categorias!$A$2:$C$54,2,FALSE)) -> Saída | E9: =IF(C9="","",VLOOKUP(C9,Categorias!$A$2:$C$54,3,FALSE)) -> CMV | F9: -500 | G9: Cresol | H9: =IF(A9="","",DATE(YEAR(A9),MONTH(A9),1)) -> 46174
A10: 01/06/2026 | B10: CRÉDITO ANTECIPAÇÃO DE RECEBÍVEIS 10260001062611934-STONE -ELO | C10: Vendas de Produtos | D10: =IF(C10="","",VLOOKUP(C10,Categorias!$A$2:$C$54,2,FALSE)) -> Entrada | E10: =IF(C10="","",VLOOKUP(C10,Categorias!$A$2:$C$54,3,FALSE)) -> Receita Bruta | F10: 204.67 | G10: Cresol | H10: =IF(A10="","",DATE(YEAR(A10),MONTH(A10),1)) -> 46174
A11: 01/06/2026 | B11: CRÉDITO ANTECIPAÇÃO DE RECEBÍVEIS 10260001062611805-STONE -VISA | C11: Vendas de Produtos | D11: =IF(C11="","",VLOOKUP(C11,Categorias!$A$2:$C$54,2,FALSE)) -> Entrada | E11: =IF(C11="","",VLOOKUP(C11,Categorias!$A$2:$C$54,3,FALSE)) -> Receita Bruta | F11: 659.74 | G11: Cresol | H11: =IF(A11="","",DATE(YEAR(A11),MONTH(A11),1)) -> 46174
A12: 01/06/2026 | B12: CRÉDITO ANTECIPAÇÃO DE RECEBÍVEIS 10260001062611777-STONE -MASTERC | C12: Vendas de Produtos | D12: =IF(C12="","",VLOOKUP(C12,Categorias!$A$2:$C$54,2,FALSE)) -> Entrada | E12: =IF(C12="","",VLOOKUP(C12,Categorias!$A$2:$C$54,3,FALSE)) -> Receita Bruta | F12: 1472.8 | G12: Cresol | H12: =IF(A12="","",DATE(YEAR(A12),MONTH(A12),1)) -> 46174
A13: 01/06/2026 | B13: CRÉDITO ANTECIPAÇÃO DE RECEBÍVEIS 10260001062611738-STONE -AMERICA | C13: Vendas de Produtos | D13: =IF(C13="","",VLOOKUP(C13,Categorias!$A$2:$C$54,2,FALSE)) -> Entrada | E13: =IF(C13="","",VLOOKUP(C13,Categorias!$A$2:$C$54,3,FALSE)) -> Receita Bruta | F13: 57.67 | G13: Cresol | H13: =IF(A13="","",DATE(YEAR(A13),MONTH(A13),1)) -> 46174
... A349: 08/06/2026 | B349: RAMON LUIS BARZON DUARTE | 06835367962 | Pix | Maquininha | C349: Vendas de Produtos | D349: =IF(C349="","",VLOOKUP(C349,Categorias!$A$2:$C$54,2,FALSE)) -> Entrada | E349: =IF(C349="","",VLOOKUP(C349,Categorias!$A$2:$C$54,3,FALSE)) -> Receita Bruta | F349: 21.56 | G349: Stone | H349: =IF(A349="","",DATE(YEAR(A349),MONTH(A349),1)) -> 46174

Sheet Categorias
A1: Categoria | B1: Tipo | C1: Grupo DRE | E1: Banco | F1: Saldo Inicial
A2: Vendas de Produtos | B2: Entrada | C2: Receita Bruta | E2: Banco do Brasil | F2: 0
A3: Vendas de Serviços | B3: Entrada | C3: Receita Bruta | E3: Itaú | F3: 0
A4: Outras Receitas | B4: Entrada | C4: Outras Receitas | E4: Caixa | F4: 0
A5: Impostos sobre Vendas | B5: Saída | C5: Deduções | E5: Cresol
A6: Devoluções | B6: Saída | C6: Deduções | E6: Stone
A7: Custo de Mercadoria Vendida | B7: Saída | C7: CMV
A8: Custo de Serviços Prestados | B8: Saída | C8: CMV
A9: Salários e Encargos | B9: Saída | C9: Despesas Operacionais
A10: Aluguel | B10: Saída | C10: Despesas Operacionais
A11: Água, Luz e Internet | B11: Saída | C11: Despesas Operacionais
A12: Material de Escritório | B12: Saída | C12: Despesas Operacionais
A13: Marketing e Publicidade | B13: Saída | C13: Despesas Operacionais
A14: Manutenção | B14: Saída | C14: Despesas Operacionais
A15: Transporte e Viagens | B15: Saída | C15: Despesas Operacionais
A16: Serviços de Terceiros | B16: Saída | C16: Despesas Operacionais
A17: Juros e Tarifas Bancárias | B17: Saída | C17: Despesas Financeiras
A18: Empréstimos e Financiamentos | B18: Saída | C18: Despesas Financeiras
... A54: PIS/COFINS | B54: Saída | C54: Deduções

Sheet DRE
A1: DRE - Demonstração do Resultado
A3: Ano: | B3: =YEAR(TODAY()) -> 2026
A5: Grupo | B5: =DATE($B$3,1,1) -> 46023 | C5: =EDATE(B5,1) -> 46054 | D5: =EDATE(B5,2) -> 46082 | E5: =EDATE(B5,3) -> 46113 | F5: =EDATE(B5,4) -> 46143 | G5: =EDATE(B5,5) -> 46174 | H5: =EDATE(B5,6) -> 46204 | I5: =EDATE(B5,7) -> 46235 | J5: =EDATE(B5,8) -> 46266 | K5: =EDATE(B5,9) -> 46296 | L5: =EDATE(B5,10) -> 46327 | M5: =EDATE(B5,11) -> 46357 | N5: Total Ano
A6: (+) Receita Bruta | B6: =SUMIFS(Lançamentos!$F:$F,Lançamentos!$E:$E,"Receita Bruta",Lançamentos!$H:$H,B$5) -> 0 | C6: =SUMIFS(Lançamentos!$F:$F,Lançamentos!$E:$E,"Receita Bruta",Lançamentos!$H:$H,C$5) -> 0 | D6: =SUMIFS(Lançamentos!$F:$F,Lançamentos!$E:$E,"Receita Bruta",Lançamentos!$H:$H,D$5) -> 0 | E6: =SUMIFS(Lançamentos!$F:$F,Lançamentos!$E:$E,"Receita Bruta",Lançamentos!$H:$H,E$5) -> 0 | F6: =SUMIFS(Lançamentos!$F:$F,Lançamentos!$E:$E,"Receita Bruta",Lançamentos!$H:$H,F$5) -> 0 | G6: =SUMIFS(Lançamentos!$F:$F,Lançamentos!$E:$E,"Receita Bruta",Lançamentos!$H:$H,G$5) -> 20878.13 | H6: =SUMIFS(Lançamentos!$F:$F,Lançamentos!$E:$E,"Receita Bruta",Lançamentos!$H:$H,H$5) -> 0 | I6: =SUMIFS(Lançamentos!$F:$F,Lançamentos!$E:$E,"Receita Bruta",Lançamentos!$H:$H,I$5) -> 0 | ... M6: =SUMIFS(Lançamentos!$F:$F,Lançamentos!$E:$E,"Receita Bruta",Lançamentos!$H:$H,M$5) -> 0 | N6: =SUM(B6:M6) -> 20878.13
A7: (-) Deduções | B7: =SUMIFS(Lançamentos!$F:$F,Lançamentos!$E:$E,"Deduções",Lançamentos!$H:$H,B$5) -> 0 | C7: =SUMIFS(Lançamentos!$F:$F,Lançamentos!$E:$E,"Deduções",Lançamentos!$H:$H,C$5) -> 0 | D7: =SUMIFS(Lançamentos!$F:$F,Lançamentos!$E:$E,"Deduções",Lançamentos!$H:$H,D$5) -> 0 | E7: =SUMIFS(Lançamentos!$F:$F,Lançamentos!$E:$E,"Deduções",Lançamentos!$H:$H,E$5) -> 0 | F7: =SUMIFS(Lançamentos!$F:$F,Lançamentos!$E:$E,"Deduções",Lançamentos!$H:$H,F$5) -> 0 | G7: =SUMIFS(Lançamentos!$F:$F,Lançamentos!$E:$E,"Deduções",Lançamentos!$H:$H,G$5) -> 0 | H7: =SUMIFS(Lançamentos!$F:$F,Lançamentos!$E:$E,"Deduções",Lançamentos!$H:$H,H$5) -> 0 | I7: =SUMIFS(Lançamentos!$F:$F,Lançamentos!$E:$E,"Deduções",Lançamentos!$H:$H,I$5) -> 0 | ... M7: =SUMIFS(Lançamentos!$F:$F,Lançamentos!$E:$E,"Deduções",Lançamentos!$H:$H,M$5) -> 0 | N7: =SUM(B7:M7) -> 0
A8: (=) Receita Líquida | B8: =B6+B7 -> 0 | C8: =C6+C7 -> 0 | D8: =D6+D7 -> 0 | E8: =E6+E7 -> 0 | F8: =F6+F7 -> 0 | G8: =G6+G7 -> 20878.13 | H8: =H6+H7 -> 0 | I8: =I6+I7 -> 0 | ... M8: =M6+M7 -> 0 | N8: =SUM(B8:M8) -> 20878.13
A9: (-) CMV | B9: =SUMIFS(Lançamentos!$F:$F,Lançamentos!$E:$E,"CMV",Lançamentos!$H:$H,B$5) -> 0 | C9: =SUMIFS(Lançamentos!$F:$F,Lançamentos!$E:$E,"CMV",Lançamentos!$H:$H,C$5) -> 0 | D9: =SUMIFS(Lançamentos!$F:$F,Lançamentos!$E:$E,"CMV",Lançamentos!$H:$H,D$5) -> 0 | E9: =SUMIFS(Lançamentos!$F:$F,Lançamentos!$E:$E,"CMV",Lançamentos!$H:$H,E$5) -> 0 | F9: =SUMIFS(Lançamentos!$F:$F,Lançamentos!$E:$E,"CMV",Lançamentos!$H:$H,F$5) -> 0 | G9: =SUMIFS(Lançamentos!$F:$F,Lançamentos!$E:$E,"CMV",Lançamentos!$H:$H,G$5) -> -14865.69 | H9: =SUMIFS(Lançamentos!$F:$F,Lançamentos!$E:$E,"CMV",Lançamentos!$H:$H,H$5) -> 0 | I9: =SUMIFS(Lançamentos!$F:$F,Lançamentos!$E:$E,"CMV",Lançamentos!$H:$H,I$5) -> 0 | ... M9: =SUMIFS(Lançamentos!$F:$F,Lançamentos!$E:$E,"CMV",Lançamentos!$H:$H,M$5) -> 0 | N9: =SUM(B9:M9) -> -14865.69
A10: (=) Lucro Bruto | B10: =B8+B9 -> 0 | C10: =C8+C9 -> 0 | D10: =D8+D9 -> 0 | E10: =E8+E9 -> 0 | F10: =F8+F9 -> 0 | G10: =G8+G9 -> 6012.44 | H10: =H8+H9 -> 0 | I10: =I8+I9 -> 0 | ... M10: =M8+M9 -> 0 | N10: =SUM(B10:M10) -> 6012.44
A11: (-) Despesas Operacionais | B11: =SUMIFS(Lançamentos!$F:$F,Lançamentos!$E:$E,"Despesas Operacionais",Lançamentos!$H:$H,B$5) -> 0 | C11: =SUMIFS(Lançamentos!$F:$F,Lançamentos!$E:$E,"Despesas Operacionais",Lançamentos!$H:$H,C$5) -> 0 | D11: =SUMIFS(Lançamentos!$F:$F,Lançamentos!$E:$E,"Despesas Operacionais",Lançamentos!$H:$H,D$5) -> 0 | E11: =SUMIFS(Lançamentos!$F:$F,Lançamentos!$E:$E,"Despesas Operacionais",Lançamentos!$H:$H,E$5) -> 0 | F11: =SUMIFS(Lançamentos!$F:$F,Lançamentos!$E:$E,"Despesas Operacionais",Lançamentos!$H:$H,F$5) -> 0 | G11: =SUMIFS(Lançamentos!$F:$F,Lançamentos!$E:$E,"Despesas Operacionais",Lançamentos!$H:$H,G$5) -> -2831.08 | H11: =SUMIFS(Lançamentos!$F:$F,Lançamentos!$E:$E,"Despesas Operacionais",Lançamentos!$H:$H,H$5) -> 0 | I11: =SUMIFS(Lançamentos!$F:$F,Lançamentos!$E:$E,"Despesas Operacionais",Lançamentos!$H:$H,I$5) -> 0 | ... M11: =SUMIFS(Lançamentos!$F:$F,Lançamentos!$E:$E,"Despesas Operacionais",Lançamentos!$H:$H,M$5) -> 0 | N11: =SUM(B11:M11) -> -2831.08
A12: (=) EBITDA | B12: =B10+B11 -> 0 | C12: =C10+C11 -> 0 | D12: =D10+D11 -> 0 | E12: =E10+E11 -> 0 | F12: =F10+F11 -> 0 | G12: =G10+G11 -> 3181.36 | H12: =H10+H11 -> 0 | I12: =I10+I11 -> 0 | ... M12: =M10+M11 -> 0 | N12: =SUM(B12:M12) -> 3181.36
A13: (+) Receitas Financeiras | B13: =SUMIFS(Lançamentos!$F:$F,Lançamentos!$E:$E,"Receitas Financeiras",Lançamentos!$H:$H,B$5) -> 0 | C13: =SUMIFS(Lançamentos!$F:$F,Lançamentos!$E:$E,"Receitas Financeiras",Lançamentos!$H:$H,C$5) -> 0 | D13: =SUMIFS(Lançamentos!$F:$F,Lançamentos!$E:$E,"Receitas Financeiras",Lançamentos!$H:$H,D$5) -> 0 | E13: =SUMIFS(Lançamentos!$F:$F,Lançamentos!$E:$E,"Receitas Financeiras",Lançamentos!$H:$H,E$5) -> 0 | F13: =SUMIFS(Lançamentos!$F:$F,Lançamentos!$E:$E,"Receitas Financeiras",Lançamentos!$H:$H,F$5) -> 0 | G13: =SUMIFS(Lançamentos!$F:$F,Lançamentos!$E:$E,"Receitas Financeiras",Lançamentos!$H:$H,G$5) -> 0 | H13: =SUMIFS(Lançamentos!$F:$F,Lançamentos!$E:$E,"Receitas Financeiras",Lançamentos!$H:$H,H$5) -> 0 | I13: =SUMIFS(Lançamentos!$F:$F,Lançamentos!$E:$E,"Receitas Financeiras",Lançamentos!$H:$H,I$5) -> 0 | ... M13: =SUMIFS(Lançamentos!$F:$F,Lançamentos!$E:$E,"Receitas Financeiras",Lançamentos!$H:$H,M$5) -> 0 | N13: =SUM(B13:M13) -> 0
A14: (-) Despesas Financeiras | B14: =SUMIFS(Lançamentos!$F:$F,Lançamentos!$E:$E,"Despesas Financeiras",Lançamentos!$H:$H,B$5) -> 0 | C14: =SUMIFS(Lançamentos!$F:$F,Lançamentos!$E:$E,"Despesas Financeiras",Lançamentos!$H:$H,C$5) -> 0 | D14: =SUMIFS(Lançamentos!$F:$F,Lançamentos!$E:$E,"Despesas Financeiras",Lançamentos!$H:$H,D$5) -> 0 | E14: =SUMIFS(Lançamentos!$F:$F,Lançamentos!$E:$E,"Despesas Financeiras",Lançamentos!$H:$H,E$5) -> 0 | F14: =SUMIFS(Lançamentos!$F:$F,Lançamentos!$E:$E,"Despesas Financeiras",Lançamentos!$H:$H,F$5) -> 0 | G14: =SUMIFS(Lançamentos!$F:$F,Lançamentos!$E:$E,"Despesas Financeiras",Lançamentos!$H:$H,G$5) -> -14.57 | H14: =SUMIFS(Lançamentos!$F:$F,Lançamentos!$E:$E,"Despesas Financeiras",Lançamentos!$H:$H,H$5) -> 0 | I14: =SUMIFS(Lançamentos!$F:$F,Lançamentos!$E:$E,"Despesas Financeiras",Lançamentos!$H:$H,I$5) -> 0 | ... M14: =SUMIFS(Lançamentos!$F:$F,Lançamentos!$E:$E,"Despesas Financeiras",Lançamentos!$H:$H,M$5) -> 0 | N14: =SUM(B14:M14) -> -14.57
A15: (+) Outras Receitas | B15: =SUMIFS(Lançamentos!$F:$F,Lançamentos!$E:$E,"Outras Receitas",Lançamentos!$H:$H,B$5) -> 0 | C15: =SUMIFS(Lançamentos!$F:$F,Lançamentos!$E:$E,"Outras Receitas",Lançamentos!$H:$H,C$5) -> 0 | D15: =SUMIFS(Lançamentos!$F:$F,Lançamentos!$E:$E,"Outras Receitas",Lançamentos!$H:$H,D$5) -> 0 | E15: =SUMIFS(Lançamentos!$F:$F,Lançamentos!$E:$E,"Outras Receitas",Lançamentos!$H:$H,E$5) -> 0 | F15: =SUMIFS(Lançamentos!$F:$F,Lançamentos!$E:$E,"Outras Receitas",Lançamentos!$H:$H,F$5) -> 0 | G15: =SUMIFS(Lançamentos!$F:$F,Lançamentos!$E:$E,"Outras Receitas",Lançamentos!$H:$H,G$5) -> 0 | H15: =SUMIFS(Lançamentos!$F:$F,Lançamentos!$E:$E,"Outras Receitas",Lançamentos!$H:$H,H$5) -> 0 | I15: =SUMIFS(Lançamentos!$F:$F,Lançamentos!$E:$E,"Outras Receitas",Lançamentos!$H:$H,I$5) -> 0 | ... M15: =SUMIFS(Lançamentos!$F:$F,Lançamentos!$E:$E,"Outras Receitas",Lançamentos!$H:$H,M$5) -> 0 | N15: =SUM(B15:M15) -> 0
A16: (=) Resultado antes dos Impostos | B16: =B12+B13+B14+B15 -> 0 | C16: =C12+C13+C14+C15 -> 0 | D16: =D12+D13+D14+D15 -> 0 | E16: =E12+E13+E14+E15 -> 0 | F16: =F12+F13+F14+F15 -> 0 | G16: =G12+G13+G14+G15 -> 3166.79 | H16: =H12+H13+H14+H15 -> 0 | I16: =I12+I13+I14+I15 -> 0 | ... M16: =M12+M13+M14+M15 -> 0 | N16: =SUM(B16:M16) -> 3166.79
A17: (-) Impostos sobre Lucro | B17: =SUMIFS(Lançamentos!$F:$F,Lançamentos!$E:$E,"Impostos",Lançamentos!$H:$H,B$5) -> 0 | C17: =SUMIFS(Lançamentos!$F:$F,Lançamentos!$E:$E,"Impostos",Lançamentos!$H:$H,C$5) -> 0 | D17: =SUMIFS(Lançamentos!$F:$F,Lançamentos!$E:$E,"Impostos",Lançamentos!$H:$H,D$5) -> 0 | E17: =SUMIFS(Lançamentos!$F:$F,Lançamentos!$E:$E,"Impostos",Lançamentos!$H:$H,E$5) -> 0 | F17: =SUMIFS(Lançamentos!$F:$F,Lançamentos!$E:$E,"Impostos",Lançamentos!$H:$H,F$5) -> 0 | G17: =SUMIFS(Lançamentos!$F:$F,Lançamentos!$E:$E,"Impostos",Lançamentos!$H:$H,G$5) -> 0 | H17: =SUMIFS(Lançamentos!$F:$F,Lançamentos!$E:$E,"Impostos",Lançamentos!$H:$H,H$5) -> 0 | I17: =SUMIFS(Lançamentos!$F:$F,Lançamentos!$E:$E,"Impostos",Lançamentos!$H:$H,I$5) -> 0 | ... M17: =SUMIFS(Lançamentos!$F:$F,Lançamentos!$E:$E,"Impostos",Lançamentos!$H:$H,M$5) -> 0 | N17: =SUM(B17:M17) -> 0
A18: (=) LUCRO LÍQUIDO | B18: =B16+B17 -> 0 | C18: =C16+C17 -> 0 | D18: =D16+D17 -> 0 | E18: =E16+E17 -> 0 | F18: =F16+F17 -> 0 | G18: =G16+G17 -> 3166.79 | H18: =H16+H17 -> 0 | I18: =I16+I17 -> 0 | ... M18: =M16+M17 -> 0 | N18: =SUM(B18:M18) -> 3166.79

Sheet Fluxo de Caixa
A1: Fluxo de Caixa
A3: Ano: | B3: =DRE!B3 -> 2026
A5: Item | B5: =DATE($B$3,1,1) -> 46023 | C5: =EDATE(B5,1) -> 46054 | D5: =EDATE(B5,2) -> 46082 | E5: =EDATE(B5,3) -> 46113 | F5: =EDATE(B5,4) -> 46143 | G5: =EDATE(B5,5) -> 46174 | H5: =EDATE(B5,6) -> 46204 | I5: =EDATE(B5,7) -> 46235 | J5: =EDATE(B5,8) -> 46266 | K5: =EDATE(B5,9) -> 46296 | L5: =EDATE(B5,10) -> 46327 | M5: =EDATE(B5,11) -> 46357 | N5: Total
A6: Saldo Inicial | B6: =SUM(Categorias!F2:F4) -> 0 | C6: =B10 -> 0 | D6: =C10 -> 0 | E6: =D10 -> 0 | F6: =E10 -> 0 | G6: =F10 -> 0 | H6: =G10 -> 3166.79 | I6: =H10 -> 3166.79 | J6: =I10 -> 3166.79 | ... M6: =L10 -> 3166.79
A7: (+) Total de Entradas | B7: =SUMIFS(Lançamentos!$F:$F,Lançamentos!$H:$H,B$5,Lançamentos!$D:$D,"Entrada") -> 0 | C7: =SUMIFS(Lançamentos!$F:$F,Lançamentos!$H:$H,C$5,Lançamentos!$D:$D,"Entrada") -> 0 | D7: =SUMIFS(Lançamentos!$F:$F,Lançamentos!$H:$H,D$5,Lançamentos!$D:$D,"Entrada") -> 0 | E7: =SUMIFS(Lançamentos!$F:$F,Lançamentos!$H:$H,E$5,Lançamentos!$D:$D,"Entrada") -> 0 | F7: =SUMIFS(Lançamentos!$F:$F,Lançamentos!$H:$H,F$5,Lançamentos!$D:$D,"Entrada") -> 0 | G7: =SUMIFS(Lançamentos!$F:$F,Lançamentos!$H:$H,G$5,Lançamentos!$D:$D,"Entrada") -> 20878.13 | H7: =SUMIFS(Lançamentos!$F:$F,Lançamentos!$H:$H,H$5,Lançamentos!$D:$D,"Entrada") -> 0 | I7: =SUMIFS(Lançamentos!$F:$F,Lançamentos!$H:$H,I$5,Lançamentos!$D:$D,"Entrada") -> 0 | ... M7: =SUMIFS(Lançamentos!$F:$F,Lançamentos!$H:$H,M$5,Lançamentos!$D:$D,"Entrada") -> 0 | N7: =SUM(B7:M7) -> 20878.13
A8: (-) Total de Saídas | B8: =SUMIFS(Lançamentos!$F:$F,Lançamentos!$H:$H,B$5,Lançamentos!$D:$D,"Saída") -> 0 | C8: =SUMIFS(Lançamentos!$F:$F,Lançamentos!$H:$H,C$5,Lançamentos!$D:$D,"Saída") -> 0 | D8: =SUMIFS(Lançamentos!$F:$F,Lançamentos!$H:$H,D$5,Lançamentos!$D:$D,"Saída") -> 0 | E8: =SUMIFS(Lançamentos!$F:$F,Lançamentos!$H:$H,E$5,Lançamentos!$D:$D,"Saída") -> 0 | F8: =SUMIFS(Lançamentos!$F:$F,Lançamentos!$H:$H,F$5,Lançamentos!$D:$D,"Saída") -> 0 | G8: =SUMIFS(Lançamentos!$F:$F,Lançamentos!$H:$H,G$5,Lançamentos!$D:$D,"Saída") -> -17711.34 | H8: =SUMIFS(Lançamentos!$F:$F,Lançamentos!$H:$H,H$5,Lançamentos!$D:$D,"Saída") -> 0 | I8: =SUMIFS(Lançamentos!$F:$F,Lançamentos!$H:$H,I$5,Lançamentos!$D:$D,"Saída") -> 0 | ... M8: =SUMIFS(Lançamentos!$F:$F,Lançamentos!$H:$H,M$5,Lançamentos!$D:$D,"Saída") -> 0 | N8: =SUM(B8:M8) -> -17711.34
A9: (=) Fluxo do Mês | B9: =B7+B8 -> 0 | C9: =C7+C8 -> 0 | D9: =D7+D8 -> 0 | E9: =E7+E8 -> 0 | F9: =F7+F8 -> 0 | G9: =G7+G8 -> 3166.79 | H9: =H7+H8 -> 0 | I9: =I7+I8 -> 0 | ... M9: =M7+M8 -> 0 | N9: =SUM(B9:M9) -> 3166.79
A10: (=) Saldo Acumulado | B10: =B6+B9 -> 0 | C10: =C6+C9 -> 0 | D10: =D6+D9 -> 0 | E10: =E6+E9 -> 0 | F10: =F6+F9 -> 0 | G10: =G6+G9 -> 3166.79 | H10: =H6+H9 -> 3166.79 | I10: =I6+I9 -> 3166.79 | ... M10: =M6+M9 -> 3166.79 | N10: =M10 -> 3166.79
A12: Detalhamento por Banco
A13: =Categorias!E2 -> Banco do Brasil | B13: =Categorias!F2+SUMIFS(Lançamentos!$F:$F,Lançamentos!$G:$G,$A13,Lançamentos!$H:$H,B$5) -> 0 | C13: =Categorias!G2+SUMIFS(Lançamentos!$F:$F,Lançamentos!$G:$G,$A13,Lançamentos!$H:$H,C$5) -> 0 | D13: =Categorias!H2+SUMIFS(Lançamentos!$F:$F,Lançamentos!$G:$G,$A13,Lançamentos!$H:$H,D$5) -> 0 | E13: =Categorias!I2+SUMIFS(Lançamentos!$F:$F,Lançamentos!$G:$G,$A13,Lançamentos!$H:$H,E$5) -> 0 | F13: =Categorias!J2+SUMIFS(Lançamentos!$F:$F,Lançamentos!$G:$G,$A13,Lançamentos!$H:$H,F$5) -> 0 | G13: =Categorias!K2+SUMIFS(Lançamentos!$F:$F,Lançamentos!$G:$G,$A13,Lançamentos!$H:$H,G$5) -> 0 | H13: =Categorias!L2+SUMIFS(Lançamentos!$F:$F,Lançamentos!$G:$G,$A13,Lançamentos!$H:$H,H$5) -> 0 | I13: =Categorias!M2+SUMIFS(Lançamentos!$F:$F,Lançamentos!$G:$G,$A13,Lançamentos!$H:$H,I$5) -> 0 | ... M13: =Categorias!Q2+SUMIFS(Lançamentos!$F:$F,Lançamentos!$G:$G,$A13,Lançamentos!$H:$H,M$5) -> 0 | N13: =M13 -> 0
A14: =Categorias!E3 -> Itaú | B14: =Categorias!F3+SUMIFS(Lançamentos!$F:$F,Lançamentos!$G:$G,$A14,Lançamentos!$H:$H,B$5) -> 0 | C14: =Categorias!G3+SUMIFS(Lançamentos!$F:$F,Lançamentos!$G:$G,$A14,Lançamentos!$H:$H,C$5) -> 0 | D14: =Categorias!H3+SUMIFS(Lançamentos!$F:$F,Lançamentos!$G:$G,$A14,Lançamentos!$H:$H,D$5) -> 0 | E14: =Categorias!I3+SUMIFS(Lançamentos!$F:$F,Lançamentos!$G:$G,$A14,Lançamentos!$H:$H,E$5) -> 0 | F14: =Categorias!J3+SUMIFS(Lançamentos!$F:$F,Lançamentos!$G:$G,$A14,Lançamentos!$H:$H,F$5) -> 0 | G14: =Categorias!K3+SUMIFS(Lançamentos!$F:$F,Lançamentos!$G:$G,$A14,Lançamentos!$H:$H,G$5) -> 0 | H14: =Categorias!L3+SUMIFS(Lançamentos!$F:$F,Lançamentos!$G:$G,$A14,Lançamentos!$H:$H,H$5) -> 0 | I14: =Categorias!M3+SUMIFS(Lançamentos!$F:$F,Lançamentos!$G:$G,$A14,Lançamentos!$H:$H,I$5) -> 0 | ... M14: =Categorias!Q3+SUMIFS(Lançamentos!$F:$F,Lançamentos!$G:$G,$A14,Lançamentos!$H:$H,M$5) -> 0 | N14: =M14 -> 0
A15: =Categorias!E4 -> Caixa | B15: =Categorias!F4+SUMIFS(Lançamentos!$F:$F,Lançamentos!$G:$G,$A15,Lançamentos!$H:$H,B$5) -> 0 | C15: =Categorias!G4+SUMIFS(Lançamentos!$F:$F,Lançamentos!$G:$G,$A15,Lançamentos!$H:$H,C$5) -> 0 | D15: =Categorias!H4+SUMIFS(Lançamentos!$F:$F,Lançamentos!$G:$G,$A15,Lançamentos!$H:$H,D$5) -> 0 | E15: =Categorias!I4+SUMIFS(Lançamentos!$F:$F,Lançamentos!$G:$G,$A15,Lançamentos!$H:$H,E$5) -> 0 | F15: =Categorias!J4+SUMIFS(Lançamentos!$F:$F,Lançamentos!$G:$G,$A15,Lançamentos!$H:$H,F$5) -> 0 | G15: =Categorias!K4+SUMIFS(Lançamentos!$F:$F,Lançamentos!$G:$G,$A15,Lançamentos!$H:$H,G$5) -> 0 | H15: =Categorias!L4+SUMIFS(Lançamentos!$F:$F,Lançamentos!$G:$G,$A15,Lançamentos!$H:$H,H$5) -> 0 | I15: =Categorias!M4+SUMIFS(Lançamentos!$F:$F,Lançamentos!$G:$G,$A15,Lançamentos!$H:$H,I$5) -> 0 | ... M15: =Categorias!Q4+SUMIFS(Lançamentos!$F:$F,Lançamentos!$G:$G,$A15,Lançamentos!$H:$H,M$5) -> 0 | N15: =M15 -> 0
A18: FLUXO DE CAIXA DIÁRIO (Mai-Dez)
A19: Data → | B19: =DATE(2026,5,1) -> 46143 | C19: =DATE(2026,5,2) -> 46144 | D19: =DATE(2026,5,3) -> 46145 | E19: =DATE(2026,5,4) -> 46146 | F19: =DATE(2026,5,5) -> 46147 | G19: =DATE(2026,5,6) -> 46148 | H19: =DATE(2026,5,7) -> 46149 | I19: =DATE(2026,5,8) -> 46150 | J19: =DATE(2026,5,9) -> 46151 | K19: =DATE(2026,5,10) -> 46152 | L19: =DATE(2026,5,11) -> 46153 | M19: =DATE(2026,5,12) -> 46154 | N19: =DATE(2026,5,13) -> 46155 | O19: =DATE(2026,5,14) -> 46156 | P19: =DATE(2026,5,15) -> 46157 | Q19: =DATE(2026,5,16) -> 46158 | R19: =DATE(2026,5,17) -> 46159 | S19: =DATE(2026,5,18) -> 46160 | T19: =DATE(2026,5,19) -> 46161 | U19: =DATE(2026,5,20) -> 46162 | V19: =DATE(2026,5,21) -> 46163 | W19: =DATE(2026,5,22) -> 46164 | X19: =DATE(2026,5,23) -> 46165 | Y19: =DATE(2026,5,24) -> 46166 | Z19: =DATE(2026,5,25) -> 46167 | AA19: =DATE(2026,5,26) -> 46168 | AB19: =DATE(2026,5,27) -> 46169 | AC19: =DATE(2026,5,28) -> 46170 | AD19: =DATE(2026,5,29) -> 46171 | AE19: =DATE(2026,5,30) -> 46172 | AF19: =DATE(2026,5,31) -> 46173 | AG19: =DATE(2026,6,1) -> 46174 | AH19: =DATE(2026,6,2) -> 46175 | AI19: =DATE(2026,6,3) -> 46176 | AJ19: =DATE(2026,6,4) -> 46177 | AK19: =DATE(2026,6,5) -> 46178 | AL19: =DATE(2026,6,6) -> 46179 | AM19: =DATE(2026,6,7) -> 46180 | AN19: =DATE(2026,6,8) -> 46181 | AO19: =DATE(2026,6,9) -> 46182 | AP19: =DATE(2026,6,10) -> 46183 | AQ19: =DATE(2026,6,11) -> 46184 | AR19: =DATE(2026,6,12) -> 46185 | AS19: =DATE(2026,6,13) -> 46186 | AT19: =DATE(2026,6,14) -> 46187 | AU19: =DATE(2026,6,15) -> 46188 | AV19: =DATE(2026,6,16) -> 46189 | AW19: =DATE(2026,6,17) -> 46190 | AX19: =DATE(2026,6,18) -> 46191 | AY19: =DATE(2026,6,19) -> 46192 | AZ19: =DATE(2026,6,20) -> 46193 | BA19: =DATE(2026,6,21) -> 46194 | BB19: =DATE(2026,6,22) -> 46195 | BC19: =DATE(2026,6,23) -> 46196 | BD19: =DATE(2026,6,24) -> 46197 | BE19: =DATE(2026,6,25) -> 46198 | BF19: =DATE(2026,6,26) -> 46199 | BG19: =DATE(2026,6,27) -> 46200 | BH19: =DATE(2026,6,28) -> 46201 | BI19: =DATE(2026,6,29) -> 46202 | BJ19: =DATE(2026,6,30) -> 46203 | BK19: =DATE(2026,7,1) -> 46204 | BL19: =DATE(2026,7,2) -> 46205 | BM19: =DATE(2026,7,3) -> 46206 | BN19: =DATE(2026,7,4) -> 46207 | BO19: =DATE(2026,7,5) -> 46208 | BP19: =DATE(2026,7,6) -> 46209 | BQ19: =DATE(2026,7,7) -> 46210 | BR19: =DATE(2026,7,8) -> 46211 | BS19: =DATE(2026,7,9) -> 46212 | BT19: =DATE(2026,7,10) -> 46213 | BU19: =DATE(2026,7,11) -> 46214 | BV19: =DATE(2026,7,12) -> 46215 | BW19: =DATE(2026,7,13) -> 46216 | BX19: =DATE(2026,7,14) -> 46217 | BY19: =DATE(2026,7,15) -> 46218 | BZ19: =DATE(2026,7,16) -> 46219 | CA19: =DATE(2026,7,17) -> 46220 | CB19: =DATE(2026,7,18) -> 46221 | CC19: =DATE(2026,7,19) -> 46222 | CD19: =DATE(2026,7,20) -> 46223 | CE19: =DATE(2026,7,21) -> 46224 | CF19: =DATE(2026,7,22) -> 46225 | CG19: =DATE(2026,7,23) -> 46226 | CH19: =DATE(2026,7,24) -> 46227 | CI19: =DATE(2026,7,25) -> 46228 | CJ19: =DATE(2026,7,26) -> 46229 | CK19: =DATE(2026,7,27) -> 46230 | CL19: =DATE(2026,7,28) -> 46231 | CM19: =DATE(2026,7,29) -> 46232 | CN19: =DATE(2026,7,30) -> 46233 | CO19: =DATE(2026,7,31) -> 46234 | CP19: =DATE(2026,8,1) -> 46235 | CQ19: =DATE(2026,8,2) -> 46236 | CR19: =DATE(2026,8,3) -> 46237 | CS19: =DATE(2026,8,4) -> 46238 | CT19: =DATE(2026,8,5) -> 46239 | CU19: =DATE(2026,8,6) -> 46240 | CV19: =DATE(2026,8,7) -> 46241 | CW19: =DATE(2026,8,8) -> 46242 | CX19: =DATE(2026,8,9) -> 46243 | CY19: =DATE(2026,8,10) -> 46244 | CZ19: =DATE(2026,8,11) -> 46245 | DA19: =DATE(2026,8,12) -> 46246 | DB19: =DATE(2026,8,13) -> 46247 | DC19: =DATE(2026,8,14) -> 46248 | DD19: =DATE(2026,8,15) -> 46249 | DE19: =DATE(2026,8,16) -> 46250 | DF19: =DATE(2026,8,17) -> 46251 | DG19: =DATE(2026,8,18) -> 46252 | DH19: =DATE(2026,8,19) -> 46253 | DI19: =DATE(2026,8,20) -> 46254 | DJ19: =DATE(2026,8,21) -> 46255 | DK19: =DATE(2026,8,22) -> 46256 | DL19: =DATE(2026,8,23) -> 46257 | DM19: =DATE(2026,8,24) -> 46258 | DN19: =DATE(2026,8,25) -> 46259 | DO19: =DATE(2026,8,26) -> 46260 | DP19: =DATE(2026,8,27) -> 46261 | DQ19: =DATE(2026,8,28) -> 46262 | DR19: =DATE(2026,8,29) -> 46263 | DS19: =DATE(2026,8,30) -> 46264 | DT19: =DATE(2026,8,31) -> 46265 | DU19: =DATE(2026,9,1) -> 46266 | DV19: =DATE(2026,9,2) -> 46267 | DW19: =DATE(2026,9,3) -> 46268 | DX19: =DATE(2026,9,4) -> 46269 | DY19: =DATE(2026,9,5) -> 46270 | DZ19: =DATE(2026,9,6) -> 46271 | EA19: =DATE(2026,9,7) -> 46272 | EB19: =DATE(2026,9,8) -> 46273 | EC19: =DATE(2026,9,9) -> 46274 | ED19: =DATE(2026,9,10) -> 46275 | EE19: =DATE(2026,9,11) -> 46276 | EF19: =DATE(2026,9,12) -> 46277 | EG19: =DATE(2026,9,13) -> 46278 | EH19: =DATE(2026,9,14) -> 46279 | EI19: =DATE(2026,9,15) -> 46280 | EJ19: =DATE(2026,9,16) -> 46281 | EK19: =DATE(2026,9,17) -> 46282 | EL19: =DATE(2026,9,18) -> 46283 | EM19: =DATE(2026,9,19) -> 46284 | EN19: =DATE(2026,9,20) -> 46285 | EO19: =DATE(2026,9,21) -> 46286 | EP19: =DATE(2026,9,22) -> 46287 | EQ19: =DATE(2026,9,23) -> 46288 | ER19: =DATE(2026,9,24) -> 46289 | ES19: =DATE(2026,9,25) -> 46290 | ET19: =DATE(2026,9,26) -> 46291 | EU19: =DATE(2026,9,27) -> 46292 | EV19: =DATE(2026,9,28) -> 46293 | EW19: =DATE(2026,9,29) -> 46294 | EX19: =DATE(2026,9,30) -> 46295 | EY19: =DATE(2026,10,1) -> 46296 | EZ19: =DATE(2026,10,2) -> 46297 | FA19: =DATE(2026,10,3) -> 46298 | FB19: =DATE(2026,10,4) -> 46299 | FC19: =DATE(2026,10,5) -> 46300 | FD19: =DATE(2026,10,6) -> 46301 | FE19: =DATE(2026,10,7) -> 46302 | FF19: =DATE(2026,10,8) -> 46303 | FG19: =DATE(2026,10,9) -> 46304 | FH19: =DATE(2026,10,10) -> 46305 | FI19: =DATE(2026,10,11) -> 46306 | FJ19: =DATE(2026,10,12) -> 46307 | FK19: =DATE(2026,10,13) -> 46308 | FL19: =DATE(2026,10,14) -> 46309 | FM19: =DATE(2026,10,15) -> 46310 | FN19: =DATE(2026,10,16) -> 46311 | FO19: =DATE(2026,10,17) -> 46312 | FP19: =DATE(2026,10,18) -> 46313 | FQ19: =DATE(2026,10,19) -> 46314 | FR19: =DATE(2026,10,20) -> 46315 | FS19: =DATE(2026,10,21) -> 46316 | FT19: =DATE(2026,10,22) -> 46317 | FU19: =DATE(2026,10,23) -> 46318 | FV19: =DATE(2026,10,24) -> 46319 | FW19: =DATE(2026,10,25) -> 46320 | FX19: =DATE(2026,10,26) -> 46321 | FY19: =DATE(2026,10,27) -> 46322 | FZ19: =DATE(2026,10,28) -> 46323 | GA19: =DATE(2026,10,29) -> 46324 | GB19: =DATE(2026,10,30) -> 46325 | GC19: =DATE(2026,10,31) -> 46326 | GD19: =DATE(2026,11,1) -> 46327 | GE19: =DATE(2026,11,2) -> 46328 | GF19: =DATE(2026,11,3) -> 46329 | GG19: =DATE(2026,11,4) -> 46330 | GH19: =DATE(2026,11,5) -> 46331 | GI19: =DATE(2026,11,6) -> 46332 | GJ19: =DATE(2026,11,7) -> 46333 | GK19: =DATE(2026,11,8) -> 46334 | GL19: =DATE(2026,11,9) -> 46335 | GM19: =DATE(2026,11,10) -> 46336 | GN19: =DATE(2026,11,11) -> 46337 | GO19: =DATE(2026,11,12) -> 46338 | GP19: =DATE(2026,11,13) -> 46339 | GQ19: =DATE(2026,11,14) -> 46340 | GR19: =DATE(2026,11,15) -> 46341 | GS19: =DATE(2026,11,16) -> 46342 | GT19: =DATE(2026,11,17) -> 46343 | GU19: =DATE(2026,11,18) -> 46344 | GV19: =DATE(2026,11,19) -> 46345 | GW19: =DATE(2026,11,20) -> 46346 | GX19: =DATE(2026,11,21) -> 46347 | GY19: =DATE(2026,11,22) -> 46348 | GZ19: =DATE(2026,11,23) -> 46349 | HA19: =DATE(2026,11,24) -> 46350 | HB19: =DATE(2026,11,25) -> 46351 | HC19: =DATE(2026,11,26) -> 46352 | HD19: =DATE(2026,11,27) -> 46353 | HE19: =DATE(2026,11,28) -> 46354 | HF19: =DATE(2026,11,29) -> 46355 | HG19: =DATE(2026,11,30) -> 46356 | HH19: =DATE(2026,12,1) -> 46357 | HI19: =DATE(2026,12,2) -> 46358 | HJ19: =DATE(2026,12,3) -> 46359 | HK19: =DATE(2026,12,4) -> 46360 | HL19: =DATE(2026,12,5) -> 46361 | HM19: =DATE(2026,12,6) -> 46362 | HN19: =DATE(2026,12,7) -> 46363 | HO19: =DATE(2026,12,8) -> 46364 | HP19: =DATE(2026,12,9) -> 46365 | HQ19: =DATE(2026,12,10) -> 46366 | HR19: =DATE(2026,12,11) -> 46367 | HS19: =DATE(2026,12,12) -> 46368 | HT19: =DATE(2026,12,13) -> 46369 | HU19: =DATE(2026,12,14) -> 46370 | HV19: =DATE(2026,12,15) -> 46371 | HW19: =DATE(2026,12,16) -> 46372 | HX19: =DATE(2026,12,17) -> 46373 | HY19: =DATE(2026,12,18) -> 46374 | HZ19: =DATE(2026,12,19) -> 46375 | IA19: =DATE(2026,12,20) -> 46376 | IB19: =DATE(2026,12,21) -> 46377 | IC19: =DATE(2026,12,22) -> 46378 | ID19: =DATE(2026,12,23) -> 46379 | IE19: =DATE(2026,12,24) -> 46380 | IF19: =DATE(2026,12,25) -> 46381 | IG19: =DATE(2026,12,26) -> 46382 | IH19: =DATE(2026,12,27) -> 46383 | II19: =DATE(2026,12,28) -> 46384 | IJ19: =DATE(2026,12,29) -> 46385 | IK19: =DATE(2026,12,30) -> 46386 | IL19: =DATE(2026,12,31) -> 46387
A20: SALDO INICIAL DO DIA | B20: =SUM(Categorias!$F$2:$F$4)+SUMIFS(Lançamentos!$F:$F,Lançamentos!$A:$A,"<"&B$19) -> 0 | C20: =B79 -> 0 | D20: =C79 -> 0 | E20: =D79 -> 0 | F20: =E79 -> 0 | G20: =F79 -> 0 | H20: =G79 -> 0 | I20: =H79 -> 0 | J20: =I79 -> 0 | ... IL20: =IK79 -> 3166.79
A21: 💰 RECEITAS
A22: Vendas de Produtos | B22: =SUMIFS(Lançamentos!$F:$F,Lançamentos!$A:$A,B$19,Lançamentos!$C:$C,"Vendas de Produtos") -> 0 | C22: =SUMIFS(Lançamentos!$F:$F,Lançamentos!$A:$A,C$19,Lançamentos!$C:$C,"Vendas de Produtos") -> 0 | D22: =SUMIFS(Lançamentos!$F:$F,Lançamentos!$A:$A,D$19,Lançamentos!$C:$C,"Vendas de Produtos") -> 0 | E22: =SUMIFS(Lançamentos!$F:$F,Lançamentos!$A:$A,E$19,Lançamentos!$C:$C,"Vendas de Produtos") -> 0 | F22: =SUMIFS(Lançamentos!$F:$F,Lançamentos!$A:$A,F$19,Lançamentos!$C:$C,"Vendas de Produtos") -> 0 | G22: =SUMIFS(Lançamentos!$F:$F,Lançamentos!$A:$A,G$19,Lançamentos!$C:$C,"Vendas de Produtos") -> 0 | H22: =SUMIFS(Lançamentos!$F:$F,Lançamentos!$A:$A,H$19,Lançamentos!$C:$C,"Vendas de Produtos") -> 0 | I22: =SUMIFS(Lançamentos!$F:$F,Lançamentos!$A:$A,I$19,Lançamentos!$C:$C,"Vendas de Produtos") -> 0 | ... IL22: =SUMIFS(Lançamentos!$F:$F,Lançamentos!$A:$A,IL$19,Lançamentos!$C:$C,"Vendas de Produtos") -> 0
A23: Vendas de Serviços | B23: =SUMIFS(Lançamentos!$F:$F,Lançamentos!$A:$A,B$19,Lançamentos!$C:$C,"Vendas de Serviços") -> 0 | C23: =SUMIFS(Lançamentos!$F:$F,Lançamentos!$A:$A,C$19,Lançamentos!$C:$C,"Vendas de Serviços") -> 0 | D23: =SUMIFS(Lançamentos!$F:$F,Lançamentos!$A:$A,D$19,Lançamentos!$C:$C,"Vendas de Serviços") -> 0 | E23: =SUMIFS(Lançamentos!$F:$F,Lançamentos!$A:$A,E$19,Lançamentos!$C:$C,"Vendas de Serviços") -> 0 | F23: =SUMIFS(Lançamentos!$F:$F,Lançamentos!$A:$A,F$19,Lançamentos!$C:$C,"Vendas de Serviços") -> 0 | G23: =SUMIFS(Lançamentos!$F:$F,Lançamentos!$A:$A,G$19,Lançamentos!$C:$C,"Vendas de Serviços") -> 0 | H23: =SUMIFS(Lançamentos!$F:$F,Lançamentos!$A:$A,H$19,Lançamentos!$C:$C,"Vendas de Serviços") -> 0 | I23: =SUMIFS(Lançamentos!$F:$F,Lançamentos!$A:$A,I$19,Lançamentos!$C:$C,"Vendas de Serviços") -> 0 | ... IL23: =SUMIFS(Lançamentos!$F:$F,Lançamentos!$A:$A,IL$19,Lançamentos!$C:$C,"Vendas de Serviços") -> 0
A24: Outras Receitas | B24: =SUMIFS(Lançamentos!$F:$F,Lançamentos!$A:$A,B$19,Lançamentos!$C:$C,"Outras Receitas") -> 0 | C24: =SUMIFS(Lançamentos!$F:$F,Lançamentos!$A:$A,C$19,Lançamentos!$C:$C,"Outras Receitas") -> 0 | D24: =SUMIFS(Lançamentos!$F:$F,Lançamentos!$A:$A,D$19,Lançamentos!$C:$C,"Outras Receitas") -> 0 | E24: =SUMIFS(Lançamentos!$F:$F,Lançamentos!$A:$A,E$19,Lançamentos!$C:$C,"Outras Receitas") -> 0 | F24: =SUMIFS(Lançamentos!$F:$F,Lançamentos!$A:$A,F$19,Lançamentos!$C:$C,"Outras Receitas") -> 0 | G24: =SUMIFS(Lançamentos!$F:$F,Lançamentos!$A:$A,G$19,Lançamentos!$C:$C,"Outras Receitas") -> 0 | H24: =SUMIFS(Lançamentos!$F:$F,Lançamentos!$A:$A,H$19,Lançamentos!$C:$C,"Outras Receitas") -> 0 | I24: =SUMIFS(Lançamentos!$F:$F,Lançamentos!$A:$A,I$19,Lançamentos!$C:$C,"Outras Receitas") -> 0 | ... IL24: =SUMIFS(Lançamentos!$F:$F,Lançamentos!$A:$A,IL$19,Lançamentos!$C:$C,"Outras Receitas") -> 0
A25: Receitas Financeiras | B25: =SUMIFS(Lançamentos!$F:$F,Lançamentos!$A:$A,B$19,Lançamentos!$C:$C,"Receitas Financeiras") -> 0 | C25: =SUMIFS(Lançamentos!$F:$F,Lançamentos!$A:$A,C$19,Lançamentos!$C:$C,"Receitas Financeiras") -> 0 | D25: =SUMIFS(Lançamentos!$F:$F,Lançamentos!$A:$A,D$19,Lançamentos!$C:$C,"Receitas Financeiras") -> 0 | E25: =SUMIFS(Lançamentos!$F:$F,Lançamentos!$A:$A,E$19,Lançamentos!$C:$C,"Receitas Financeiras") -> 0 | F25: =SUMIFS(Lançamentos!$F:$F,Lançamentos!$A:$A,F$19,Lançamentos!$C:$C,"Receitas Financeiras") -> 0 | G25: =SUMIFS(Lançamentos!$F:$F,Lançamentos!$A:$A,G$19,Lançamentos!$C:$C,"Receitas Financeiras") -> 0 | H25: =SUMIFS(Lançamentos!$F:$F,Lançamentos!$A:$A,H$19,Lançamentos!$C:$C,"Receitas Financeiras") -> 0 | I25: =SUMIFS(Lançamentos!$F:$F,Lançamentos!$A:$A,I$19,Lançamentos!$C:$C,"Receitas Financeiras") -> 0 | ... IL25: =SUMIFS(Lançamentos!$F:$F,Lançamentos!$A:$A,IL$19,Lançamentos!$C:$C,"Receitas Financeiras") -> 0
A26: Recebimento de Clientes | B26: =SUMIFS(Lançamentos!$F:$F,Lançamentos!$A:$A,B$19,Lançamentos!$C:$C,"Recebimento de Clientes") -> 0 | C26: =SUMIFS(Lançamentos!$F:$F,Lançamentos!$A:$A,C$19,Lançamentos!$C:$C,"Recebimento de Clientes") -> 0 | D26: =SUMIFS(Lançamentos!$F:$F,Lançamentos!$A:$A,D$19,Lançamentos!$C:$C,"Recebimento de Clientes") -> 0 | E26: =SUMIFS(Lançamentos!$F:$F,Lançamentos!$A:$A,E$19,Lançamentos!$C:$C,"Recebimento de Clientes") -> 0 | F26: =SUMIFS(Lançamentos!$F:$F,Lançamentos!$A:$A,F$19,Lançamentos!$C:$C,"Recebimento de Clientes") -> 0 | G26: =SUMIFS(Lançamentos!$F:$F,Lançamentos!$A:$A,G$19,Lançamentos!$C:$C,"Recebimento de Clientes") -> 0 | H26: =SUMIFS(Lançamentos!$F:$F,Lançamentos!$A:$A,H$19,Lançamentos!$C:$C,"Recebimento de Clientes") -> 0 | I26: =SUMIFS(Lançamentos!$F:$F,Lançamentos!$A:$A,I$19,Lançamentos!$C:$C,"Recebimento de Clientes") -> 0 | ... IL26: =SUMIFS(Lançamentos!$F:$F,Lançamentos!$A:$A,IL$19,Lançamentos!$C:$C,"Recebimento de Clientes") -> 0
A27: Vendas Online | B27: =SUMIFS(Lançamentos!$F:$F,Lançamentos!$A:$A,B$19,Lançamentos!$C:$C,"Vendas Online") -> 0 | C27: =SUMIFS(Lançamentos!$F:$F,Lançamentos!$A:$A,C$19,Lançamentos!$C:$C,"Vendas Online") -> 0 | D27: =SUMIFS(Lançamentos!$F:$F,Lançamentos!$A:$A,D$19,Lançamentos!$C:$C,"Vendas Online") -> 0 | E27: =SUMIFS(Lançamentos!$F:$F,Lançamentos!$A:$A,E$19,Lançamentos!$C:$C,"Vendas Online") -> 0 | F27: =SUMIFS(Lançamentos!$F:$F,Lançamentos!$A:$A,F$19,Lançamentos!$C:$C,"Vendas Online") -> 0 | G27: =SUMIFS(Lançamentos!$F:$F,Lançamentos!$A:$A,G$19,Lançamentos!$C:$C,"Vendas Online") -> 0 | H27: =SUMIFS(Lançamentos!$F:$F,Lançamentos!$A:$A,H$19,Lançamentos!$C:$C,"Vendas Online") -> 0 | I27: =SUMIFS(Lançamentos!$F:$F,Lançamentos!$A:$A,I$19,Lançamentos!$C:$C,"Vendas Online") -> 0 | ... IL27: =SUMIFS(Lançamentos!$F:$F,Lançamentos!$A:$A,IL$19,Lançamentos!$C:$C,"Vendas Online") -> 0
A28: Comissões Recebidas | B28: =SUMIFS(Lançamentos!$F:$F,Lançamentos!$A:$A,B$19,Lançamentos!$C:$C,"Comissões Recebidas") -> 0 | C28: =SUMIFS(Lançamentos!$F:$F,Lançamentos!$A:$A,C$19,Lançamentos!$C:$C,"Comissões Recebidas") -> 0 | D28: =SUMIFS(Lançamentos!$F:$F,Lançamentos!$A:$A,D$19,Lançamentos!$C:$C,"Comissões Recebidas") -> 0 | E28: =SUMIFS(Lançamentos!$F:$F,Lançamentos!$A:$A,E$19,Lançamentos!$C:$C,"Comissões Recebidas") -> 0 | F28: =SUMIFS(Lançamentos!$F:$F,Lançamentos!$A:$A,F$19,Lançamentos!$C:$C,"Comissões Recebidas") -> 0 | G28: =SUMIFS(Lançamentos!$F:$F,Lançamentos!$A:$A,G$19,Lançamentos!$C:$C,"Comissões Recebidas") -> 0 | H28: =SUMIFS(Lançamentos!$F:$F,Lançamentos!$A:$A,H$19,Lançamentos!$C:$C,"Comissões Recebidas") -> 0 | I28: =SUMIFS(Lançamentos!$F:$F,Lançamentos!$A:$A,I$19,Lançamentos!$C:$C,"Comissões Recebidas") -> 0 | ... IL28: =SUMIFS(Lançamentos!$F:$F,Lançamentos!$A:$A,IL$19,Lançamentos!$C:$C,"Comissões Recebidas") -> 0
A29: Aluguel Recebido | B29: =SUMIFS(Lançamentos!$F:$F,Lançamentos!$A:$A,B$19,Lançamentos!$C:$C,"Aluguel Recebido") -> 0 | C29: =SUMIFS(Lançamentos!$F:$F,Lançamentos!$A:$A,C$19,Lançamentos!$C:$C,"Aluguel Recebido") -> 0 | D29: =SUMIFS(Lançamentos!$F:$F,Lançamentos!$A:$A,D$19,Lançamentos!$C:$C,"Aluguel Recebido") -> 0 | E29: =SUMIFS(Lançamentos!$F:$F,Lançamentos!$A:$A,E$19,Lançamentos!$C:$C,"Aluguel Recebido") -> 0 | F29: =SUMIFS(Lançamentos!$F:$F,Lançamentos!$A:$A,F$19,Lançamentos!$C:$C,"Aluguel Recebido") -> 0 | G29: =SUMIFS(Lançamentos!$F:$F,Lançamentos!$A:$A,G$19,Lançamentos!$C:$C,"Aluguel Recebido") -> 0 | H29: =SUMIFS(Lançamentos!$F:$F,Lançamentos!$A:$A,H$19,Lançamentos!$C:$C,"Aluguel Recebido") -> 0 | I29: =SUMIFS(Lançamentos!$F:$F,Lançamentos!$A:$A,I$19,Lançamentos!$C:$C,"Aluguel Recebido") -> 0 | ... IL29: =SUMIFS(Lançamentos!$F:$F,Lançamentos!$A:$A,IL$19,Lançamentos!$C:$C,"Aluguel Recebido") -> 0
A30: Reembolsos | B30: =SUMIFS(Lançamentos!$F:$F,Lançamentos!$A:$A,B$19,Lançamentos!$C:$C,"Reembolsos") -> 0 | C30: =SUMIFS(Lançamentos!$F:$F,Lançamentos!$A:$A,C$19,Lançamentos!$C:$C,"Reembolsos") -> 0 | D30: =SUMIFS(Lançamentos!$F:$F,Lançamentos!$A:$A,D$19,Lançamentos!$C:$C,"Reembolsos") -> 0 | E30: =SUMIFS(Lançamentos!$F:$F,Lançamentos!$A:$A,E$19,Lançamentos!$C:$C,"Reembolsos") -> 0 | F30: =SUMIFS(Lançamentos!$F:$F,Lançamentos!$A:$A,F$19,Lançamentos!$C:$C,"Reembolsos") -> 0 | G30: =SUMIFS(Lançamentos!$F:$F,Lançamentos!$A:$A,G$19,Lançamentos!$C:$C,"Reembolsos") -> 0 | H30: =SUMIFS(Lançamentos!$F:$F,Lançamentos!$A:$A,H$19,Lançamentos!$C:$C,"Reembolsos") -> 0 | I30: =SUMIFS(Lançamentos!$F:$F,Lançamentos!$A:$A,I$19,Lançamentos!$C:$C,"Reembolsos") -> 0 | ... IL30: =SUMIFS(Lançamentos!$F:$F,Lançamentos!$A:$A,IL$19,Lançamentos!$C:$C,"Reembolsos") -> 0
A31: Aporte de Sócios | B31: =SUMIFS(Lançamentos!$F:$F,Lançamentos!$A:$A,B$19,Lançamentos!$C:$C,"Aporte de Sócios") -> 0 | C31: =SUMIFS(Lançamentos!$F:$F,Lançamentos!$A:$A,C$19,Lançamentos!$C:$C,"Aporte de Sócios") -> 0 | D31: =SUMIFS(Lançamentos!$F:$F,Lançamentos!$A:$A,D$19,Lançamentos!$C:$C,"Aporte de Sócios") -> 0 | E31: =SUMIFS(Lançamentos!$F:$F,Lançamentos!$A:$A,E$19,Lançamentos!$C:$C,"Aporte de Sócios") -> 0 | F31: =SUMIFS(Lançamentos!$F:$F,Lançamentos!$A:$A,F$19,Lançamentos!$C:$C,"Aporte de Sócios") -> 0 | G31: =SUMIFS(Lançamentos!$F:$F,Lançamentos!$A:$A,G$19,Lançamentos!$C:$C,"Aporte de Sócios") -> 0 | H31: =SUMIFS(Lançamentos!$F:$F,Lançamentos!$A:$A,H$19,Lançamentos!$C:$C,"Aporte de Sócios") -> 0 | I31: =SUMIFS(Lançamentos!$F:$F,Lançamentos!$A:$A,I$19,Lançamentos!$C:$C,"Aporte de Sócios") -> 0 | ... IL31: =SUMIFS(Lançamentos!$F:$F,Lançamentos!$A:$A,IL$19,Lançamentos!$C:$C,"Aporte de Sócios") -> 0
A32: Empréstimo Recebido | B32: =SUMIFS(Lançamentos!$F:$F,Lançamentos!$A:$A,B$19,Lançamentos!$C:$C,"Empréstimo Recebido") -> 0 | C32: =SUMIFS(Lançamentos!$F:$F,Lançamentos!$A:$A,C$19,Lançamentos!$C:$C,"Empréstimo Recebido") -> 0 | D32: =SUMIFS(Lançamentos!$F:$F,Lançamentos!$A:$A,D$19,Lançamentos!$C:$C,"Empréstimo Recebido") -> 0 | E32: =SUMIFS(Lançamentos!$F:$F,Lançamentos!$A:$A,E$19,Lançamentos!$C:$C,"Empréstimo Recebido") -> 0 | F32: =SUMIFS(Lançamentos!$F:$F,Lançamentos!$A:$A,F$19,Lançamentos!$C:$C,"Empréstimo Recebido") -> 0 | G32: =SUMIFS(Lançamentos!$F:$F,Lançamentos!$A:$A,G$19,Lançamentos!$C:$C,"Empréstimo Recebido") -> 0 | H32: =SUMIFS(Lançamentos!$F:$F,Lançamentos!$A:$A,H$19,Lançamentos!$C:$C,"Empréstimo Recebido") -> 0 | I32: =SUMIFS(Lançamentos!$F:$F,Lançamentos!$A:$A,I$19,Lançamentos!$C:$C,"Empréstimo Recebido") -> 0 | ... IL32: =SUMIFS(Lançamentos!$F:$F,Lançamentos!$A:$A,IL$19,Lançamentos!$C:$C,"Empréstimo Recebido") -> 0
A33: TOTAL ENTRADAS | B33: =SUM(B22:B32) -> 0 | C33: =SUM(C22:C32) -> 0 | D33: =SUM(D22:D32) -> 0 | E33: =SUM(E22:E32) -> 0 | F33: =SUM(F22:F32) -> 0 | G33: =SUM(G22:G32) -> 0 | H33: =SUM(H22:H32) -> 0 | I33: =SUM(I22:I32) -> 0 | ... IL33: =SUM(IL22:IL32) -> 0
A34: 💸 DESPESAS
A35: Impostos sobre Vendas | B35: =SUMIFS(Lançamentos!$F:$F,Lançamentos!$A:$A,B$19,Lançamentos!$C:$C,"Impostos sobre Vendas") -> 0 | C35: =SUMIFS(Lançamentos!$F:$F,Lançamentos!$A:$A,C$19,Lançamentos!$C:$C,"Impostos sobre Vendas") -> 0 | D35: =SUMIFS(Lançamentos!$F:$F,Lançamentos!$A:$A,D$19,Lançamentos!$C:$C,"Impostos sobre Vendas") -> 0 | E35: =SUMIFS(Lançamentos!$F:$F,Lançamentos!$A:$A,E$19,Lançamentos!$C:$C,"Impostos sobre Vendas") -> 0 | F35: =SUMIFS(Lançamentos!$F:$F,Lançamentos!$A:$A,F$19,Lançamentos!$C:$C,"Impostos sobre Vendas") -> 0 | G35: =SUMIFS(Lançamentos!$F:$F,Lançamentos!$A:$A,G$19,Lançamentos!$C:$C,"Impostos sobre Vendas") -> 0 | H35: =SUMIFS(Lançamentos!$F:$F,Lançamentos!$A:$A,H$19,Lançamentos!$C:$C,"Impostos sobre Vendas") -> 0 | I35: =SUMIFS(Lançamentos!$F:$F,Lançamentos!$A:$A,I$19,Lançamentos!$C:$C,"Impostos sobre Vendas") -> 0 | ... IL35: =SUMIFS(Lançamentos!$F:$F,Lançamentos!$A:$A,IL$19,Lançamentos!$C:$C,"Impostos sobre Vendas") -> 0
A36: Devoluções | B36: =SUMIFS(Lançamentos!$F:$F,Lançamentos!$A:$A,B$19,Lançamentos!$C:$C,"Devoluções") -> 0 | C36: =SUMIFS(Lançamentos!$F:$F,Lançamentos!$A:$A,C$19,Lançamentos!$C:$C,"Devoluções") -> 0 | D36: =SUMIFS(Lançamentos!$F:$F,Lançamentos!$A:$A,D$19,Lançamentos!$C:$C,"Devoluções") -> 0 | E36: =SUMIFS(Lançamentos!$F:$F,Lançamentos!$A:$A,E$19,Lançamentos!$C:$C,"Devoluções") -> 0 | F36: =SUMIFS(Lançamentos!$F:$F,Lançamentos!$A:$A,F$19,Lançamentos!$C:$C,"Devoluções") -> 0 | G36: =SUMIFS(Lançamentos!$F:$F,Lançamentos!$A:$A,G$19,Lançamentos!$C:$C,"Devoluções") -> 0 | H36: =SUMIFS(Lançamentos!$F:$F,Lançamentos!$A:$A,H$19,Lançamentos!$C:$C,"Devoluções") -> 0 | I36: =SUMIFS(Lançamentos!$F:$F,Lançamentos!$A:$A,I$19,Lançamentos!$C:$C,"Devoluções") -> 0 | ... IL36: =SUMIFS(Lançamentos!$F:$F,Lançamentos!$A:$A,IL$19,Lançamentos!$C:$C,"Devoluções") -> 0
A37: Custo de Mercadoria Vendida | B37: =SUMIFS(Lançamentos!$F:$F,Lançamentos!$A:$A,B$19,Lançamentos!$C:$C,"Custo de Mercadoria Vendida") -> 0 | C37: =SUMIFS(Lançamentos!$F:$F,Lançamentos!$A:$A,C$19,Lançamentos!$C:$C,"Custo de Mercadoria Vendida") -> 0 | D37: =SUMIFS(Lançamentos!$F:$F,Lançamentos!$A:$A,D$19,Lançamentos!$C:$C,"Custo de Mercadoria Vendida") -> 0 | E37: =SUMIFS(Lançamentos!$F:$F,Lançamentos!$A:$A,E$19,Lançamentos!$C:$C,"Custo de Mercadoria Vendida") -> 0 | F37: =SUMIFS(Lançamentos!$F:$F,Lançamentos!$A:$A,F$19,Lançamentos!$C:$C,"Custo de Mercadoria Vendida") -> 0 | G37: =SUMIFS(Lançamentos!$F:$F,Lançamentos!$A:$A,G$19,Lançamentos!$C:$C,"Custo de Mercadoria Vendida") -> 0 | H37: =SUMIFS(Lançamentos!$F:$F,Lançamentos!$A:$A,H$19,Lançamentos!$C:$C,"Custo de Mercadoria Vendida") -> 0 | I37: =SUMIFS(Lançamentos!$F:$F,Lançamentos!$A:$A,I$19,Lançamentos!$C:$C,"Custo de Mercadoria Vendida") -> 0 | ... IL37: =SUMIFS(Lançamentos!$F:$F,Lançamentos!$A:$A,IL$19,Lançamentos!$C:$C,"Custo de Mercadoria Vendida") -> 0
A38: Custo de Serviços Prestados | B38: =SUMIFS(Lançamentos!$F:$F,Lançamentos!$A:$A,B$19,Lançamentos!$C:$C,"Custo de Serviços Prestados") -> 0 | C38: =SUMIFS(Lançamentos!$F:$F,Lançamentos!$A:$A,C$19,Lançamentos!$C:$C,"Custo de Serviços Prestados") -> 0 | D38: =SUMIFS(Lançamentos!$F:$F,Lançamentos!$A:$A,D$19,Lançamentos!$C:$C,"Custo de Serviços Prestados") -> 0 | E38: =SUMIFS(Lançamentos!$F:$F,Lançamentos!$A:$A,E$19,Lançamentos!$C:$C,"Custo de Serviços Prestados") -> 0 | F38: =SUMIFS(Lançamentos!$F:$F,Lançamentos!$A:$A,F$19,Lançamentos!$C:$C,"Custo de Serviços Prestados") -> 0 | G38: =SUMIFS(Lançamentos!$F:$F,Lançamentos!$A:$A,G$19,Lançamentos!$C:$C,"Custo de Serviços Prestados") -> 0 | H38: =SUMIFS(Lançamentos!$F:$F,Lançamentos!$A:$A,H$19,Lançamentos!$C:$C,"Custo de Serviços Prestados") -> 0 | I38: =SUMIFS(Lançamentos!$F:$F,Lançamentos!$A:$A,I$19,Lançamentos!$C:$C,"Custo de Serviços Prestados") -> 0 | ... IL38: =SUMIFS(Lançamentos!$F:$F,Lançamentos!$A:$A,IL$19,Lançamentos!$C:$C,"Custo de Serviços Prestados") -> 0
A39: Salários e Encargos | B39: =SUMIFS(Lançamentos!$F:$F,Lançamentos!$A:$A,B$19,Lançamentos!$C:$C,"Salários e Encargos") -> 0 | C39: =SUMIFS(Lançamentos!$F:$F,Lançamentos!$A:$A,C$19,Lançamentos!$C:$C,"Salários e Encargos") -> 0 | D39: =SUMIFS(Lançamentos!$F:$F,Lançamentos!$A:$A,D$19,Lançamentos!$C:$C,"Salários e Encargos") -> 0 | E39: =SUMIFS(Lançamentos!$F:$F,Lançamentos!$A:$A,E$19,Lançamentos!$C:$C,"Salários e Encargos") -> 0 | F39: =SUMIFS(Lançamentos!$F:$F,Lançamentos!$A:$A,F$19,Lançamentos!$C:$C,"Salários e Encargos") -> 0 | G39: =SUMIFS(Lançamentos!$F:$F,Lançamentos!$A:$A,G$19,Lançamentos!$C:$C,"Salários e Encargos") -> 0 | H39: =SUMIFS(Lançamentos!$F:$F,Lançamentos!$A:$A,H$19,Lançamentos!$C:$C,"Salários e Encargos") -> 0 | I39: =SUMIFS(Lançamentos!$F:$F,Lançamentos!$A:$A,I$19,Lançamentos!$C:$C,"Salários e Encargos") -> 0 | ... IL39: =SUMIFS(Lançamentos!$F:$F,Lançamentos!$A:$A,IL$19,Lançamentos!$C:$C,"Salários e Encargos") -> 0
A40: Aluguel | B40: =SUMIFS(Lançamentos!$F:$F,Lançamentos!$A:$A,B$19,Lançamentos!$C:$C,"Aluguel") -> 0 | C40: =SUMIFS(Lançamentos!$F:$F,Lançamentos!$A:$A,C$19,Lançamentos!$C:$C,"Aluguel") -> 0 | D40: =SUMIFS(Lançamentos!$F:$F,Lançamentos!$A:$A,D$19,Lançamentos!$C:$C,"Aluguel") -> 0 | E40: =SUMIFS(Lançamentos!$F:$F,Lançamentos!$A:$A,E$19,Lançamentos!$C:$C,"Aluguel") -> 0 | F40: =SUMIFS(Lançamentos!$F:$F,Lançamentos!$A:$A,F$19,Lançamentos!$C:$C,"Aluguel") -> 0 | G40: =SUMIFS(Lançamentos!$F:$F,Lançamentos!$A:$A,G$19,Lançamentos!$C:$C,"Aluguel") -> 0 | H40: =SUMIFS(Lançamentos!$F:$F,Lançamentos!$A:$A,H$19,Lançamentos!$C:$C,"Aluguel") -> 0 | I40: =SUMIFS(Lançamentos!$F:$F,Lançamentos!$A:$A,I$19,Lançamentos!$C:$C,"Aluguel") -> 0 | ... IL40: =SUMIFS(Lançamentos!$F:$F,Lançamentos!$A:$A,IL$19,Lançamentos!$C:$C,"Aluguel") -> 0
A41: Água, Luz e Internet | B41: =SUMIFS(Lançamentos!$F:$F,Lançamentos!$A:$A,B$19,Lançamentos!$C:$C,"Água, Luz e Internet") -> 0 | C41: =SUMIFS(Lançamentos!$F:$F,Lançamentos!$A:$A,C$19,Lançamentos!$C:$C,"Água, Luz e Internet") -> 0 | D41: =SUMIFS(Lançamentos!$F:$F,Lançamentos!$A:$A,D$19,Lançamentos!$C:$C,"Água, Luz e Internet") -> 0 | E41: =SUMIFS(Lançamentos!$F:$F,Lançamentos!$A:$A,E$19,Lançamentos!$C:$C,"Água, Luz e Internet") -> 0 | F41: =SUMIFS(Lançamentos!$F:$F,Lançamentos!$A:$A,F$19,Lançamentos!$C:$C,"Água, Luz e Internet") -> 0 | G41: =SUMIFS(Lançamentos!$F:$F,Lançamentos!$A:$A,G$19,Lançamentos!$C:$C,"Água, Luz e Internet") -> 0 | H41: =SUMIFS(Lançamentos!$F:$F,Lançamentos!$A:$A,H$19,Lançamentos!$C:$C,"Água, Luz e Internet") -> 0 | I41: =SUMIFS(Lançamentos!$F:$F,Lançamentos!$A:$A,I$19,Lançamentos!$C:$C,"Água, Luz e Internet") -> 0 | ... IL41: =SUMIFS(Lançamentos!$F:$F,Lançamentos!$A:$A,IL$19,Lançamentos!$C:$C,"Água, Luz e Internet") -> 0
A42: Material de Escritório | B42: =SUMIFS(Lançamentos!$F:$F,Lançamentos!$A:$A,B$19,Lançamentos!$C:$C,"Material de Escritório") -> 0 | C42: =SUMIFS(Lançamentos!$F:$F,Lançamentos!$A:$A,C$19,Lançamentos!$C:$C,"Material de Escritório") -> 0 | D42: =SUMIFS(Lançamentos!$F:$F,Lançamentos!$A:$A,D$19,Lançamentos!$C:$C,"Material de Escritório") -> 0 | E42: =SUMIFS(Lançamentos!$F:$F,Lançamentos!$A:$A,E$19,Lançamentos!$C:$C,"Material de Escritório") -> 0 | F42: =SUMIFS(Lançamentos!$F:$F,Lançamentos!$A:$A,F$19,Lançamentos!$C:$C,"Material de Escritório") -> 0 | G42: =SUMIFS(Lançamentos!$F:$F,Lançamentos!$A:$A,G$19,Lançamentos!$C:$C,"Material de Escritório") -> 0 | H42: =SUMIFS(Lançamentos!$F:$F,Lançamentos!$A:$A,H$19,Lançamentos!$C:$C,"Material de Escritório") -> 0 | I42: =SUMIFS(Lançamentos!$F:$F,Lançamentos!$A:$A,I$19,Lançamentos!$C:$C,"Material de Escritório") -> 0 | ... IL42: =SUMIFS(Lançamentos!$F:$F,Lançamentos!$A:$A,IL$19,Lançamentos!$C:$C,"Material de Escritório") -> 0
A43: Marketing e Publicidade | B43: =SUMIFS(Lançamentos!$F:$F,Lançamentos!$A:$A,B$19,Lançamentos!$C:$C,"Marketing e Publicidade") -> 0 | C43: =SUMIFS(Lançamentos!$F:$F,Lançamentos!$A:$A,C$19,Lançamentos!$C:$C,"Marketing e Publicidade") -> 0 | D43: =SUMIFS(Lançamentos!$F:$F,Lançamentos!$A:$A,D$19,Lançamentos!$C:$C,"Marketing e Publicidade") -> 0 | E43: =SUMIFS(Lançamentos!$F:$F,Lançamentos!$A:$A,E$19,Lançamentos!$C:$C,"Marketing e Publicidade") -> 0 | F43: =SUMIFS(Lançamentos!$F:$F,Lançamentos!$A:$A,F$19,Lançamentos!$C:$C,"Marketing e Publicidade") -> 0 | G43: =SUMIFS(Lançamentos!$F:$F,Lançamentos!$A:$A,G$19,Lançamentos!$C:$C,"Marketing e Publicidade") -> 0 | H43: =SUMIFS(Lançamentos!$F:$F,Lançamentos!$A:$A,H$19,Lançamentos!$C:$C,"Marketing e Publicidade") -> 0 | I43: =SUMIFS(Lançamentos!$F:$F,Lançamentos!$A:$A,I$19,Lançamentos!$C:$C,"Marketing e Publicidade") -> 0 | ... IL43: =SUMIFS(Lançamentos!$F:$F,Lançamentos!$A:$A,IL$19,Lançamentos!$C:$C,"Marketing e Publicidade") -> 0
A44: Manutenção | B44: =SUMIFS(Lançamentos!$F:$F,Lançamentos!$A:$A,B$19,Lançamentos!$C:$C,"Manutenção") -> 0 | C44: =SUMIFS(Lançamentos!$F:$F,Lançamentos!$A:$A,C$19,Lançamentos!$C:$C,"Manutenção") -> 0 | D44: =SUMIFS(Lançamentos!$F:$F,Lançamentos!$A:$A,D$19,Lançamentos!$C:$C,"Manutenção") -> 0 | E44: =SUMIFS(Lançamentos!$F:$F,Lançamentos!$A:$A,E$19,Lançamentos!$C:$C,"Manutenção") -> 0 | F44: =SUMIFS(Lançamentos!$F:$F,Lançamentos!$A:$A,F$19,Lançamentos!$C:$C,"Manutenção") -> 0 | G44: =SUMIFS(Lançamentos!$F:$F,Lançamentos!$A:$A,G$19,Lançamentos!$C:$C,"Manutenção") -> 0 | H44: =SUMIFS(Lançamentos!$F:$F,Lançamentos!$A:$A,H$19,Lançamentos!$C:$C,"Manutenção") -> 0 | I44: =SUMIFS(Lançamentos!$F:$F,Lançamentos!$A:$A,I$19,Lançamentos!$C:$C,"Manutenção") -> 0 | ... IL44: =SUMIFS(Lançamentos!$F:$F,Lançamentos!$A:$A,IL$19,Lançamentos!$C:$C,"Manutenção") -> 0
A45: Transporte e Viagens | B45: =SUMIFS(Lançamentos!$F:$F,Lançamentos!$A:$A,B$19,Lançamentos!$C:$C,"Transporte e Viagens") -> 0 | C45: =SUMIFS(Lançamentos!$F:$F,Lançamentos!$A:$A,C$19,Lançamentos!$C:$C,"Transporte e Viagens") -> 0 | D45: =SUMIFS(Lançamentos!$F:$F,Lançamentos!$A:$A,D$19,Lançamentos!$C:$C,"Transporte e Viagens") -> 0 | E45: =SUMIFS(Lançamentos!$F:$F,Lançamentos!$A:$A,E$19,Lançamentos!$C:$C,"Transporte e Viagens") -> 0 | F45: =SUMIFS(Lançamentos!$F:$F,Lançamentos!$A:$A,F$19,Lançamentos!$C:$C,"Transporte e Viagens") -> 0 | G45: =SUMIFS(Lançamentos!$F:$F,Lançamentos!$A:$A,G$19,Lançamentos!$C:$C,"Transporte e Viagens") -> 0 | H45: =SUMIFS(Lançamentos!$F:$F,Lançamentos!$A:$A,H$19,Lançamentos!$C:$C,"Transporte e Viagens") -> 0 | I45: =SUMIFS(Lançamentos!$F:$F,Lançamentos!$A:$A,I$19,Lançamentos!$C:$C,"Transporte e Viagens") -> 0 | ... IL45: =SUMIFS(Lançamentos!$F:$F,Lançamentos!$A:$A,IL$19,Lançamentos!$C:$C,"Transporte e Viagens") -> 0
A46: Serviços de Terceiros | B46: =SUMIFS(Lançamentos!$F:$F,Lançamentos!$A:$A,B$19,Lançamentos!$C:$C,"Serviços de Terceiros") -> 0 | C46: =SUMIFS(Lançamentos!$F:$F,Lançamentos!$A:$A,C$19,Lançamentos!$C:$C,"Serviços de Terceiros") -> 0 | D46: =SUMIFS(Lançamentos!$F:$F,Lançamentos!$A:$A,D$19,Lançamentos!$C:$C,"Serviços de Terceiros") -> 0 | E46: =SUMIFS(Lançamentos!$F:$F,Lançamentos!$A:$A,E$19,Lançamentos!$C:$C,"Serviços de Terceiros") -> 0 | F46: =SUMIFS(Lançamentos!$F:$F,Lançamentos!$A:$A,F$19,Lançamentos!$C:$C,"Serviços de Terceiros") -> 0 | G46: =SUMIFS(Lançamentos!$F:$F,Lançamentos!$A:$A,G$19,Lançamentos!$C:$C,"Serviços de Terceiros") -> 0 | H46: =SUMIFS(Lançamentos!$F:$F,Lançamentos!$A:$A,H$19,Lançamentos!$C:$C,"Serviços de Terceiros") -> 0 | I46: =SUMIFS(Lançamentos!$F:$F,Lançamentos!$A:$A,I$19,Lançamentos!$C:$C,"Serviços de Terceiros") -> 0 | ... IL46: =SUMIFS(Lançamentos!$F:$F,Lançamentos!$A:$A,IL$19,Lançamentos!$C:$C,"Serviços de Terceiros") -> 0
A47: Juros e Tarifas Bancárias | B47: =SUMIFS(Lançamentos!$F:$F,Lançamentos!$A:$A,B$19,Lançamentos!$C:$C,"Juros e Tarifas Bancárias") -> 0 | C47: =SUMIFS(Lançamentos!$F:$F,Lançamentos!$A:$A,C$19,Lançamentos!$C:$C,"Juros e Tarifas Bancárias") -> 0 | D47: =SUMIFS(Lançamentos!$F:$F,Lançamentos!$A:$A,D$19,Lançamentos!$C:$C,"Juros e Tarifas Bancárias") -> 0 | E47: =SUMIFS(Lançamentos!$F:$F,Lançamentos!$A:$A,E$19,Lançamentos!$C:$C,"Juros e Tarifas Bancárias") -> 0 | F47: =SUMIFS(Lançamentos!$F:$F,Lançamentos!$A:$A,F$19,Lançamentos!$C:$C,"Juros e Tarifas Bancárias") -> 0 | G47: =SUMIFS(Lançamentos!$F:$F,Lançamentos!$A:$A,G$19,Lançamentos!$C:$C,"Juros e Tarifas Bancárias") -> 0 | H47: =SUMIFS(Lançamentos!$F:$F,Lançamentos!$A:$A,H$19,Lançamentos!$C:$C,"Juros e Tarifas Bancárias") -> 0 | I47: =SUMIFS(Lançamentos!$F:$F,Lançamentos!$A:$A,I$19,Lançamentos!$C:$C,"Juros e Tarifas Bancárias") -> 0 | ... IL47: =SUMIFS(Lançamentos!$F:$F,Lançamentos!$A:$A,IL$19,Lançamentos!$C:$C,"Juros e Tarifas Bancárias") -> 0
A48: Empréstimos e Financiamentos | B48: =SUMIFS(Lançamentos!$F:$F,Lançamentos!$A:$A,B$19,Lançamentos!$C:$C,"Empréstimos e Financiamentos") -> 0 | C48: =SUMIFS(Lançamentos!$F:$F,Lançamentos!$A:$A,C$19,Lançamentos!$C:$C,"Empréstimos e Financiamentos") -> 0 | D48: =SUMIFS(Lançamentos!$F:$F,Lançamentos!$A:$A,D$19,Lançamentos!$C:$C,"Empréstimos e Financiamentos") -> 0 | E48: =SUMIFS(Lançamentos!$F:$F,Lançamentos!$A:$A,E$19,Lançamentos!$C:$C,"Empréstimos e Financiamentos") -> 0 | F48: =SUMIFS(Lançamentos!$F:$F,Lançamentos!$A:$A,F$19,Lançamentos!$C:$C,"Empréstimos e Financiamentos") -> 0 | G48: =SUMIFS(Lançamentos!$F:$F,Lançamentos!$A:$A,G$19,Lançamentos!$C:$C,"Empréstimos e Financiamentos") -> 0 | H48: =SUMIFS(Lançamentos!$F:$F,Lançamentos!$A:$A,H$19,Lançamentos!$C:$C,"Empréstimos e Financiamentos") -> 0 | I48: =SUMIFS(Lançamentos!$F:$F,Lançamentos!$A:$A,I$19,Lançamentos!$C:$C,"Empréstimos e Financiamentos") -> 0 | ... IL48: =SUMIFS(Lançamentos!$F:$F,Lançamentos!$A:$A,IL$19,Lançamentos!$C:$C,"Empréstimos e Financiamentos") -> 0
A49: Impostos sobre Lucro | B49: =SUMIFS(Lançamentos!$F:$F,Lançamentos!$A:$A,B$19,Lançamentos!$C:$C,"Impostos sobre Lucro") -> 0 | C49: =SUMIFS(Lançamentos!$F:$F,Lançamentos!$A:$A,C$19,Lançamentos!$C:$C,"Impostos sobre Lucro") -> 0 | D49: =SUMIFS(Lançamentos!$F:$F,Lançamentos!$A:$A,D$19,Lançamentos!$C:$C,"Impostos sobre Lucro") -> 0 | E49: =SUMIFS(Lançamentos!$F:$F,Lançamentos!$A:$A,E$19,Lançamentos!$C:$C,"Impostos sobre Lucro") -> 0 | F49: =SUMIFS(Lançamentos!$F:$F,Lançamentos!$A:$A,F$19,Lançamentos!$C:$C,"Impostos sobre Lucro") -> 0 | G49: =SUMIFS(Lançamentos!$F:$F,Lançamentos!$A:$A,G$19,Lançamentos!$C:$C,"Impostos sobre Lucro") -> 0 | H49: =SUMIFS(Lançamentos!$F:$F,Lançamentos!$A:$A,H$19,Lançamentos!$C:$C,"Impostos sobre Lucro") -> 0 | I49: =SUMIFS(Lançamentos!$F:$F,Lançamentos!$A:$A,I$19,Lançamentos!$C:$C,"Impostos sobre Lucro") -> 0 | ... IL49: =SUMIFS(Lançamentos!$F:$F,Lançamentos!$A:$A,IL$19,Lançamentos!$C:$C,"Impostos sobre Lucro") -> 0
A50: Frete sobre Vendas | B50: =SUMIFS(Lançamentos!$F:$F,Lançamentos!$A:$A,B$19,Lançamentos!$C:$C,"Frete sobre Vendas") -> 0 | C50: =SUMIFS(Lançamentos!$F:$F,Lançamentos!$A:$A,C$19,Lançamentos!$C:$C,"Frete sobre Vendas") -> 0 | D50: =SUMIFS(Lançamentos!$F:$F,Lançamentos!$A:$A,D$19,Lançamentos!$C:$C,"Frete sobre Vendas") -> 0 | E50: =SUMIFS(Lançamentos!$F:$F,Lançamentos!$A:$A,E$19,Lançamentos!$C:$C,"Frete sobre Vendas") -> 0 | F50: =SUMIFS(Lançamentos!$F:$F,Lançamentos!$A:$A,F$19,Lançamentos!$C:$C,"Frete sobre Vendas") -> 0 | G50: =SUMIFS(Lançamentos!$F:$F,Lançamentos!$A:$A,G$19,Lançamentos!$C:$C,"Frete sobre Vendas") -> 0 | H50: =SUMIFS(Lançamentos!$F:$F,Lançamentos!$A:$A,H$19,Lançamentos!$C:$C,"Frete sobre Vendas") -> 0 | I50: =SUMIFS(Lançamentos!$F:$F,Lançamentos!$A:$A,I$19,Lançamentos!$C:$C,"Frete sobre Vendas") -> 0 | ... IL50: =SUMIFS(Lançamentos!$F:$F,Lançamentos!$A:$A,IL$19,Lançamentos!$C:$C,"Frete sobre Vendas") -> 0
A51: Embalagens | B51: =SUMIFS(Lançamentos!$F:$F,Lançamentos!$A:$A,B$19,Lançamentos!$C:$C,"Embalagens") -> 0 | C51: =SUMIFS(Lançamentos!$F:$F,Lançamentos!$A:$A,C$19,Lançamentos!$C:$C,"Embalagens") -> 0 | D51: =SUMIFS(Lançamentos!$F:$F,Lançamentos!$A:$A,D$19,Lançamentos!$C:$C,"Embalagens") -> 0 | E51: =SUMIFS(Lançamentos!$F:$F,Lançamentos!$A:$A,E$19,Lançamentos!$C:$C,"Embalagens") -> 0 | F51: =SUMIFS(Lançamentos!$F:$F,Lançamentos!$A:$A,F$19,Lançamentos!$C:$C,"Embalagens") -> 0 | G51: =SUMIFS(Lançamentos!$F:$F,Lançamentos!$A:$A,G$19,Lançamentos!$C:$C,"Embalagens") -> 0 | H51: =SUMIFS(Lançamentos!$F:$F,Lançamentos!$A:$A,H$19,Lançamentos!$C:$C,"Embalagens") -> 0 | I51: =SUMIFS(Lançamentos!$F:$F,Lançamentos!$A:$A,I$19,Lançamentos!$C:$C,"Embalagens") -> 0 | ... IL51: =SUMIFS(Lançamentos!$F:$F,Lançamentos!$A:$A,IL$19,Lançamentos!$C:$C,"Embalagens") -> 0
A52: Combustível | B52: =SUMIFS(Lançamentos!$F:$F,Lançamentos!$A:$A,B$19,Lançamentos!$C:$C,"Combustível") -> 0 | C52: =SUMIFS(Lançamentos!$F:$F,Lançamentos!$A:$A,C$19,Lançamentos!$C:$C,"Combustível") -> 0 | D52: =SUMIFS(Lançamentos!$F:$F,Lançamentos!$A:$A,D$19,Lançamentos!$C:$C,"Combustível") -> 0 | E52: =SUMIFS(Lançamentos!$F:$F,Lançamentos!$A:$A,E$19,Lançamentos!$C:$C,"Combustível") -> 0 | F52: =SUMIFS(Lançamentos!$F:$F,Lançamentos!$A:$A,F$19,Lançamentos!$C:$C,"Combustível") -> 0 | G52: =SUMIFS(Lançamentos!$F:$F,Lançamentos!$A:$A,G$19,Lançamentos!$C:$C,"Combustível") -> 0 | H52: =SUMIFS(Lançamentos!$F:$F,Lançamentos!$A:$A,H$19,Lançamentos!$C:$C,"Combustível") -> 0 | I52: =SUMIFS(Lançamentos!$F:$F,Lançamentos!$A:$A,I$19,Lançamentos!$C:$C,"Combustível") -> 0 | ... IL52: =SUMIFS(Lançamentos!$F:$F,Lançamentos!$A:$A,IL$19,Lançamentos!$C:$C,"Combustível") -> 0
A53: Pró-labore | B53: =SUMIFS(Lançamentos!$F:$F,Lançamentos!$A:$A,B$19,Lançamentos!$C:$C,"Pró-labore") -> 0 | C53: =SUMIFS(Lançamentos!$F:$F,Lançamentos!$A:$A,C$19,Lançamentos!$C:$C,"Pró-labore") -> 0 | D53: =SUMIFS(Lançamentos!$F:$F,Lançamentos!$A:$A,D$19,Lançamentos!$C:$C,"Pró-labore") -> 0 | E53: =SUMIFS(Lançamentos!$F:$F,Lançamentos!$A:$A,E$19,Lançamentos!$C:$C,"Pró-labore") -> 0 | F53: =SUMIFS(Lançamentos!$F:$F,Lançamentos!$A:$A,F$19,Lançamentos!$C:$C,"Pró-labore") -> 0 | G53: =SUMIFS(Lançamentos!$F:$F,Lançamentos!$A:$A,G$19,Lançamentos!$C:$C,"Pró-labore") -> 0 | H53: =SUMIFS(Lançamentos!$F:$F,Lançamentos!$A:$A,H$19,Lançamentos!$C:$C,"Pró-labore") -> 0 | I53: =SUMIFS(Lançamentos!$F:$F,Lançamentos!$A:$A,I$19,Lançamentos!$C:$C,"Pró-labore") -> 0 | ... IL53: =SUMIFS(Lançamentos!$F:$F,Lançamentos!$A:$A,IL$19,Lançamentos!$C:$C,"Pró-labore") -> 0
A54: Benefícios (VR/VT/Plano) | B54: =SUMIFS(Lançamentos!$F:$F,Lançamentos!$A:$A,B$19,Lançamentos!$C:$C,"Benefícios (VR/VT/Plano)") -> 0 | C54: =SUMIFS(Lançamentos!$F:$F,Lançamentos!$A:$A,C$19,Lançamentos!$C:$C,"Benefícios (VR/VT/Plano)") -> 0 | D54: =SUMIFS(Lançamentos!$F:$F,Lançamentos!$A:$A,D$19,Lançamentos!$C:$C,"Benefícios (VR/VT/Plano)") -> 0 | E54: =SUMIFS(Lançamentos!$F:$F,Lançamentos!$A:$A,E$19,Lançamentos!$C:$C,"Benefícios (VR/VT/Plano)") -> 0 | F54: =SUMIFS(Lançamentos!$F:$F,Lançamentos!$A:$A,F$19,Lançamentos!$C:$C,"Benefícios (VR/VT/Plano)") -> 0 | G54: =SUMIFS(Lançamentos!$F:$F,Lançamentos!$A:$A,G$19,Lançamentos!$C:$C,"Benefícios (VR/VT/Plano)") -> 0 | H54: =SUMIFS(Lançamentos!$F:$F,Lançamentos!$A:$A,H$19,Lançamentos!$C:$C,"Benefícios (VR/VT/Plano)") -> 0 | I54: =SUMIFS(Lançamentos!$F:$F,Lançamentos!$A:$A,I$19,Lançamentos!$C:$C,"Benefícios (VR/VT/Plano)") -> 0 | ... IL54: =SUMIFS(Lançamentos!$F:$F,Lançamentos!$A:$A,IL$19,Lançamentos!$C:$C,"Benefícios (VR/VT/Plano)") -> 0
A55: Software e Assinaturas | B55: =SUMIFS(Lançamentos!$F:$F,Lançamentos!$A:$A,B$19,Lançamentos!$C:$C,"Software e Assinaturas") -> 0 | C55: =SUMIFS(Lançamentos!$F:$F,Lançamentos!$A:$A,C$19,Lançamentos!$C:$C,"Software e Assinaturas") -> 0 | D55: =SUMIFS(Lançamentos!$F:$F,Lançamentos!$A:$A,D$19,Lançamentos!$C:$C,"Software e Assinaturas") -> 0 | E55: =SUMIFS(Lançamentos!$F:$F,Lançamentos!$A:$A,E$19,Lançamentos!$C:$C,"Software e Assinaturas") -> 0 | F55: =SUMIFS(Lançamentos!$F:$F,Lançamentos!$A:$A,F$19,Lançamentos!$C:$C,"Software e Assinaturas") -> 0 | G55: =SUMIFS(Lançamentos!$F:$F,Lançamentos!$A:$A,G$19,Lançamentos!$C:$C,"Software e Assinaturas") -> 0 | H55: =SUMIFS(Lançamentos!$F:$F,Lançamentos!$A:$A,H$19,Lançamentos!$C:$C,"Software e Assinaturas") -> 0 | I55: =SUMIFS(Lançamentos!$F:$F,Lançamentos!$A:$A,I$19,Lançamentos!$C:$C,"Software e Assinaturas") -> 0 | ... IL55: =SUMIFS(Lançamentos!$F:$F,Lançamentos!$A:$A,IL$19,Lançamentos!$C:$C,"Software e Assinaturas") -> 0
A56: Telefone e Celular | B56: =SUMIFS(Lançamentos!$F:$F,Lançamentos!$A:$A,B$19,Lançamentos!$C:$C,"Telefone e Celular") -> 0 | C56: =SUMIFS(Lançamentos!$F:$F,Lançamentos!$A:$A,C$19,Lançamentos!$C:$C,"Telefone e Celular") -> 0 | D56: =SUMIFS(Lançamentos!$F:$F,Lançamentos!$A:$A,D$19,Lançamentos!$C:$C,"Telefone e Celular") -> 0 | E56: =SUMIFS(Lançamentos!$F:$F,Lançamentos!$A:$A,E$19,Lançamentos!$C:$C,"Telefone e Celular") -> 0 | F56: =SUMIFS(Lançamentos!$F:$F,Lançamentos!$A:$A,F$19,Lançamentos!$C:$C,"Telefone e Celular") -> 0 | G56: =SUMIFS(Lançamentos!$F:$F,Lançamentos!$A:$A,G$19,Lançamentos!$C:$C,"Telefone e Celular") -> 0 | H56: =SUMIFS(Lançamentos!$F:$F,Lançamentos!$A:$A,H$19,Lançamentos!$C:$C,"Telefone e Celular") -> 0 | I56: =SUMIFS(Lançamentos!$F:$F,Lançamentos!$A:$A,I$19,Lançamentos!$C:$C,"Telefone e Celular") -> 0 | ... IL56: =SUMIFS(Lançamentos!$F:$F,Lançamentos!$A:$A,IL$19,Lançamentos!$C:$C,"Telefone e Celular") -> 0
A57: Limpeza e Conservação | B57: =SUMIFS(Lançamentos!$F:$F,Lançamentos!$A:$A,B$19,Lançamentos!$C:$C,"Limpeza e Conservação") -> 0 | C57: =SUMIFS(Lançamentos!$F:$F,Lançamentos!$A:$A,C$19,Lançamentos!$C:$C,"Limpeza e Conservação") -> 0 | D57: =SUMIFS(Lançamentos!$F:$F,Lançamentos!$A:$A,D$19,Lançamentos!$C:$C,"Limpeza e Conservação") -> 0 | E57: =SUMIFS(Lançamentos!$F:$F,Lançamentos!$A:$A,E$19,Lançamentos!$C:$C,"Limpeza e Conservação") -> 0 | F57: =SUMIFS(Lançamentos!$F:$F,Lançamentos!$A:$A,F$19,Lançamentos!$C:$C,"Limpeza e Conservação") -> 0 | G57: =SUMIFS(Lançamentos!$F:$F,Lançamentos!$A:$A,G$19,Lançamentos!$C:$C,"Limpeza e Conservação") -> 0 | H57: =SUMIFS(Lançamentos!$F:$F,Lançamentos!$A:$A,H$19,Lançamentos!$C:$C,"Limpeza e Conservação") -> 0 | I57: =SUMIFS(Lançamentos!$F:$F,Lançamentos!$A:$A,I$19,Lançamentos!$C:$C,"Limpeza e Conservação") -> 0 | ... IL57: =SUMIFS(Lançamentos!$F:$F,Lançamentos!$A:$A,IL$19,Lançamentos!$C:$C,"Limpeza e Conservação") -> 0
A58: Seguros | B58: =SUMIFS(Lançamentos!$F:$F,Lançamentos!$A:$A,B$19,Lançamentos!$C:$C,"Seguros") -> 0 | C58: =SUMIFS(Lançamentos!$F:$F,Lançamentos!$A:$A,C$19,Lançamentos!$C:$C,"Seguros") -> 0 | D58: =SUMIFS(Lançamentos!$F:$F,Lançamentos!$A:$A,D$19,Lançamentos!$C:$C,"Seguros") -> 0 | E58: =SUMIFS(Lançamentos!$F:$F,Lançamentos!$A:$A,E$19,Lançamentos!$C:$C,"Seguros") -> 0 | F58: =SUMIFS(Lançamentos!$F:$F,Lançamentos!$A:$A,F$19,Lançamentos!$C:$C,"Seguros") -> 0 | G58: =SUMIFS(Lançamentos!$F:$F,Lançamentos!$A:$A,G$19,Lançamentos!$C:$C,"Seguros") -> 0 | H58: =SUMIFS(Lançamentos!$F:$F,Lançamentos!$A:$A,H$19,Lançamentos!$C:$C,"Seguros") -> 0 | I58: =SUMIFS(Lançamentos!$F:$F,Lançamentos!$A:$A,I$19,Lançamentos!$C:$C,"Seguros") -> 0 | ... IL58: =SUMIFS(Lançamentos!$F:$F,Lançamentos!$A:$A,IL$19,Lançamentos!$C:$C,"Seguros") -> 0
A59: Treinamento e Capacitação | B59: =SUMIFS(Lançamentos!$F:$F,Lançamentos!$A:$A,B$19,Lançamentos!$C:$C,"Treinamento e Capacitação") -> 0 | C59: =SUMIFS(Lançamentos!$F:$F,Lançamentos!$A:$A,C$19,Lançamentos!$C:$C,"Treinamento e Capacitação") -> 0 | D59: =SUMIFS(Lançamentos!$F:$F,Lançamentos!$A:$A,D$19,Lançamentos!$C:$C,"Treinamento e Capacitação") -> 0 | E59: =SUMIFS(Lançamentos!$F:$F,Lançamentos!$A:$A,E$19,Lançamentos!$C:$C,"Treinamento e Capacitação") -> 0 | F59: =SUMIFS(Lançamentos!$F:$F,Lançamentos!$A:$A,F$19,Lançamentos!$C:$C,"Treinamento e Capacitação") -> 0 | G59: =SUMIFS(Lançamentos!$F:$F,Lançamentos!$A:$A,G$19,Lançamentos!$C:$C,"Treinamento e Capacitação") -> 0 | H59: =SUMIFS(Lançamentos!$F:$F,Lançamentos!$A:$A,H$19,Lançamentos!$C:$C,"Treinamento e Capacitação") -> 0 | I59: =SUMIFS(Lançamentos!$F:$F,Lançamentos!$A:$A,I$19,Lançamentos!$C:$C,"Treinamento e Capacitação") -> 0 | ... IL59: =SUMIFS(Lançamentos!$F:$F,Lançamentos!$A:$A,IL$19,Lançamentos!$C:$C,"Treinamento e Capacitação") -> 0
A60: Honorários Contábeis | B60: =SUMIFS(Lançamentos!$F:$F,Lançamentos!$A:$A,B$19,Lançamentos!$C:$C,"Honorários Contábeis") -> 0 | C60: =SUMIFS(Lançamentos!$F:$F,Lançamentos!$A:$A,C$19,Lançamentos!$C:$C,"Honorários Contábeis") -> 0 | D60: =SUMIFS(Lançamentos!$F:$F,Lançamentos!$A:$A,D$19,Lançamentos!$C:$C,"Honorários Contábeis") -> 0 | E60: =SUMIFS(Lançamentos!$F:$F,Lançamentos!$A:$A,E$19,Lançamentos!$C:$C,"Honorários Contábeis") -> 0 | F60: =SUMIFS(Lançamentos!$F:$F,Lançamentos!$A:$A,F$19,Lançamentos!$C:$C,"Honorários Contábeis") -> 0 | G60: =SUMIFS(Lançamentos!$F:$F,Lançamentos!$A:$A,G$19,Lançamentos!$C:$C,"Honorários Contábeis") -> 0 | H60: =SUMIFS(Lançamentos!$F:$F,Lançamentos!$A:$A,H$19,Lançamentos!$C:$C,"Honorários Contábeis") -> 0 | I60: =SUMIFS(Lançamentos!$F:$F,Lançamentos!$A:$A,I$19,Lançamentos!$C:$C,"Honorários Contábeis") -> 0 | ... IL60: =SUMIFS(Lançamentos!$F:$F,Lançamentos!$A:$A,IL$19,Lançamentos!$C:$C,"Honorários Contábeis") -> 0
A61: Honorários Jurídicos | B61: =SUMIFS(Lançamentos!$F:$F,Lançamentos!$A:$A,B$19,Lançamentos!$C:$C,"Honorários Jurídicos") -> 0 | C61: =SUMIFS(Lançamentos!$F:$F,Lançamentos!$A:$A,C$19,Lançamentos!$C:$C,"Honorários Jurídicos") -> 0 | D61: =SUMIFS(Lançamentos!$F:$F,Lançamentos!$A:$A,D$19,Lançamentos!$C:$C,"Honorários Jurídicos") -> 0 | E61: =SUMIFS(Lançamentos!$F:$F,Lançamentos!$A:$A,E$19,Lançamentos!$C:$C,"Honorários Jurídicos") -> 0 | F61: =SUMIFS(Lançamentos!$F:$F,Lançamentos!$A:$A,F$19,Lançamentos!$C:$C,"Honorários Jurídicos") -> 0 | G61: =SUMIFS(Lançamentos!$F:$F,Lançamentos!$A:$A,G$19,Lançamentos!$C:$C,"Honorários Jurídicos") -> 0 | H61: =SUMIFS(Lançamentos!$F:$F,Lançamentos!$A:$A,H$19,Lançamentos!$C:$C,"Honorários Jurídicos") -> 0 | I61: =SUMIFS(Lançamentos!$F:$F,Lançamentos!$A:$A,I$19,Lançamentos!$C:$C,"Honorários Jurídicos") -> 0 | ... IL61: =SUMIFS(Lançamentos!$F:$F,Lançamentos!$A:$A,IL$19,Lançamentos!$C:$C,"Honorários Jurídicos") -> 0
A62: Equipamentos e Informática | B62: =SUMIFS(Lançamentos!$F:$F,Lançamentos!$A:$A,B$19,Lançamentos!$C:$C,"Equipamentos e Informática") -> 0 | C62: =SUMIFS(Lançamentos!$F:$F,Lançamentos!$A:$A,C$19,Lançamentos!$C:$C,"Equipamentos e Informática") -> 0 | D62: =SUMIFS(Lançamentos!$F:$F,Lançamentos!$A:$A,D$19,Lançamentos!$C:$C,"Equipamentos e Informática") -> 0 | E62: =SUMIFS(Lançamentos!$F:$F,Lançamentos!$A:$A,E$19,Lançamentos!$C:$C,"Equipamentos e Informática") -> 0 | F62: =SUMIFS(Lançamentos!$F:$F,Lançamentos!$A:$A,F$19,Lançamentos!$C:$C,"Equipamentos e Informática") -> 0 | G62: =SUMIFS(Lançamentos!$F:$F,Lançamentos!$A:$A,G$19,Lançamentos!$C:$C,"Equipamentos e Informática") -> 0 | H62: =SUMIFS(Lançamentos!$F:$F,Lançamentos!$A:$A,H$19,Lançamentos!$C:$C,"Equipamentos e Informática") -> 0 | I62: =SUMIFS(Lançamentos!$F:$F,Lançamentos!$A:$A,I$19,Lançamentos!$C:$C,"Equipamentos e Informática") -> 0 | ... IL62: =SUMIFS(Lançamentos!$F:$F,Lançamentos!$A:$A,IL$19,Lançamentos!$C:$C,"Equipamentos e Informática") -> 0
A63: Móveis e Utensílios | B63: =SUMIFS(Lançamentos!$F:$F,Lançamentos!$A:$A,B$19,Lançamentos!$C:$C,"Móveis e Utensílios") -> 0 | C63: =SUMIFS(Lançamentos!$F:$F,Lançamentos!$A:$A,C$19,Lançamentos!$C:$C,"Móveis e Utensílios") -> 0 | D63: =SUMIFS(Lançamentos!$F:$F,Lançamentos!$A:$A,D$19,Lançamentos!$C:$C,"Móveis e Utensílios") -> 0 | E63: =SUMIFS(Lançamentos!$F:$F,Lançamentos!$A:$A,E$19,Lançamentos!$C:$C,"Móveis e Utensílios") -> 0 | F63: =SUMIFS(Lançamentos!$F:$F,Lançamentos!$A:$A,F$19,Lançamentos!$C:$C,"Móveis e Utensílios") -> 0 | G63: =SUMIFS(Lançamentos!$F:$F,Lançamentos!$A:$A,G$19,Lançamentos!$C:$C,"Móveis e Utensílios") -> 0 | H63: =SUMIFS(Lançamentos!$F:$F,Lançamentos!$A:$A,H$19,Lançamentos!$C:$C,"Móveis e Utensílios") -> 0 | I63: =SUMIFS(Lançamentos!$F:$F,Lançamentos!$A:$A,I$19,Lançamentos!$C:$C,"Móveis e Utensílios") -> 0 | ... IL63: =SUMIFS(Lançamentos!$F:$F,Lançamentos!$A:$A,IL$19,Lançamentos!$C:$C,"Móveis e Utensílios") -> 0
A64: Refeições e Confraternizações | B64: =SUMIFS(Lançamentos!$F:$F,Lançamentos!$A:$A,B$19,Lançamentos!$C:$C,"Refeições e Confraternizações") -> 0 | C64: =SUMIFS(Lançamentos!$F:$F,Lançamentos!$A:$A,C$19,Lançamentos!$C:$C,"Refeições e Confraternizações") -> 0 | D64: =SUMIFS(Lançamentos!$F:$F,Lançamentos!$A:$A,D$19,Lançamentos!$C:$C,"Refeições e Confraternizações") -> 0 | E64: =SUMIFS(Lançamentos!$F:$F,Lançamentos!$A:$A,E$19,Lançamentos!$C:$C,"Refeições e Confraternizações") -> 0 | F64: =SUMIFS(Lançamentos!$F:$F,Lançamentos!$A:$A,F$19,Lançamentos!$C:$C,"Refeições e Confraternizações") -> 0 | G64: =SUMIFS(Lançamentos!$F:$F,Lançamentos!$A:$A,G$19,Lançamentos!$C:$C,"Refeições e Confraternizações") -> 0 | H64: =SUMIFS(Lançamentos!$F:$F,Lançamentos!$A:$A,H$19,Lançamentos!$C:$C,"Refeições e Confraternizações") -> 0 | I64: =SUMIFS(Lançamentos!$F:$F,Lançamentos!$A:$A,I$19,Lançamentos!$C:$C,"Refeições e Confraternizações") -> 0 | ... IL64: =SUMIFS(Lançamentos!$F:$F,Lançamentos!$A:$A,IL$19,Lançamentos!$C:$C,"Refeições e Confraternizações") -> 0
A65: Correios e Entregas | B65: =SUMIFS(Lançamentos!$F:$F,Lançamentos!$A:$A,B$19,Lançamentos!$C:$C,"Correios e Entregas") -> 0 | C65: =SUMIFS(Lançamentos!$F:$F,Lançamentos!$A:$A,C$19,Lançamentos!$C:$C,"Correios e Entregas") -> 0 | D65: =SUMIFS(Lançamentos!$F:$F,Lançamentos!$A:$A,D$19,Lançamentos!$C:$C,"Correios e Entregas") -> 0 | E65: =SUMIFS(Lançamentos!$F:$F,Lançamentos!$A:$A,E$19,Lançamentos!$C:$C,"Correios e Entregas") -> 0 | F65: =SUMIFS(Lançamentos!$F:$F,Lançamentos!$A:$A,F$19,Lançamentos!$C:$C,"Correios e Entregas") -> 0 | G65: =SUMIFS(Lançamentos!$F:$F,Lançamentos!$A:$A,G$19,Lançamentos!$C:$C,"Correios e Entregas") -> 0 | H65: =SUMIFS(Lançamentos!$F:$F,Lançamentos!$A:$A,H$19,Lançamentos!$C:$C,"Correios e Entregas") -> 0 | I65: =SUMIFS(Lançamentos!$F:$F,Lançamentos!$A:$A,I$19,Lançamentos!$C:$C,"Correios e Entregas") -> 0 | ... IL65: =SUMIFS(Lançamentos!$F:$F,Lançamentos!$A:$A,IL$19,Lançamentos!$C:$C,"Correios e Entregas") -> 0
A66: Taxas e Anuidades | B66: =SUMIFS(Lançamentos!$F:$F,Lançamentos!$A:$A,B$19,Lançamentos!$C:$C,"Taxas e Anuidades") -> 0 | C66: =SUMIFS(Lançamentos!$F:$F,Lançamentos!$A:$A,C$19,Lançamentos!$C:$C,"Taxas e Anuidades") -> 0 | D66: =SUMIFS(Lançamentos!$F:$F,Lançamentos!$A:$A,D$19,Lançamentos!$C:$C,"Taxas e Anuidades") -> 0 | E66: =SUMIFS(Lançamentos!$F:$F,Lançamentos!$A:$A,E$19,Lançamentos!$C:$C,"Taxas e Anuidades") -> 0 | F66: =SUMIFS(Lançamentos!$F:$F,Lançamentos!$A:$A,F$19,Lançamentos!$C:$C,"Taxas e Anuidades") -> 0 | G66: =SUMIFS(Lançamentos!$F:$F,Lançamentos!$A:$A,G$19,Lançamentos!$C:$C,"Taxas e Anuidades") -> 0 | H66: =SUMIFS(Lançamentos!$F:$F,Lançamentos!$A:$A,H$19,Lançamentos!$C:$C,"Taxas e Anuidades") -> 0 | I66: =SUMIFS(Lançamentos!$F:$F,Lançamentos!$A:$A,I$19,Lançamentos!$C:$C,"Taxas e Anuidades") -> 0 | ... IL66: =SUMIFS(Lançamentos!$F:$F,Lançamentos!$A:$A,IL$19,Lançamentos!$C:$C,"Taxas e Anuidades") -> 0
A67: IOF | B67: =SUMIFS(Lançamentos!$F:$F,Lançamentos!$A:$A,B$19,Lançamentos!$C:$C,"IOF") -> 0 | C67: =SUMIFS(Lançamentos!$F:$F,Lançamentos!$A:$A,C$19,Lançamentos!$C:$C,"IOF") -> 0 | D67: =SUMIFS(Lançamentos!$F:$F,Lançamentos!$A:$A,D$19,Lançamentos!$C:$C,"IOF") -> 0 | E67: =SUMIFS(Lançamentos!$F:$F,Lançamentos!$A:$A,E$19,Lançamentos!$C:$C,"IOF") -> 0 | F67: =SUMIFS(Lançamentos!$F:$F,Lançamentos!$A:$A,F$19,Lançamentos!$C:$C,"IOF") -> 0 | G67: =SUMIFS(Lançamentos!$F:$F,Lançamentos!$A:$A,G$19,Lançamentos!$C:$C,"IOF") -> 0 | H67: =SUMIFS(Lançamentos!$F:$F,Lançamentos!$A:$A,H$19,Lançamentos!$C:$C,"IOF") -> 0 | I67: =SUMIFS(Lançamentos!$F:$F,Lançamentos!$A:$A,I$19,Lançamentos!$C:$C,"IOF") -> 0 | ... IL67: =SUMIFS(Lançamentos!$F:$F,Lançamentos!$A:$A,IL$19,Lançamentos!$C:$C,"IOF") -> 0
A68: Cartão de Crédito | B68: =SUMIFS(Lançamentos!$F:$F,Lançamentos!$A:$A,B$19,Lançamentos!$C:$C,"Cartão de Crédito") -> 0 | C68: =SUMIFS(Lançamentos!$F:$F,Lançamentos!$A:$A,C$19,Lançamentos!$C:$C,"Cartão de Crédito") -> 0 | D68: =SUMIFS(Lançamentos!$F:$F,Lançamentos!$A:$A,D$19,Lançamentos!$C:$C,"Cartão de Crédito") -> 0 | E68: =SUMIFS(Lançamentos!$F:$F,Lançamentos!$A:$A,E$19,Lançamentos!$C:$C,"Cartão de Crédito") -> 0 | F68: =SUMIFS(Lançamentos!$F:$F,Lançamentos!$A:$A,F$19,Lançamentos!$C:$C,"Cartão de Crédito") -> 0 | G68: =SUMIFS(Lançamentos!$F:$F,Lançamentos!$A:$A,G$19,Lançamentos!$C:$C,"Cartão de Crédito") -> 0 | H68: =SUMIFS(Lançamentos!$F:$F,Lançamentos!$A:$A,H$19,Lançamentos!$C:$C,"Cartão de Crédito") -> 0 | I68: =SUMIFS(Lançamentos!$F:$F,Lançamentos!$A:$A,I$19,Lançamentos!$C:$C,"Cartão de Crédito") -> 0 | ... IL68: =SUMIFS(Lançamentos!$F:$F,Lançamentos!$A:$A,IL$19,Lançamentos!$C:$C,"Cartão de Crédito") -> 0
A69: Multas e Juros | B69: =SUMIFS(Lançamentos!$F:$F,Lançamentos!$A:$A,B$19,Lançamentos!$C:$C,"Multas e Juros") -> 0 | C69: =SUMIFS(Lançamentos!$F:$F,Lançamentos!$A:$A,C$19,Lançamentos!$C:$C,"Multas e Juros") -> 0 | D69: =SUMIFS(Lançamentos!$F:$F,Lançamentos!$A:$A,D$19,Lançamentos!$C:$C,"Multas e Juros") -> 0 | E69: =SUMIFS(Lançamentos!$F:$F,Lançamentos!$A:$A,E$19,Lançamentos!$C:$C,"Multas e Juros") -> 0 | F69: =SUMIFS(Lançamentos!$F:$F,Lançamentos!$A:$A,F$19,Lançamentos!$C:$C,"Multas e Juros") -> 0 | G69: =SUMIFS(Lançamentos!$F:$F,Lançamentos!$A:$A,G$19,Lançamentos!$C:$C,"Multas e Juros") -> 0 | H69: =SUMIFS(Lançamentos!$F:$F,Lançamentos!$A:$A,H$19,Lançamentos!$C:$C,"Multas e Juros") -> 0 | I69: =SUMIFS(Lançamentos!$F:$F,Lançamentos!$A:$A,I$19,Lançamentos!$C:$C,"Multas e Juros") -> 0 | ... IL69: =SUMIFS(Lançamentos!$F:$F,Lançamentos!$A:$A,IL$19,Lançamentos!$C:$C,"Multas e Juros") -> 0
A70: Pagamento de Fornecedores | B70: =SUMIFS(Lançamentos!$F:$F,Lançamentos!$A:$A,B$19,Lançamentos!$C:$C,"Pagamento de Fornecedores") -> 0 | C70: =SUMIFS(Lançamentos!$F:$F,Lançamentos!$A:$A,C$19,Lançamentos!$C:$C,"Pagamento de Fornecedores") -> 0 | D70: =SUMIFS(Lançamentos!$F:$F,Lançamentos!$A:$A,D$19,Lançamentos!$C:$C,"Pagamento de Fornecedores") -> 0 | E70: =SUMIFS(Lançamentos!$F:$F,Lançamentos!$A:$A,E$19,Lançamentos!$C:$C,"Pagamento de Fornecedores") -> 0 | F70: =SUMIFS(Lançamentos!$F:$F,Lançamentos!$A:$A,F$19,Lançamentos!$C:$C,"Pagamento de Fornecedores") -> 0 | G70: =SUMIFS(Lançamentos!$F:$F,Lançamentos!$A:$A,G$19,Lançamentos!$C:$C,"Pagamento de Fornecedores") -> 0 | H70: =SUMIFS(Lançamentos!$F:$F,Lançamentos!$A:$A,H$19,Lançamentos!$C:$C,"Pagamento de Fornecedores") -> 0 | I70: =SUMIFS(Lançamentos!$F:$F,Lançamentos!$A:$A,I$19,Lançamentos!$C:$C,"Pagamento de Fornecedores") -> 0 | ... IL70: =SUMIFS(Lançamentos!$F:$F,Lançamentos!$A:$A,IL$19,Lançamentos!$C:$C,"Pagamento de Fornecedores") -> 0
A71: Retirada de Sócios | B71: =SUMIFS(Lançamentos!$F:$F,Lançamentos!$A:$A,B$19,Lançamentos!$C:$C,"Retirada de Sócios") -> 0 | C71: =SUMIFS(Lançamentos!$F:$F,Lançamentos!$A:$A,C$19,Lançamentos!$C:$C,"Retirada de Sócios") -> 0 | D71: =SUMIFS(Lançamentos!$F:$F,Lançamentos!$A:$A,D$19,Lançamentos!$C:$C,"Retirada de Sócios") -> 0 | E71: =SUMIFS(Lançamentos!$F:$F,Lançamentos!$A:$A,E$19,Lançamentos!$C:$C,"Retirada de Sócios") -> 0 | F71: =SUMIFS(Lançamentos!$F:$F,Lançamentos!$A:$A,F$19,Lançamentos!$C:$C,"Retirada de Sócios") -> 0 | G71: =SUMIFS(Lançamentos!$F:$F,Lançamentos!$A:$A,G$19,Lançamentos!$C:$C,"Retirada de Sócios") -> 0 | H71: =SUMIFS(Lançamentos!$F:$F,Lançamentos!$A:$A,H$19,Lançamentos!$C:$C,"Retirada de Sócios") -> 0 | I71: =SUMIFS(Lançamentos!$F:$F,Lançamentos!$A:$A,I$19,Lançamentos!$C:$C,"Retirada de Sócios") -> 0 | ... IL71: =SUMIFS(Lançamentos!$F:$F,Lançamentos!$A:$A,IL$19,Lançamentos!$C:$C,"Retirada de Sócios") -> 0
A72: INSS / FGTS | B72: =SUMIFS(Lançamentos!$F:$F,Lançamentos!$A:$A,B$19,Lançamentos!$C:$C,"INSS / FGTS") -> 0 | C72: =SUMIFS(Lançamentos!$F:$F,Lançamentos!$A:$A,C$19,Lançamentos!$C:$C,"INSS / FGTS") -> 0 | D72: =SUMIFS(Lançamentos!$F:$F,Lançamentos!$A:$A,D$19,Lançamentos!$C:$C,"INSS / FGTS") -> 0 | E72: =SUMIFS(Lançamentos!$F:$F,Lançamentos!$A:$A,E$19,Lançamentos!$C:$C,"INSS / FGTS") -> 0 | F72: =SUMIFS(Lançamentos!$F:$F,Lançamentos!$A:$A,F$19,Lançamentos!$C:$C,"INSS / FGTS") -> 0 | G72: =SUMIFS(Lançamentos!$F:$F,Lançamentos!$A:$A,G$19,Lançamentos!$C:$C,"INSS / FGTS") -> 0 | H72: =SUMIFS(Lançamentos!$F:$F,Lançamentos!$A:$A,H$19,Lançamentos!$C:$C,"INSS / FGTS") -> 0 | I72: =SUMIFS(Lançamentos!$F:$F,Lançamentos!$A:$A,I$19,Lançamentos!$C:$C,"INSS / FGTS") -> 0 | ... IL72: =SUMIFS(Lançamentos!$F:$F,Lançamentos!$A:$A,IL$19,Lançamentos!$C:$C,"INSS / FGTS") -> 0
A73: Simples Nacional / DAS | B73: =SUMIFS(Lançamentos!$F:$F,Lançamentos!$A:$A,B$19,Lançamentos!$C:$C,"Simples Nacional / DAS") -> 0 | C73: =SUMIFS(Lançamentos!$F:$F,Lançamentos!$A:$A,C$19,Lançamentos!$C:$C,"Simples Nacional / DAS") -> 0 | D73: =SUMIFS(Lançamentos!$F:$F,Lançamentos!$A:$A,D$19,Lançamentos!$C:$C,"Simples Nacional / DAS") -> 0 | E73: =SUMIFS(Lançamentos!$F:$F,Lançamentos!$A:$A,E$19,Lançamentos!$C:$C,"Simples Nacional / DAS") -> 0 | F73: =SUMIFS(Lançamentos!$F:$F,Lançamentos!$A:$A,F$19,Lançamentos!$C:$C,"Simples Nacional / DAS") -> 0 | G73: =SUMIFS(Lançamentos!$F:$F,Lançamentos!$A:$A,G$19,Lançamentos!$C:$C,"Simples Nacional / DAS") -> 0 | H73: =SUMIFS(Lançamentos!$F:$F,Lançamentos!$A:$A,H$19,Lançamentos!$C:$C,"Simples Nacional / DAS") -> 0 | I73: =SUMIFS(Lançamentos!$F:$F,Lançamentos!$A:$A,I$19,Lançamentos!$C:$C,"Simples Nacional / DAS") -> 0 | ... IL73: =SUMIFS(Lançamentos!$F:$F,Lançamentos!$A:$A,IL$19,Lançamentos!$C:$C,"Simples Nacional / DAS") -> 0
A74: ISS | B74: =SUMIFS(Lançamentos!$F:$F,Lançamentos!$A:$A,B$19,Lançamentos!$C:$C,"ISS") -> 0 | C74: =SUMIFS(Lançamentos!$F:$F,Lançamentos!$A:$A,C$19,Lançamentos!$C:$C,"ISS") -> 0 | D74: =SUMIFS(Lançamentos!$F:$F,Lançamentos!$A:$A,D$19,Lançamentos!$C:$C,"ISS") -> 0 | E74: =SUMIFS(Lançamentos!$F:$F,Lançamentos!$A:$A,E$19,Lançamentos!$C:$C,"ISS") -> 0 | F74: =SUMIFS(Lançamentos!$F:$F,Lançamentos!$A:$A,F$19,Lançamentos!$C:$C,"ISS") -> 0 | G74: =SUMIFS(Lançamentos!$F:$F,Lançamentos!$A:$A,G$19,Lançamentos!$C:$C,"ISS") -> 0 | H74: =SUMIFS(Lançamentos!$F:$F,Lançamentos!$A:$A,H$19,Lançamentos!$C:$C,"ISS") -> 0 | I74: =SUMIFS(Lançamentos!$F:$F,Lançamentos!$A:$A,I$19,Lançamentos!$C:$C,"ISS") -> 0 | ... IL74: =SUMIFS(Lançamentos!$F:$F,Lançamentos!$A:$A,IL$19,Lançamentos!$C:$C,"ISS") -> 0
A75: ICMS | B75: =SUMIFS(Lançamentos!$F:$F,Lançamentos!$A:$A,B$19,Lançamentos!$C:$C,"ICMS") -> 0 | C75: =SUMIFS(Lançamentos!$F:$F,Lançamentos!$A:$A,C$19,Lançamentos!$C:$C,"ICMS") -> 0 | D75: =SUMIFS(Lançamentos!$F:$F,Lançamentos!$A:$A,D$19,Lançamentos!$C:$C,"ICMS") -> 0 | E75: =SUMIFS(Lançamentos!$F:$F,Lançamentos!$A:$A,E$19,Lançamentos!$C:$C,"ICMS") -> 0 | F75: =SUMIFS(Lançamentos!$F:$F,Lançamentos!$A:$A,F$19,Lançamentos!$C:$C,"ICMS") -> 0 | G75: =SUMIFS(Lançamentos!$F:$F,Lançamentos!$A:$A,G$19,Lançamentos!$C:$C,"ICMS") -> 0 | H75: =SUMIFS(Lançamentos!$F:$F,Lançamentos!$A:$A,H$19,Lançamentos!$C:$C,"ICMS") -> 0 | I75: =SUMIFS(Lançamentos!$F:$F,Lançamentos!$A:$A,I$19,Lançamentos!$C:$C,"ICMS") -> 0 | ... IL75: =SUMIFS(Lançamentos!$F:$F,Lançamentos!$A:$A,IL$19,Lançamentos!$C:$C,"ICMS") -> 0
A76: PIS/COFINS | B76: =SUMIFS(Lançamentos!$F:$F,Lançamentos!$A:$A,B$19,Lançamentos!$C:$C,"PIS/COFINS") -> 0 | C76: =SUMIFS(Lançamentos!$F:$F,Lançamentos!$A:$A,C$19,Lançamentos!$C:$C,"PIS/COFINS") -> 0 | D76: =SUMIFS(Lançamentos!$F:$F,Lançamentos!$A:$A,D$19,Lançamentos!$C:$C,"PIS/COFINS") -> 0 | E76: =SUMIFS(Lançamentos!$F:$F,Lançamentos!$A:$A,E$19,Lançamentos!$C:$C,"PIS/COFINS") -> 0 | F76: =SUMIFS(Lançamentos!$F:$F,Lançamentos!$A:$A,F$19,Lançamentos!$C:$C,"PIS/COFINS") -> 0 | G76: =SUMIFS(Lançamentos!$F:$F,Lançamentos!$A:$A,G$19,Lançamentos!$C:$C,"PIS/COFINS") -> 0 | H76: =SUMIFS(Lançamentos!$F:$F,Lançamentos!$A:$A,H$19,Lançamentos!$C:$C,"PIS/COFINS") -> 0 | I76: =SUMIFS(Lançamentos!$F:$F,Lançamentos!$A:$A,I$19,Lançamentos!$C:$C,"PIS/COFINS") -> 0 | ... IL76: =SUMIFS(Lançamentos!$F:$F,Lançamentos!$A:$A,IL$19,Lançamentos!$C:$C,"PIS/COFINS") -> 0
A77: TOTAL SAÍDAS | B77: =SUM(B35:B76) -> 0 | C77: =SUM(C35:C76) -> 0 | D77: =SUM(D35:D76) -> 0 | E77: =SUM(E35:E76) -> 0 | F77: =SUM(F35:F76) -> 0 | G77: =SUM(G35:G76) -> 0 | H77: =SUM(H35:H76) -> 0 | I77: =SUM(I35:I76) -> 0 | ... IL77: =SUM(IL35:IL76) -> 0
A78: FLUXO DO DIA | B78: =B33+B77 -> 0 | C78: =C33+C77 -> 0 | D78: =D33+D77 -> 0 | E78: =E33+E77 -> 0 | F78: =F33+F77 -> 0 | G78: =G33+G77 -> 0 | H78: =H33+H77 -> 0 | I78: =I33+I77 -> 0 | ... IL78: =IL33+IL77 -> 0
A79: SALDO FINAL DO DIA | B79: =B20+B78 -> 0 | C79: =C20+C78 -> 0 | D79: =D20+D78 -> 0 | E79: =E20+E78 -> 0 | F79: =F20+F78 -> 0 | G79: =G20+G78 -> 0 | H79: =H20+H78 -> 0 | I79: =I20+I78 -> 0 | ... IL79: =IL20+IL78 -> 3166.79
A81: FORECAST DIÁRIO (Mai-Dez)
A82: Data → | B82: =B19 -> 46143 | C82: =C19 -> 46144 | D82: =D19 -> 46145 | E82: =E19 -> 46146 | F82: =F19 -> 46147 | G82: =G19 -> 46148 | H82: =H19 -> 46149 | I82: =I19 -> 46150 | ... IL82: =IL19 -> 46387
A83: SALDO INICIAL DO DIA (Forecast) | B83: =SUM(Categorias!$F$2:$F$4) -> 0 | C83: =B142 -> 0 | D83: =C142 -> 0 | E83: =D142 -> 0 | F83: =E142 -> 0 | G83: =F142 -> 0 | H83: =G142 -> 0 | I83: =H142 -> 0 | J83: =I142 -> 0 | ... IL83: =IK142 -> 0
A84: 💰 RECEITAS PREVISTAS
A85: Vendas de Produtos
A86: Vendas de Serviços
A87: Outras Receitas
A88: Receitas Financeiras
A89: Recebimento de Clientes
A90: Vendas Online
A91: Comissões Recebidas
A92: Aluguel Recebido
A93: Reembolsos
A94: Aporte de Sócios
A95: Empréstimo Recebido
A96: TOTAL ENTRADAS PREVISTAS | B96: =SUM(B85:B95) -> 0 | C96: =SUM(C85:C95) -> 0 | D96: =SUM(D85:D95) -> 0 | E96: =SUM(E85:E95) -> 0 | F96: =SUM(F85:F95) -> 0 | G96: =SUM(G85:G95) -> 0 | H96: =SUM(H85:H95) -> 0 | I96: =SUM(I85:I95) -> 0 | ... IL96: =SUM(IL85:IL95) -> 0
A97: 💸 DESPESAS PREVISTAS
A98: Impostos sobre Vendas
A99: Devoluções
A100: Custo de Mercadoria Vendida
A101: Custo de Serviços Prestados
A102: Salários e Encargos
A103: Aluguel
A104: Água, Luz e Internet
A105: Material de Escritório
A106: Marketing e Publicidade
...

Sheet Dashboard
B2: DASHBOARD FINANCEIRO
B4: FILTROS
B5: Mês Inicial | C5: Mês Final | D5: Categoria | E5: Banco
B6: =DATE(YEAR(TODAY()),1,1) -> 46023 | C6: =DATE(YEAR(TODAY()),12,1) -> 46357 | D6: Todas | E6: Todos
B8: ENTRADAS | C8: SAÍDAS | D8: RESULTADO | E8: SALDO ATUAL
B9: =SUMIFS(Lançamentos!$F:$F,Lançamentos!$H:$H,">="&$B$6,Lançamentos!$H:$H,"<="&$C$6,Lançamentos!$C:$C,IF($D$6="Todas","*",$D$6),Lançamentos!$G:$G,IF($E$6="Todos","*",$E$6),Lançamentos!$D:$D,"Entrada") -> 20878.13 | C9: =SUMIFS(Lançamentos!$F:$F,Lançamentos!$H:$H,">="&$B$6,Lançamentos!$H:$H,"<="&$C$6,Lançamentos!$C:$C,IF($D$6="Todas","*",$D$6),Lançamentos!$G:$G,IF($E$6="Todos","*",$E$6),Lançamentos!$D:$D,"Saída") -> -17711.34 | D9: =B9+C9 -> 3166.79 | E9: =SUM(Categorias!F2:F4)+SUMIFS(Lançamentos!$F:$F,Lançamentos!$H:$H,"<="&$C$6) -> 3166.79
B11: EVOLUÇÃO MENSAL | H11: TOP DESPESAS POR CATEGORIA
B12: Mês | C12: Entradas | D12: Saídas | E12: Resultado | F12: Saldo Acum. | H12: Categoria | I12: Valor | J12: % | L12: Categoria (aux) | M12: Tipo (aux) | N12: Valor (aux)
B13: =IF(EDATE($B$6,0)<=$C$6,EDATE($B$6,0),"") -> 46023 | C13: =IF(B13="","",SUMIFS(Lançamentos!$F:$F,Lançamentos!$H:$H,B13,Lançamentos!$C:$C,IF($D$6="Todas","*",$D$6),Lançamentos!$G:$G,IF($E$6="Todos","*",$E$6),Lançamentos!$D:$D,"Entrada")) -> 0 | D13: =IF(B13="","",SUMIFS(Lançamentos!$F:$F,Lançamentos!$H:$H,B13,Lançamentos!$C:$C,IF($D$6="Todas","*",$D$6),Lançamentos!$G:$G,IF($E$6="Todos","*",$E$6),Lançamentos!$D:$D,"Saída")) -> 0 | E13: =IF(B13="","",C13+D13) -> 0 | F13: =IF(B13="","",SUM(Categorias!F2:F4)+E13) -> 0 | H13: =IFERROR(INDEX($L$13:$L$65,MATCH(I13,$N$13:$N$65,0)),"") -> Pagamento de Fornecedores | I13: {=IFERROR(SMALL(IF(($M$13:$M$65="Saída")*($N$13:$N$65<0),$N$13:$N$65),1),"")} -> -14865.69 | J13: =IFERROR(I13/SUMIFS($N$13:$N$65,$M$13:$M$65,"Saída"),0) -> 0.83933175 | L13: =Categorias!A2 -> Vendas de Produtos | M13: =Categorias!B2 -> Entrada | N13: =SUMIFS(Lançamentos!$F:$F,Lançamentos!$H:$H,">="&$B$6,Lançamentos!$H:$H,"<="&$C$6,Lançamentos!$C:$C,L13,Lançamentos!$G:$G,IF($E$6="Todos","*",$E$6)) -> 20878.13
B14: =IF(EDATE($B$6,1)<=$C$6,EDATE($B$6,1),"") -> 46054 | C14: =IF(B14="","",SUMIFS(Lançamentos!$F:$F,Lançamentos!$H:$H,B14,Lançamentos!$C:$C,IF($D$6="Todas","*",$D$6),Lançamentos!$G:$G,IF($E$6="Todos","*",$E$6),Lançamentos!$D:$D,"Entrada")) -> 0 | D14: =IF(B14="","",SUMIFS(Lançamentos!$F:$F,Lançamentos!$H:$H,B14,Lançamentos!$C:$C,IF($D$6="Todas","*",$D$6),Lançamentos!$G:$G,IF($E$6="Todos","*",$E$6),Lançamentos!$D:$D,"Saída")) -> 0 | E14: =IF(B14="","",C14+D14) -> 0 | F14: =IF(B14="","",F13+E14) -> 0 | H14: =IFERROR(INDEX($L$13:$L$65,MATCH(I14,$N$13:$N$65,0)),"") -> Aluguel | I14: {=IFERROR(SMALL(IF(($M$13:$M$65="Saída")*($N$13:$N$65<0),$N$13:$N$65),2),"")} -> -2474.18 | J14: =IFERROR(I14/SUMIFS($N$13:$N$65,$M$13:$M$65,"Saída"),0) -> 0.13969468 | L14: =Categorias!A3 -> Vendas de Serviços | M14: =Categorias!B3 -> Entrada | N14: =SUMIFS(Lançamentos!$F:$F,Lançamentos!$H:$H,">="&$B$6,Lançamentos!$H:$H,"<="&$C$6,Lançamentos!$C:$C,L14,Lançamentos!$G:$G,IF($E$6="Todos","*",$E$6)) -> 0
B15: =IF(EDATE($B$6,2)<=$C$6,EDATE($B$6,2),"") -> 46082 | C15: =IF(B15="","",SUMIFS(Lançamentos!$F:$F,Lançamentos!$H:$H,B15,Lançamentos!$C:$C,IF($D$6="Todas","*",$D$6),Lançamentos!$G:$G,IF($E$6="Todos","*",$E$6),Lançamentos!$D:$D,"Entrada")) -> 0 | D15: =IF(B15="","",SUMIFS(Lançamentos!$F:$F,Lançamentos!$H:$H,B15,Lançamentos!$C:$C,IF($D$6="Todas","*",$D$6),Lançamentos!$G:$G,IF($E$6="Todos","*",$E$6),Lançamentos!$D:$D,"Saída")) -> 0 | E15: =IF(B15="","",C15+D15) -> 0 | F15: =IF(B15="","",F14+E15) -> 0 | H15: =IFERROR(INDEX($L$13:$L$65,MATCH(I15,$N$13:$N$65,0)),"") -> Seguros | I15: {=IFERROR(SMALL(IF(($M$13:$M$65="Saída")*($N$13:$N$65<0),$N$13:$N$65),3),"")} -> -356.9 | J15: =IFERROR(I15/SUMIFS($N$13:$N$65,$M$13:$M$65,"Saída"),0) -> 0.020150932 | L15: =Categorias!A4 -> Outras Receitas | M15: =Categorias!B4 -> Entrada | N15: =SUMIFS(Lançamentos!$F:$F,Lançamentos!$H:$H,">="&$B$6,Lançamentos!$H:$H,"<="&$C$6,Lançamentos!$C:$C,L15,Lançamentos!$G:$G,IF($E$6="Todos","*",$E$6)) -> 0
B16: =IF(EDATE($B$6,3)<=$C$6,EDATE($B$6,3),"") -> 46113 | C16: =IF(B16="","",SUMIFS(Lançamentos!$F:$F,Lançamentos!$H:$H,B16,Lançamentos!$C:$C,IF($D$6="Todas","*",$D$6),Lançamentos!$G:$G,IF($E$6="Todos","*",$E$6),Lançamentos!$D:$D,"Entrada")) -> 0 | D16: =IF(B16="","",SUMIFS(Lançamentos!$F:$F,Lançamentos!$H:$H,B16,Lançamentos!$C:$C,IF($D$6="Todas","*",$D$6),Lançamentos!$G:$G,IF($E$6="Todos","*",$E$6),Lançamentos!$D:$D,"Saída")) -> 0 | E16: =IF(B16="","",C16+D16) -> 0 | F16: =IF(B16="","",F15+E16) -> 0 | H16: =IFERROR(INDEX($L$13:$L$65,MATCH(I16,$N$13:$N$65,0)),"") -> Juros e Tarifas Bancárias | I16: {=IFERROR(SMALL(IF(($M$13:$M$65="Saída")*($N$13:$N$65<0),$N$13:$N$65),4),"")} -> -14.57 | J16: =IFERROR(I16/SUMIFS($N$13:$N$65,$M$13:$M$65,"Saída"),0) -> 0.0008226368 | L16: =Categorias!A5 -> Impostos sobre Vendas | M16: =Categorias!B5 -> Saída | N16: =SUMIFS(Lançamentos!$F:$F,Lançamentos!$H:$H,">="&$B$6,Lançamentos!$H:$H,"<="&$C$6,Lançamentos!$C:$C,L16,Lançamentos!$G:$G,IF($E$6="Todos","*",$E$6)) -> 0
B17: =IF(EDATE($B$6,4)<=$C$6,EDATE($B$6,4),"") -> 46143 | C17: =IF(B17="","",SUMIFS(Lançamentos!$F:$F,Lançamentos!$H:$H,B17,Lançamentos!$C:$C,IF($D$6="Todas","*",$D$6),Lançamentos!$G:$G,IF($E$6="Todos","*",$E$6),Lançamentos!$D:$D,"Entrada")) -> 0 | D17: =IF(B17="","",SUMIFS(Lançamentos!$F:$F,Lançamentos!$H:$H,B17,Lançamentos!$C:$C,IF($D$6="Todas","*",$D$6),Lançamentos!$G:$G,IF($E$6="Todos","*",$E$6),Lançamentos!$D:$D,"Saída")) -> 0 | E17: =IF(B17="","",C17+D17) -> 0 | F17: =IF(B17="","",F16+E17) -> 0 | H17: =IFERROR(INDEX($L$13:$L$65,MATCH(I17,$N$13:$N$65,0)),"") | I17: {=IFERROR(SMALL(IF(($M$13:$M$65="Saída")*($N$13:$N$65<0),$N$13:$N$65),5),"")} | J17: =IFERROR(I17/SUMIFS($N$13:$N$65,$M$13:$M$65,"Saída"),0) -> 0 | L17: =Categorias!A6 -> Devoluções | M17: =Categorias!B6 -> Saída | N17: =SUMIFS(Lançamentos!$F:$F,Lançamentos!$H:$H,">="&$B$6,Lançamentos!$H:$H,"<="&$C$6,Lançamentos!$C:$C,L17,Lançamentos!$G:$G,IF($E$6="Todos","*",$E$6)) -> 0
B18: =IF(EDATE($B$6,5)<=$C$6,EDATE($B$6,5),"") -> 46174 | C18: =IF(B18="","",SUMIFS(Lançamentos!$F:$F,Lançamentos!$H:$H,B18,Lançamentos!$C:$C,IF($D$6="Todas","*",$D$6),Lançamentos!$G:$G,IF($E$6="Todos","*",$E$6),Lançamentos!$D:$D,"Entrada")) -> 20878.13 | D18: =IF(B18="","",SUMIFS(Lançamentos!$F:$F,Lançamentos!$H:$H,B18,Lançamentos!$C:$C,IF($D$6="Todas","*",$D$6),Lançamentos!$G:$G,IF($E$6="Todos","*",$E$6),Lançamentos!$D:$D,"Saída")) -> -17711.34 | E18: =IF(B18="","",C18+D18) -> 3166.79 | F18: =IF(B18="","",F17+E18) -> 3166.79 | H18: =IFERROR(INDEX($L$13:$L$65,MATCH(I18,$N$13:$N$65,0)),"") | I18: {=IFERROR(SMALL(IF(($M$13:$M$65="Saída")*($N$13:$N$65<0),$N$13:$N$65),6),"")} | J18: =IFERROR(I18/SUMIFS($N$13:$N$65,$M$13:$M$65,"Saída"),0) -> 0 | L18: =Categorias!A7 -> Custo de Mercadoria Vendida | M18: =Categorias!B7 -> Saída | N18: =SUMIFS(Lançamentos!$F:$F,Lançamentos!$H:$H,">="&$B$6,Lançamentos!$H:$H,"<="&$C$6,Lançamentos!$C:$C,L18,Lançamentos!$G:$G,IF($E$6="Todos","*",$E$6)) -> 0
B19: =IF(EDATE($B$6,6)<=$C$6,EDATE($B$6,6),"") -> 46204 | C19: =IF(B19="","",SUMIFS(Lançamentos!$F:$F,Lançamentos!$H:$H,B19,Lançamentos!$C:$C,IF($D$6="Todas","*",$D$6),Lançamentos!$G:$G,IF($E$6="Todos","*",$E$6),Lançamentos!$D:$D,"Entrada")) -> 0 | D19: =IF(B19="","",SUMIFS(Lançamentos!$F:$F,Lançamentos!$H:$H,B19,Lançamentos!$C:$C,IF($D$6="Todas","*",$D$6),Lançamentos!$G:$G,IF($E$6="Todos","*",$E$6),Lançamentos!$D:$D,"Saída")) -> 0 | E19: =IF(B19="","",C19+D19) -> 0 | F19: =IF(B19="","",F18+E19) -> 3166.79 | H19: =IFERROR(INDEX($L$13:$L$65,MATCH(I19,$N$13:$N$65,0)),"") | I19: {=IFERROR(SMALL(IF(($M$13:$M$65="Saída")*($N$13:$N$65<0),$N$13:$N$65),7),"")} | J19: =IFERROR(I19/SUMIFS($N$13:$N$65,$M$13:$M$65,"Saída"),0) -> 0 | L19: =Categorias!A8 -> Custo de Serviços Prestados | M19: =Categorias!B8 -> Saída | N19: =SUMIFS(Lançamentos!$F:$F,Lançamentos!$H:$H,">="&$B$6,Lançamentos!$H:$H,"<="&$C$6,Lançamentos!$C:$C,L19,Lançamentos!$G:$G,IF($E$6="Todos","*",$E$6)) -> 0
B20: =IF(EDATE($B$6,7)<=$C$6,EDATE($B$6,7),"") -> 46235 | C20: =IF(B20="","",SUMIFS(Lançamentos!$F:$F,Lançamentos!$H:$H,B20,Lançamentos!$C:$C,IF($D$6="Todas","*",$D$6),Lançamentos!$G:$G,IF($E$6="Todos","*",$E$6),Lançamentos!$D:$D,"Entrada")) -> 0 | D20: =IF(B20="","",SUMIFS(Lançamentos!$F:$F,Lançamentos!$H:$H,B20,Lançamentos!$C:$C,IF($D$6="Todas","*",$D$6),Lançamentos!$G:$G,IF($E$6="Todos","*",$E$6),Lançamentos!$D:$D,"Saída")) -> 0 | E20: =IF(B20="","",C20+D20) -> 0 | F20: =IF(B20="","",F19+E20) -> 3166.79 | H20: =IFERROR(INDEX($L$13:$L$65,MATCH(I20,$N$13:$N$65,0)),"") | I20: {=IFERROR(SMALL(IF(($M$13:$M$65="Saída")*($N$13:$N$65<0),$N$13:$N$65),8),"")} | J20: =IFERROR(I20/SUMIFS($N$13:$N$65,$M$13:$M$65,"Saída"),0) -> 0 | L20: =Categorias!A9 -> Salários e Encargos | M20: =Categorias!B9 -> Saída | N20: =SUMIFS(Lançamentos!$F:$F,Lançamentos!$H:$H,">="&$B$6,Lançamentos!$H:$H,"<="&$C$6,Lançamentos!$C:$C,L20,Lançamentos!$G:$G,IF($E$6="Todos","*",$E$6)) -> 0
B21: =IF(EDATE($B$6,8)<=$C$6,EDATE($B$6,8),"") -> 46266 | C21: =IF(B21="","",SUMIFS(Lançamentos!$F:$F,Lançamentos!$H:$H,B21,Lançamentos!$C:$C,IF($D$6="Todas","*",$D$6),Lançamentos!$G:$G,IF($E$6="Todos","*",$E$6))) -> 0 | D21: =IF(B21="","",SUMIFS(Lançamentos!$F:$F,Lançamentos!$H:$H,B21,Lançamentos!$C:$C,IF($D$6="Todas","*",$D$6),Lançamentos!$G:$G,IF($E$6="Todos","*",$E$6))) -> 0 | E21: =IF(B21="","",C21+D21) -> 0 | F21: =IF(B21="","",F20+E21) -> 3166.79 | H21: =IFERROR(INDEX($L$13:$L$65,MATCH(I21,$N$13:$N$65,0)),"") | I21: {=IFERROR(SMALL(IF(($M$13:$M$65="Saída")*($N$13:$N$65<0),$N$13:$N$65),9),"")} | J21: =IFERROR(I21/SUMIFS($N$13:$N$65,$M$13:$M$65,"Saída"),0) -> 0 | L21: =Categorias!A10 -> Aluguel | M21: =Categorias!B10 -> Saída | N21: =SUMIFS(Lançamentos!$F:$F,Lançamentos!$H:$H,">="&$B$6,Lançamentos!$H:$H,"<="&$C$6,Lançamentos!$C:$C,L21,Lançamentos!$G:$G,IF($E$6="Todos","*",$E$6)) -> -2474.18
B22: =IF(EDATE($B$6,9)<=$C$6,EDATE($B$6,9),"") -> 46296 | C22: =IF(B22="","",SUMIFS(Lançamentos!$F:$F,Lançamentos!$H:$H,B22,Lançamentos!$C:$C,IF($D$6="Todas","*",$D$6),Lançamentos!$G:$G,IF($E$6="Todos","*",$E$6))) -> 0 | D22: =IF(B22="","",SUMIFS(Lançamentos!$F:$F,Lançamentos!$H:$H,B22,Lançamentos!$C:$C,IF($D$6="Todas","*",$D$6),Lançamentos!$G:$G,IF($E$6="Todos","*",$E$6))) -> 0 | E22: =IF(B22="","",C22+D22) -> 0 | F22: =IF(B22="","",F21+E22) -> 3166.79 | H22: =IFERROR(INDEX($L$13:$L$65,MATCH(I22,$N$13:$N$65,0)),"") | I22: {=IFERROR(SMALL(IF(($M$13:$M$65="Saída")*($N$13:$N$65<0),$N$13:$N$65),10),"")} | J22: =IFERROR(I22/SUMIFS($N$13:$N$65,$M$13:$M$65,"Saída"),0) -> 0 | L22: =Categorias!A11 -> Água, Luz e Internet | M22: =Categorias!B11 -> Saída | N22: =SUMIFS(Lançamentos!$F:$F,Lançamentos!$H:$H,">="&$B$6,Lançamentos!$H:$H,"<="&$C$6,Lançamentos!$C:$C,L22,Lançamentos!$G:$G,IF($E$6="Todos","*",$E$6)) -> 0
B23: =IF(EDATE($B$6,10)<=$C$6,EDATE($B$6,10),"") -> 46327 | C23: =IF(B23="","",SUMIFS(Lançamentos!$F:$F,Lançamentos!$H:$H,B23,Lançamentos!$C:$C,IF($D$6="Todas","*",$D$6),Lançamentos!$G:$G,IF($E$6="Todos","*",$E$6))) -> 0 | D23: =IF(B23="","",SUMIFS(Lançamentos!$F:$F,Lançamentos!$H:$H,B23,Lançamentos!$C:$C,IF($D$6="Todas","*",$D$6),Lançamentos!$G:$G,IF($E$6="Todos","*",$E$6))) -> 0 | E23: =IF(B23="","",C23+D23) -> 0 | F23: =IF(B23="","",F22+E23) -> 3166.79 | H23: =IFERROR(INDEX($L$13:$L$65,MATCH(I23,$N$13:$N$65,0)),"") | I23: {=IFERROR(SMALL(IF(($M$13:$M$65="Saída")*($N$13:$N$65<0),$N$13:$N$65),11),"")} | J23: =IFERROR(I23/SUMIFS($N$13:$N$65,$M$13:$M$65,"Saída"),0) -> 0 | L23: =Categorias!A12 -> Material de Escritório | M23: =Categorias!B12 -> Saída | N23: =SUMIFS(Lançamentos!$F:$F,Lançamentos!$H:$H,">="&$B$6,Lançamentos!$H:$H,"<="&$C$6,Lançamentos!$C:$C,L23,Lançamentos!$G:$G,IF($E$6="Todos","*",$E$6)) -> 0
B24: =IF(EDATE($B$6,11)<=$C$6,EDATE($B$6,11),"") -> 46357 | C24: =IF(B24="","",SUMIFS(Lançamentos!$F:$F,Lançamentos!$H:$H,B24,Lançamentos!$C:$C,IF($D$6="Todas","*",$D$6),Lançamentos!$G:$G,IF($E$6="Todos","*",$E$6))) -> 0 | D24: =IF(B24="","",SUMIFS(Lançamentos!$F:$F,Lançamentos!$H:$H,B24,Lançamentos!$C:$C,IF($D$6="Todas","*",$D$6),Lançamentos!$G:$G,IF($E$6="Todos","*",$E$6))) -> 0 | E24: =IF(B24="","",C24+D24) -> 0 | F24: =IF(B24="","",F23+E24) -> 3166.79 | H24: =IFERROR(INDEX($L$13:$L$65,MATCH(I24,$N$13:$N$65,0)),"") | I24: {=IFERROR(SMALL(IF(($M$13:$M$65="Saída")*($N$13:$N$65<0),$N$13:$N$65),12),"")} | J24: =IFERROR(I24/SUMIFS($N$13:$N$65,$M$13:$M$65,"Saída"),0) -> 0 | L24: =Categorias!A13 -> Marketing e Publicidade | M24: =Categorias!B13 -> Saída | N24: =SUMIFS(Lançamentos!$F:$F,Lançamentos!$H:$H,">="&$B$6,Lançamentos!$H:$H,"<="&$C$6,Lançamentos!$C:$C,L24,Lançamentos!$G:$G,IF($E$6="Todos","*",$E$6)) -> 0
H25: TOP RECEITAS POR CATEGORIA | L25: =Categorias!A14 -> Manutenção | M25: =Categorias!B14 -> Saída | N25: =SUMIFS(Lançamentos!$F:$F,Lançamentos!$H:$H,">="&$B$6,Lançamentos!$H:$H,"<="&$C$6,Lançamentos!$C:$C,L25,Lançamentos!$G:$G,IF($E$6="Todos","*",$E$6)) -> 0
H26: Categoria | I26: Valor | J26: % | L26: =Categorias!A15 -> Transporte e Viagens | M26: =Categorias!B15 -> Saída | N26: =SUMIFS(Lançamentos!$F:$F,Lançamentos!$H:$H,">="&$B$6,Lançamentos!$H:$H,"<="&$C$6,Lançamentos!$C:$C,L26,Lançamentos!$G:$G,IF($E$6="Todos","*",$E$6)) -> 0
H27: =IFERROR(INDEX($L$13:$L$65,MATCH(I27,$N$13:$N$65,0)),"") -> Vendas de Produtos | I27: {=IFERROR(LARGE(IF(($M$13:$M$65="Entrada")*($N$13:$N$65>0),$N$13:$N$65),1),"")} -> 20878.13 | J27: =IFERROR(I27/SUMIFS($N$13:$N$65,$M$13:$M$65,"Entrada"),0) -> 1 | L27: =Categorias!A16 -> Serviços de Terceiros | M27: =Categorias!B16 -> Saída | N27: =SUMIFS(Lançamentos!$F:$F,Lançamentos!$H:$H,">="&$B$6,Lançamentos!$H:$H,"<="&$C$6,Lançamentos!$C:$C,L27,Lançamentos!$G:$G,IF($E$6="Todos","*",$E$6)) -> 0
H28: =IFERROR(INDEX($L$13:$L$65,MATCH(I28,$N$13:$N$65,0)),"") | I28: {=IFERROR(LARGE(IF(($M$13:$M$65="Entrada")*($N$13:$N$65>0),$N$13:$N$65),2),"")} | J28: =IFERROR(I28/SUMIFS($N$13:$N$65,$M$13:$M$65,"Entrada"),0) -> 0 | L28: =Categorias!A17 -> Juros e Tarifas Bancárias | M28: =Categorias!B17 -> Saída | N28: =SUMIFS(Lançamentos!$F:$F,Lançamentos!$H:$H,">="&$B$6,Lançamentos!$H:$H,"<="&$C$6,Lançamentos!$C:$C,L28,Lançamentos!$G:$G,IF($E$6="Todos","*",$E$6)) -> -14.57
H29: =IFERROR(INDEX($L$13:$L$65,MATCH(I29,$N$13:$N$65,0)),"") | I29: {=IFERROR(LARGE(IF(($M$13:$M$65="Entrada")*($N$13:$N$65>0),$N$13:$N$65),3),"")} | J29: =IFERROR(I29/SUMIFS($N$13:$N$65,$M$13:$M$65,"Entrada"),0) -> 0 | L29: =Categorias!A18 -> Empréstimos e Financiamentos | M29: =Categorias!B18 -> Saída | N29: =SUMIFS(Lançamentos!$F:$F,Lançamentos!$H:$H,">="&$B$6,Lançamentos!$H:$H,"<="&$C$6,Lançamentos!$C:$C,L29,Lançamentos!$G:$G,IF($E$6="Todos","*",$E$6)) -> 0
H30: =IFERROR(INDEX($L$13:$L$65,MATCH(I30,$N$13:$N$65,0)),"") | I30: {=IFERROR(LARGE(IF(($M$13:$M$65="Entrada")*($N$13:$N$65>0),$N$13:$N$65),4),"")} | J30: =IFERROR(I30/SUMIFS($N$13:$N$65,$M$13:$M$65,"Entrada"),0) -> 0 | L30: =Categorias!A19 -> Receitas Financeiras | M30: =Categorias!B19 -> Entrada | N30: =SUMIFS(Lançamentos!$F:$F,Lançamentos!$H:$H,">="&$B$6,Lançamentos!$H:$H,"<="&$C$6,Lançamentos!$C:$C,L30,Lançamentos!$G:$G,IF($E$6="Todos","*",$E$6)) -> 0
L31: =Categorias!A20 -> Impostos sobre Lucro | M31: =Categorias!B20 -> Saída | N31: =SUMIFS(Lançamentos!$F:$F,Lançamentos!$H:$H,">="&$B$6,Lançamentos!$H:$H,"<="&$C$6,Lançamentos!$C:$C,L31,Lançamentos!$G:$G,IF($E$6="Todos","*",$E$6)) -> 0
L32: =Categorias!A21 -> Recebimento de Clientes | M32: =Categorias!B21 -> Entrada | N32: =SUMIFS(Lançamentos!$F:$F,Lançamentos!$H:$H,">="&$B$6,Lançamentos!$H:$H,"<="&$C$6,Lançamentos!$C:$C,L32,Lançamentos!$G:$G,IF($E$6="Todos","*",$E$6)) -> 0
L33: =Categorias!A22 -> Vendas Online | M33: =Categorias!B22 -> Entrada | N33: =SUMIFS(Lançamentos!$F:$F,Lançamentos!$H:$H,">="&$B$6,Lançamentos!$H:$H,"<="&$C$6,Lançamentos!$C:$C,L33,Lançamentos!$G:$G,IF($E$6="Todos","*",$E$6)) -> 0
L34: =Categorias!A23 -> Comissões Recebidas | M34: =Categorias!B23 -> Entrada | N34: =SUMIFS(Lançamentos!$F:$F,Lançamentos!$H:$H,">="&$B$6,Lançamentos!$H:$H,"<="&$C$6,Lançamentos!$C:$C,L34,Lançamentos!$G:$G,IF($E$6="Todos","*",$E$6)) -> 0
L35: =Categorias!A24 -> Aluguel Recebido | M35: =Categorias!B24 -> Entrada | N35: =SUMIFS(Lançamentos!$F:$F,Lançamentos!$H:$H,">="&$B$6,Lançamentos!$H:$H,"<="&$C$6,Lançamentos!$C:$C,L35,Lançamentos!$G:$G,IF($E$6="Todos","*",$E$6)) -> 0
L36: =Categorias!A25 -> Reembolsos | M36: =Categorias!B25 -> Entrada | N36: =SUMIFS(Lançamentos!$F:$F,Lançamentos!$H:$H,">="&$B$6,Lançamentos!$H:$H,"<="&$C$6,Lançamentos!$C:$C,L36,Lançamentos!$G:$G,IF($E$6="Todos","*",$E$6)) -> 0
L37: =Categorias!A26 -> Aporte de Sócios | M37: =Categorias!B26 -> Entrada | N37: =SUMIFS(Lançamentos!$F:$F,Lançamentos!$H:$H,">="&$B$6,Lançamentos!$H:$H,"<="&$C$6,Lançamentos!$C:$C,L37,Lançamentos!$G:$G,IF($E$6="Todos","*",$E$6)) -> 0
L38: =Categorias!A27 -> Empréstimo Recebido | M38: =Categorias!B27 -> Entrada | N38: =SUMIFS(Lançamentos!$F:$F,Lançamentos!$H:$H,">="&$B$6,Lançamentos!$H:$H,"<="&$C$6,Lançamentos!$C:$C,L38,Lançamentos!$G:$G,IF($E$6="Todos","*",$E$6)) -> 0
L39: =Categorias!A28 -> Frete sobre Vendas | M39: =Categorias!B28 -> Saída | N39: =SUMIFS(Lançamentos!$F:$F,Lançamentos!$H:$H,">="&$B$6,Lançamentos!$H:$H,"<="&$C$6,Lançamentos!$C:$C,L39,Lançamentos!$G:$G,IF($E$6="Todos","*",$E$6)) -> 0
L40: =Categorias!A29 -> Embalagens | M40: =Categorias!B29 -> Saída | N40: =SUMIFS(Lançamentos!$F:$F,Lançamentos!$H:$H,">="&$B$6,Lançamentos!$H:$H,"<="&$C$6,Lançamentos!$C:$C,L40,Lançamentos!$G:$G,IF($E$6="Todos","*",$E$6)) -> 0
L41: =Categorias!A30 -> Combustível | M41: =Categorias!B30 -> Saída | N41: =SUMIFS(Lançamentos!$F:$F,Lançamentos!$H:$H,">="&$B$6,Lançamentos!$H:$H,"<="&$C$6,Lançamentos!$C:$C,L41,Lançamentos!$G:$G,IF($E$6="Todos","*",$E$6)) -> 0
L42: =Categorias!A31 -> Pró-labore | M42: =Categorias!B31 -> Saída | N42: =SUMIFS(Lançamentos!$F:$F,Lançamentos!$H:$H,">="&$B$6,Lançamentos!$H:$H,"<="&$C$6,Lançamentos!$C:$C,L42,Lançamentos!$G:$G,IF($E$6="Todos","*",$E$6)) -> 0
... L65: =Categorias!A54 -> PIS/COFINS | M65: =Categorias!B54 -> Saída | N65: =SUMIFS(Lançamentos!$F:$F,Lançamentos!$H:$H,">="&$B$6,Lançamentos!$H:$H,"<="&$C$6,Lançamentos!$C:$C,L65,Lançamentos!$G:$G,IF($E$6="Todos","*",$E$6)) -> 0

Sheet Realizado vs Forecast
B2: REALIZADO vs FORECAST
B4: FILTROS | J4: DESVIO POR CATEGORIA
B5: Data Inicial | C5: Data Final | D5: Visão | E5: Banco | J5: Categoria | K5: Realizado | L5: Forecast | M5: Desvio
B6: =DATE(2026,6,1) -> 46174 | C6: 46181 | D6: Ano | E6: Todos | J6: Vendas de Produtos | K6: =SUMIFS(Lançamentos!$F:$F,Lançamentos!$A:$A,">="&$B$6,Lançamentos!$A:$A,"<="&$C$6,Lançamentos!$C:$C,J6,Lançamentos!$G:$G,IF($E$6="Todos","*",$E$6)) -> 0 | L6: {=SUMPRODUCT(('Fluxo de Caixa'!$B$82:$IL$82>=$B$6)*('Fluxo de Caixa'!$B$82:$IL$82<=$C$6)*'Fluxo de Caixa'!$B$85:$IL$85)} -> 0 | M6: =K6-L6 -> 0
J7: Vendas de Serviços | K7: =SUMIFS(Lançamentos!$F:$F,Lançamentos!$A:$A,">="&$B$6,Lançamentos!$A:$A,"<="&$C$6,Lançamentos!$C:$C,J7,Lançamentos!$G:$G,IF($E$6="Todos","*",$E$6)) -> 0 | L7: {=SUMPRODUCT(('Fluxo de Caixa'!$B$82:$IL$82>=$B$6)*('Fluxo de Caixa'!$B$82:$IL$82<=$C$6)*'Fluxo de Caixa'!$B$86:$IL$86)} -> 0 | M7: =K7-L7 -> 0
B8: REALIZADO | C8: FORECAST | D8: DESVIO R$ | E8: DESVIO % | J8: Outras Receitas | K8: =SUMIFS(Lançamentos!$F:$F,Lançamentos!$A:$A,">="&$B$6,Lançamentos!$A:$A,"<="&$C$6,Lançamentos!$C:$C,J8,Lançamentos!$G:$G,IF($E$6="Todos","*",$E$6)) -> 0 | L8: {=SUMPRODUCT(('Fluxo de Caixa'!$B$82:$IL$82>=$B$6)*('Fluxo de Caixa'!$B$82:$IL$82<=$C$6)*'Fluxo de Caixa'!$B$87:$IL$87)} -> 0 | M8: =K8-L8 -> 0
A9: Entradas | B9: =SUMIFS(Lançamentos!$F:$F,Lançamentos!$A:$A,">="&$B$6,Lançamentos!$A:$A,"<="&$C$6,Lançamentos!$G:$G,IF($E$6="Todos","*",$E$6),Lançamentos!$D:$D,"Entrada") -> 0 | C9: {=SUMPRODUCT(('Fluxo de Caixa'!$B$82:$IL$82>=$B$6)*('Fluxo de Caixa'!$B$82:$IL$82<=$C$6)*'Fluxo de Caixa'!$B$96:$IL$96)} -> 0 | D9: =B9-C9 -> 0 | E9: =IFERROR((B9-C9)/C9,0) -> 0 | J9: Receitas Financeiras | K9: =SUMIFS(Lançamentos!$F:$F,Lançamentos!$A:$A,">="&$B$6,Lançamentos!$A:$A,"<="&$C$6,Lançamentos!$C:$C,J9,Lançamentos!$G:$G,IF($E$6="Todos","*",$E$6)) -> 0 | L9: {=SUMPRODUCT(('Fluxo de Caixa'!$B$82:$IL$82>=$B$6)*('Fluxo de Caixa'!$B$82:$IL$82<=$C$6)*'Fluxo de Caixa'!$B$88:$IL$88)} -> 0 | M9: =K9-L9 -> 0
A10: Saídas | B10: =SUMIFS(Lançamentos!$F:$F,Lançamentos!$A:$A,">="&$B$6,Lançamentos!$A:$A,"<="&$C$6,Lançamentos!$G:$G,IF($E$6="Todos","*",$E$6),Lançamentos!$D:$D,"Saída") -> 0 | C10: {=SUMPRODUCT(('Fluxo de Caixa'!$B$82:$IL$82>=$B$6)*('Fluxo de Caixa'!$B$82:$IL$82<=$C$6)*'Fluxo de Caixa'!$B$140:$IL$140)} -> 0 | D10: =C10-B10 -> 0 | E10: =IFERROR((C10-B10)/C10,0) -> 0 | J10: Recebimento de Clientes | K10: =SUMIFS(Lançamentos!$F:$F,Lançamentos!$A:$A,">="&$B$6,Lançamentos!$A:$A,"<="&$C$6,Lançamentos!$C:$C,J10,Lançamentos!$G:$G,IF($E$6="Todos","*",$E$6)) -> 0 | L10: {=SUMPRODUCT(('Fluxo de Caixa'!$B$82:$IL$82>=$B$6)*('Fluxo de Caixa'!$B$82:$IL$82<=$C$6)*'Fluxo de Caixa'!$B$89:$IL$89)} -> 0 | M10: =K10-L10 -> 0
A11: Resultado | B11: =B9-B10 -> 0 | C11: =C9-C10 -> 0 | D11: =B11-C11 -> 0 | E11: =IFERROR((B11-C11)/ABS(C11),0) -> 0 | J11: Vendas Online | K11: =SUMIFS(Lançamentos!$F:$F,Lançamentos!$A:$A,">="&$B$6,Lançamentos!$A:$A,"<="&$C$6,Lançamentos!$C:$C,J11,Lançamentos!$G:$G,IF($E$6="Todos","*",$E$6)) -> 0 | L11: {=SUMPRODUCT(('Fluxo de Caixa'!$B$82:$IL$82>=$B$6)*('Fluxo de Caixa'!$B$82:$IL$82<=$C$6)*'Fluxo de Caixa'!$B$90:$IL$90)} -> 0 | M11: =K11-L11 -> 0
J12: Comissões Recebidas | K12: =SUMIFS(Lançamentos!$F:$F,Lançamentos!$A:$A,">="&$B$6,Lançamentos!$A:$A,"<="&$C$6,Lançamentos!$C:$C,J12,Lançamentos!$G:$G,IF($E$6="Todos","*",$E$6)) -> 0 | L12: {=SUMPRODUCT(('Fluxo de Caixa'!$B$82:$IL$82>=$B$6)*('Fluxo de Caixa'!$B$82:$IL$82<=$C$6)*'Fluxo de Caixa'!$B$91:$IL$91)} -> 0 | M12: =K12-L12 -> 0
B13: EVOLUÇÃO TEMPORAL (conforme visão) | J13: Aluguel Recebido | K13: =SUMIFS(Lançamentos!$F:$F,Lançamentos!$A:$A,">="&$B$6,Lançamentos!$A:$A,"<="&$C$6,Lançamentos!$C:$C,J13,Lançamentos!$G:$G,IF($E$6="Todos","*",$E$6)) -> 0 | L13: {=SUMPRODUCT(('Fluxo de Caixa'!$B$82:$IL$82>=$B$6)*('Fluxo de Caixa'!$B$82:$IL$82<=$C$6)*'Fluxo de Caixa'!$B$92:$IL$92)} -> 0 | M13: =K13-L13 -> 0
B14: Período | C14: Realizado Entradas | D14: Forecast Entradas | E14: Realizado Saídas | F14: Forecast Saídas | G14: Desvio Resultado | H14: Desvio % | J14: Reembolsos | K14: =SUMIFS(Lançamentos!$F:$F,Lançamentos!$A:$A,">="&$B$6,Lançamentos!$A:$A,"<="&$C$6,Lançamentos!$C:$C,J14,Lançamentos!$G:$G,IF($E$6="Todos","*",$E$6)) -> 0 | L14: {=SUMPRODUCT(('Fluxo de Caixa'!$B$82:$IL$82>=$B$6)*('Fluxo de Caixa'!$B$82:$IL$82<=$C$6)*'Fluxo de Caixa'!$B$93:$IL$93)} -> 0 | M14: =K14-L14 -> 0
B15: =IF($D$6="Dia",$B$6,IF($D$6="Semana",$B$6-WEEKDAY($B$6,2)+1,IF($D$6="Mês",DATE(YEAR($B$6),MONTH($B$6),1),DATE(YEAR($B$6),1,1)))) -> 46023 | C15: =IF(B15="","",SUMIFS(Lançamentos!$F:$F,Lançamentos!$A:$A,">="&B15,Lançamentos!$A:$A,"<="&MIN($C$6,IF($D$6="Dia",B15,IF($D$6="Semana",B15+6,IF($D$6="Mês",EOMONTH(B15,0),DATE(YEAR(B15),12,31))))),Lançamentos!$G:$G,IF($E$6="Todos","*",$E$6),Lançamentos!$D:$D,"Entrada")) -> 0 | D15: {=IF(B15="","",SUMPRODUCT(('Fluxo de Caixa'!$B$82:$IL$82>=B15)*('Fluxo de Caixa'!$B$82:$IL$82<=MIN($C$6,IF($D$6="Dia",B15,IF($D$6="Semana",B15+6,IF($D$6="Mês",EOMONTH(B15,0),DATE(YEAR(B15),12,31))))))*'Fluxo de Caixa'!$B$96:$IL$96))} -> 0 | E15: =IF(B15="","",SUMIFS(Lançamentos!$F:$F,Lançamentos!$A:$A,">="&B15,Lançamentos!$A:$A,"<="&MIN($C$6,IF($D$6="Dia",B15,IF($D$6="Semana",B15+6,IF($D$6="Mês",EOMONTH(B15,0),DATE(YEAR(B15),12,31))))),Lançamentos!$G:$G,IF($E$6="Todos","*",$E$6),Lançamentos!$D:$D,"Saída")) -> 0 | F15: {=IF(B15="","",SUMPRODUCT(('Fluxo de Caixa'!$B$82:$IL$82>=B15)*('Fluxo de Caixa'!$B$82:$IL$82<=MIN($C$6,IF($D$6="Dia",B15,IF($D$6="Semana",B15+6,IF($D$6="Mês",EOMONTH(B15,0),DATE(YEAR(B15),12,31))))))*'Fluxo de Caixa'!$B$140:$IL$140))} -> 0 | G15: =IF(B15="","",(C15-E15)-(D15-F15)) -> 0 | H15: =IF(B15="","",IFERROR(G15/ABS(D15-F15),0)) -> 0 | J15: Aporte de Sócios | K15: =SUMIFS(Lançamentos!$F:$F,Lançamentos!$A:$A,">="&$B$6,Lançamentos!$A:$A,"<="&$C$6,Lançamentos!$C:$C,J15,Lançamentos!$G:$G,IF($E$6="Todos","*",$E$6)) -> 0 | L15: {=SUMPRODUCT(('Fluxo de Caixa'!$B$82:$IL$82>=$B$6)*('Fluxo de Caixa'!$B$82:$IL$82<=$C$6)*'Fluxo de Caixa'!$B$94:$IL$94)} -> 0 | M15: =K15-L15 -> 0
B16: =IF(B15="","",IF($D$6="Dia",IF(B15+1>$C$6,"",B15+1),IF($D$6="Semana",IF(B15+7>$C$6,"",B15+7),IF($D$6="Mês",IF(EDATE(B15,1)>$C$6,"",EDATE(B15,1)),IF(DATE(YEAR(B15)+1,1,1)>$C$6,"",DATE(YEAR(B15)+1,1,1)))))) | C16: =IF(B16="","",SUMIFS(Lançamentos!$F:$F,Lançamentos!$A:$A,">="&B16,Lançamentos!$A:$A,"<="&MIN($C$6,IF($D$6="Dia",B16,IF($D$6="Semana",B16+6,IF($D$6="Mês",EOMONTH(B16,0),DATE(YEAR(B16),12,31))))),Lançamentos!$G:$G,IF($E$6="Todos","*",$E$6),Lançamentos!$D:$D,"Entrada")) | D16: {=IF(B16="","",SUMPRODUCT(('Fluxo de Caixa'!$B$82:$IL$82>=B16)*('Fluxo de Caixa'!$B$82:$IL$82<=MIN($C$6,IF($D$6="Dia",B16,IF($D$6="Semana",B16+6,IF($D$6="Mês",EOMONTH(B16,0),DATE(YEAR(B16),12,31))))))*'Fluxo de Caixa'!$B$96:$IL$96))} | E16: =IF(B16="","",SUMIFS(Lançamentos!$F:$F,Lançamentos!$A:$A,">="&B16,Lançamentos!$A:$A,"<="&MIN($C$6,IF($D$6="Dia",B16,IF($D$6="Semana",B16+6,IF($D$6="Mês",EOMONTH(B16,0),DATE(YEAR(B16),12,31))))),Lançamentos!$G:$G,IF($E$6="Todos","*",$E$6),Lançamentos!$D:$D,"Saída")) | F16: {=IF(B16="","",SUMPRODUCT(('Fluxo de Caixa'!$B$82:$IL$82>=B16)*('Fluxo de Caixa'!$B$82:$IL$82<=MIN($C$6,IF($D$6="Dia",B16,IF($D$6="Semana",B16+6,IF($D$6="Mês",EOMONTH(B16,0),DATE(YEAR(B16),12,31))))))*'Fluxo de Caixa'!$B$140:$IL$140))} | G16: =IF(B16="","",(C16-E16)-(D16-F16)) | H16: =IF(B16="","",IFERROR(G16/ABS(D16-F16),0)) | J16: Empréstimo Recebido | K16: =SUMIFS(Lançamentos!$F:$F,Lançamentos!$A:$A,">="&$B$6,Lançamentos!$A:$A,"<="&$C$6,Lançamentos!$C:$C,J16,Lançamentos!$G:$G,IF($E$6="Todos","*",$E$6)) -> 0 | L16: {=SUMPRODUCT(('Fluxo de Caixa'!$B$82:$IL$82>=$B$6)*('Fluxo de Caixa'!$B$82:$IL$82<=$C$6)*'Fluxo de Caixa'!$B$95:$IL$95)} -> 0 | M16: =K16-L16 -> 0
B17: =IF(B16="","",IF($D$6="Dia",IF(B16+1>$C$6,"",B16+1),IF($D$6="Semana",IF(B16+7>$C$6,"",B16+7),IF($D$6="Mês",IF(EDATE(B16,1)>$C$6,"",EDATE(B16,1)),IF(DATE(YEAR(B16)+1,1,1)>$C$6,"",DATE(YEAR(B16)+1,1,1)))))) | C17: =IF(B17="","",SUMIFS(Lançamentos!$F:$F,Lançamentos!$A:$A,">="&B17,Lançamentos!$A:$A,"<="&MIN($C$6,IF($D$6="Dia",B17,IF($D$6="Semana",B17+6,IF($D$6="Mês",EOMONTH(B17,0),DATE(YEAR(B17),12,31))))),Lançamentos!$G:$G,IF($E$6="Todos","*",$E$6),Lançamentos!$D:$D,"Entrada")) | D17: {=IF(B17="","",SUMPRODUCT(('Fluxo de Caixa'!$B$82:$IL$82>=B17)*('Fluxo de Caixa'!$B$82:$IL$82<=MIN($C$6,IF($D$6="Dia",B17,IF($D$6="Semana",B17+6,IF($D$6="Mês",EOMONTH(B17,0),DATE(YEAR(B17),12,31))))))*'Fluxo de Caixa'!$B$96:$IL$96))} | E17: =IF(B17="","",SUMIFS(Lançamentos!$F:$F,Lançamentos!$A:$A,">="&B17,Lançamentos!$A:$A,"<="&MIN($C$6,IF($D$6="Dia",B17,IF($D$6="Semana",B17+6,IF($D$6="Mês",EOMONTH(B17,0),DATE(YEAR(B17),12,31))))),Lançamentos!$G:$G,IF($E$6="Todos","*",$E$6),Lançamentos!$D:$D,"Saída")) | F17: {=IF(B17="","",SUMPRODUCT(('Fluxo de Caixa'!$B$82:$IL$82>=B17)*('Fluxo de Caixa'!$B$82:$IL$82<=MIN($C$6,IF($D$6="Dia",B17,IF($D$6="Semana",B17+6,IF($D$6="Mês",EOMONTH(B17,0),DATE(YEAR(B17),12,31))))))*'Fluxo de Caixa'!$B$140:$IL$140))} | G17: =IF(B17="","",(C17-E17)-(D17-F17)) | H17: =IF(B17="","",IFERROR(G17/ABS(D17-F17),0)) | J17: Impostos sobre Vendas | K17: =SUMIFS(Lançamentos!$F:$F,Lançamentos!$A:$A,">="&$B$6,Lançamentos!$A:$A,"<="&$C$6,Lançamentos!$C:$C,J17,Lançamentos!$G:$G,IF($E$6="Todos","*",$E$6)) -> 0 | L17: {=SUMPRODUCT(('Fluxo de Caixa'!$B$82:$IL$82>=$B$6)*('Fluxo de Caixa'!$B$82:$IL$82<=$C$6)*'Fluxo de Caixa'!$B$98:$IL$98)} -> 0 | M17: =K17-L17 -> 0
B18: =IF(B17="","",IF($D$6="Dia",IF(B17+1>$C$6,"",B17+1),IF($D$6="Semana",IF(B17+7>$C$6,"",B17+7),IF($D$6="Mês",IF(EDATE(B17,1)>$C$6,"",EDATE(B17,1)),IF(DATE(YEAR(B17)+1,1,1)>$C$6,"",DATE(YEAR(B17)+1,1,1)))))) | C18: =IF(B18="","",SUMIFS(Lançamentos!$F:$F,Lançamentos!$A:$A,">="&B18,Lançamentos!$A:$A,"<="&MIN($C$6,IF($D$6="Dia",B18,IF($D$6="Semana",B18+6,IF($D$6="Mês",EOMONTH(B18,0),DATE(YEAR(B18),12,31))))),Lançamentos!$G:$G,IF($E$6="Todos","*",$E$6),Lançamentos!$D:$D,"Entrada")) | D18: {=IF(B18="","",SUMPRODUCT(('Fluxo de Caixa'!$B$82:$IL$82>=B18)*('Fluxo de Caixa'!$B$82:$IL$82<=MIN($C$6,IF($D$6="Dia",B18,IF($D$6="Semana",B18+6,IF($D$6="Mês",EOMONTH(B18,0),DATE(YEAR(B18),12,31))))))*'Fluxo de Caixa'!$B$96:$IL$96))} | E18: =IF(B18="","",SUMIFS(Lançamentos!$F:$F,Lançamentos!$A:$A,">="&B18,Lançamentos!$A:$A,"<="&MIN($C$6,IF($D$6="Dia",B18,IF($D$6="Semana",B18+6,IF($D$6="Mês",EOMONTH(B18,0),DATE(YEAR(B18),12,31))))),Lançamentos!$G:$G,IF($E$6="Todos","*",$E$6),Lançamentos!$D:$D,"Saída")) | F18: {=IF(B18="","",SUMPRODUCT(('Fluxo de Caixa'!$B$82:$IL$82>=B18)*('Fluxo de Caixa'!$B$82:$IL$82<=MIN($C$6,IF($D$6="Dia",B18,IF($D$6="Semana",B18+6,IF($D$6="Mês",EOMONTH(B18,0),DATE(YEAR(B18),12,31))))))*'Fluxo de Caixa'!$B$140:$IL$140))} | G18: =IF(B18="","",(C18-E18)-(D18-F18)) | H18: =IF(B18="","",IFERROR(G18/ABS(D18-F18),0)) | J18: Devoluções | K18: =SUMIFS(Lançamentos!$F:$F,Lançamentos!$A:$A,">="&$B$6,Lançamentos!$A:$A,"<="&$C$6,Lançamentos!$C:$C,J18,Lançamentos!$G:$G,IF($E$6="Todos","*",$E$6)) -> 0 | L18: {=SUMPRODUCT(('Fluxo de Caixa'!$B$82:$IL$82>=$B$6)*('Fluxo de Caixa'!$B$82:$IL$82<=$C$6)*'Fluxo de Caixa'!$B$99:$IL$99)} -> 0 | M18: =K18-L18 -> 0
B19: =IF(B18="","",IF($D$6="Dia",IF(B18+1>$C$6,"",B18+1),IF($D$6="Semana",IF(B18+7>$C$6,"",B18+7),IF($D$6="Mês",IF(EDATE(B18,1)>$C$6,"",EDATE(B18,1)),IF(DATE(YEAR(B18)+1,1,1)>$C$6,"",DATE(YEAR(B18)+1,1,1)))))) | C19: =IF(B19="","",SUMIFS(Lançamentos!$F:$F,Lançamentos!$A:$A,">="&B19,Lançamentos!$A:$A,"<="&MIN($C$6,IF($D$6="Dia",B19,IF($D$6="Semana",B19+6,IF($D$6="Mês",EOMONTH(B19,0),DATE(YEAR(B19),12,31))))),Lançamentos!$G:$G,IF($E$6="Todos","*",$E$6),Lançamentos!$D:$D,"Entrada")) | D19: {=IF(B19="","",SUMPRODUCT(('Fluxo de Caixa'!$B$82:$IL$82>=B19)*('Fluxo de Caixa'!$B$82:$IL$82<=MIN($C$6,IF($D$6="Dia",B19,IF($D$6="Semana",B19+6,IF($D$6="Mês",EOMONTH(B19,0),DATE(YEAR(B19),12,31))))))*'Fluxo de Caixa'!$B$96:$IL$96))} | E19: =IF(B19="","",SUMIFS(Lançamentos!$F:$F,Lançamentos!$A:$A,">="&B19,Lançamentos!$A:$A,"<="&MIN($C$6,IF($D$6="Dia",B19,IF($D$6="Semana",B19+6,IF($D$6="Mês",EOMONTH(B19,0),DATE(YEAR(B19),12,31))))),Lançamentos!$G:$G,IF($E$6="Todos","*",$E$6),Lançamentos!$D:$D,"Saída")) | F19: {=IF(B19="","",SUMPRODUCT(('Fluxo de Caixa'!$B$82:$IL$82>=B19)*('Fluxo de Caixa'!$B$82:$IL$82<=MIN($C$6,IF($D$6="Dia",B19,IF($D$6="Semana",B19+6,IF($D$6="Mês",EOMONTH(B19,0),DATE(YEAR(B19),12,31))))))*'Fluxo de Caixa'!$B$140:$IL$140))} | G19: =IF(B19="","",(C19-E19)-(D19-F19)) | H19: =IF(B19="","",IFERROR(G19/ABS(D19-F19),0)) | J19: Custo de Mercadoria Vendida | K19: =SUMIFS(Lançamentos!$F:$F,Lançamentos!$A:$A,">="&$B$6,Lançamentos!$A:$A,"<="&$C$6,Lançamentos!$C:$C,J19,Lançamentos!$G:$G,IF($E$6="Todos","*",$E$6)) -> 0 | L19: {=SUMPRODUCT(('Fluxo de Caixa'!$B$82:$IL$82>=$B$6)*('Fluxo de Caixa'!$B$82:$IL$82<=$C$6)*'Fluxo de Caixa'!$B$100:$IL$100)} -> 0 | M19: =K19-L19 -> 0
B20: =IF(B19="","",IF($D$6="Dia",IF(B19+1>$C$6,"",B19+1),IF($D$6="Semana",IF(B19+7>$C$6,"",B19+7),IF($D$6="Mês",IF(EDATE(B19,1)>$C$6,"",EDATE(B19,1)),IF(DATE(YEAR(B19)+1,1,1)>$C$6,"",DATE(YEAR(B19)+1,1,1)))))) | C20: =IF(B20="","",SUMIFS(Lançamentos!$F:$F,Lançamentos!$A:$A,">="&B20,Lançamentos!$A:$A,"<="&MIN($C$6,IF($D$6="Dia",B20,IF($D$6="Semana",B20+6,IF($D$6="Mês",EOMONTH(B20,0),DATE(YEAR(B20),12,31))))),Lançamentos!$G:$G,IF($E$6="Todos","*",$E$6),Lançamentos!$D:$D,"Entrada")) | D20: {=IF(B20="","",SUMPRODUCT(('Fluxo de Caixa'!$B$82:$IL$82>=B20)*('Fluxo de Caixa'!$B$82:$IL$82<=MIN($C$6,IF($D$6="Dia",B20,IF($D$6="Semana",B20+6,IF($D$6="Mês",EOMONTH(B20,0),DATE(YEAR(B20),12,31))))))*'Fluxo de Caixa'!$B$96:$IL$96))} | E20: =IF(B20="","",SUMIFS(Lançamentos!$F:$F,Lançamentos!$A:$A,">="&B20,Lançamentos!$A:$A,"<="&MIN($C$6,IF($D$6="Dia",B20,IF($D$6="Semana",B20+6,IF($D$6="Mês",EOMONTH(B20,0),DATE(YEAR(B20),12,31))))),Lançamentos!$G:$G,IF($E$6="Todos","*",$E$6),Lançamentos!$D:$D,"Saída")) | F20: {=IF(B20="","",SUMPRODUCT(('Fluxo de Caixa'!$B$82:$IL$82>=B20)*('Fluxo de Caixa'!$B$82:$IL$82<=MIN($C$6,IF($D$6="Dia",B20,IF($D$6="Semana",B20+6,IF($D$6="Mês",EOMONTH(B20,0),DATE(YEAR(B20),12,31))))))*'Fluxo de Caixa'!$B$140:$IL$140))} | G20: =IF(B20="","",(C20-E20)-(D20-F20)) | H20: =IF(B20="","",IFERROR(G20/ABS(D20-F20),0)) | J20: Custo de Serviços Prestados | K20: =SUMIFS(Lançamentos!$F:$F,Lançamentos!$A:$A,">="&$B$6,Lançamentos!$A:$A,"<="&$C$6,Lançamentos!$C:$C,J20,Lançamentos!$G:$G,IF($E$6="Todos","*",$E$6)) -> 0 | L20: {=SUMPRODUCT(('Fluxo de Caixa'!$B$82:$IL$82>=$B$6)*('Fluxo de Caixa'!$B$82:$IL$82<=$C$6)*'Fluxo de Caixa'!$B$101:$IL$101)} -> 0 | M20: =K20-L20 -> 0
B21: =IF(B20="","",IF($D$6="Dia",IF(B20+1>$C$6,"",B20+1),IF($D$6="Semana",IF(B20+7>$C$6,"",B20+7),IF($D$6="Mês",IF(EDATE(B20,1)>$C$6,"",EDATE(B20,1)),IF(DATE(YEAR(B20)+1,1,1)>$C$6,"",DATE(YEAR(B20)+1,1,1)))))) | C21: =IF(B21="","",SUMIFS(Lançamentos!$F:$F,Lançamentos!$A:$A,">="&B21,Lançamentos!$A:$A,"<="&MIN($C$6,IF($D$6="Dia",B21,IF($D$6="Semana",B21+6,IF($D$6="Mês",EOMONTH(B21,0),DATE(YEAR(B21),12,31))))),Lançamentos!$G:$G,IF($E$6="Todos","*",$E$6),Lançamentos!$D:$D,"Entrada")) | D21: {=IF(B21="","",SUMPRODUCT(('Fluxo de Caixa'!$B$82:$IL$82>=B21)*('Fluxo de Caixa'!$B$82:$IL$82<=MIN($C$6,IF($D$6="Dia",B21,IF($D$6="Semana",B21+6,IF($D$6="Mês",EOMONTH(B21,0),DATE(YEAR(B21),12,31))))))*'Fluxo de Caixa'!$B$96:$IL$96))} | E21: =IF(B21="","",SUMIFS(Lançamentos!$F:$F,Lançamentos!$A:$A,">="&B21,Lançamentos!$A:$A,"<="&MIN($C$6,IF($D$6="Dia",B21,IF($D$6="Semana",B21+6,IF($D$6="Mês",EOMONTH(B21,0),DATE(YEAR(B21),12,31))))),Lançamentos!$G:$G,IF($E$6="Todos","*",$E$6),Lançamentos!$D:$D,"Saída")) | F21: {=IF(B21="","",SUMPRODUCT(('Fluxo de Caixa'!$B$82:$IL$82>=B21)*('Fluxo de Caixa'!$B$82:$IL$82<=MIN($C$6,IF($D$6="Dia",B21,IF($D$6="Semana",B21+6,IF($D$6="Mês",EOMONTH(B21,0),DATE(YEAR(B21),12,31))))))*'Fluxo de Caixa'!$B$140:$IL$140))} | G21: =IF(B21="","",(C21-E21)-(D21-F21)) | H21: =IF(B21="","",IFERROR(G21/ABS(D21-F21),0)) | J21: Salários e Encargos | K21: =SUMIFS(Lançamentos!$F:$F,Lançamentos!$A:$A,">="&$B$6,Lançamentos!$A:$A,"<="&$C$6,Lançamentos!$C:$C,J21,Lançamentos!$G:$G,IF($E$6="Todos","*",$E$6)) -> 0 | L21: {=SUMPRODUCT(('Fluxo de Caixa'!$B$82:$IL$82>=$B$6)*('Fluxo de Caixa'!$B$82:$IL$82<=$C$6)*'Fluxo de Caixa'!$B$102:$IL$102)} -> 0 | M21: =K21-L21 -> 0
B22: =IF(B21="","",IF($D$6="Dia",IF(B21+1>$C$6,"",B21+1),IF($D$6="Semana",IF(B21+7>$C$6,"",B21+7),IF($D$6="Mês",IF(EDATE(B21,1)>$C$6,"",EDATE(B21,1)),IF(DATE(YEAR(B21)+1,1,1)>$C$6,"",DATE(YEAR(B21)+1,1,1)))))) | C22: =IF(B22="","",SUMIFS(Lançamentos!$F:$F,Lançamentos!$A:$A,">="&B22,Lançamentos!$A:$A,"<="&MIN($C$6,IF($D$6="Dia",B22,IF($D$6="Semana",B22+6,IF($D$6="Mês",EOMONTH(B22,0),DATE(YEAR(B22),12,31))))),Lançamentos!$G:$G,IF($E$6="Todos","*",$E$6),Lançamentos!$D:$D,"Entrada")) | D22: {=IF(B22="","",SUMPRODUCT(('Fluxo de Caixa'!$B$82:$IL$82>=B22)*('Fluxo de Caixa'!$B$82:$IL$82<=MIN($C$6,IF($D$6="Dia",B22,IF($D$6="Semana",B22+6,IF($D$6="Mês",EOMONTH(B22,0),DATE(YEAR(B22),12,31))))))*'Fluxo de Caixa'!$B$96:$IL$96))} | E22: =IF(B22="","",SUMIFS(Lançamentos!$F:$F,Lançamentos!$A:$A,">="&B22,Lançamentos!$A:$A,"<="&MIN($C$6,IF($D$6="Dia",B22,IF($D$6="Semana",B22+6,IF($D$6="Mês",EOMONTH(B22,0),DATE(YEAR(B22),12,31))))),Lançamentos!$G:$G,IF($E$6="Todos","*",$E$6),Lançamentos!$D:$D,"Saída")) | F22: {=IF(B22="","",SUMPRODUCT(('Fluxo de Caixa'!$B$82:$IL$82>=B22)*('Fluxo de Caixa'!$B$82:$IL$82<=MIN($C$6,IF($D$6="Dia",B22,IF($D$6="Semana",B22+6,IF($D$6="Mês",EOMONTH(B22,0),DATE(YEAR(B22),12,31))))))*'Fluxo de Caixa'!$B$140:$IL$140))} | G22: =IF(B22="","",(C22-E22)-(D22-F22)) | H22: =IF(B22="","",IFERROR(G22/ABS(D22-F22),0)) | J22: Aluguel | K22: =SUMIFS(Lançamentos!$F:$F,Lançamentos!$A:$A,">="&$B$6,Lançamentos!$A:$A,"<="&$C$6,Lançamentos!$C:$C,J22,Lançamentos!$G:$G,IF($E$6="Todos","*",$E$6)) -> 0 | L22: {=SUMPRODUCT(('Fluxo de Caixa'!$B$82:$IL$82>=$B$6)*('Fluxo de Caixa'!$B$82:$IL$82<=$C$6)*'Fluxo de Caixa'!$B$103:$IL$103)} -> 0 | M22: =K22-L22 -> 0
B23: =IF(B22="","",IF($D$6="Dia",IF(B22+1>$C$6,"",B22+1),IF($D$6="Semana",IF(B22+7>$C$6,"",B22+7),IF($D$6="Mês",IF(EDATE(B22,1)>$C$6,"",EDATE(B22,1)),IF(DATE(YEAR(B22)+1,1,1)>$C$6,"",DATE(YEAR(B22)+1,1,1)))))) | C23: =IF(B23="","",SUMIFS(Lançamentos!$F:$F,Lançamentos!$A:$A,">="&B23,Lançamentos!$A:$A,"<="&MIN($C$6,IF($D$6="Dia",B23,IF($D$6="Semana",B23+6,IF($D$6="Mês",EOMONTH(B23,0),DATE(YEAR(B23),12,31))))),Lançamentos!$G:$G,IF($E$6="Todos","*",$E$6),Lançamentos!$D:$D,"Entrada")) | D23: {=IF(B23="","",SUMPRODUCT(('Fluxo de Caixa'!$B$82:$IL$82>=B23)*('Fluxo de Caixa'!$B$82:$IL$82<=MIN($C$6,IF($D$6="Dia",B23,IF($D$6="Semana",B23+6,IF($D$6="Mês",EOMONTH(B23,0),DATE(YEAR(B23),12,31))))))*'Fluxo de Caixa'!$B$96:$IL$96))} | E23: =IF(B23="","",SUMIFS(Lançamentos!$F:$F,Lançamentos!$A:$A,">="&B23,Lançamentos!$A:$A,"<="&MIN($C$6,IF($D$6="Dia",B23,IF($D$6="Semana",B23+6,IF($D$6="Mês",EOMONTH(B23,0),DATE(YEAR(B23),12,31))))),Lançamentos!$G:$G,IF($E$6="Todos","*",$E$6),Lançamentos!$D:$D,"Saída")) | F23: {=IF(B23="","",SUMPRODUCT(('Fluxo de Caixa'!$B$82:$IL$82>=B23)*('Fluxo de Caixa'!$B$82:$IL$82<=MIN($C$6,IF($D$6="Dia",B23,IF($D$6="Semana",B23+6,IF($D$6="Mês",EOMONTH(B23,0),DATE(YEAR(B23),12,31))))))*'Fluxo de Caixa'!$B$140:$IL$140))} | G23: =IF(B23="","",(C23-E23)-(D23-F23)) | H23: =IF(B23="","",IFERROR(G23/ABS(D23-F23),0)) | J23: Água, Luz e Internet | K23: =SUMIFS(Lançamentos!$F:$F,Lançamentos!$A:$A,">="&$B$6,Lançamentos!$A:$A,"<="&$C$6,Lançamentos!$C:$C,J23,Lançamentos!$G:$G,IF($E$6="Todos","*",$E$6)) -> 0 | L23: {=SUMPRODUCT(('Fluxo de Caixa'!$B$82:$IL$82>=$B$6)*('Fluxo de Caixa'!$B$82:$IL$82<=$C$6)*'Fluxo de Caixa'!$B$104:$IL$104)} -> 0 | M23: =K23-L23 -> 0
B24: =IF(B23="","",IF($D$6="Dia",IF(B23+1>$C$6,"",B23+1),IF($D$6="Semana",IF(B23+7>$C$6,"",B23+7),IF($D$6="Mês",IF(EDATE(B23,1)>$C$6,"",EDATE(B23,1)),IF(DATE(YEAR(B23)+1,1,1)>$C$6,"",DATE(YEAR(B23)+1,1,1)))))) | C24: =IF(B24="","",SUMIFS(Lançamentos!$F:$F,Lançamentos!$A:$A,">="&B24,Lançamentos!$A:$A,"<="&MIN($C$6,IF($D$6="Dia",B24,IF($D$6="Semana",B24+6,IF($D$6="Mês",EOMONTH(B24,0),DATE(YEAR(B24),12,31))))),Lançamentos!$G:$G,IF($E$6="Todos","*",$E$6),Lançamentos!$D:$D,"Entrada")) | D24: {=IF(B24="","",SUMPRODUCT(('Fluxo de Caixa'!$B$82:$IL$82>=B24)*('Fluxo de Caixa'!$B$82:$IL$82<=MIN($C$6,IF($D$6="Dia",B24,IF($D$6="Semana",B24+6,IF($D$6="Mês",EOMONTH(B24,0),DATE(YEAR(B24),12,31))))))*'Fluxo de Caixa'!$B$96:$IL$96))} | E24: =IF(B24="","",SUMIFS(Lançamentos!$F:$F,Lançamentos!$A:$A,">="&B24,Lançamentos!$A:$A,"<="&MIN($C$6,IF($D$6="Dia",B24,IF($D$6="Semana",B24+6,IF($D$6="Mês",EOMONTH(B24,0),DATE(YEAR(B24),12,31))))),Lançamentos!$G:$G,IF($E$6="Todos","*",$E$6),Lançamentos!$D:$D,"Saída")) | F24: {=IF(B24="","",SUMPRODUCT(('Fluxo de Caixa'!$B$82:$IL$82>=B24)*('Fluxo de Caixa'!$B$82:$IL$82<=MIN($C$6,IF($D$6="Dia",B24,IF($D$6="Semana",B24+6,IF($D$6="Mês",EOMONTH(B24,0),DATE(YEAR(B24),12,31))))))*'Fluxo de Caixa'!$B$140:$IL$140))} | G24: =IF(B24="","",(C24-E24)-(D24-F24)) | H24: =IF(B24="","",IFERROR(G24/ABS(D24-F24),0)) | J24: Material de Escritório | K24: =SUMIFS(Lançamentos!$F:$F,Lançamentos!$A:$A,">="&$B$6,Lançamentos!$A:$A,"<="&$C$6,Lançamentos!$C:$C,J24,Lançamentos!$G:$G,IF($E$6="Todos","*",$E$6)) -> 0 | L24: {=SUMPRODUCT(('Fluxo de Caixa'!$B$82:$IL$82>=$B$6)*('Fluxo de Caixa'!$B$82:$IL$82<=$C$6)*'Fluxo de Caixa'!$B$105:$IL$105)} -> 0 | M24: =K24-L24 -> 0
B25: =IF(B24="","",IF($D$6="Dia",IF(B24+1>$C$6,"",B24+1),IF($D$6="Semana",IF(B24+7>$C$6,"",B24+7),IF($D$6="Mês",IF(EDATE(B24,1)>$C$6,"",EDATE(B24,1)),IF(DATE(YEAR(B24)+1,1,1)>$C$6,"",DATE(YEAR(B24)+1,1,1)))))) | C25: =IF(B25="","",SUMIFS(Lançamentos!$F:$F,Lançamentos!$A:$A,">="&B25,Lançamentos!$A:$A,"<="&MIN($C$6,IF($D$6="Dia",B25,IF($D$6="Semana",B25+6,IF($D$6="Mês",EOMONTH(B25,0),DATE(YEAR(B25),12,31))))),Lançamentos!$G:$G,IF($E$6="Todos","*",$E$6),Lançamentos!$D:$D,"Entrada")) | D25: {=IF(B25="","",SUMPRODUCT(('Fluxo de Caixa'!$B$82:$IL$82>=B25)*('Fluxo de Caixa'!$B$82:$IL$82<=MIN($C$6,IF($D$6="Dia",B25,IF($D$6="Semana",B25+6,IF($D$6="Mês",EOMONTH(B25,0),DATE(YEAR(B25),12,31))))))*'Fluxo de Caixa'!$B$96:$IL$96))} | E25: =IF(B25="","",SUMIFS(Lançamentos!$F:$F,Lançamentos!$A:$A,">="&B25,Lançamentos!$A:$A,"<="&MIN($C$6,IF($D$6="Dia",B25,IF($D$6="Semana",B25+6,IF($D$6="Mês",EOMONTH(B25,0),DATE(YEAR(B25),12,31))))),Lançamentos!$G:$G,IF($E$6="Todos","*",$E$6),Lançamentos!$D:$D,"Saída")) | F25: {=IF(B25="","",SUMPRODUCT(('Fluxo de Caixa'!$B$82:$IL$82>=B25)*('Fluxo de Caixa'!$B$82:$IL$82<=MIN($C$6,IF($D$6="Dia",B25,IF($D$6="Semana",B25+6,IF($D$6="Mês",EOMONTH(B25,0),DATE(YEAR(B25),12,31))))))*'Fluxo de Caixa'!$B$140:$IL$140))} | G25: =IF(B25="","",(C25-E25)-(D25-F25)) | H25: =IF(B25="","",IFERROR(G25/ABS(D25-F25),0)) | J25: Marketing e Publicidade | K25: =SUMIFS(Lançamentos!$F:$F,Lançamentos!$A:$A,">="&$B$6,Lançamentos!$A:$A,"<="&$C$6,Lançamentos!$C:$C,J25,Lançamentos!$G:$G,IF($E$6="Todos","*",$E$6)) -> 0 | L25: {=SUMPRODUCT(('Fluxo de Caixa'!$B$82:$IL$82>=$B$6)*('Fluxo de Caixa'!$B$82:$IL$82<=$C$6)*'Fluxo de Caixa'!$B$106:$IL$106)} -> 0 | M25: =K25-L25 -> 0
B26: =IF(B25="","",IF($D$6="Dia",IF(B25+1>$C$6,"",B25+1),IF($D$6="Semana",IF(B25+7>$C$6,"",B25+7),IF($D$6="Mês",IF(EDATE(B25,1)>$C$6,"",EDATE(B25,1)),IF(DATE(YEAR(B25)+1,1,1)>$C$6,"",DATE(YEAR(B25)+1,1,1)))))) | C26: =IF(B26="","",SUMIFS(Lançamentos!$F:$F,Lançamentos!$A:$A,">="&B26,Lançamentos!$A:$A,"<="&MIN($C$6,IF($D$6="Dia",B26,IF($D$6="Semana",B26+6,IF($D$6="Mês",EOMONTH(B26,0),DATE(YEAR(B26),12,31))))),Lançamentos!$G:$G,IF($E$6="Todos","*",$E$6),Lançamentos!$D:$D,"Entrada")) | D26: {=IF(B26="","",SUMPRODUCT(('Fluxo de Caixa'!$B$82:$IL$82>=B26)*('Fluxo de Caixa'!$B$82:$IL$82<=MIN($C$6,IF($D$6="Dia",B26,IF($D$6="Semana",B26+6,IF($D$6="Mês",EOMONTH(B26,0),DATE(YEAR(B26),12,31))))))*'Fluxo de Caixa'!$B$96:$IL$96))} | E26: =IF(B26="","",SUMIFS(Lançamentos!$F:$F,Lançamentos!$A:$A,">="&B26,Lançamentos!$A:$A,"<="&MIN($C$6,IF($D$6="Dia",B26,IF($D$6="Semana",B26+6,IF($D$6="Mês",EOMONTH(B26,0),DATE(YEAR(B26),12,31))))),Lançamentos!$G:$G,IF($E$6="Todos","*",$E$6),Lançamentos!$D:$D,"Saída")) | F26: {=IF(B26="","",SUMPRODUCT(('Fluxo de Caixa'!$B$82:$IL$82>=B26)*('Fluxo de Caixa'!$B$82:$IL$82<=MIN($C$6,IF($D$6="Dia",B26,IF($D$6="Semana",B26+6,IF($D$6="Mês",EOMONTH(B26,0),DATE(YEAR(B26),12,31))))))*'Fluxo de Caixa'!$B$140:$IL$140))} | G26: =IF(B26="","",(C26-E26)-(D26-F26)) | H26: =IF(B26="","",IFERROR(G26/ABS(D26-F26),0)) | J26: Manutenção | K26: =SUMIFS(Lançamentos!$F:$F,Lançamentos!$A:$A,">="&$B$6,Lançamentos!$A:$A,"<="&$C$6,Lançamentos!$C:$C,J26,Lançamentos!$G:$G,IF($E$6="Todos","*",$E$6)) -> 0 | L26: {=SUMPRODUCT(('Fluxo de Caixa'!$B$82:$IL$82>=$B$6)*('Fluxo de Caixa'!$B$82:$IL$82<=$C$6)*'Fluxo de Caixa'!$B$107:$IL$107)} -> 0 | M26: =K26-L26 -> 0
B27: =IF(B26="","",IF($D$6="Dia",IF(B26+1>$C$6,"",B26+1),IF($D$6="Semana",IF(B26+7>$C$6,"",B26+7),IF($D$6="Mês",IF(EDATE(B26,1)>$C$6,"",EDATE(B26,1)),IF(DATE(YEAR(B26)+1,1,1)>$C$6,"",DATE(YEAR(B26)+1,1,1)))))) | C27: =IF(B27="","",SUMIFS(Lançamentos!$F:$F,Lançamentos!$A:$A,">="&B27,Lançamentos!$A:$A,"<="&MIN($C$6,IF($D$6="Dia",B27,IF($D$6="Semana",B27+6,IF($D$6="Mês",EOMONTH(B27,0),DATE(YEAR(B27),12,31))))),Lançamentos!$G:$G,IF($E$6="Todos","*",$E$6),Lançamentos!$D:$D,"Entrada")) | D27: {=IF(B27="","",SUMPRODUCT(('Fluxo de Caixa'!$B$82:$IL$82>=B27)*('Fluxo de Caixa'!$B$82:$IL$82<=MIN($C$6,IF($D$6="Dia",B27,IF($D$6="Semana",B27+6,IF($D$6="Mês",EOMONTH(B27,0),DATE(YEAR(B27),12,31))))))*'Fluxo de Caixa'!$B$96:$IL$96))} | E27: =IF(B27="","",SUMIFS(Lançamentos!$F:$F,Lançamentos!$A:$A,">="&B27,Lançamentos!$A:$A,"<="&MIN($C$6,IF($D$6="Dia",B27,IF($D$6="Semana",B27+6,IF($D$6="Mês",EOMONTH(B27,0),DATE(YEAR(B27),12,31))))),Lançamentos!$G:$G,IF($E$6="Todos","*",$E$6),Lançamentos!$D:$D,"Saída")) | F27: {=IF(B27="","",SUMPRODUCT(('Fluxo de Caixa'!$B$82:$IL$82>=B27)*('Fluxo de Caixa'!$B$82:$IL$82<=MIN($C$6,IF($D$6="Dia",B27,IF($D$6="Semana",B27+6,IF($D$6="Mês",EOMONTH(B27,0),DATE(YEAR(B27),12,31))))))*'Fluxo de Caixa'!$B$140:$IL$140))} | G27: =IF(B27="","",(C27-E27)-(D27-F27)) | H27: =IF(B27="","",IFERROR(G27/ABS(D27-F27),0)) | J27: Transporte e Viagens | K27: =SUMIFS(Lançamentos!$F:$F,Lançamentos!$A:$A,">="&$B$6,Lançamentos!$A:$A,"<="&$C$6,Lançamentos!$C:$C,J27,Lançamentos!$G:$G,IF($E$6="Todos","*",$E$6)) -> 0 | L27: {=SUMPRODUCT(('Fluxo de Caixa'!$B$82:$IL$82>=$B$6)*('Fluxo de Caixa'!$B$82:$IL$82<=$C$6)*'Fluxo de Caixa'!$B$108:$IL$108)} -> 0 | M27: =K27-L27 -> 0
B28: =IF(B27="","",IF($D$6="Dia",IF(B27+1>$C$6,"",B27+1),IF($D$6="Semana",IF(B27+7>$C$6,"",B27+7),IF($D$6="Mês",IF(EDATE(B27,1)>$C$6,"",EDATE(B27,1)),IF(DATE(YEAR(B27)+1,1,1)>$C$6,"",DATE(YEAR(B27)+1,1,1)))))) | C28: =IF(B28="","",SUMIFS(Lançamentos!$F:$F,Lançamentos!$A:$A,">="&B28,Lançamentos!$A:$A,"<="&MIN($C$6,IF($D$6="Dia",B28,IF($D$6="Semana",B28+6,IF($D$6="Mês",EOMONTH(B28,0),DATE(YEAR(B28),12,31))))),Lançamentos!$G:$G,IF($E$6="Todos","*",$E$6),Lançamentos!$D:$D,"Entrada")) | D28: {=IF(B28="","",SUMPRODUCT(('Fluxo de Caixa'!$B$82:$IL$82>=B28)*('Fluxo de Caixa'!$B$82:$IL$82<=MIN($C$6,IF($D$6="Dia",B28,IF($D$6="Semana",B28+6,IF($D$6="Mês",EOMONTH(B28,0),DATE(YEAR(B28),12,31))))))*'Fluxo de Caixa'!$B$96:$IL$96))} | E28: =IF(B28="","",SUMIFS(Lançamentos!$F:$F,Lançamentos!$A:$A,">="&B28,Lançamentos!$A:$A,"<="&MIN($C$6,IF($D$6="Dia",B28,IF($D$6="Semana",B28+6,IF($D$6="Mês",EOMONTH(B28,0),DATE(YEAR(B28),12,31))))),Lançamentos!$G:$G,IF($E$6="Todos","*",$E$6),Lançamentos!$D:$D,"Saída")) | F28: {=IF(B28="","",SUMPRODUCT(('Fluxo de Caixa'!$B$82:$IL$82>=B28)*('Fluxo de Caixa'!$B$82:$IL$82<=MIN($C$6,IF($D$6="Dia",B28,IF($D$6="Semana",B28+6,IF($D$6="Mês",EOMONTH(B28,0),DATE(YEAR(B28),12,31))))))*'Fluxo de Caixa'!$B$140:$IL$140))} | G28: =IF(B28="","",(C28-E28)-(D28-F28)) | H28: =IF(B28="","",IFERROR(G28/ABS(D28-F28),0)) | J28: Serviços de Terceiros | K28: =SUMIFS(Lançamentos!$F:$F,Lançamentos!$A:$A,">="&$B$6,Lançamentos!$A:$A,"<="&$C$6,Lançamentos!$C:$C,J28,Lançamentos!$G:$G,IF($E$6="Todos","*",$E$6)) -> 0 | L28: {=SUMPRODUCT(('Fluxo de Caixa'!$B$82:$IL$82>=$B$6)*('Fluxo de Caixa'!$B$82:$IL$82<=$C$6)*'Fluxo de Caixa'!$B$109:$IL$109)} -> 0 | M28: =K28-L28 -> 0
B29: =IF(B28="","",IF($D$6="Dia",IF(B28+1>$C$6,"",B28+1),IF($D$6="Semana",IF(B28+7>$C$6,"",B28+7),IF($D$6="Mês",IF(EDATE(B28,1)>$C$6,"",EDATE(B28,1)),IF(DATE(YEAR(B28)+1,1,1)>$C$6,"",DATE(YEAR(B28)+1,1,1)))))) | C29: =IF(B29="","",SUMIFS(Lançamentos!$F:$F,Lançamentos!$A:$A,">="&B29,Lançamentos!$A:$A,"<="&MIN($C$6,IF($D$6="Dia",B29,IF($D$6="Semana",B29+6,IF($D$6="Mês",EOMONTH(B29,0),DATE(YEAR(B29),12,31))))),Lançamentos!$G:$G,IF($E$6="Todos","*",$E$6),Lançamentos!$D:$D,"Entrada")) | D29: {=IF(B29="","",SUMPRODUCT(('Fluxo de Caixa'!$B$82:$IL$82>=B29)*('Fluxo de Caixa'!$B$82:$IL$82<=MIN($C$6,IF($D$6="Dia",B29,IF($D$6="Semana",B29+6,IF($D$6="Mês",EOMONTH(B29,0),DATE(YEAR(B29),12,31))))))*'Fluxo de Caixa'!$B$96:$IL$96))} | E29: =IF(B29="","",SUMIFS(Lançamentos!$F:$F,Lançamentos!$A:$A,">="&B29,Lançamentos!$A:$A,"<="&MIN($C$6,IF($D$6="Dia",B29,IF($D$6="Semana",B29+6,IF($D$6="Mês",EOMONTH(B29,0),DATE(YEAR(B29),12,31))))),Lançamentos!$G:$G,IF($E$6="Todos","*",$E$6),Lançamentos!$D:$D,"Saída")) | F29: {=IF(B29="","",SUMPRODUCT(('Fluxo de Caixa'!$B$82:$IL$82>=B29)*('Fluxo de Caixa'!$B$82:$IL$82<=MIN($C$6,IF($D$6="Dia",B29,IF($D$6="Semana",B29+6,IF($D$6="Mês",EOMONTH(B29,0),DATE(YEAR(B29),12,31))))))*'Fluxo de Caixa'!$B$140:$IL$140))} | G29: =IF(B29="","",(C29-E29)-(D29-F29)) | H29: =IF(B29="","",IFERROR(G29/ABS(D29-F29),0)) | J29: Juros e Tarifas Bancárias | K29: =SUMIFS(Lançamentos!$F:$F,Lançamentos!$A:$A,">="&$B$6,Lançamentos!$A:$A,"<="&$C$6,Lançamentos!$C:$C,J29,Lançamentos!$G:$G,IF($E$6="Todos","*",$E$6)) -> 0 | L29: {=SUMPRODUCT(('Fluxo de Caixa'!$B$82:$IL$82>=$B$6)*('Fluxo de Caixa'!$B$82:$IL$82<=$C$6)*'Fluxo de Caixa'!$B$110:$IL$110)} -> 0 | M29: =K29-L29 -> 0
B30: =IF(B29="","",IF($D$6="Dia",IF(B29+1>$C$6,"",B29+1),IF($D$6="Semana",IF(B29+7>$C$6,"",B29+7),IF($D$6="Mês",IF(EDATE(B29,1)>$C$6,"",EDATE(B29,1)),IF(DATE(YEAR(B29)+1,1,1)>$C$6,"",DATE(YEAR(B29)+1,1,1)))))) | C30: =IF(B30="","",SUMIFS(Lançamentos!$F:$F,Lançamentos!$A:$A,">="&B30,Lançamentos!$A:$A,"<="&MIN($C$6,IF($D$6="Dia",B30,IF($D$6="Semana",B30+6,IF($D$6="Mês",EOMONTH(B30,0),DATE(YEAR(B30),12,31))))),Lançamentos!$G:$G,IF($E$6="Todos","*",$E$6),Lançamentos!$D:$D,"Entrada")) | D30: {=IF(B30="","",SUMPRODUCT(('Fluxo de Caixa'!$B$82:$IL$82>=B30)*('Fluxo de Caixa'!$B$82:$IL$82<=MIN($C$6,IF($D$6="Dia",B30,IF($D$6="Semana",B30+6,IF($D$6="Mês",EOMONTH(B30,0),DATE(YEAR(B30),12,31))))))*'Fluxo de Caixa'!$B$96:$IL$96))} | E30: =IF(B30="","",SUMIFS(Lançamentos!$F:$F,Lançamentos!$A:$A,">="&B30,Lançamentos!$A:$A,"<="&MIN($C$6,IF($D$6="Dia",B30,IF($D$6="Semana",B30+6,IF($D$6="Mês",EOMONTH(B30,0),DATE(YEAR(B30),12,31))))),Lançamentos!$G:$G,IF($E$6="Todos","*",$E$6),Lançamentos!$D:$D,"Saída")) | F30: {=IF(B30="","",SUMPRODUCT(('Fluxo de Caixa'!$B$82:$IL$82>=B30)*('Fluxo de Caixa'!$B$82:$IL$82<=MIN($C$6,IF($D$6="Dia",B30,IF($D$6="Semana",B30+6,IF($D$6="Mês",EOMONTH(B30,0),DATE(YEAR(B30),12,31))))))*'Fluxo de Caixa'!$B$140:$IL$140))} | G30: =IF(B30="","",(C30-E30)-(D30-F30)) | H30: =IF(B30="","",IFERROR(G30/ABS(D30-F30),0)) | J30: Empréstimos e Financiamentos | K30: =SUMIFS(Lançamentos!$F:$F,Lançamentos!$A:$A,">="&$B$6,Lançamentos!$A:$A,"<="&$C$6,Lançamentos!$C:$C,J30,Lançamentos!$G:$G,IF($E$6="Todos","*",$E$6)) -> 0 | L30: {=SUMPRODUCT(('Fluxo de Caixa'!$B$82:$IL$82>=$B$6)*('Fluxo de Caixa'!$B$82:$IL$82<=$C$6)*'Fluxo de Caixa'!$B$111:$IL$111)} -> 0 | M30: =K30-L30 -> 0
B31: =IF(B30="","",IF($D$6="Dia",IF(B30+1>$C$6,"",B30+1),IF($D$6="Semana",IF(B30+7>$C$6,"",B30+7),IF($D$6="Mês",IF(EDATE(B30,1)>$C$6,"",EDATE(B30,1)),IF(DATE(YEAR(B30)+1,1,1)>$C$6,"",DATE(YEAR(B30)+1,1,1)))))) | C31: =IF(B31="","",SUMIFS(Lançamentos!$F:$F,Lançamentos!$A:$A,">="&B31,Lançamentos!$A:$A,"<="&MIN($C$6,IF($D$6="Dia",B31,IF($D$6="Semana",B31+6,IF($D$6="Mês",EOMONTH(B31,0),DATE(YEAR(B31),12,31))))),Lançamentos!$G:$G,IF($E$6="Todos","*",$E$6),Lançamentos!$D:$D,"Entrada")) | D31: {=IF(B31="","",SUMPRODUCT(('Fluxo de Caixa'!$B$82:$IL$82>=B31)*('Fluxo de Caixa'!$B$82:$IL$82<=MIN($C$6,IF($D$6="Dia",B31,IF($D$6="Semana",B31+6,IF($D$6="Mês",EOMONTH(B31,0),DATE(YEAR(B31),12,31))))))*'Fluxo de Caixa'!$B$96:$IL$96))} | E31: =IF(B31="","",SUMIFS(Lançamentos!$F:$F,Lançamentos!$A:$A,">="&B31,Lançamentos!$A:$A,"<="&MIN($C$6,IF($D$6="Dia",B31,IF($D$6="Semana",B31+6,IF($D$6="Mês",EOMONTH(B31,0),DATE(YEAR(B31),12,31))))),Lançamentos!$G:$G,IF($E$6="Todos","*",$E$6),Lançamentos!$D:$D,"Saída")) | F31: {=IF(B31="","",SUMPRODUCT(('Fluxo de Caixa'!$B$82:$IL$82>=B31)*('Fluxo de Caixa'!$B$82:$IL$82<=MIN($C$6,IF($D$6="Dia",B31,IF($D$6="Semana",B31+6,IF($D$6="Mês",EOMONTH(B31,0),DATE(YEAR(B31),12,31))))))*'Fluxo de Caixa'!$B$140:$IL$140))} | G31: =IF(B31="","",(C31-E31)-(D31-F31)) | H31: =IF(B31="","",IFERROR(G31/ABS(D31-F31),0)) | J31: Impostos sobre Lucro | K31: =SUMIFS(Lançamentos!$F:$F,Lançamentos!$A:$A,">="&$B$6,Lançamentos!$A:$A,"<="&$C$6,Lançamentos!$C:$C,J31,Lançamentos!$G:$G,IF($E$6="Todos","*",$E$6)) -> 0 | L31: {=SUMPRODUCT(('Fluxo de Caixa'!$B$82:$IL$82>=$B$6)*('Fluxo de Caixa'!$B$82:$IL$82<=$C$6)*'Fluxo de Caixa'!$B$112:$IL$112)} -> 0 | M31: =K31-L31 -> 0
B32: =IF(B31="","",IF($D$6="Dia",IF(B31+1>$C$6,"",B31+1),IF($D$6="Semana",IF(B31+7>$C$6,"",B31+7),IF($D$6="Mês",IF(EDATE(B31,1)>$C$6,"",EDATE(B31,1)),IF(DATE(YEAR(B31)+1,1,1)>$C$6,"",DATE(YEAR(B31)+1,1,1)))))) | C32: =IF(B32="","",SUMIFS(Lançamentos!$F:$F,Lançamentos!$A:$A,">="&B32,Lançamentos!$A:$A,"<="&MIN($C$6,IF($D$6="Dia",B32,IF($D$6="Semana",B32+6,IF($D$6="Mês",EOMONTH(B32,0),DATE(YEAR(B32),12,31))))),Lançamentos!$G:$G,IF($E$6="Todos","*",$E$6),Lançamentos!$D:$D,"Entrada")) | D32: {=IF(B32="","",SUMPRODUCT(('Fluxo de Caixa'!$B$82:$IL$82>=B32)*('Fluxo de Caixa'!$B$82:$IL$82<=MIN($C$6,IF($D$6="Dia",B32,IF($D$6="Semana",B32+6,IF($D$6="Mês",EOMONTH(B32,0),DATE(YEAR(B32),12,31))))))*'Fluxo de Caixa'!$B$96:$IL$96))} | E32: =IF(B32="","",SUMIFS(Lançamentos!$F:$F,Lançamentos!$A:$A,">="&B32,Lançamentos!$A:$A,"<="&MIN($C$6,IF($D$6="Dia",B32,IF($D$6="Semana",B32+6,IF($D$6="Mês",EOMONTH(B32,0),DATE(YEAR(B32),12,31))))),Lançamentos!$G:$G,IF($E$6="Todos","*",$E$6),Lançamentos!$D:$D,"Saída")) | F32: {=IF(B32="","",SUMPRODUCT(('Fluxo de Caixa'!$B$82:$IL$82>=B32)*('Fluxo de Caixa'!$B$82:$IL$82<=MIN($C$6,IF($D$6="Dia",B32,IF($D$6="Semana",B32+6,IF($D$6="Mês",EOMONTH(B32,0),DATE(YEAR(B32),12,31))))))*'Fluxo de Caixa'!$B$140:$IL$140))} | G32: =IF(B32="","",(C32-E32)-(D32-F32)) | H32: =IF(B32="","",IFERROR(G32/ABS(D32-F32),0)) | J32: Frete sobre Vendas | K32: =SUMIFS(Lançamentos!$F:$F,Lançamentos!$A:$A,">="&$B$6,Lançamentos!$A:$A,"<="&$C$6,Lançamentos!$C:$C,J32,Lançamentos!$G:$G,IF($E$6="Todos","*",$E$6)) -> 0 | L32: {=SUMPRODUCT(('Fluxo de Caixa'!$B$82:$IL$82>=$B$6)*('Fluxo de Caixa'!$B$82:$IL$82<=$C$6)*'Fluxo de Caixa'!$B$113:$IL$113)} -> 0 | M32: =K32-L32 -> 0
B33: =IF(B32="","",IF($D$6="Dia",IF(B32+1>$C$6,"",B32+1),IF($D$6="Semana",IF(B32+7>$C$6,"",B32+7),IF($D$6="Mês",IF(EDATE(B32,1)>$C$6,"",EDATE(B32,1)),IF(DATE(YEAR(B32)+1,1,1)>$C$6,"",DATE(YEAR(B32)+1,1,1)))))) | C33: =IF(B33="","",SUMIFS(Lançamentos!$F:$F,Lançamentos!$A:$A,">="&B33,Lançamentos!$A:$A,"<="&MIN($C$6,IF($D$6="Dia",B33,IF($D$6="Semana",B33+6,IF($D$6="Mês",EOMONTH(B33,0),DATE(YEAR(B33),12,31))))),Lançamentos!$G:$G,IF($E$6="Todos","*",$E$6),Lançamentos!$D:$D,"Entrada")) | D33: {=IF(B33="","",SUMPRODUCT(('Fluxo de Caixa'!$B$82:$IL$82>=B33)*('Fluxo de Caixa'!$B$82:$IL$82<=MIN($C$6,IF($D$6="Dia",B33,IF($D$6="Semana",B33+6,IF($D$6="Mês",EOMONTH(B33,0),DATE(YEAR(B33),12,31))))))*'Fluxo de Caixa'!$B$96:$IL$96))} | E33: =IF(B33="","",SUMIFS(Lançamentos!$F:$F,Lançamentos!$A:$A,">="&B33,Lançamentos!$A:$A,"<="&MIN($C$6,IF($D$6="Dia",B33,IF($D$6="Semana",B33+6,IF($D$6="Mês",EOMONTH(B33,0),DATE(YEAR(B33),12,31))))),Lançamentos!$G:$G,IF($E$6="Todos","*",$E$6),Lançamentos!$D:$D,"Saída")) | F33: {=IF(B33="","",SUMPRODUCT(('Fluxo de Caixa'!$B$82:$IL$82>=B33)*('Fluxo de Caixa'!$B$82:$IL$82<=MIN($C$6,IF($D$6="Dia",B33,IF($D$6="Semana",B33+6,IF($D$6="Mês",EOMONTH(B33,0),DATE(YEAR(B33),12,31))))))*'Fluxo de Caixa'!$B$140:$IL$140))} | G33: =IF(B33="","",(C33-E33)-(D33-F33)) | H33: =IF(B33="","",IFERROR(G33/ABS(D33-F33),0)) | J33: Embalagens | K33: =SUMIFS(Lançamentos!$F:$F,Lançamentos!$A:$A,">="&$B$6,Lançamentos!$A:$A,"<="&$C$6,Lançamentos!$C:$C,J33,Lançamentos!$G:$G,IF($E$6="Todos","*",$E$6)) -> 0 | L33: {=SUMPRODUCT(('Fluxo de Caixa'!$B$82:$IL$82>=$B$6)*('Fluxo de Caixa'!$B$82:$IL$82<=$C$6)*'Fluxo de Caixa'!$B$114:$IL$114)} -> 0 | M33: =K33-L33 -> 0
B34: =IF(B33="","",IF($D$6="Dia",IF(B33+1>$C$6,"",B33+1),IF($D$6="Semana",IF(B33+7>$C$6,"",B33+7),IF($D$6="Mês",IF(EDATE(B33,1)>$C$6,"",EDATE(B33,1)),IF(DATE(YEAR(B33)+1,1,1)>$C$6,"",DATE(YEAR(B33)+1,1,1)))))) | C34: =IF(B34="","",SUMIFS(Lançamentos!$F:$F,Lançamentos!$A:$A,">="&B34,Lançamentos!$A:$A,"<="&MIN($C$6,IF($D$6="Dia",B34,IF($D$6="Semana",B34+6,IF($D$6="Mês",EOMONTH(B34,0),DATE(YEAR(B34),12,31))))),Lançamentos!$G:$G,IF($E$6="Todos","*",$E$6),Lançamentos!$D:$D,"Entrada")) | D34: {=IF(B34="","",SUMPRODUCT(('Fluxo de Caixa'!$B$82:$IL$82>=B34)*('Fluxo de Caixa'!$B$82:$IL$82<=MIN($C$6,IF($D$6="Dia",B34,IF($D$6="Semana",B34+6,IF($D$6="Mês",EOMONTH(B34,0),DATE(YEAR(B34),12,31))))))*'Fluxo de Caixa'!$B$96:$IL$96))} | E34: =IF(B34="","",SUMIFS(Lançamentos!$F:$F,Lançamentos!$A:$A,">="&B34,Lançamentos!$A:$A,"<="&MIN($C$6,IF($D$6="Dia",B34,IF($D$6="Semana",B34+6,IF($D$6="Mês",EOMONTH(B34,0),DATE(YEAR(B34),12,31))))),Lançamentos!$G:$G,IF($E$6="Todos","*",$E$6),Lançamentos!$D:$D,"Saída")) | F34: {=IF(B34="","",SUMPRODUCT(('Fluxo de Caixa'!$B$82:$IL$82>=B34)*('Fluxo de Caixa'!$B$82:$IL$82<=MIN($C$6,IF($D$6="Dia",B34,IF($D$6="Semana",B34+6,IF($D$6="Mês",EOMONTH(B34,0),DATE(YEAR(B34),12,31))))))*'Fluxo de Caixa'!$B$140:$IL$140))} | G34: =IF(B34="","",(C34-E34)-(D34-F34)) | H34: =IF(B34="","",IFERROR(G34/ABS(D34-F34),0)) | J34: Combustível | K34: =SUMIFS(Lançamentos!$F:$F,Lançamentos!$A:$A,">="&$B$6,Lançamentos!$A:$A,"<="&$C$6,Lançamentos!$C:$C,J34,Lançamentos!$G:$G,IF($E$6="Todos","*",$E$6)) -> 0 | L34: {=SUMPRODUCT(('Fluxo de Caixa'!$B$82:$IL$82>=$B$6)*('Fluxo de Caixa'!$B$82:$IL$82<=$C$6)*'Fluxo de Caixa'!$B$115:$IL$115)} -> 0 | M34: =K34-L34 -> 0
B35: =IF(B34="","",IF($D$6="Dia",IF(B34+1>$C$6,"",B34+1),IF($D$6="Semana",IF(B34+7>$C$6,"",B34+7),IF($D$6="Mês",IF(EDATE(B34,1)>$C$6,"",EDATE(B34,1)),IF(DATE(YEAR(B34)+1,1,1)>$C$6,"",DATE(YEAR(B34)+1,1,1)))))) | C35: =IF(B35="","",SUMIFS(Lançamentos!$F:$F,Lançamentos!$A:$A,">="&B35,Lançamentos!$A:$A,"<="&MIN($C$6,IF($D$6="Dia",B35,IF($D$6="Semana",B35+6,IF($D$6="Mês",EOMONTH(B35,0),DATE(YEAR(B35),12,31))))),Lançamentos!$G:$G,IF($E$6="Todos","*",$E$6),Lançamentos!$D:$D,"Entrada")) | D35: {=IF(B35="","",SUMPRODUCT(('Fluxo de Caixa'!$B$82:$IL$82>=B35)*('Fluxo de Caixa'!$B$82:$IL$82<=MIN($C$6,IF($D$6="Dia",B35,IF($D$6="Semana",B35+6,IF($D$6="Mês",EOMONTH(B35,0),DATE(YEAR(B35),12,31))))))*'Fluxo de Caixa'!$B$96:$IL$96))} | E35: =IF(B35="","",SUMIFS(Lançamentos!$F:$F,Lançamentos!$A:$A,">="&B35,Lançamentos!$A:$A,"<="&MIN($C$6,IF($D$6="Dia",B35,IF($D$6="Semana",B35+6,IF($D$6="Mês",EOMONTH(B35,0),DATE(YEAR(B35),12,31))))),Lançamentos!$G:$G,IF($E$6="Todos","*",$E$6),Lançamentos!$D:$D,"Saída")) | F35: {=IF(B35="","",SUMPRODUCT(('Fluxo de Caixa'!$B$82:$IL$82>=B35)*('Fluxo de Caixa'!$B$82:$IL$82<=MIN($C$6,IF($D$6="Dia",B35,IF($D$6="Semana",B35+6,IF($D$6="Mês",EOMONTH(B35,0),DATE(YEAR(B35),12,31))))))*'Fluxo de Caixa'!$B$140:$IL$140))} | G35: =IF(B35="","",(C35-E35)-(D35-F35)) | H35: =IF(B35="","",IFERROR(G35/ABS(D35-F35),0)) | J35: Pró-labore | K35: =SUMIFS(Lançamentos!$F:$F,Lançamentos!$A:$A,">="&$B$6,Lançamentos!$A:$A,"<="&$C$6,Lançamentos!$C:$C,J35,Lançamentos!$G:$G,IF($E$6="Todos","*",$E$6)) -> 0 | L35: {=SUMPRODUCT(('Fluxo de Caixa'!$B$82:$IL$82>=$B$6)*('Fluxo de Caixa'!$B$82:$IL$82<=$C$6)*'Fluxo de Caixa'!$B$116:$IL$116)} -> 0 | M35: =K35-L35 -> 0
B36: =IF(B35="","",IF($D$6="Dia",IF(B35+1>$C$6,"",B35+1),IF($D$6="Semana",IF(B35+7>$C$6,"",B35+7),IF($D$6="Mês",IF(EDATE(B35,1)>$C$6,"",EDATE(B35,1)),IF(DATE(YEAR(B35)+1,1,1)>$C$6,"",DATE(YEAR(B35)+1,1,1)))))) | C36: =IF(B36="","",SUMIFS(Lançamentos!$F:$F,Lançamentos!$A:$A,">="&B36,Lançamentos!$A:$A,"<="&MIN($C$6,IF($D$6="Dia",B36,IF($D$6="Semana",B36+6,IF($D$6="Mês",EOMONTH(B36,0),DATE(YEAR(B36),12,31))))),Lançamentos!$G:$G,IF($E$6="Todos","*",$E$6),Lançamentos!$D:$D,"Entrada")) | D36: {=IF(B36="","",SUMPRODUCT(('Fluxo de Caixa'!$B$82:$IL$82>=B36)*('Fluxo de Caixa'!$B$82:$IL$82<=MIN($C$6,IF($D$6="Dia",B36,IF($D$6="Semana",B36+6,IF($D$6="Mês",EOMONTH(B36,0),DATE(YEAR(B36),12,31))))))*'Fluxo de Caixa'!$B$96:$IL$96))} | E36: =IF(B36="","",SUMIFS(Lançamentos!$F:$F,Lançamentos!$A:$A,">="&B36,Lançamentos!$A:$A,"<="&MIN($C$6,IF($D$6="Dia",B36,IF($D$6="Semana",B36+6,IF($D$6="Mês",EOMONTH(B36,0),DATE(YEAR(B36),12,31))))),Lançamentos!$G:$G,IF($E$6="Todos","*",$E$6),Lançamentos!$D:$D,"Saída")) | F36: {=IF(B36="","",SUMPRODUCT(('Fluxo de Caixa'!$B$82:$IL$82>=B36)*('Fluxo de Caixa'!$B$82:$IL$82<=MIN($C$6,IF($D$6="Dia",B36,IF($D$6="Semana",B36+6,IF($D$6="Mês",EOMONTH(B36,0),DATE(YEAR(B36),12,31))))))*'Fluxo de Caixa'!$B$140:$IL$140))} | G36: =IF(B36="","",(C36-E36)-(D36-F36)) | H36: =IF(B36="","",IFERROR(G36/ABS(D36-F36),0)) | J36: Benefícios (VR/VT/Plano) | K36: =SUMIFS(Lançamentos!$F:$F,Lançamentos!$A:$A,">="&$B$6,Lançamentos!$A:$A,"<="&$C$6,Lançamentos!$C:$C,J36,Lançamentos!$G:$G,IF($E$6="Todos","*",$E$6)) -> 0 | L36: {=SUMPRODUCT(('Fluxo de Caixa'!$B$82:$IL$82>=$B$6)*('Fluxo de Caixa'!$B$82:$IL$82<=$C$6)*'Fluxo de Caixa'!$B$117:$IL$117)} -> 0 | M36: =K36-L36 -> 0
B37: =IF(B36="","",IF($D$6="Dia",IF(B36+1>$C$6,"",B36+1),IF($D$6="Semana",IF(B36+7>$C$6,"",B36+7),IF($D$6="Mês",IF(EDATE(B36,1)>$C$6,"",EDATE(B36,1)),IF(DATE(YEAR(B36)+1,1,1)>$C$6,"",DATE(YEAR(B36)+1,1,1)))))) | C37: =IF(B37="","",SUMIFS(Lançamentos!$F:$F,Lançamentos!$A:$A,">="&B37,Lançamentos!$A:$A,"<="&MIN($C$6,IF($D$6="Dia",B37,IF($D$6="Semana",B37+6,IF($D$6="Mês",EOMONTH(B37,0),DATE(YEAR(B37),12,31))))),Lançamentos!$G:$G,IF($E$6="Todos","*",$E$6),Lançamentos!$D:$D,"Entrada")) | D37: {=IF(B37="","",SUMPRODUCT(('Fluxo de Caixa'!$B$82:$IL$82>=B37)*('Fluxo de Caixa'!$B$82:$IL$82<=MIN($C$6,IF($D$6="Dia",B37,IF($D$6="Semana",B37+6,IF($D$6="Mês",EOMONTH(B37,0),DATE(YEAR(B37),12,31))))))*'Fluxo de Caixa'!$B$96:$IL$96))} | E37: =IF(B37="","",SUMIFS(Lançamentos!$F:$F,Lançamentos!$A:$A,">="&B37,Lançamentos!$A:$A,"<="&MIN($C$6,IF($D$6="Dia",B37,IF($D$6="Semana",B37+6,IF($D$6="Mês",EOMONTH(B37,0),DATE(YEAR(B37),12,31))))),Lançamentos!$G:$G,IF($E$6="Todos","*",$E$6),Lançamentos!$D:$D,"Saída")) | F37: {=IF(B37="","",SUMPRODUCT(('Fluxo de Caixa'!$B$82:$IL$82>=B37)*('Fluxo de Caixa'!$B$82:$IL$82<=MIN($C$6,IF($D$6="Dia",B37,IF($D$6="Semana",B37+6,IF($D$6="Mês",EOMONTH(B37,0),DATE(YEAR(B37),12,31))))))*'Fluxo de Caixa'!$B$140:$IL$140))} | G37: =IF(B37="","",(C37-E37)-(D37-F37)) | H37: =IF(B37="","",IFERROR(G37/ABS(D37-F37),0)) | J37: Software e Assinaturas | K37: =SUMIFS(Lançamentos!$F:$F,Lançamentos!$A:$A,">="&$B$6,Lançamentos!$A:$A,"<="&$C$6,Lançamentos!$C:$C,J37,Lançamentos!$G:$G,IF($E$6="Todos","*",$E$6)) -> 0 | L37: {=SUMPRODUCT(('Fluxo de Caixa'!$B$82:$IL$82>=$B$6)*('Fluxo de Caixa'!$B$82:$IL$82<=$C$6)*'Fluxo de Caixa'!$B$118:$IL$118)} -> 0 | M37: =K37-L37 -> 0
B38: =IF(B37="","",IF($D$6="Dia",IF(B37+1>$C$6,"",B37+1),IF($D$6="Semana",IF(B37+7>$C$6,"",B37+7),IF($D$6="Mês",IF(EDATE(B37,1)>$C$6,"",EDATE(B37,1)),IF(DATE(YEAR(B37)+1,1,1)>$C$6,"",DATE(YEAR(B37)+1,1,1)))))) | C38: =IF(B38="","",SUMIFS(Lançamentos!$F:$F,Lançamentos!$A:$A,">="&B38,Lançamentos!$A:$A,"<="&MIN($C$6,IF($D$6="Dia",B38,IF($D$6="Semana",B38+6,IF($D$6="Mês",EOMONTH(B38,0),DATE(YEAR(B38),12,31))))),Lançamentos!$G:$G,IF($E$6="Todos","*",$E$6),Lançamentos!$D:$D,"Entrada")) | D38: {=IF(B38="","",SUMPRODUCT(('Fluxo de Caixa'!$B$82:$IL$82>=B38)*('Fluxo de Caixa'!$B$82:$IL$82<=MIN($C$6,IF($D$6="Dia",B38,IF($D$6="Semana",B38+6,IF($D$6="Mês",EOMONTH(B38,0),DATE(YEAR(B38),12,31))))))*'Fluxo de Caixa'!$B$96:$IL$96))} | E38: =IF(B38="","",SUMIFS(Lançamentos!$F:$F,Lançamentos!$A:$A,">="&B38,Lançamentos!$A:$A,"<="&MIN($C$6,IF($D$6="Dia",B38,IF($D$6="Semana",B38+6,IF($D$6="Mês",EOMONTH(B38,0),DATE(YEAR(B38),12,31))))),Lançamentos!$G:$G,IF($E$6="Todos","*",$E$6),Lançamentos!$D:$D,"Saída")) | F38: {=IF(B38="","",SUMPRODUCT(('Fluxo de Caixa'!$B$82:$IL$82>=B38)*('Fluxo de Caixa'!$B$82:$IL$82<=MIN($C$6,IF($D$6="Dia",B38,IF($D$6="Semana",B38+6,IF($D$6="Mês",EOMONTH(B38,0),DATE(YEAR(B38),12,31))))))*'Fluxo de Caixa'!$B$140:$IL$140))} | G38: =IF(B38="","",(C38-E38)-(D38-F38)) | H38: =IF(B38="","",IFERROR(G38/ABS(D38-F38),0)) | J38: Telefone e Celular | K38: =SUMIFS(Lançamentos!$F:$F,Lançamentos!$A:$A,">="&$B$6,Lançamentos!$A:$A,"<="&$C$6,Lançamentos!$C:$C,J38,Lançamentos!$G:$G,IF($E$6="Todos","*",$E$6)) -> 0 | L38: {=SUMPRODUCT(('Fluxo de Caixa'!$B$82:$IL$82>=$B$6)*('Fluxo de Caixa'!$B$82:$IL$82<=$C$6)*'Fluxo de Caixa'!$B$119:$IL$119)} -> 0 | M38: =K38-L38 -> 0
B39: =IF(B38="","",IF($D$6="Dia",IF(B38+1>$C$6,"",B38+1),IF($D$6="Semana",IF(B38+7>$C$6,"",B38+7),IF($D$6="Mês",IF(EDATE(B38,1)>$C$6,"",EDATE(B38,1)),IF(DATE(YEAR(B38)+1,1,1)>$C$6,"",DATE(YEAR(B38)+1,1,1)))))) | C39: =IF(B39="","",SUMIFS(Lançamentos!$F:$F,Lançamentos!$A:$A,">="&B39,Lançamentos!$A:$A,"<="&MIN($C$6,IF($D$6="Dia",B39,IF($D$6="Semana",B39+6,IF($D$6="Mês",EOMONTH(B39,0),DATE(YEAR(B39),12,31))))),Lançamentos!$G:$G,IF($E$6="Todos","*",$E$6),Lançamentos!$D:$D,"Entrada")) | D39: {=IF(B39="","",SUMPRODUCT(('Fluxo de Caixa'!$B$82:$IL$82>=B39)*('Fluxo de Caixa'!$B$82:$IL$82<=MIN($C$6,IF($D$6="Dia",B39,IF($D$6="Semana",B39+6,IF($D$6="Mês",EOMONTH(B39,0),DATE(YEAR(B39),12,31))))))*'Fluxo de Caixa'!$B$96:$IL$96))} | E39: =IF(B39="","",SUMIFS(Lançamentos!$F:$F,Lançamentos!$A:$A,">="&B39,Lançamentos!$A:$A,"<="&MIN($C$6,IF($D$6="Dia",B39,IF($D$6="Semana",B39+6,IF($D$6="Mês",EOMONTH(B39,0),DATE(YEAR(B39),12,31))))),Lançamentos!$G:$G,IF($E$6="Todos","*",$E$6),Lançamentos!$D:$D,"Saída")) | F39: {=IF(B39="","",SUMPRODUCT(('Fluxo de Caixa'!$B$82:$IL$82>=B39)*('Fluxo de Caixa'!$B$82:$IL$82<=MIN($C$6,IF($D$6="Dia",B39,IF($D$6="Semana",B39+6,IF($D$6="Mês",EOMONTH(B39,0),DATE(YEAR(B39),12,31))))))*'Fluxo de Caixa'!$B$140:$IL$140))} | G39: =IF(B39="","",(C39-E39)-(D39-F39)) | H39: =IF(B39="","",IFERROR(G39/ABS(D39-F39),0)) | J39: Limpeza e Conservação | K39: =SUMIFS(Lançamentos!$F:$F,Lançamentos!$A:$A,">="&$B$6,Lançamentos!$A:$A,"<="&$C$6,Lançamentos!$C:$C,J39,Lançamentos!$G:$G,IF($E$6="Todos","*",$E$6)) -> 0 | L39: {=SUMPRODUCT(('Fluxo de Caixa'!$B$82:$IL$82>=$B$6)*('Fluxo de Caixa'!$B$82:$IL$82<=$C$6)*'Fluxo de Caixa'!$B$120:$IL$120)} -> 0 | M39: =K39-L39 -> 0
B40: =IF(B39="","",IF($D$6="Dia",IF(B39+1>$C$6,"",B39+1),IF($D$6="Semana",IF(B39+7>$C$6,"",B39+7),IF($D$6="Mês",IF(EDATE(B39,1)>$C$6,"",EDATE(B39,1)),IF(DATE(YEAR(B39)+1,1,1)>$C$6,"",DATE(YEAR(B39)+1,1,1)))))) | C40: =IF(B40="","",SUMIFS(Lançamentos!$F:$F,Lançamentos!$A:$A,">="&B40,Lançamentos!$A:$A,"<="&MIN($C$6,IF($D$6="Dia",B40,IF($D$6="Semana",B40+6,IF($D$6="Mês",EOMONTH(B40,0),DATE(YEAR(B40),12,31))))),Lançamentos!$G:$G,IF($E$6="Todos","*",$E$6),Lançamentos!$D:$D,"Entrada")) | D40: {=IF(B40="","",SUMPRODUCT(('Fluxo de Caixa'!$B$82:$IL$82>=B40)*('Fluxo de Caixa'!$B$82:$IL$82<=MIN($C$6,IF($D$6="Dia",B40,IF($D$6="Semana",B40+6,IF($D$6="Mês",EOMONTH(B40,0),DATE(YEAR(B40),12,31))))))*'Fluxo de Caixa'!$B$96:$IL$96))} | E40: =IF(B40="","",SUMIFS(Lançamentos!$F:$F,Lançamentos!$A:$A,">="&B40,Lançamentos!$A:$A,"<="&MIN($C$6,IF($D$6="Dia",B40,IF($D$6="Semana",B40+6,IF($D$6="Mês",EOMONTH(B40,0),DATE(YEAR(B40),12,31))))),Lançamentos!$G:$G,IF($E$6="Todos","*",$E$6),Lançamentos!$D:$D,"Saída")) | F40: {=IF(B40="","",SUMPRODUCT(('Fluxo de Caixa'!$B$82:$IL$82>=B40)*('Fluxo de Caixa'!$B$82:$IL$82<=MIN($C$6,IF($D$6="Dia",B40,IF($D$6="Semana",B40+6,IF($D$6="Mês",EOMONTH(B40,0),DATE(YEAR(B40),12,31))))))*'Fluxo de Caixa'!$B$140:$IL$140))} | G40: =IF(B40="","",(C40-E40)-(D40-F40)) | H40: =IF(B40="","",IFERROR(G40/ABS(D40-F40),0)) | J40: Seguros | K40: =SUMIFS(Lançamentos!$F:$F,Lançamentos!$A:$A,">="&$B$6,Lançamentos!$A:$A,"<="&$C$6,Lançamentos!$C:$C,J40,Lançamentos!$G:$G,IF($E$6="Todos","*",$E$6)) -> 0 | L40: {=SUMPRODUCT(('Fluxo de Caixa'!$B$82:$IL$82>=$B$6)*('Fluxo de Caixa'!$B$82:$IL$82<=$C$6)*'Fluxo de Caixa'!$B$121:$IL$121)} -> 0 | M40: =K40-L40 -> 0
B41: =IF(B40="","",IF($D$6="Dia",IF(B40+1>$C$6,"",B40+1),IF($D$6="Semana",IF(B40+7>$C$6,"",B40+7),IF($D$6="Mês",IF(EDATE(B40,1)>$C$6,"",EDATE(B40,1)),IF(DATE(YEAR(B40)+1,1,1)>$C$6,"",DATE(YEAR(B40)+1,1,1)))))) | C41: =IF(B41="","",SUMIFS(Lançamentos!$F:$F,Lançamentos!$A:$A,">="&B41,Lançamentos!$A:$A,"<="&MIN($C$6,IF($D$6="Dia",B41,IF($D$6="Semana",B41+6,IF($D$6="Mês",EOMONTH(B41,0),DATE(YEAR(B41),12,31))))),Lançamentos!$G:$G,IF($E$6="Todos","*",$E$6),Lançamentos!$D:$D,"Entrada")) | D41: {=IF(B41="","",SUMPRODUCT(('Fluxo de Caixa'!$B$82:$IL$82>=B41)*('Fluxo de Caixa'!$B$82:$IL$82<=MIN($C$6,IF($D$6="Dia",B41,IF($D$6="Semana",B41+6,IF($D$6="Mês",EOMONTH(B41,0),DATE(YEAR(B41),12,31))))))*'Fluxo de Caixa'!$B$96:$IL$96))} | E41: =IF(B41="","",SUMIFS(Lançamentos!$F:$F,Lançamentos!$A:$A,">="&B41,Lançamentos!$A:$A,"<="&MIN($C$6,IF($D$6="Dia",B41,IF($D$6="Semana",B41+6,IF($D$6="Mês",EOMONTH(B41,0),DATE(YEAR(B41),12,31))))),Lançamentos!$G:$G,IF($E$6="Todos","*",$E$6),Lançamentos!$D:$D,"Saída")) | F41: {=IF(B41="","",SUMPRODUCT(('Fluxo de Caixa'!$B$82:$IL$82>=B41)*('Fluxo de Caixa'!$B$82:$IL$82<=MIN($C$6,IF($D$6="Dia",B41,IF($D$6="Semana",B41+6,IF($D$6="Mês",EOMONTH(B41,0),DATE(YEAR(B41),12,31))))))*'Fluxo de Caixa'!$B$140:$IL$140))} | G41: =IF(B41="","",(C41-E41)-(D41-F41)) | H41: =IF(B41="","",IFERROR(G41/ABS(D41-F41),0)) | J41: Treinamento e Capacitação | K41: =SUMIFS(Lançamentos!$F:$F,Lançamentos!$A:$A,">="&$B$6,Lançamentos!$A:$A,"<="&$C$6,Lançamentos!$C:$C,J41,Lançamentos!$G:$G,IF($E$6="Todos","*",$E$6)) -> 0 | L41: {=SUMPRODUCT(('Fluxo de Caixa'!$B$82:$IL$82>=$B$6)*('Fluxo de Caixa'!$B$82:$IL$82<=$C$6)*'Fluxo de Caixa'!$B$122:$IL$122)} -> 0 | M41: =K41-L41 -> 0
B42: =IF(B41="","",IF($D$6="Dia",IF(B41+1>$C$6,"",B41+1),IF($D$6="Semana",IF(B41+7>$C$6,"",B41+7),IF($D$6="Mês",IF(EDATE(B41,1)>$C$6,"",EDATE(B41,1)),IF(DATE(YEAR(B41)+1,1,1)>$C$6,"",DATE(YEAR(B41)+1,1,1)))))) | C42: =IF(B42="","",SUMIFS(Lançamentos!$F:$F,Lançamentos!$A:$A,">="&B42,Lançamentos!$A:$A,"<="&MIN($C$6,IF($D$6="Dia",B42,IF($D$6="Semana",B42+6,IF($D$6="Mês",EOMONTH(B42,0),DATE(YEAR(B42),12,31))))),Lançamentos!$G:$G,IF($E$6="Todos","*",$E$6),Lançamentos!$D:$D,"Entrada")) | D42: {=IF(B42="","",SUMPRODUCT(('Fluxo de Caixa'!$B$82:$IL$82>=B42)*('Fluxo de Caixa'!$B$82:$IL$82<=MIN($C$6,IF($D$6="Dia",B42,IF($D$6="Semana",B42+6,IF($D$6="Mês",EOMONTH(B42,0),DATE(YEAR(B42),12,31))))))*'Fluxo de Caixa'!$B$96:$IL$96))} | E42: =IF(B42="","",SUMIFS(Lançamentos!$F:$F,Lançamentos!$A:$A,">="&B42,Lançamentos!$A:$A,"<="&MIN($C$6,IF($D$6="Dia",B42,IF($D$6="Semana",B42+6,IF($D$6="Mês",EOMONTH(B42,0),DATE(YEAR(B42),12,31))))),Lançamentos!$G:$G,IF($E$6="Todos","*",$E$6),Lançamentos!$D:$D,"Saída")) | F42: {=IF(B42="","",SUMPRODUCT(('Fluxo de Caixa'!$B$82:$IL$82>=B42)*('Fluxo de Caixa'!$B$82:$IL$82<=MIN($C$6,IF($D$6="Dia",B42,IF($D$6="Semana",B42+6,IF($D$6="Mês",EOMONTH(B42,0),DATE(YEAR(B42),12,31))))))*'Fluxo de Caixa'!$B$140:$IL$140))} | G42: =IF(B42="","",(C42-E42)-(D42-F42)) | H42: =IF(B42="","",IFERROR(G42/ABS(D42-F42),0)) | J42: Honorários Contábeis | K42: =SUMIFS(Lançamentos!$F:$F,Lançamentos!$A:$A,">="&$B$6,Lançamentos!$A:$A,"<="&$C$6,Lançamentos!$C:$C,J42,Lançamentos!$G:$G,IF($E$6="Todos","*",$E$6)) -> 0 | L42: {=SUMPRODUCT(('Fluxo de Caixa'!$B$82:$IL$82>=$B$6)*('Fluxo de Caixa'!$B$82:$IL$82<=$C$6)*'Fluxo de Caixa'!$B$123:$IL$123)} -> 0 | M42: =K42-L42 -> 0
B43: =IF(B42="","",IF($D$6="Dia",IF(B42+1>$C$6,"",B42+1),IF($D$6="Semana",IF(B42+7>$C$6,"",B42+7),IF($D$6="Mês",IF(EDATE(B42,1)>$C$6,"",EDATE(B42,1)),IF(DATE(YEAR(B42)+1,1,1)>$C$6,"",DATE(YEAR(B42)+1,1,1)))))) | C43: =IF(B43="","",SUMIFS(Lançamentos!$F:$F,Lançamentos!$A:$A,">="&B43,Lançamentos!$A:$A,"<="&MIN($C$6,IF($D$6="Dia",B43,IF($D$6="Semana",B43+6,IF($D$6="Mês",EOMONTH(B43,0),DATE(YEAR(B43),12,31))))),Lançamentos!$G:$G,IF($E$6="Todos","*",$E$6),Lançamentos!$D:$D,"Entrada")) | D43: {=IF(B43="","",SUMPRODUCT(('Fluxo de Caixa'!$B$82:$IL$82>=B43)*('Fluxo de Caixa'!$B$82:$IL$82<=MIN($C$6,IF($D$6="Dia",B43,IF($D$6="Semana",B43+6,IF($D$6="Mês",EOMONTH(B43,0),DATE(YEAR(B43),12,31))))))*'Fluxo de Caixa'!$B$96:$IL$96))} | E43: =IF(B43="","",SUMIFS(Lançamentos!$F:$F,Lançamentos!$A:$A,">="&B43,Lançamentos!$A:$A,"<="&MIN($C$6,IF($D$6="Dia",B43,IF($D$6="Semana",B43+6,IF($D$6="Mês",EOMONTH(B43,0),DATE(YEAR(B43),12,31))))),Lançamentos!$G:$G,IF($E$6="Todos","*",$E$6),Lançamentos!$D:$D,"Saída")) | F43: {=IF(B43="","",SUMPRODUCT(('Fluxo de Caixa'!$B$82:$IL$82>=B43)*('Fluxo de Caixa'!$B$82:$IL$82<=MIN($C$6,IF($D$6="Dia",B43,IF($D$6="Semana",B43+6,IF($D$6="Mês",EOMONTH(B43,0),DATE(YEAR(B43),12,31))))))*'Fluxo de Caixa'!$B$140:$IL$140))} | G43: =IF(B43="","",(C43-E43)-(D43-F43)) | H43: =IF(B43="","",IFERROR(G43/ABS(D43-F43),0)) | J43: Honorários Jurídicos | K43: =SUMIFS(Lançamentos!$F:$F,Lançamentos!$A:$A,">="&$B$6,Lançamentos!$A:$A,"<="&$C$6,Lançamentos!$C:$C,J43,Lançamentos!$G:$G,IF($E$6="Todos","*",$E$6)) -> 0 | L43: {=SUMPRODUCT(('Fluxo de Caixa'!$B$82:$IL$82>=$B$6)*('Fluxo de Caixa'!$B$82:$IL$82<=$C$6)*'Fluxo de Caixa'!$B$124:$IL$124)} -> 0 | M43: =K43-L43 -> 0
B44: =IF(B43="","",IF($D$6="Dia",IF(B43+1>$C$6,"",B43+1),IF($D$6="Semana",IF(B43+7>$C$6,"",B43+7),IF($D$6="Mês",IF(EDATE(B43,1)>$C$6,"",EDATE(B43,1)),IF(DATE(YEAR(B43)+1,1,1)>$C$6,"",DATE(YEAR(B43)+1,1,1)))))) | C44: =IF(B44="","",SUMIFS(Lançamentos!$F:$F,Lançamentos!$A:$A,">="&B44,Lançamentos!$A:$A,"<="&MIN($C$6,IF($D$6="Dia",B44,IF($D$6="Semana",B44+6,IF($D$6="Mês",EOMONTH(B44,0),DATE(YEAR(B44),12,31))))),Lançamentos!$G:$G,IF($E$6="Todos","*",$E$6),Lançamentos!$D:$D,"Entrada")) | D44: {=IF(B44="","",SUMPRODUCT(('Fluxo de Caixa'!$B$82:$IL$82>=B44)*('Fluxo de Caixa'!$B$82:$IL$82<=MIN($C$6,IF($D$6="Dia",B44,IF($D$6="Semana",B44+6,IF($D$6="Mês",EOMONTH(B44,0),DATE(YEAR(B44),12,31))))))*'Fluxo de Caixa'!$B$96:$IL$96))} | E44: =IF(B44="","",SUMIFS(Lançamentos!$F:$F,Lançamentos!$A:$A,">="&B44,Lançamentos!$A:$A,"<="&MIN($C$6,IF($D$6="Dia",B44,IF($D$6="Semana",B44+6,IF($D$6="Mês",EOMONTH(B44,0),DATE(YEAR(B44),12,31))))),Lançamentos!$G:$G,IF($E$6="Todos","*",$E$6),Lançamentos!$D:$D,"Saída")) | F44: {=IF(B44="","",SUMPRODUCT(('Fluxo de Caixa'!$B$82:$IL$82>=B44)*('Fluxo de Caixa'!$B$82:$IL$82<=MIN($C$6,IF($D$6="Dia",B44,IF($D$6="Semana",B44+6,IF($D$6="Mês",EOMONTH(B44,0),DATE(YEAR(B44),12,31))))))*'Fluxo de Caixa'!$B$140:$IL$140))} | G44: =IF(B44="","",(C44-E44)-(D44-F44)) | H44: =IF(B44="","",IFERROR(G44/ABS(D44-F44),0)) | J44: Equipamentos e Informática | K44: =SUMIFS(Lançamentos!$F:$F,Lançamentos!$A:$A,">="&$B$6,Lançamentos!$A:$A,"<="&$C$6,Lançamentos!$C:$C,J44,Lançamentos!$G:$G,IF($E$6="Todos","*",$E$6)) -> 0 | L44: {=SUMPRODUCT(('Fluxo de Caixa'!$B$82:$IL$82>=$B$6)*('Fluxo de Caixa'!$B$82:$IL$82<=$C$6)*'Fluxo de Caixa'!$B$125:$IL$125)} -> 0 | M44: =K44-L44 -> 0
B45: =IF(B44="","",IF($D$6="Dia",IF(B44+1>$C$6,"",B44+1),IF($D$6="Semana",IF(B44+7>$C$6,"",B44+7),IF($D$6="Mês",IF(EDATE(B44,1)>$C$6,"",EDATE(B44,1)),IF(DATE(YEAR(B44)+1,1,1)>$C$6,"",DATE(YEAR(B44)+1,1,1)))))) | C45: =IF(B45="","",SUMIFS(Lançamentos!$F:$F,Lançamentos!$A:$A,">="&B45,Lançamentos!$A:$A,"<="&MIN($C$6,IF($D$6="Dia",B45,IF($D$6="Semana",B45+6,IF($D$6="Mês",EOMONTH(B45,0),DATE(YEAR(B45),12,31))))),Lançamentos!$G:$G,IF($E$6="Todos","*",$E$6),Lançamentos!$D:$D,"Entrada")) | D45: {=IF(B45="","",SUMPRODUCT(('Fluxo de Caixa'!$B$82:$IL$82>=B45)*('Fluxo de Caixa'!$B$82:$IL$82<=MIN($C$6,IF($D$6="Dia",B45,IF($D$6="Semana",B45+6,IF($D$6="Mês",EOMONTH(B45,0),DATE(YEAR(B45),12,31))))))*'Fluxo de Caixa'!$B$96:$IL$96))} | E45: =IF(B45="","",SUMIFS(Lançamentos!$F:$F,Lançamentos!$A:$A,">="&B45,Lançamentos!$A:$A,"<="&MIN($C$6,IF($D$6="Dia",B45,IF($D$6="Semana",B45+6,IF($D$6="Mês",EOMONTH(B45,0),DATE(YEAR(B45),12,31))))),Lançamentos!$G:$G,IF($E$6="Todos","*",$E$6),Lançamentos!$D:$D,"Saída")) | F45: {=IF(B45="","",SUMPRODUCT(('Fluxo de Caixa'!$B$82:$IL$82>=B45)*('Fluxo de Caixa'!$B$82:$IL$82<=MIN($C$6,IF($D$6="Dia",B45,IF($D$6="Semana",B45+6,IF($D$6="Mês",EOMONTH(B45,0),DATE(YEAR(B45),12,31))))))*'Fluxo de Caixa'!$B$140:$IL$140))} | G45: =IF(B45="","",(C45-E45)-(D45-F45)) | H45: =IF(B45="","",IFERROR(G45/ABS(D45-F45),0)) | J45: Móveis e Utensílios | K45: =SUMIFS(Lançamentos!$F:$F,Lançamentos!$A:$A,">="&$B$6,Lançamentos!$A:$A,"<="&$C$6,Lançamentos!$C:$C,J45,Lançamentos!$G:$G,IF($E$6="Todos","*",$E$6)) -> 0 | L45: {=SUMPRODUCT(('Fluxo de Caixa'!$B$82:$IL$82>=$B$6)*('Fluxo de Caixa'!$B$82:$IL$82<=$C$6)*'Fluxo de Caixa'!$B$126:$IL$126)} -> 0 | M45: =K45-L45 -> 0
B46: =IF(B45="","",IF($D$6="Dia",IF(B45+1>$C$6,"",B45+1),IF($D$6="Semana",IF(B45+7>$C$6,"",B45+7),IF($D$6="Mês",IF(EDATE(B45,1)>$C$6,"",EDATE(B45,1)),IF(DATE(YEAR(B45)+1,1,1)>$C$6,"",DATE(YEAR(B45)+1,1,1)))))) | C46: =IF(B46="","",SUMIFS(Lançamentos!$F:$F,Lançamentos!$A:$A,">="&B46,Lançamentos!$A:$A,"<="&MIN($C$6,IF($D$6="Dia",B46,IF($D$6="Semana",B46+6,IF($D$6="Mês",EOMONTH(B46,0),DATE(YEAR(B46),12,31))))),Lançamentos!$G:$G,IF($E$6="Todos","*",$E$6),Lançamentos!$D:$D,"Entrada")) | D46: {=IF(B46="","",SUMPRODUCT(('Fluxo de Caixa'!$B$82:$IL$82>=B46)*('Fluxo de Caixa'!$B$82:$IL$82<=MIN($C$6,IF($D$6="Dia",B46,IF($D$6="Semana",B46+6,IF($D$6="Mês",EOMONTH(B46,0),DATE(YEAR(B46),12,31))))))*'Fluxo de Caixa'!$B$96:$IL$96))} | E46: =IF(B46="","",SUMIFS(Lançamentos!$F:$F,Lançamentos!$A:$A,">="&B46,Lançamentos!$A:$A,"<="&MIN($C$6,IF($D$6="Dia",B46,IF($D$6="Semana",B46+6,IF($D$6="Mês",EOMONTH(B46,0),DATE(YEAR(B46),12,31))))),Lançamentos!$G:$G,IF($E$6="Todos","*",$E$6),Lançamentos!$D:$D,"Saída")) | F46: {=IF(B46="","",SUMPRODUCT(('Fluxo de Caixa'!$B$82:$IL$82>=B46)*('Fluxo de Caixa'!$B$82:$IL$82<=MIN($C$6,IF($D$6="Dia",B46,IF($D$6="Semana",B46+6,IF($D$6="Mês",EOMONTH(B46,0),DATE(YEAR(B46),12,31))))))*'Fluxo de Caixa'!$B$140:$IL$140))} | G46: =IF(B46="","",(C46-E46)-(D46-F46)) | H46: =IF(B46="","",IFERROR(G46/ABS(D46-F46),0)) | J46: Refeições e Confraternizações | K46: =SUMIFS(Lançamentos!$F:$F,Lançamentos!$A:$A,">="&$B$6,Lançamentos!$A:$A,"<="&$C$6,Lançamentos!$C:$C,J46,Lançamentos!$G:$G,IF($E$6="Todos","*",$E$6)) -> 0 | L46: {=SUMPRODUCT(('Fluxo de Caixa'!$B$82:$IL$82>=$B$6)*('Fluxo de Caixa'!$B$82:$IL$82<=$C$6)*'Fluxo de Caixa'!$B$127:$IL$127)} -> 0 | M46: =K46-L46 -> 0
B47: =IF(B46="","",IF($D$6="Dia",IF(B46+1>$C$6,"",B46+1),IF($D$6="Semana",IF(B46+7>$C$6,"",B46+7),IF($D$6="Mês",IF(EDATE(B46,1)>$C$6,"",EDATE(B46,1)),IF(DATE(YEAR(B46)+1,1,1)>$C$6,"",DATE(YEAR(B46)+1,1,1)))))) | C47: =IF(B47="","",SUMIFS(Lançamentos!$F:$F,Lançamentos!$A:$A,">="&B47,Lançamentos!$A:$A,"<="&MIN($C$6,IF($D$6="Dia",B47,IF($D$6="Semana",B47+6,IF($D$6="Mês",EOMONTH(B47,0),DATE(YEAR(B47),12,31))))),Lançamentos!$G:$G,IF($E$6="Todos","*",$E$6),Lançamentos!$D:$D,"Entrada")) | D47: {=IF(B47="","",SUMPRODUCT(('Fluxo de Caixa'!$B$82:$IL$82>=B47)*('Fluxo de Caixa'!$B$82:$IL$82<=MIN($C$6,IF($D$6="Dia",B47,IF($D$6="Semana",B47+6,IF($D$6="Mês",EOMONTH(B47,0),DATE(YEAR(B47),12,31))))))*'Fluxo de Caixa'!$B$96:$IL$96))} | E47: =IF(B47="","",SUMIFS(Lançamentos!$F:$F,Lançamentos!$A:$A,">="&B47,Lançamentos!$A:$A,"<="&MIN($C$6,IF($D$6="Dia",B47,IF($D$6="Semana",B47+6,IF($D$6="Mês",EOMONTH(B47,0),DATE(YEAR(B47),12,31))))),Lançamentos!$G:$G,IF($E$6="Todos","*",$E$6),Lançamentos!$D:$D,"Saída")) | F47: {=IF(B47="","",SUMPRODUCT(('Fluxo de Caixa'!$B$82:$IL$82>=B47)*('Fluxo de Caixa'!$B$82:$IL$82<=MIN($C$6,IF($D$6="Dia",B47,IF($D$6="Semana",B47+6,IF($D$6="Mês",EOMONTH(B47,0),DATE(YEAR(B47),12,31))))))*'Fluxo de Caixa'!$B$140:$IL$140))} | G47: =IF(B47="","",(C47-E47)-(D47-F47)) | H47: =IF(B47="","",IFERROR(G47/ABS(D47-F47),0)) | J47: Correios e Entregas | K47: =SUMIFS(Lançamentos!$F:$F,Lançamentos!$A:$A,">="&$B$6,Lançamentos!$A:$A,"<="&$C$6,Lançamentos!$C:$C,J47,Lançamentos!$G:$G,IF($E$6="Todos","*",$E$6)) -> 0 | L47: {=SUMPRODUCT(('Fluxo de Caixa'!$B$82:$IL$82>=$B$6)*('Fluxo de Caixa'!$B$82:$IL$82<=$C$6)*'Fluxo de Caixa'!$B$128:$IL$128)} -> 0 | M47: =K47-L47 -> 0
B48: =IF(B47="","",IF($D$6="Dia",IF(B47+1>$C$6,"",B47+1),IF($D$6="Semana",IF(B47+7>$C$6,"",B47+7),IF($D$6="Mês",IF(EDATE(B47,1)>$C$6,"",EDATE(B47,1)),IF(DATE(YEAR(B47)+1,1,1)>$C$6,"",DATE(YEAR(B47)+1,1,1)))))) | C48: =IF(B48="","",SUMIFS(Lançamentos!$F:$F,Lançamentos!$A:$A,">="&B48,Lançamentos!$A:$A,"<="&MIN($C$6,IF($D$6="Dia",B48,IF($D$6="Semana",B48+6,IF($D$6="Mês",EOMONTH(B48,0),DATE(YEAR(B48),12,31))))),Lançamentos!$G:$G,IF($E$6="Todos","*",$E$6),Lançamentos!$D:$D,"Entrada")) | D48: {=IF(B48="","",SUMPRODUCT(('Fluxo de Caixa'!$B$82:$IL$82>=B48)*('Fluxo de Caixa'!$B$82:$IL$82<=MIN($C$6,IF($D$6="Dia",B48,IF($D$6="Semana",B48+6,IF($D$6="Mês",EOMONTH(B48,0),DATE(YEAR(B48),12,31))))))*'Fluxo de Caixa'!$B$96:$IL$96))} | E48: =IF(B48="","",SUMIFS(Lançamentos!$F:$F,Lançamentos!$A:$A,">="&B48,Lançamentos!$A:$A,"<="&MIN($C$6,IF($D$6="Dia",B48,IF($D$6="Semana",B48+6,IF($D$6="Mês",EOMONTH(B48,0),DATE(YEAR(B48),12,31))))),Lançamentos!$G:$G,IF($E$6="Todos","*",$E$6),Lançamentos!$D:$D,"Saída")) | F48: {=IF(B48="","",SUMPRODUCT(('Fluxo de Caixa'!$B$82:$IL$82>=B48)*('Fluxo de Caixa'!$B$82:$IL$82<=MIN($C$6,IF($D$6="Dia",B48,IF($D$6="Semana",B48+6,IF($D$6="Mês",EOMONTH(B48,0),DATE(YEAR(B48),12,31))))))*'Fluxo de Caixa'!$B$140:$IL$140))} | G48: =IF(B48="","",(C48-E48)-(D48-F48)) | H48: =IF(B48="","",IFERROR(G48/ABS(D48-F48),0)) | J48: Taxas e Anuidades | K48: =SUMIFS(Lançamentos!$F:$F,Lançamentos!$A:$A,">="&$B$6,Lançamentos!$A:$A,"<="&$C$6,Lançamentos!$C:$C,J48,Lançamentos!$G:$G,IF($E$6="Todos","*",$E$6)) -> 0 | L48: {=SUMPRODUCT(('Fluxo de Caixa'!$B$82:$IL$82>=$B$6)*('Fluxo de Caixa'!$B$82:$IL$82<=$C$6)*'Fluxo de Caixa'!$B$129:$IL$129)} -> 0 | M48: =K48-L48 -> 0
B49: =IF(B48="","",IF($D$6="Dia",IF(B48+1>$C$6,"",B48+1),IF($D$6="Semana",IF(B48+7>$C$6,"",B48+7),IF($D$6="Mês",IF(EDATE(B48,1)>$C$6,"",EDATE(B48,1)),IF(DATE(YEAR(B48)+1,1,1)>$C$6,"",DATE(YEAR(B48)+1,1,1)))))) | C49: =IF(B49="","",SUMIFS(Lançamentos!$F:$F,Lançamentos!$A:$A,">="&B49,Lançamentos!$A:$A,"<="&MIN($C$6,IF($D$6="Dia",B49,IF($D$6="Semana",B49+6,IF($D$6="Mês",EOMONTH(B49,0),DATE(YEAR(B49),12,31))))),Lançamentos!$G:$G,IF($E$6="Todos","*",$E$6),Lançamentos!$D:$D,"Entrada")) | D49: {=IF(B49="","",SUMPRODUCT(('Fluxo de Caixa'!$B$82:$IL$82>=B49)*('Fluxo de Caixa'!$B$82:$IL$82<=MIN($C$6,IF($D$6="Dia",B49,IF($D$6="Semana",B49+6,IF($D$6="Mês",EOMONTH(B49,0),DATE(YEAR(B49),12,31))))))*'Fluxo de Caixa'!$B$96:$IL$96))} | E49: =IF(B49="","",SUMIFS(Lançamentos!$F:$F,Lançamentos!$A:$A,">="&B49,Lançamentos!$A:$A,"<="&MIN($C$6,IF($D$6="Dia",B49,IF($D$6="Semana",B49+6,IF($D$6="Mês",EOMONTH(B49,0),DATE(YEAR(B49),12,31))))),Lançamentos!$G:$G,IF($E$6="Todos","*",$E$6),Lançamentos!$D:$D,"Saída")) | F49: {=IF(B49="","",SUMPRODUCT(('Fluxo de Caixa'!$B$82:$IL$82>=B49)*('Fluxo de Caixa'!$B$82:$IL$82<=MIN($C$6,IF($D$6="Dia",B49,IF($D$6="Semana",B49+6,IF($D$6="Mês",EOMONTH(B49,0),DATE(YEAR(B49),12,31))))))*'Fluxo de Caixa'!$B$140:$IL$140))} | G49: =IF(B49="","",(C49-E49)-(D49-F49)) | H49: =IF(B49="","",IFERROR(G49/ABS(D49-F49),0)) | J49: IOF | K49: =SUMIFS(Lançamentos!$F:$F,Lançamentos!$A:$A,">="&$B$6,Lançamentos!$A:$A,"<="&$C$6,Lançamentos!$C:$C,J49,Lançamentos!$G:$G,IF($E$6="Todos","*",$E$6)) -> 0 | L49: {=SUMPRODUCT(('Fluxo de Caixa'!$B$82:$IL$82>=$B$6)*('Fluxo de Caixa'!$B$82:$IL$82<=$C$6)*'Fluxo de Caixa'!$B$130:$IL$130)} -> 0 | M49: =K49-L49 -> 0
B50: =IF(B49="","",IF($D$6="Dia",IF(B49+1>$C$6,"",B49+1),IF($D$6="Semana",IF(B49+7>$C$6,"",B49+7),IF($D$6="Mês",IF(EDATE(B49,1)>$C$6,"",EDATE(B49,1)),IF(DATE(YEAR(B49)+1,1,1)>$C$6,"",DATE(YEAR(B49)+1,1,1)))))) | C50: =IF(B50="","",SUMIFS(Lançamentos!$F:$F,Lançamentos!$A:$A,">="&B50,Lançamentos!$A:$A,"<="&MIN($C$6,IF($D$6="Dia",B50,IF($D$6="Semana",B50+6,IF($D$6="Mês",EOMONTH(B50,0),DATE(YEAR(B50),12,31))))),Lançamentos!$G:$G,IF($E$6="Todos","*",$E$6),Lançamentos!$D:$D,"Entrada")) | D50: {=IF(B50="","",SUMPRODUCT(('Fluxo de Caixa'!$B$82:$IL$82>=B50)*('Fluxo de Caixa'!$B$82:$IL$82<=MIN($C$6,IF($D$6="Dia",B50,IF($D$6="Semana",B50+6,IF($D$6="Mês",EOMONTH(B50,0),DATE(YEAR(B50),12,31))))))*'Fluxo de Caixa'!$B$96:$IL$96))} | E50: =IF(B50="","",SUMIFS(Lançamentos!$F:$F,Lançamentos!$A:$A,">="&B50,Lançamentos!$A:$A,"<="&MIN($C$6,IF($D$6="Dia",B50,IF($D$6="Semana",B50+6,IF($D$6="Mês",EOMONTH(B50,0),DATE(YEAR(B50),12,31))))),Lançamentos!$G:$G,IF($E$6="Todos","*",$E$6),Lançamentos!$D:$D,"Saída")) | F50: {=IF(B50="","",SUMPRODUCT(('Fluxo de Caixa'!$B$82:$IL$82>=B50)*('Fluxo de Caixa'!$B$82:$IL$82<=MIN($C$6,IF($D$6="Dia",B50,IF($D$6="Semana",B50+6,IF($D$6="Mês",EOMONTH(B50,0),DATE(YEAR(B50),12,31))))))*'Fluxo de Caixa'!$B$140:$IL$140))} | G50: =IF(B50="","",(C50-E50)-(D50-F50)) | H50: =IF(B50="","",IFERROR(G50/ABS(D50-F50),0)) | J50: Cartão de Crédito | K50: =SUMIFS(Lançamentos!$F:$F,Lançamentos!$A:$A,">="&$B$6,Lançamentos!$A:$A,"<="&$C$6,Lançamentos!$C:$C,J50,Lançamentos!$G:$G,IF($E$6="Todos","*",$E$6)) -> 0 | L50: {=SUMPRODUCT(('Fluxo de Caixa'!$B$82:$IL$82>=$B$6)*('Fluxo de Caixa'!$B$82:$IL$82<=$C$6)*'Fluxo de Caixa'!$B$131:$IL$131)} -> 0 | M50: =K50-L50 -> 0
B51: =IF(B50="","",IF($D$6="Dia",IF(B50+1>$C$6,"",B50+1),IF($D$6="Semana",IF(B50+7>$C$6,"",B50+7),IF($D$6="Mês",IF(EDATE(B50,1)>$C$6,"",EDATE(B50,1)),IF(DATE(YEAR(B50)+1,1,1)>$C$6,"",DATE(YEAR(B50)+1,1,1)))))) | C51: =IF(B51="","",SUMIFS(Lançamentos!$F:$F,Lançamentos!$A:$A,">="&B51,Lançamentos!$A:$A,"<="&MIN($C$6,IF($D$6="Dia",B51,IF($D$6="Semana",B51+6,IF($D$6="Mês",EOMONTH(B51,0),DATE(YEAR(B51),12,31))))),Lançamentos!$G:$G,IF($E$6="Todos","*",$E$6),Lançamentos!$D:$D,"Entrada")) | D51: {=IF(B51="","",SUMPRODUCT(('Fluxo de Caixa'!$B$82:$IL$82>=B51)*('Fluxo de Caixa'!$B$82:$IL$82<=MIN($C$6,IF($D$6="Dia",B51,IF($D$6="Semana",B51+6,IF($D$6="Mês",EOMONTH(B51,0),DATE(YEAR(B51),12,31))))))*'Fluxo de Caixa'!$B$96:$IL$96))} | E51: =IF(B51="","",SUMIFS(Lançamentos!$F:$F,Lançamentos!$A:$A,">="&B51,Lançamentos!$A:$A,"<="&MIN($C$6,IF($D$6="Dia",B51,IF($D$6="Semana",B51+6,IF($D$6="Mês",EOMONTH(B51,0),DATE(YEAR(B51),12,31))))),Lançamentos!$G:$G,IF($E$6="Todos","*",$E$6),Lançamentos!$D:$D,"Saída")) | F51: {=IF(B51="","",SUMPRODUCT(('Fluxo de Caixa'!$B$82:$IL$82>=B51)*('Fluxo de Caixa'!$B$82:$IL$82<=MIN($C$6,IF($D$6="Dia",B51,IF($D$6="Semana",B51+6,IF($D$6="Mês",EOMONTH(B51,0),DATE(YEAR(B51),12,31))))))*'Fluxo de Caixa'!$B$140:$IL$140))} | G51: =IF(B51="","",(C51-E51)-(D51-F51)) | H51: =IF(B51="","",IFERROR(G51/ABS(D51-F51),0)) | J51: Multas e Juros | K51: =SUMIFS(Lançamentos!$F:$F,Lançamentos!$A:$A,">="&$B$6,Lançamentos!$A:$A,"<="&$C$6,Lançamentos!$C:$C,J51,Lançamentos!$G:$G,IF($E$6="Todos","*",$E$6)) -> 0 | L51: {=SUMPRODUCT(('Fluxo de Caixa'!$B$82:$IL$82>=$B$6)*('Fluxo de Caixa'!$B$82:$IL$82<=$C$6)*'Fluxo de Caixa'!$B$132:$IL$132)} -> 0 | M51: =K51-L51 -> 0
B52: =IF(B51="","",IF($D$6="Dia",IF(B51+1>$C$6,"",B51+1),IF($D$6="Semana",IF(B51+7>$C$6,"",B51+7),IF($D$6="Mês",IF(EDATE(B51,1)>$C$6,"",EDATE(B51,1)),IF(DATE(YEAR(B51)+1,1,1)>$C$6,"",DATE(YEAR(B51)+1,1,1)))))) | C52: =IF(B52="","",SUMIFS(Lançamentos!$F:$F,Lançamentos!$A:$A,">="&B52,Lançamentos!$A:$A,"<="&MIN($C$6,IF($D$6="Dia",B52,IF($D$6="Semana",B52+6,IF($D$6="Mês",EOMONTH(B52,0),DATE(YEAR(B52),12,31))))),Lançamentos!$G:$G,IF($E$6="Todos","*",$E$6),Lançamentos!$D:$D,"Entrada")) | D52: {=IF(B52="","",SUMPRODUCT(('Fluxo de Caixa'!$B$82:$IL$82>=B52)*('Fluxo de Caixa'!$B$82:$IL$82<=MIN($C$6,IF($D$6="Dia",B52,IF($D$6="Semana",B52+6,IF($D$6="Mês",EOMONTH(B52,0),DATE(YEAR(B52),12,31))))))*'Fluxo de Caixa'!$B$96:$IL$96))} | E52: =IF(B52="","",SUMIFS(Lançamentos!$F:$F,Lançamentos!$A:$A,">="&B52,Lançamentos!$A:$A,"<="&MIN($C$6,IF($D$6="Dia",B52,IF($D$6="Semana",B52+6,IF($D$6="Mês",EOMONTH(B52,0),DATE(YEAR(B52),12,31))))),Lançamentos!$G:$G,IF($E$6="Todos","*",$E$6),Lançamentos!$D:$D,"Saída")) | F52: {=IF(B52="","",SUMPRODUCT(('Fluxo de Caixa'!$B$82:$IL$82>=B52)*('Fluxo de Caixa'!$B$82:$IL$82<=MIN($C$6,IF($D$6="Dia",B52,IF($D$6="Semana",B52+6,IF($D$6="Mês",EOMONTH(B52,0),DATE(YEAR(B52),12,31))))))*'Fluxo de Caixa'!$B$140:$IL$140))} | G52: =IF(B52="","",(C52-E52)-(D52-F52)) | H52: =IF(B52="","",IFERROR(G52/ABS(D52-F52),0)) | J52: Pagamento de Fornecedores | K52: =SUMIFS(Lançamentos!$F:$F,Lançamentos!$A:$A,">="&$B$6,Lançamentos!$A:$A,"<="&$C$6,Lançamentos!$C:$C,J52,Lançamentos!$G:$G,IF($E$6="Todos","*",$E$6)) -> 0 | L52: {=SUMPRODUCT(('Fluxo de Caixa'!$B$82:$IL$82>=$B$6)*('Fluxo de Caixa'!$B$82:$IL$82<=$C$6)*'Fluxo de Caixa'!$B$133:$IL$133)} -> 0 | M52: =K52-L52 -> 0
B53: =IF(B52="","",IF($D$6="Dia",IF(B52+1>$C$6,"",B52+1),IF($D$6="Semana",IF(B52+7>$C$6,"",B52+7),IF($D$6="Mês",IF(EDATE(B52,1)>$C$6,"",EDATE(B52,1)),IF(DATE(YEAR(B52)+1,1,1)>$C$6,"",DATE(YEAR(B52)+1,1,1)))))) | C53: =IF(B53="","",SUMIFS(Lançamentos!$F:$F,Lançamentos!$A:$A,">="&B53,Lançamentos!$A:$A,"<="&MIN($C$6,IF($D$6="Dia",B53,IF($D$6="Semana",B53+6,IF($D$6="Mês",EOMONTH(B53,0),DATE(YEAR(B53),12,31))))),Lançamentos!$G:$G,IF($E$6="Todos","*",$E$6),Lançamentos!$D:$D,"Entrada")) | D53: {=IF(B53="","",SUMPRODUCT(('Fluxo de Caixa'!$B$82:$IL$82>=B53)*('Fluxo de Caixa'!$B$82:$IL$82<=MIN($C$6,IF($D$6="Dia",B53,IF($D$6="Semana",B53+6,IF($D$6="Mês",EOMONTH(B53,0),DATE(YEAR(B53),12,31))))))*'Fluxo de Caixa'!$B$96:$IL$96))} | E53: =IF(B53="","",SUMIFS(Lançamentos!$F:$F,Lançamentos!$A:$A,">="&B53,Lançamentos!$A:$A,"<="&MIN($C$6,IF($D$6="Dia",B53,IF($D$6="Semana",B53+6,IF($D$6="Mês",EOMONTH(B53,0),DATE(YEAR(B53),12,31))))),Lançamentos!$G:$G,IF($E$6="Todos","*",$E$6),Lançamentos!$D:$D,"Saída")) | F53: {=IF(B53="","",SUMPRODUCT(('Fluxo de Caixa'!$B$82:$IL$82>=B53)*('Fluxo de Caixa'!$B$82:$IL$82<=MIN($C$6,IF($D$6="Dia",B53,IF($D$6="Semana",B53+6,IF($D$6="Mês",EOMONTH(B53,0),DATE(YEAR(B53),12,31))))))*'Fluxo de Caixa'!$B$140:$IL$140))} | G53: =IF(B53="","",(C53-E53)-(D53-F53)) | H53: =IF(B53="","",IFERROR(G53/ABS(D53-F53),0)) | J53: Retirada de Sócios | K53: =SUMIFS(Lançamentos!$F:$F,Lançamentos!$A:$A,">="&$B$6,Lançamentos!$A:$A,"<="&$C$6,Lançamentos!$C:$C,J53,Lançamentos!$G:$G,IF($E$6="Todos","*",$E$6)) -> 0 | L53: {=SUMPRODUCT(('Fluxo de Caixa'!$B$82:$IL$82>=$B$6)*('Fluxo de Caixa'!$B$82:$IL$82<=$C$6)*'Fluxo de Caixa'!$B$134:$IL$134)} -> 0 | M53: =K53-L53 -> 0
B54: =IF(B53="","",IF($D$6="Dia",IF(B53+1>$C$6,"",B53+1),IF($D$6="Semana",IF(B53+7>$C$6,"",B53+7),IF($D$6="Mês",IF(EDATE(B53,1)>$C$6,"",EDATE(B53,1)),IF(DATE(YEAR(B53)+1,1,1)>$C$6,"",DATE(YEAR(B53)+1,1,1)))))) | C54: =IF(B54="","",SUMIFS(Lançamentos!$F:$F,Lançamentos!$A:$A,">="&B54,Lançamentos!$A:$A,"<="&MIN($C$6,IF($D$6="Dia",B54,IF($D$6="Semana",B54+6,IF($D$6="Mês",EOMONTH(B54,0),DATE(YEAR(B54),12,31))))),Lançamentos!$G:$G,IF($E$6="Todos","*",$E$6),Lançamentos!$D:$D,"Entrada")) | D54: {=IF(B54="","",SUMPRODUCT(('Fluxo de Caixa'!$B$82:$IL$82>=B54)*('Fluxo de Caixa'!$B$82:$IL$82<=MIN($C$6,IF($D$6="Dia",B54,IF($D$6="Semana",B54+6,IF($D$6="Mês",EOMONTH(B54,0),DATE(YEAR(B54),12,31))))))*'Fluxo de Caixa'!$B$96:$IL$96))} | E54: =IF(B54="","",SUMIFS(Lançamentos!$F:$F,Lançamentos!$A:$A,">="&B54,Lançamentos!$A:$A,"<="&MIN($C$6,IF($D$6="Dia",B54,IF($D$6="Semana",B54+6,IF($D$6="Mês",EOMONTH(B54,0),DATE(YEAR(B54),12,31))))),Lançamentos!$G:$G,IF($E$6="Todos","*",$E$6),Lançamentos!$D:$D,"Saída")) | F54: {=IF(B54="","",SUMPRODUCT(('Fluxo de Caixa'!$B$82:$IL$82>=B54)*('Fluxo de Caixa'!$B$82:$IL$82<=MIN($C$6,IF($D$6="Dia",B54,IF($D$6="Semana",B54+6,IF($D$6="Mês",EOMONTH(B54,0),DATE(YEAR(B54),12,31))))))*'Fluxo de Caixa'!$B$140:$IL$140))} | G54: =IF(B54="","",(C54-E54)-(D54-F54)) | H54: =IF(B54="","",IFERROR(G54/ABS(D54-F54),0)) | J54: INSS / FGTS | K54: =SUMIFS(Lançamentos!$F:$F,Lançamentos!$A:$A,">="&$B$6,Lançamentos!$A:$A,"<="&$C$6,Lançamentos!$C:$C,J54,Lançamentos!$G:$G,IF($E$6="Todos","*",$E$6)) -> 0 | L54: {=SUMPRODUCT(('Fluxo de Caixa'!$B$82:$IL$82>=$B$6)*('Fluxo de Caixa'!$B$82:$IL$82<=$C$6)*'Fluxo de Caixa'!$B$135:$IL$135)} -> 0 | M54: =K54-L54 -> 0
B55: =IF(B54="","",IF($D$6="Dia",IF(B54+1>$C$6,"",B54+1),IF($D$6="Semana",IF(B54+7>$C$6,"",B54+7),IF($D$6="Mês",IF(EDATE(B54,1)>$C$6,"",EDATE(B54,1)),IF(DATE(YEAR(B54)+1,1,1)>$C$6,"",DATE(YEAR(B54)+1,1,1)))))) | C55: =IF(B55="","",SUMIFS(Lançamentos!$F:$F,Lançamentos!$A:$A,">="&B55,Lançamentos!$A:$A,"<="&MIN($C$6,IF($D$6="Dia",B55,IF($D$6="Semana",B55+6,IF($D$6="Mês",EOMONTH(B55,0),DATE(YEAR(B55),12,31))))),Lançamentos!$G:$G,IF($E$6="Todos","*",$E$6),Lançamentos!$D:$D,"Entrada")) | D55: {=IF(B55="","",SUMPRODUCT(('Fluxo de Caixa'!$B$82:$IL$82>=B55)*('Fluxo de Caixa'!$B$82:$IL$82<=MIN($C$6,IF($D$6="Dia",B55,IF($D$6="Semana",B55+6,IF($D$6="Mês",EOMONTH(B55,0),DATE(YEAR(B55),12,31))))))*'Fluxo de Caixa'!$B$96:$IL$96))} | E55: =IF(B55="","",SUMIFS(Lançamentos!$F:$F,Lançamentos!$A:$A,">="&B55,Lançamentos!$A:$A,"<="&MIN($C$6,IF($D$6="Dia",B55,IF($D$6="Semana",B55+6,IF($D$6="Mês",EOMONTH(B55,0),DATE(YEAR(B55),12,31))))),Lançamentos!$G:$G,IF($E$6="Todos","*",$E$6),Lançamentos!$D:$D,"Saída")) | F55: {=IF(B55="","",SUMPRODUCT(('Fluxo de Caixa'!$B$82:$IL$82>=B55)*('Fluxo de Caixa'!$B$82:$IL$82<=MIN($C$6,IF($D$6="Dia",B55,IF($D$6="Semana",B55+6,IF($D$6="Mês",EOMONTH(B55,0),DATE(YEAR(B55),12,31))))))*'Fluxo de Caixa'!$B$140:$IL$140))} | G55: =IF(B55="","",(C55-E55)-(D55-F55)) | H55: =IF(B55="","",IFERROR(G55/ABS(D55-F55),0)) | J55: Simples Nacional / DAS | K55: =SUMIFS(Lançamentos!$F:$F,Lançamentos!$A:$A,">="&$B$6,Lançamentos!$A:$A,"<="&$C$6,Lançamentos!$C:$C,J55,Lançamentos!$G:$G,IF($E$6="Todos","*",$E$6)) -> 0 | L55: {=SUMPRODUCT(('Fluxo de Caixa'!$B$82:$IL$82>=$B$6)*('Fluxo de Caixa'!$B$82:$IL$82<=$C$6)*'Fluxo de Caixa'!$B$136:$IL$136)} -> 0 | M55: =K55-L55 -> 0
B56: =IF(B55="","",IF($D$6="Dia",IF(B55+1>$C$6,"",B55+1),IF($D$6="Semana",IF(B55+7>$C$6,"",B55+7),IF($D$6="Mês",IF(EDATE(B55,1)>$C$6,"",EDATE(B55,1)),IF(DATE(YEAR(B55)+1,1,1)>$C$6,"",DATE(YEAR(B55)+1,1,1)))))) | C56: =IF(B56="","",SUMIFS(Lançamentos!$F:$F,Lançamentos!$A:$A,">="&B56,Lançamentos!$A:$A,"<="&MIN($C$6,IF($D$6="Dia",B56,IF($D$6="Semana",B56+6,IF($D$6="Mês",EOMONTH(B56,0),DATE(YEAR(B56),12,31))))),Lançamentos!$G:$G,IF($E$6="Todos","*",$E$6),Lançamentos!$D:$D,"Entrada")) | D56: {=IF(B56="","",SUMPRODUCT(('Fluxo de Caixa'!$B$82:$IL$82>=B56)*('Fluxo de Caixa'!$B$82:$IL$82<=MIN($C$6,IF($D$6="Dia",B56,IF($D$6="Semana",B56+6,IF($D$6="Mês",EOMONTH(B56,0),DATE(YEAR(B56),12,31))))))*'Fluxo de Caixa'!$B$96:$IL$96))} | E56: =IF(B56="","",SUMIFS(Lançamentos!$F:$F,Lançamentos!$A:$A,">="&B56,Lançamentos!$A:$A,"<="&MIN($C$6,IF($D$6="Dia",B56,IF($D$6="Semana",B56+6,IF($D$6="Mês",EOMONTH(B56,0),DATE(YEAR(B56),12,31))))),Lançamentos!$G:$G,IF($E$6="Todos","*",$E$6),Lançamentos!$D:$D,"Saída")) | F56: {=IF(B56="","",SUMPRODUCT(('Fluxo de Caixa'!$B$82:$IL$82>=B56)*('Fluxo de Caixa'!$B$82:$IL$82<=MIN($C$6,IF($D$6="Dia",B56,IF($D$6="Semana",B56+6,IF($D$6="Mês",EOMONTH(B56,0),DATE(YEAR(B56),12,31))))))*'Fluxo de Caixa'!$B$140:$IL$140))} | G56: =IF(B56="","",(C56-E56)-(D56-F56)) | H56: =IF(B56="","",IFERROR(G56/ABS(D56-F56),0)) | J56: ISS | K56: =SUMIFS(Lançamentos!$F:$F,Lançamentos!$A:$A,">="&$B$6,Lançamentos!$A:$A,"<="&$C$6,Lançamentos!$C:$C,J56,Lançamentos!$G:$G,IF($E$6="Todos","*",$E$6)) -> 0 | L56: {=SUMPRODUCT(('Fluxo de Caixa'!$B$82:$IL$82>=$B$6)*('Fluxo de Caixa'!$B$82:$IL$82<=$C$6)*'Fluxo de Caixa'!$B$137:$IL$137)} -> 0 | M56: =K56-L56 -> 0
B57: =IF(B56="","",IF($D$6="Dia",IF(B56+1>$C$6,"",B56+1),IF($D$6="Semana",IF(B56+7>$C$6,"",B56+7),IF($D$6="Mês",IF(EDATE(B56,1)>$C$6,"",EDATE(B56,1)),IF(DATE(YEAR(B56)+1,1,1)>$C$6,"",DATE(YEAR(B56)+1,1,1)))))) | C57: =IF(B57="","",SUMIFS(Lançamentos!$F:$F,Lançamentos!$A:$A,">="&B57,Lançamentos!$A:$A,"<="&MIN($C$6,IF($D$6="Dia",B57,IF($D$6="Semana",B57+6,IF($D$6="Mês",EOMONTH(B57,0),DATE(YEAR(B57),12,31))))),Lançamentos!$G:$G,IF($E$6="Todos","*",$E$6),Lançamentos!$D:$D,"Entrada")) | D57: {=IF(B57="","",SUMPRODUCT(('Fluxo de Caixa'!$B$82:$IL$82>=B57)*('Fluxo de Caixa'!$B$82:$IL$82<=MIN($C$6,IF($D$6="Dia",B57,IF($D$6="Semana",B57+6,IF($D$6="Mês",EOMONTH(B57,0),DATE(YEAR(B57),12,31))))))*'Fluxo de Caixa'!$B$96:$IL$96))} | E57: =IF(B57="","",SUMIFS(Lançamentos!$F:$F,Lançamentos!$A:$A,">="&B57,Lançamentos!$A:$A,"<="&MIN($C$6,IF($D$6="Dia",B57,IF($D$6="Semana",B57+6,IF($D$6="Mês",EOMONTH(B57,0),DATE(YEAR(B57),12,31))))),Lançamentos!$G:$G,IF($E$6="Todos","*",$E$6),Lançamentos!$D:$D,"Saída")) | F57: {=IF(B57="","",SUMPRODUCT(('Fluxo de Caixa'!$B$82:$IL$82>=B57)*('Fluxo de Caixa'!$B$82:$IL$82<=MIN($C$6,IF($D$6="Dia",B57,IF($D$6="Semana",B57+6,IF($D$6="Mês",EOMONTH(B57,0),DATE(YEAR(B57),12,31))))))*'Fluxo de Caixa'!$B$140:$IL$140))} | G57: =IF(B57="","",(C57-E57)-(D57-F57)) | H57: =IF(B57="","",IFERROR(G57/ABS(D57-F57),0)) | J57: ICMS | K57: =SUMIFS(Lançamentos!$F:$F,Lançamentos!$A:$A,">="&$B$6,Lançamentos!$A:$A,"<="&$C$6,Lançamentos!$C:$C,J57,Lançamentos!$G:$G,IF($E$6="Todos","*",$E$6)) -> 0 | L57: {=SUMPRODUCT(('Fluxo de Caixa'!$B$82:$IL$82>=$B$6)*('Fluxo de Caixa'!$B$82:$IL$82<=$C$6)*'Fluxo de Caixa'!$B$138:$IL$138)} -> 0 | M57: =K57-L57 -> 0
B58: =IF(B57="","",IF($D$6="Dia",IF(B57+1>$C$6,"",B57+1),IF($D$6="Semana",IF(B57+7>$C$6,"",B57+7),IF($D$6="Mês",IF(EDATE(B57,1)>$C$6,"",EDATE(B57,1)),IF(DATE(YEAR(B57)+1,1,1)>$C$6,"",DATE(YEAR(B57)+1,1,1)))))) | C58: =IF(B58="","",SUMIFS(Lançamentos!$F:$F,Lançamentos!$A:$A,">="&B58,Lançamentos!$A:$A,"<="&MIN($C$6,IF($D$6="Dia",B58,IF($D$6="Semana",B58+6,IF($D$6="Mês",EOMONTH(B58,0),DATE(YEAR(B58),12,31))))),Lançamentos!$G:$G,IF($E$6="Todos","*",$E$6),Lançamentos!$D:$D,"Entrada")) | D58: {=IF(B58="","",SUMPRODUCT(('Fluxo de Caixa'!$B$82:$IL$82>=B58)*('Fluxo de Caixa'!$B$82:$IL$82<=MIN($C$6,IF($D$6="Dia",B58,IF($D$6="Semana",B58+6,IF($D$6="Mês",EOMONTH(B58,0),DATE(YEAR(B58),12,31))))))*'Fluxo de Caixa'!$B$96:$IL$96))} | E58: =IF(B58="","",SUMIFS(Lançamentos!$F:$F,Lançamentos!$A:$A,">="&B58,Lançamentos!$A:$A,"<="&MIN($C$6,IF($D$6="Dia",B58,IF($D$6="Semana",B58+6,IF($D$6="Mês",EOMONTH(B58,0),DATE(YEAR(B58),12,31))))),Lançamentos!$G:$G,IF($E$6="Todos","*",$E$6),Lançamentos!$D:$D,"Saída")) | F58: {=IF(B58="","",SUMPRODUCT(('Fluxo de Caixa'!$B$82:$IL$82>=B58)*('Fluxo de Caixa'!$B$82:$IL$82<=MIN($C$6,IF($D$6="Dia",B58,IF($D$6="Semana",B58+6,IF($D$6="Mês",EOMONTH(B58,0),DATE(YEAR(B58),12,31))))))*'Fluxo de Caixa'!$B$140:$IL$140))} | G58: =IF(B58="","",(C58-E58)-(D58-F58)) | H58: =IF(B58="","",IFERROR(G58/ABS(D58-F58),0)) | J58: PIS/COFINS | K58: =SUMIFS(Lançamentos!$F:$F,Lançamentos!$A:$A,">="&$B$6,Lançamentos!$A:$A,"<="&$C$6,Lançamentos!$C:$C,J58,Lançamentos!$G:$G,IF($E$6="Todos","*",$E$6)) -> 0 | L58: {=SUMPRODUCT(('Fluxo de Caixa'!$B$82:$IL$82>=$B$6)*('Fluxo de Caixa'!$B$82:$IL$82<=$C$6)*'Fluxo de Caixa'!$B$139:$IL$139)} -> 0 | M58: =K58-L58 -> 0
B59: =IF(B58="","",IF($D$6="Dia",IF(B58+1>$C$6,"",B58+1),IF($D$6="Semana",IF(B58+7>$C$6,"",B58+7),IF($D$6="Mês",IF(EDATE(B58,1)>$C$6,"",EDATE(B58,1)),IF(DATE(YEAR(B58)+1,1,1)>$C$6,"",DATE(YEAR(B58)+1,1,1)))))) | C59: =IF(B59="","",SUMIFS(Lançamentos!$F:$F,Lançamentos!$A:$A,">="&B59,Lançamentos!$A:$A,"<="&MIN($C$6,IF($D$6="Dia",B59,IF($D$6="Semana",B59+6,IF($D$6="Mês",EOMONTH(B59,0),DATE(YEAR(B59),12,31))))),Lançamentos!$G:$G,IF($E$6="Todos","*",$E$6),Lançamentos!$D:$D,"Entrada")) | D59: {=IF(B59="","",SUMPRODUCT(('Fluxo de Caixa'!$B$82:$IL$82>=B59)*('Fluxo de Caixa'!$B$82:$IL$82<=MIN($C$6,IF($D$6="Dia",B59,IF($D$6="Semana",B59+6,IF($D$6="Mês",EOMONTH(B59,0),DATE(YEAR(B59),12,31))))))*'Fluxo de Caixa'!$B$96:$IL$96))} | E59: =IF(B59="","",SUMIFS(Lançamentos!$F:$F,Lançamentos!$A:$A,">="&B59,Lançamentos!$A:$A,"<="&MIN($C$6,IF($D$6="Dia",B59,IF($D$6="Semana",B59+6,IF($D$6="Mês",EOMONTH(B59,0),DATE(YEAR(B59),12,31))))),Lançamentos!$G:$G,IF($E$6="Todos","*",$E$6),Lançamentos!$D:$D,"Saída")) | F59: {=IF(B59="","",SUMPRODUCT(('Fluxo de Caixa'!$B$82:$IL$82>=B59)*('Fluxo de Caixa'!$B$82:$IL$82<=MIN($C$6,IF($D$6="Dia",B59,IF($D$6="Semana",B59+6,IF($D$6="Mês",EOMONTH(B59,0),DATE(YEAR(B59),12,31))))))*'Fluxo de Caixa'!$B$140:$IL$140))} | G59: =IF(B59="","",(C59-E59)-(D59-F59)) | H59: =IF(B59="","",IFERROR(G59/ABS(D59-F59),0))
B60: =IF(B59="","",IF($D$6="Dia",IF(B59+1>$C$6,"",B59+1),IF($D$6="Semana",IF(B59+7>$C$6,"",B59+7),IF($D$6="Mês",IF(EDATE(B59,1)>$C$6,"",EDATE(B59,1)),IF(DATE(YEAR(B59)+1,1,1)>$C$6,"",DATE(YEAR(B59)+1,1,1)))))) | C60: =IF(B60="","",SUMIFS(Lançamentos!$F:$F,Lançamentos!$A:$A,">="&B60,Lançamentos!$A:$A,"<="&MIN($C$6,IF($D$6="Dia",B60,IF($D$6="Semana",B60+6,IF($D$6="Mês",EOMONTH(B60,0),DATE(YEAR(B60),12,31))))),Lançamentos!$G:$G,IF($E$6="Todos","*",$E$6),Lançamentos!$D:$D,"Entrada")) | D60: {=IF(B60="","",SUMPRODUCT(('Fluxo de Caixa'!$B$82:$IL$82>=B60)*('Fluxo de Caixa'!$B$82:$IL$82<=MIN($C$6,IF($D$6="Dia",B60,IF($D$6="Semana",B60+6,IF($D$6="Mês",EOMONTH(B60,0),DATE(YEAR(B60),12,31))))))*'Fluxo de Caixa'!$B$96:$IL$96))} | E60: =IF(B60="","",SUMIFS(Lançamentos!$F:$F,Lançamentos!$A:$A,">="&B60,Lançamentos!$A:$A,"<="&MIN($C$6,IF($D$6="Dia",B60,IF($D$6="Semana",B60+6,IF($D$6="Mês",EOMONTH(B60,0),DATE(YEAR(B60),12,31))))),Lançamentos!$G:$G,IF($E$6="Todos","*",$E$6),Lançamentos!$D:$D,"Saída")) | F60: {=IF(B60="","",SUMPRODUCT(('Fluxo de Caixa'!$B$82:$IL$82>=B60)*('Fluxo de Caixa'!$B$82:$IL$82<=MIN($C$6,IF($D$6="Dia",B60,IF($D$6="Semana",B60+6,IF($D$6="Mês",EOMONTH(B60,0),DATE(YEAR(B60),12,31))))))*'Fluxo de Caixa'!$B$140:$IL$140))} | G60: =IF(B60="","",(C60-E60)-(D60-F60)) | H60: =IF(B60="","",IFERROR(G60/ABS(D60-F60),0))
B61: =IF(B60="","",IF($D$6="Dia",IF(B60+1>$C$6,"",B60+1),IF($D$6="Semana",IF(B60+7>$C$6,"",B60+7),IF($D$6="Mês",IF(EDATE(B60,1)>$C$6,"",EDATE(B60,1)),IF(DATE(YEAR(B60)+1,1,1)>$C$6,"",DATE(YEAR(B60)+1,1,1)))))) | C61: =IF(B61="","",SUMIFS(Lançamentos!$F:$F,Lançamentos!$A:$A,">="&B61,Lançamentos!$A:$A,"<="&MIN($C$6,IF($D$6="Dia",B61,IF($D$6="Semana",B61+6,IF($D$6="Mês",EOMONTH(B61,0),DATE(YEAR(B61),12,31))))),Lançamentos!$G:$G,IF($E$6="Todos","*",$E$6),Lançamentos!$D:$D,"Entrada")) | D61: {=IF(B61="","",SUMPRODUCT(('Fluxo de Caixa'!$B$82:$IL$82>=B61)*('Fluxo de Caixa'!$B$82:$IL$82<=MIN($C$6,IF($D$6="Dia",B61,IF($D$6="Semana",B61+6,IF($D$6="Mês",EOMONTH(B61,0),DATE(YEAR(B61),12,31))))))*'Fluxo de Caixa'!$B$96:$IL$96))} | E61: =IF(B61="","",SUMIFS(Lançamentos!$F:$F,Lançamentos!$A:$A,">="&B61,Lançamentos!$A:$A,"<="&MIN($C$6,IF($D$6="Dia",B61,IF($D$6="Semana",B61+6,IF($D$6="Mês",EOMONTH(B61,0),DATE(YEAR(B61),12,31))))),Lançamentos!$G:$G,IF($E$6="Todos","*",$E$6),Lançamentos!$D:$D,"Saída")) | F61: {=IF(B61="","",SUMPRODUCT(('Fluxo de Caixa'!$B$82:$IL$82>=B61)*('Fluxo de Caixa'!$B$82:$IL$82<=MIN($C$6,IF($D$6="Dia",B61,IF($D$6="Semana",B61+6,IF($D$6="Mês",EOMONTH(B61,0),DATE(YEAR(B61),12,31))))))*'Fluxo de Caixa'!$B$140:$IL$140))} | G61: =IF(B61="","",(C61-E61)-(D61-F61)) | H61: =IF(B61="","",IFERROR(G61/ABS(D61-F61),0))
B62: =IF(B61="","",IF($D$6="Dia",IF(B61+1>$C$6,"",B61+1),IF($D$6="Semana",IF(B61+7>$C$6,"",B61+7),IF($D$6="Mês",IF(EDATE(B61,1)>$C$6,"",EDATE(B61,1)),IF(DATE(YEAR(B61)+1,1,1)>$C$6,"",DATE(YEAR(B61)+1,1,1)))))) | C62: =IF(B62="","",SUMIFS(Lançamentos!$F:$F,Lançamentos!$A:$A,">="&B62,Lançamentos!$A:$A,"<="&MIN($C$6,IF($D$6="Dia",B62,IF($D$6="Semana",B62+6,IF($D$6="Mês",EOMONTH(B62,0),DATE(YEAR(B62),12,31))))),Lançamentos!$G:$G,IF($E$6="Todos","*",$E$6),Lançamentos!$D:$D,"Entrada")) | D62: {=IF(B62="","",SUMPRODUCT(('Fluxo de Caixa'!$B$82:$IL$82>=B62)*('Fluxo de Caixa'!$B$82:$IL$82<=MIN($C$6,IF($D$6="Dia",B62,IF($D$6="Semana",B62+6,IF($D$6="Mês",EOMONTH(B62,0),DATE(YEAR(B62),12,31))))))*'Fluxo de Caixa'!$B$96:$IL$96))} | E62: =IF(B62="","",SUMIFS(Lançamentos!$F:$F,Lançamentos!$A:$A,">="&B62,Lançamentos!$A:$A,"<="&MIN($C$6,IF($D$6="Dia",B62,IF($D$6="Semana",B62+6,IF($D$6="Mês",EOMONTH(B62,0),DATE(YEAR(B62),12,31))))),Lançamentos!$G:$G,IF($E$6="Todos","*",$E$6),Lançamentos!$D:$D,"Saída")) | F62: {=IF(B62="","",SUMPRODUCT(('Fluxo de Caixa'!$B$82:$IL$82>=B62)*('Fluxo de Caixa'!$B$82:$IL$82<=MIN($C$6,IF($D$6="Dia",B62,IF($D$6="Semana",B62+6,IF($D$6="Mês",EOMONTH(B62,0),DATE(YEAR(B62),12,31))))))*'Fluxo de Caixa'!$B$140:$IL$140))} | G62: =IF(B62="","",(C62-E62)-(D62-F62)) | H62: =IF(B62="","",IFERROR(G62/ABS(D62-F62),0))
B63: =IF(B62="","",IF($D$6="Dia",IF(B62+1>$C$6,"",B62+1),IF($D$6="Semana",IF(B62+7>$C$6,"",B62+7),IF($D$6="Mês",IF(EDATE(B62,1)>$C$6,"",EDATE(B62,1)),IF(DATE(YEAR(B62)+1,1,1)>$C$6,"",DATE(YEAR(B62)+1,1,1)))))) | C63: =IF(B63="","",SUMIFS(Lançamentos!$F:$F,Lançamentos!$A:$A,">="&B63,Lançamentos!$A:$A,"<="&MIN($C$6,IF($D$6="Dia",B63,IF($D$6="Semana",B63+6,IF($D$6="Mês",EOMONTH(B63,0),DATE(YEAR(B63),12,31))))),Lançamentos!$G:$G,IF($E$6="Todos","*",$E$6),Lançamentos!$D:$D,"Entrada")) | D63: {=IF(B63="","",SUMPRODUCT(('Fluxo de Caixa'!$B$82:$IL$82>=B63)*('Fluxo de Caixa'!$B$82:$IL$82<=MIN($C$6,IF($D$6="Dia",B63,IF($D$6="Semana",B63+6,IF($D$6="Mês",EOMONTH(B63,0),DATE(YEAR(B63),12,31))))))*'Fluxo de Caixa'!$B$96:$IL$96))} | E63: =IF(B63="","",SUMIFS(Lançamentos!$F:$F,Lançamentos!$A:$A,">="&B63,Lançamentos!$A:$A,"<="&MIN($C$6,IF($D$6="Dia",B63,IF($D$6="Semana",B63+6,IF($D$6="Mês",EOMONTH(B63,0),DATE(YEAR(B63),12,31))))),Lançamentos!$G:$G,IF($E$6="Todos","*",$E$6),Lançamentos!$D:$D,"Saída")) | F63: {=IF(B63="","",SUMPRODUCT(('Fluxo de Caixa'!$B$82:$IL$82>=B63)*('Fluxo de Caixa'!$B$82:$IL$82<=MIN($C$6,IF($D$6="Dia",B63,IF($D$6="Semana",B63+6,IF($D$6="Mês",EOMONTH(B63,0),DATE(YEAR(B63),12,31))))))*'Fluxo de Caixa'!$B$140:$IL$140))} | G63: =IF(B63="","",(C63-E63)-(D63-F63)) | H63: =IF(B63="","",IFERROR(G63/ABS(D63-F63),0))
B64: =IF(B63="","",IF($D$6="Dia",IF(B63+1>$C$6,"",B63+1),IF($D$6="Semana",IF(B63+7>$C$6,"",B63+7),IF($D$6="Mês",IF(EDATE(B63,1)>$C$6,"",EDATE(B63,1)),IF(DATE(YEAR(B63)+1,1,1)>$C$6,"",DATE(YEAR(B63)+1,1,1)))))) | C64: =IF(B64="","",SUMIFS(Lançamentos!$F:$F,Lançamentos!$A:$A,">="&B64,Lançamentos!$A:$A,"<="&MIN($C$6,IF($D$6="Dia",B64,IF($D$6="Semana",B64+6,IF($D$6="Mês",EOMONTH(B64,0),DATE(YEAR(B64),12,31))))),Lançamentos!$G:$G,IF($E$6="Todos","*",$E$6),Lançamentos!$D:$D,"Entrada")) | D64: {=IF(B64="","",SUMPRODUCT(('Fluxo de Caixa'!$B$82:$IL$82>=B64)*('Fluxo de Caixa'!$B$82:$IL$82<=MIN($C$6,IF($D$6="Dia",B64,IF($D$6="Semana",B64+6,IF($D$6="Mês",EOMONTH(B64,0),DATE(YEAR(B64),12,31))))))*'Fluxo de Caixa'!$B$96:$IL$96))} | E64: =IF(B64="","",SUMIFS(Lançamentos!$F:$F,Lançamentos!$A:$A,">="&B64,Lançamentos!$A:$A,"<="&MIN($C$6,IF($D$6="Dia",B64,IF($D$6="Semana",B64+6,IF($D$6="Mês",EOMONTH(B64,0),DATE(YEAR(B64),12,31))))),Lançamentos!$G:$G,IF($E$6="Todos","*",$E$6),Lançamentos!$D:$D,"Saída")) | F64: {=IF(B64="","",SUMPRODUCT(('Fluxo de Caixa'!$B$82:$IL$82>=B64)*('Fluxo de Caixa'!$B$82:$IL$82<=MIN($C$6,IF($D$6="Dia",B64,IF($D$6="Semana",B64+6,IF($D$6="Mês",EOMONTH(B64,0),DATE(YEAR(B64),12,31))))))*'Fluxo de Caixa'!$B$140:$IL$140))} | G64: =IF(B64="","",(C64-E64)-(D64-F64)) | H64: =IF(B64="","",IFERROR(G64/ABS(D64-F64),0))
B65: =IF(B64="","",IF($D$6="Dia",IF(B64+1>$C$6,"",B64+1),IF($D$6="Semana",IF(B64+7>$C$6,"",B64+7),IF($D$6="Mês",IF(EDATE(B64,1)>$C$6,"",EDATE(B64,1)),IF(DATE(YEAR(B64)+1,1,1)>$C$6,"",DATE(YEAR(B64)+1,1,1)))))) | C65: =IF(B65="","",SUMIFS(Lançamentos!$F:$F,Lançamentos!$A:$A,">="&B65,Lançamentos!$A:$A,"<="&MIN($C$6,IF($D$6="Dia",B65,IF($D$6="Semana",B65+6,IF($D$6="Mês",EOMONTH(B65,0),DATE(YEAR(B65),12,31))))),Lançamentos!$G:$G,IF($E$6="Todos","*",$E$6),Lançamentos!$D:$D,"Entrada")) | D65: {=IF(B65="","",SUMPRODUCT(('Fluxo de Caixa'!$B$82:$IL$82>=B65)*('Fluxo de Caixa'!$B$82:$IL$82<=MIN($C$6,IF($D$6="Dia",B65,IF($D$6="Semana",B65+6,IF($D$6="Mês",EOMONTH(B65,0),DATE(YEAR(B65),12,31))))))*'Fluxo de Caixa'!$B$96:$IL$96))} | E65: =IF(B65="","",SUMIFS(Lançamentos!$F:$F,Lançamentos!$A:$A,">="&B65,Lançamentos!$A:$A,"<="&MIN($C$6,IF($D$6="Dia",B65,IF($D$6="Semana",B65+6,IF($D$6="Mês",EOMONTH(B65,0),DATE(YEAR(B65),12,31))))),Lançamentos!$G:$G,IF($E$6="Todos","*",$E$6),Lançamentos!$D:$D,"Saída")) | F65: {=IF(B65="","",SUMPRODUCT(('Fluxo de Caixa'!$B$82:$IL$82>=B65)*('Fluxo de Caixa'!$B$82:$IL$82<=MIN($C$6,IF($D$6="Dia",B65,IF($D$6="Semana",B65+6,IF($D$6="Mês",EOMONTH(B65,0),DATE(YEAR(B65),12,31))))))*'Fluxo de Caixa'!$B$140:$IL$140))} | G65: =IF(B65="","",(C65-E65)-(D65-F65)) | H65: =IF(B65="","",IFERROR(G65/ABS(D65-F65),0))
B66: =IF(B65="","",IF($D$6="Dia",IF(B65+1>$C$6,"",B65+1),IF($D$6="Semana",IF(B65+7>$C$6,"",B65+7),IF($D$6="Mês",IF(EDATE(B65,1)>$C$6,"",EDATE(B65,1)),IF(DATE(YEAR(B65)+1,1,1)>$C$6,"",DATE(YEAR(B65)+1,1,1)))))) | C66: =IF(B66="","",SUMIFS(Lançamentos!$F:$F,Lançamentos!$A:$A,">="&B66,Lançamentos!$A:$A,"<="&MIN($C$6,IF($D$6="Dia",B66,IF($D$6="Semana",B66+6,IF($D$6="Mês",EOMONTH(B66,0),DATE(YEAR(B66),12,31))))),Lançamentos!$G:$G,IF($E$6="Todos","*",$E$6),Lançamentos!$D:$D,"Entrada")) | D66: {=IF(B66="","",SUMPRODUCT(('Fluxo de Caixa'!$B$82:$IL$82>=B66)*('Fluxo de Caixa'!$B$82:$IL$82<=MIN($C$6,IF($D$6="Dia",B66,IF($D$6="Semana",B66+6,IF($D$6="Mês",EOMONTH(B66,0),DATE(YEAR(B66),12,31))))))*'Fluxo de Caixa'!$B$96:$IL$96))} | E66: =IF(B66="","",SUMIFS(Lançamentos!$F:$F,Lançamentos!$A:$A,">="&B66,Lançamentos!$A:$A,"<="&MIN($C$6,IF($D$6="Dia",B66,IF($D$6="Semana",B66+6,IF($D$6="Mês",EOMONTH(B66,0),DATE(YEAR(B66),12,31))))),Lançamentos!$G:$G,IF($E$6="Todos","*",$E$6),Lançamentos!$D:$D,"Saída")) | F66: {=IF(B66="","",SUMPRODUCT(('Fluxo de Caixa'!$B$82:$IL$82>=B66)*('Fluxo de Caixa'!$B$82:$IL$82<=MIN($C$6,IF($D$6="Dia",B66,IF($D$6="Semana",B66+6,IF($D$6="Mês",EOMONTH(B66,0),DATE(YEAR(B66),12,31))))))*'Fluxo de Caixa'!$B$140:$IL$140))} | G66: =IF(B66="","",(C66-E66)-(D66-F66)) | H66: =IF(B66="","",IFERROR(G66/ABS(D66-F66),0))
B67: =IF(B66="","",IF($D$6="Dia",IF(B66+1>$C$6,"",B66+1),IF($D$6="Semana",IF(B66+7>$C$6,"",B66+7),IF($D$6="Mês",IF(EDATE(B66,1)>$C$6,"",EDATE(B66,1)),IF(DATE(YEAR(B66)+1,1,1)>$C$6,"",DATE(YEAR(B66)+1,1,1)))))) | C67: =IF(B67="","",SUMIFS(Lançamentos!$F:$F,Lançamentos!$A:$A,">="&B67,Lançamentos!$A:$A,"<="&MIN($C$6,IF($D$6="Dia",B67,IF($D$6="Semana",B67+6,IF($D$6="Mês",EOMONTH(B67,0),DATE(YEAR(B67),12,31))))),Lançamentos!$G:$G,IF($E$6="Todos","*",$E$6),Lançamentos!$D:$D,"Entrada")) | D67: {=IF(B67="","",SUMPRODUCT(('Fluxo de Caixa'!$B$82:$IL$82>=B67)*('Fluxo de Caixa'!$B$82:$IL$82<=MIN($C$6,IF($D$6="Dia",B67,IF($D$6="Semana",B67+6,IF($D$6="Mês",EOMONTH(B67,0),DATE(YEAR(B67),12,31))))))*'Fluxo de Caixa'!$B$96:$IL$96))} | E67: =IF(B67="","",SUMIFS(Lançamentos!$F:$F,Lançamentos!$A:$A,">="&B67,Lançamentos!$A:$A,"<="&MIN($C$6,IF($D$6="Dia",B67,IF($D$6="Semana",B67+6,IF($D$6="Mês",EOMONTH(B67,0),DATE(YEAR(B67),12,31))))),Lançamentos!$G:$G,IF($E$6="Todos","*",$E$6),Lançamentos!$D:$D,"Saída")) | F67: {=IF(B67="","",SUMPRODUCT(('Fluxo de Caixa'!$B$82:$IL$82>=B67)*('Fluxo de Caixa'!$B$82:$IL$82<=MIN($C$6,IF($D$6="Dia",B67,IF($D$6="Semana",B67+6,IF($D$6="Mês",EOMONTH(B67,0),DATE(YEAR(B67),12,31))))))*'Fluxo de Caixa'!$B$140:$IL$140))} | G67: =IF(B67="","",(C67-E67)-(D67-F67)) | H67: =IF(B67="","",IFERROR(G67/ABS(D67-F67),0))
