Workbook

Sheet Lançamentos
A1: Data | B1: Descrição | C1: Categoria | D1: Tipo | E1: Grupo DRE | F1: Entrada | G1: Saída | H1: Valor | I1: Banco | J1: Mês
A2: 46027 | B2: Venda de produto - NF 001 | C2: Vendas de Produtos | D2: =IF(C2="","",VLOOKUP(C2,Categorias!$A$2:$C$54,2,FALSE)) -> Receita | E2: =IF(C2="","",VLOOKUP(C2,Categorias!$A$2:$C$54,3,FALSE)) -> Receita Bruta | F2: 15000 | H2: =IF(F2="",0,F2)-IF(G2="",0,G2) -> 15000 | I2: Banco do Brasil | J2: =IF(A2="","",DATE(YEAR(A2),MONTH(A2),1)) -> 46023
A3: 46032 | B3: Aluguel janeiro | C3: Aluguel | D3: =IF(C3="","",VLOOKUP(C3,Categorias!$A$2:$C$54,2,FALSE)) -> Despesa | E3: =IF(C3="","",VLOOKUP(C3,Categorias!$A$2:$C$54,3,FALSE)) -> Despesas Operacionais | G3: 3500 | H3: =IF(F3="",0,F3)-IF(G3="",0,G3) -> -3500 | I3: Itaú | J3: =IF(A3="","",DATE(YEAR(A3),MONTH(A3),1)) -> 46023
A4: 46068 | B4: Serviço prestado | C4: Vendas de Serviços | D4: =IF(C4="","",VLOOKUP(C4,Categorias!$A$2:$C$54,2,FALSE)) -> Receita | E4: =IF(C4="","",VLOOKUP(C4,Categorias!$A$2:$C$54,3,FALSE)) -> Receita Bruta | F4: 8000 | H4: =IF(F4="",0,F4)-IF(G4="",0,G4) -> 8000 | I4: Banco do Brasil | J4: =IF(A4="","",DATE(YEAR(A4),MONTH(A4),1)) -> 46054
A5: 46073 | B5: Folha de pagamento | C5: Salários e Encargos | D5: =IF(C5="","",VLOOKUP(C5,Categorias!$A$2:$C$54,2,FALSE)) -> Despesa | E5: =IF(C5="","",VLOOKUP(C5,Categorias!$A$2:$C$54,3,FALSE)) -> Despesas Operacionais | G5: 12000 | H5: =IF(F5="",0,F5)-IF(G5="",0,G5) -> -12000 | I5: Itaú | J5: =IF(A5="","",DATE(YEAR(A5),MONTH(A5),1)) -> 46054
A6: 46152 | B6: Serviço prestado | C6: Vendas de Serviços | D6: =IF(C6="","",VLOOKUP(C6,Categorias!$A$2:$C$54,2,FALSE)) -> Receita | E6: =IF(C6="","",VLOOKUP(C6,Categorias!$A$2:$C$54,3,FALSE)) -> Receita Bruta | F6: 25000 | H6: =IF(F6="",0,F6)-IF(G6="",0,G6) -> 25000 | I6: Banco do Brasil | J6: =IF(A6="","",DATE(YEAR(A6),MONTH(A6),1)) -> 46143
D7: =IF(C7="","",VLOOKUP(C7,Categorias!$A$2:$C$54,2,FALSE)) | E7: =IF(C7="","",VLOOKUP(C7,Categorias!$A$2:$C$54,3,FALSE)) | H7: =IF(F7="",0,F7)-IF(G7="",0,G7) -> 0 | J7: =IF(A7="","",DATE(YEAR(A7),MONTH(A7),1))
D8: =IF(C8="","",VLOOKUP(C8,Categorias!$A$2:$C$54,2,FALSE)) | E8: =IF(C8="","",VLOOKUP(C8,Categorias!$A$2:$C$54,3,FALSE)) | H8: =IF(F8="",0,F8)-IF(G8="",0,G8) -> 0 | J8: =IF(A8="","",DATE(YEAR(A8),MONTH(A8),1))
D9: =IF(C9="","",VLOOKUP(C9,Categorias!$A$2:$C$54,2,FALSE)) | E9: =IF(C9="","",VLOOKUP(C9,Categorias!$A$2:$C$54,3,FALSE)) | H9: =IF(F9="",0,F9)-IF(G9="",0,G9) -> 0 | J9: =IF(A9="","",DATE(YEAR(A9),MONTH(A9),1))
D10: =IF(C10="","",VLOOKUP(C10,Categorias!$A$2:$C$54,2,FALSE)) | E10: =IF(C10="","",VLOOKUP(C10,Categorias!$A$2:$C$54,3,FALSE)) | H10: =IF(F10="",0,F10)-IF(G10="",0,G10) -> 0 | J10: =IF(A10="","",DATE(YEAR(A10),MONTH(A10),1))
D11: =IF(C11="","",VLOOKUP(C11,Categorias!$A$2:$C$54,2,FALSE)) | E11: =IF(C11="","",VLOOKUP(C11,Categorias!$A$2:$C$54,3,FALSE)) | H11: =IF(F11="",0,F11)-IF(G11="",0,G11) -> 0 | J11: =IF(A11="","",DATE(YEAR(A11),MONTH(A11),1))
D12: =IF(C12="","",VLOOKUP(C12,Categorias!$A$2:$C$54,2,FALSE)) | E12: =IF(C12="","",VLOOKUP(C12,Categorias!$A$2:$C$54,3,FALSE)) | H12: =IF(F12="",0,F12)-IF(G12="",0,G12) -> 0 | J12: =IF(A12="","",DATE(YEAR(A12),MONTH(A12),1))
D13: =IF(C13="","",VLOOKUP(C13,Categorias!$A$2:$C$54,2,FALSE)) | E13: =IF(C13="","",VLOOKUP(C13,Categorias!$A$2:$C$54,3,FALSE)) | H13: =IF(F13="",0,F13)-IF(G13="",0,G13) -> 0 | J13: =IF(A13="","",DATE(YEAR(A13),MONTH(A13),1))
D14: =IF(C14="","",VLOOKUP(C14,Categorias!$A$2:$C$54,2,FALSE)) | E14: =IF(C14="","",VLOOKUP(C14,Categorias!$A$2:$C$54,3,FALSE)) | H14: =IF(F14="",0,F14)-IF(G14="",0,G14) -> 0 | J14: =IF(A14="","",DATE(YEAR(A14),MONTH(A14),1))
D15: =IF(C15="","",VLOOKUP(C15,Categorias!$A$2:$C$54,2,FALSE)) | E15: =IF(C15="","",VLOOKUP(C15,Categorias!$A$2:$C$54,3,FALSE)) | H15: =IF(F15="",0,F15)-IF(G15="",0,G15) -> 0 | J15: =IF(A15="","",DATE(YEAR(A15),MONTH(A15),1))
D16: =IF(C16="","",VLOOKUP(C16,Categorias!$A$2:$C$54,2,FALSE)) | E16: =IF(C16="","",VLOOKUP(C16,Categorias!$A$2:$C$54,3,FALSE)) | H16: =IF(F16="",0,F16)-IF(G16="",0,G16) -> 0 | J16: =IF(A16="","",DATE(YEAR(A16),MONTH(A16),1))
D17: =IF(C17="","",VLOOKUP(C17,Categorias!$A$2:$C$54,2,FALSE)) | E17: =IF(C17="","",VLOOKUP(C17,Categorias!$A$2:$C$54,3,FALSE)) | H17: =IF(F17="",0,F17)-IF(G17="",0,G17) -> 0 | J17: =IF(A17="","",DATE(YEAR(A17),MONTH(A17),1))
D18: =IF(C18="","",VLOOKUP(C18,Categorias!$A$2:$C$54,2,FALSE)) | E18: =IF(C18="","",VLOOKUP(C18,Categorias!$A$2:$C$54,3,FALSE)) | H18: =IF(F18="",0,F18)-IF(G18="",0,G18) -> 0 | J18: =IF(A18="","",DATE(YEAR(A18),MONTH(A18),1))
... D200: =IF(C200="","",VLOOKUP(C200,Categorias!$A$2:$C$54,2,FALSE)) | E200: =IF(C200="","",VLOOKUP(C200,Categorias!$A$2:$C$54,3,FALSE)) | H200: =IF(F200="",0,F200)-IF(G200="",0,G200) -> 0 | J200: =IF(A200="","",DATE(YEAR(A200),MONTH(A200),1))

Sheet Categorias
A1: Categoria | B1: Tipo | C1: Grupo DRE | E1: Banco | F1: Saldo Inicial
A2: Vendas de Produtos | B2: Receita | C2: Receita Bruta | E2: Banco do Brasil | F2: 0
A3: Vendas de Serviços | B3: Receita | C3: Receita Bruta | E3: Itaú | F3: 0
A4: Outras Receitas | B4: Receita | C4: Outras Receitas | E4: Caixa | F4: 0
A5: Impostos sobre Vendas | B5: Despesa | C5: Deduções
A6: Devoluções | B6: Despesa | C6: Deduções
A7: Custo de Mercadoria Vendida | B7: Despesa | C7: CMV
A8: Custo de Serviços Prestados | B8: Despesa | C8: CMV
A9: Salários e Encargos | B9: Despesa | C9: Despesas Operacionais
A10: Aluguel | B10: Despesa | C10: Despesas Operacionais
A11: Água, Luz e Internet | B11: Despesa | C11: Despesas Operacionais
A12: Material de Escritório | B12: Despesa | C12: Despesas Operacionais
A13: Marketing e Publicidade | B13: Despesa | C13: Despesas Operacionais
A14: Manutenção | B14: Despesa | C14: Despesas Operacionais
A15: Transporte e Viagens | B15: Despesa | C15: Despesas Operacionais
A16: Serviços de Terceiros | B16: Despesa | C16: Despesas Operacionais
... A54: PIS/COFINS | B54: Despesa | C54: Deduções

Sheet DRE
A1: DRE - Demonstração do Resultado
A3: Ano: | B3: =YEAR(TODAY()) -> 2026
A5: Grupo | B5: =DATE($B$3,1,1) -> 46023 | C5: =EDATE(B5,1) -> 46054 | D5: =EDATE(B5,2) -> 46082 | E5: =EDATE(B5,3) -> 46113 | F5: =EDATE(B5,4) -> 46143 | G5: =EDATE(B5,5) -> 46174 | H5: =EDATE(B5,6) -> 46204 | I5: =EDATE(B5,7) -> 46235 | J5: =EDATE(B5,8) -> 46266 | K5: =EDATE(B5,9) -> 46296 | L5: =EDATE(B5,10) -> 46327 | M5: =EDATE(B5,11) -> 46357 | N5: Total Ano
A6: (+) Receita Bruta | B6: =SUMIFS(Lançamentos!$F:$F,Lançamentos!$E:$E,"Receita Bruta",Lançamentos!$J:$J,B$5) -> 15000 | C6: =SUMIFS(Lançamentos!$F:$F,Lançamentos!$E:$E,"Receita Bruta",Lançamentos!$J:$J,C$5) -> 8000 | D6: =SUMIFS(Lançamentos!$F:$F,Lançamentos!$E:$E,"Receita Bruta",Lançamentos!$J:$J,D$5) -> 0 | E6: =SUMIFS(Lançamentos!$F:$F,Lançamentos!$E:$E,"Receita Bruta",Lançamentos!$J:$J,E$5) -> 0 | F6: =SUMIFS(Lançamentos!$F:$F,Lançamentos!$E:$E,"Receita Bruta",Lançamentos!$J:$J,F$5) -> 25000 | G6: =SUMIFS(Lançamentos!$F:$F,Lançamentos!$E:$E,"Receita Bruta",Lançamentos!$J:$J,G$5) -> 0 | H6: =SUMIFS(Lançamentos!$F:$F,Lançamentos!$E:$E,"Receita Bruta",Lançamentos!$J:$J,H$5) -> 0 | I6: =SUMIFS(Lançamentos!$F:$F,Lançamentos!$E:$E,"Receita Bruta",Lançamentos!$J:$J,I$5) -> 0 | ... M6: =SUMIFS(Lançamentos!$F:$F,Lançamentos!$E:$E,"Receita Bruta",Lançamentos!$J:$J,M$5) -> 0 | N6: =SUM(B6:M6) -> 48000
A7: (-) Deduções | B7: =-SUMIFS(Lançamentos!$G:$G,Lançamentos!$E:$E,"Deduções",Lançamentos!$J:$J,B$5) -> 0 | C7: =-SUMIFS(Lançamentos!$G:$G,Lançamentos!$E:$E,"Deduções",Lançamentos!$J:$J,C$5) -> 0 | D7: =-SUMIFS(Lançamentos!$G:$G,Lançamentos!$E:$E,"Deduções",Lançamentos!$J:$J,D$5) -> 0 | E7: =-SUMIFS(Lançamentos!$G:$G,Lançamentos!$E:$E,"Deduções",Lançamentos!$J:$J,E$5) -> 0 | F7: =-SUMIFS(Lançamentos!$G:$G,Lançamentos!$E:$E,"Deduções",Lançamentos!$J:$J,F$5) -> 0 | G7: =-SUMIFS(Lançamentos!$G:$G,Lançamentos!$E:$E,"Deduções",Lançamentos!$J:$J,G$5) -> 0 | H7: =-SUMIFS(Lançamentos!$G:$G,Lançamentos!$E:$E,"Deduções",Lançamentos!$J:$J,H$5) -> 0 | I7: =-SUMIFS(Lançamentos!$G:$G,Lançamentos!$E:$E,"Deduções",Lançamentos!$J:$J,I$5) -> 0 | ... M7: =-SUMIFS(Lançamentos!$G:$G,Lançamentos!$E:$E,"Deduções",Lançamentos!$J:$J,M$5) -> 0 | N7: =SUM(B7:M7) -> 0
A8: (=) Receita Líquida | B8: =B6+B7 -> 15000 | C8: =C6+C7 -> 8000 | D8: =D6+D7 -> 0 | E8: =E6+E7 -> 0 | F8: =F6+F7 -> 25000 | G8: =G6+G7 -> 0 | H8: =H6+H7 -> 0 | I8: =I6+I7 -> 0 | ... M8: =M6+M7 -> 0 | N8: =SUM(B8:M8) -> 48000
A9: (-) CMV | B9: =-SUMIFS(Lançamentos!$G:$G,Lançamentos!$E:$E,"CMV",Lançamentos!$J:$J,B$5) -> 0 | C9: =-SUMIFS(Lançamentos!$G:$G,Lançamentos!$E:$E,"CMV",Lançamentos!$J:$J,C$5) -> 0 | D9: =-SUMIFS(Lançamentos!$G:$G,Lançamentos!$E:$E,"CMV",Lançamentos!$J:$J,D$5) -> 0 | E9: =-SUMIFS(Lançamentos!$G:$G,Lançamentos!$E:$E,"CMV",Lançamentos!$J:$J,E$5) -> 0 | F9: =-SUMIFS(Lançamentos!$G:$G,Lançamentos!$E:$E,"CMV",Lançamentos!$J:$J,F$5) -> 0 | G9: =-SUMIFS(Lançamentos!$G:$G,Lançamentos!$E:$E,"CMV",Lançamentos!$J:$J,G$5) -> 0 | H9: =-SUMIFS(Lançamentos!$G:$G,Lançamentos!$E:$E,"CMV",Lançamentos!$J:$J,H$5) -> 0 | I9: =-SUMIFS(Lançamentos!$G:$G,Lançamentos!$E:$E,"CMV",Lançamentos!$J:$J,I$5) -> 0 | ... M9: =-SUMIFS(Lançamentos!$G:$G,Lançamentos!$E:$E,"CMV",Lançamentos!$J:$J,M$5) -> 0 | N9: =SUM(B9:M9) -> 0
A10: (=) Lucro Bruto | B10: =B8+B9 -> 15000 | C10: =C8+C9 -> 8000 | D10: =D8+D9 -> 0 | E10: =E8+E9 -> 0 | F10: =F8+F9 -> 25000 | G10: =G8+G9 -> 0 | H10: =H8+H9 -> 0 | I10: =I8+I9 -> 0 | ... M10: =M8+M9 -> 0 | N10: =SUM(B10:M10) -> 48000
A11: (-) Despesas Operacionais | B11: =-SUMIFS(Lançamentos!$G:$G,Lançamentos!$E:$E,"Despesas Operacionais",Lançamentos!$J:$J,B$5) -> -3500 | C11: =-SUMIFS(Lançamentos!$G:$G,Lançamentos!$E:$E,"Despesas Operacionais",Lançamentos!$J:$J,C$5) -> -12000 | D11: =-SUMIFS(Lançamentos!$G:$G,Lançamentos!$E:$E,"Despesas Operacionais",Lançamentos!$J:$J,D$5) -> 0 | E11: =-SUMIFS(Lançamentos!$G:$G,Lançamentos!$E:$E,"Despesas Operacionais",Lançamentos!$J:$J,E$5) -> 0 | F11: =-SUMIFS(Lançamentos!$G:$G,Lançamentos!$E:$E,"Despesas Operacionais",Lançamentos!$J:$J,F$5) -> 0 | G11: =-SUMIFS(Lançamentos!$G:$G,Lançamentos!$E:$E,"Despesas Operacionais",Lançamentos!$J:$J,G$5) -> 0 | H11: =-SUMIFS(Lançamentos!$G:$G,Lançamentos!$E:$E,"Despesas Operacionais",Lançamentos!$J:$J,H$5) -> 0 | I11: =-SUMIFS(Lançamentos!$G:$G,Lançamentos!$E:$E,"Despesas Operacionais",Lançamentos!$J:$J,I$5) -> 0 | ... M11: =-SUMIFS(Lançamentos!$G:$G,Lançamentos!$E:$E,"Despesas Operacionais",Lançamentos!$J:$J,M$5) -> 0 | N11: =SUM(B11:M11) -> -15500
A12: (=) EBITDA | B12: =B10+B11 -> 11500 | C12: =C10+C11 -> -4000 | D12: =D10+D11 -> 0 | E12: =E10+E11 -> 0 | F12: =F10+F11 -> 25000 | G12: =G10+G11 -> 0 | H12: =H10+H11 -> 0 | I12: =I10+I11 -> 0 | ... M12: =M10+M11 -> 0 | N12: =SUM(B12:M12) -> 32500
A13: (+) Receitas Financeiras | B13: =SUMIFS(Lançamentos!$F:$F,Lançamentos!$E:$E,"Receitas Financeiras",Lançamentos!$J:$J,B$5) -> 0 | C13: =SUMIFS(Lançamentos!$F:$F,Lançamentos!$E:$E,"Receitas Financeiras",Lançamentos!$J:$J,C$5) -> 0 | D13: =SUMIFS(Lançamentos!$F:$F,Lançamentos!$E:$E,"Receitas Financeiras",Lançamentos!$J:$J,D$5) -> 0 | E13: =SUMIFS(Lançamentos!$F:$F,Lançamentos!$E:$E,"Receitas Financeiras",Lançamentos!$J:$J,E$5) -> 0 | F13: =SUMIFS(Lançamentos!$F:$F,Lançamentos!$E:$E,"Receitas Financeiras",Lançamentos!$J:$J,F$5) -> 0 | G13: =SUMIFS(Lançamentos!$F:$F,Lançamentos!$E:$E,"Receitas Financeiras",Lançamentos!$J:$J,G$5) -> 0 | H13: =SUMIFS(Lançamentos!$F:$F,Lançamentos!$E:$E,"Receitas Financeiras",Lançamentos!$J:$J,H$5) -> 0 | I13: =SUMIFS(Lançamentos!$F:$F,Lançamentos!$E:$E,"Receitas Financeiras",Lançamentos!$J:$J,I$5) -> 0 | ... M13: =SUMIFS(Lançamentos!$F:$F,Lançamentos!$E:$E,"Receitas Financeiras",Lançamentos!$J:$J,M$5) -> 0 | N13: =SUM(B13:M13) -> 0
A14: (-) Despesas Financeiras | B14: =-SUMIFS(Lançamentos!$G:$G,Lançamentos!$E:$E,"Despesas Financeiras",Lançamentos!$J:$J,B$5) -> 0 | C14: =-SUMIFS(Lançamentos!$G:$G,Lançamentos!$E:$E,"Despesas Financeiras",Lançamentos!$J:$J,C$5) -> 0 | D14: =-SUMIFS(Lançamentos!$G:$G,Lançamentos!$E:$E,"Despesas Financeiras",Lançamentos!$J:$J,D$5) -> 0 | E14: =-SUMIFS(Lançamentos!$G:$G,Lançamentos!$E:$E,"Despesas Financeiras",Lançamentos!$J:$J,E$5) -> 0 | F14: =-SUMIFS(Lançamentos!$G:$G,Lançamentos!$E:$E,"Despesas Financeiras",Lançamentos!$J:$J,F$5) -> 0 | G14: =-SUMIFS(Lançamentos!$G:$G,Lançamentos!$E:$E,"Despesas Financeiras",Lançamentos!$J:$J,G$5) -> 0 | H14: =-SUMIFS(Lançamentos!$G:$G,Lançamentos!$E:$E,"Despesas Financeiras",Lançamentos!$J:$J,H$5) -> 0 | I14: =-SUMIFS(Lançamentos!$G:$G,Lançamentos!$E:$E,"Despesas Financeiras",Lançamentos!$J:$J,I$5) -> 0 | ... M14: =-SUMIFS(Lançamentos!$G:$G,Lançamentos!$E:$E,"Despesas Financeiras",Lançamentos!$J:$J,M$5) -> 0 | N14: =SUM(B14:M14) -> 0
A15: (+) Outras Receitas | B15: =SUMIFS(Lançamentos!$F:$F,Lançamentos!$E:$E,"Outras Receitas",Lançamentos!$J:$J,B$5) -> 0 | C15: =SUMIFS(Lançamentos!$F:$F,Lançamentos!$E:$E,"Outras Receitas",Lançamentos!$J:$J,C$5) -> 0 | D15: =SUMIFS(Lançamentos!$F:$F,Lançamentos!$E:$E,"Outras Receitas",Lançamentos!$J:$J,D$5) -> 0 | E15: =SUMIFS(Lançamentos!$F:$F,Lançamentos!$E:$E,"Outras Receitas",Lançamentos!$J:$J,E$5) -> 0 | F15: =SUMIFS(Lançamentos!$F:$F,Lançamentos!$E:$E,"Outras Receitas",Lançamentos!$J:$J,F$5) -> 0 | G15: =SUMIFS(Lançamentos!$F:$F,Lançamentos!$E:$E,"Outras Receitas",Lançamentos!$J:$J,G$5) -> 0 | H15: =SUMIFS(Lançamentos!$F:$F,Lançamentos!$E:$E,"Outras Receitas",Lançamentos!$J:$J,H$5) -> 0 | I15: =SUMIFS(Lançamentos!$F:$F,Lançamentos!$E:$E,"Outras Receitas",Lançamentos!$J:$J,I$5) -> 0 | ... M15: =SUMIFS(Lançamentos!$F:$F,Lançamentos!$E:$E,"Outras Receitas",Lançamentos!$J:$J,M$5) -> 0 | N15: =SUM(B15:M15) -> 0
A16: (=) Resultado antes dos Impostos | B16: =B12+B13+B14+B15 -> 11500 | C16: =C12+C13+C14+C15 -> -4000 | D16: =D12+D13+D14+D15 -> 0 | E16: =E12+E13+E14+E15 -> 0 | F16: =F12+F13+F14+F15 -> 25000 | G16: =G12+G13+G14+G15 -> 0 | H16: =H12+H13+H14+H15 -> 0 | I16: =I12+I13+I14+I15 -> 0 | ... M16: =M12+M13+M14+M15 -> 0 | N16: =SUM(B16:M16) -> 32500
A17: (-) Impostos sobre Lucro | B17: =-SUMIFS(Lançamentos!$G:$G,Lançamentos!$E:$E,"Impostos",Lançamentos!$J:$J,B$5) -> 0 | C17: =-SUMIFS(Lançamentos!$G:$G,Lançamentos!$E:$E,"Impostos",Lançamentos!$J:$J,C$5) -> 0 | D17: =-SUMIFS(Lançamentos!$G:$G,Lançamentos!$E:$E,"Impostos",Lançamentos!$J:$J,D$5) -> 0 | E17: =-SUMIFS(Lançamentos!$G:$G,Lançamentos!$E:$E,"Impostos",Lançamentos!$J:$J,E$5) -> 0 | F17: =-SUMIFS(Lançamentos!$G:$G,Lançamentos!$E:$E,"Impostos",Lançamentos!$J:$J,F$5) -> 0 | G17: =-SUMIFS(Lançamentos!$G:$G,Lançamentos!$E:$E,"Impostos",Lançamentos!$J:$J,G$5) -> 0 | H17: =-SUMIFS(Lançamentos!$G:$G,Lançamentos!$E:$E,"Impostos",Lançamentos!$J:$J,H$5) -> 0 | I17: =-SUMIFS(Lançamentos!$G:$G,Lançamentos!$E:$E,"Impostos",Lançamentos!$J:$J,I$5) -> 0 | ... M17: =-SUMIFS(Lançamentos!$G:$G,Lançamentos!$E:$E,"Impostos",Lançamentos!$J:$J,M$5) -> 0 | N17: =SUM(B17:M17) -> 0
A18: (=) LUCRO LÍQUIDO | B18: =B16+B17 -> 11500 | C18: =C16+C17 -> -4000 | D18: =D16+D17 -> 0 | E18: =E16+E17 -> 0 | F18: =F16+F17 -> 25000 | G18: =G16+G17 -> 0 | H18: =H16+H17 -> 0 | I18: =I16+I17 -> 0 | ... M18: =M16+M17 -> 0 | N18: =SUM(B18:M18) -> 32500

Sheet Fluxo de Caixa
A1: Fluxo de Caixa
A3: Ano: | B3: =DRE!B3 -> 2026
A5: Item | B5: =DATE($B$3,1,1) -> 46023 | C5: =EDATE(B5,1) -> 46054 | D5: =EDATE(B5,2) -> 46082 | E5: =EDATE(B5,3) -> 46113 | F5: =EDATE(B5,4) -> 46143 | G5: =EDATE(B5,5) -> 46174 | H5: =EDATE(B5,6) -> 46204 | I5: =EDATE(B5,7) -> 46235 | J5: =EDATE(B5,8) -> 46266 | K5: =EDATE(B5,9) -> 46296 | L5: =EDATE(B5,10) -> 46327 | M5: =EDATE(B5,11) -> 46357 | N5: Total
A6: Saldo Inicial | B6: =SUM(Categorias!F2:F4) -> 0 | C6: =B10 -> 11500 | D6: =C10 -> 7500 | E6: =D10 -> 7500 | F6: =E10 -> 7500 | G6: =F10 -> 32500 | H6: =G10 -> 32500 | I6: =H10 -> 32500 | J6: =I10 -> 32500 | ... M6: =L10 -> 32500
A7: (+) Total de Entradas | B7: =SUMIFS(Lançamentos!$F:$F,Lançamentos!$J:$J,B$5) -> 15000 | C7: =SUMIFS(Lançamentos!$F:$F,Lançamentos!$J:$J,C$5) -> 8000 | D7: =SUMIFS(Lançamentos!$F:$F,Lançamentos!$J:$J,D$5) -> 0 | E7: =SUMIFS(Lançamentos!$F:$F,Lançamentos!$J:$J,E$5) -> 0 | F7: =SUMIFS(Lançamentos!$F:$F,Lançamentos!$J:$J,F$5) -> 25000 | G7: =SUMIFS(Lançamentos!$F:$F,Lançamentos!$J:$J,G$5) -> 0 | H7: =SUMIFS(Lançamentos!$F:$F,Lançamentos!$J:$J,H$5) -> 0 | I7: =SUMIFS(Lançamentos!$F:$F,Lançamentos!$J:$J,I$5) -> 0 | ... M7: =SUMIFS(Lançamentos!$F:$F,Lançamentos!$J:$J,M$5) -> 0 | N7: =SUM(B7:M7) -> 48000
A8: (-) Total de Saídas | B8: =-SUMIFS(Lançamentos!$G:$G,Lançamentos!$J:$J,B$5) -> -3500 | C8: =-SUMIFS(Lançamentos!$G:$G,Lançamentos!$J:$J,C$5) -> -12000 | D8: =-SUMIFS(Lançamentos!$G:$G,Lançamentos!$J:$J,D$5) -> 0 | E8: =-SUMIFS(Lançamentos!$G:$G,Lançamentos!$J:$J,E$5) -> 0 | F8: =-SUMIFS(Lançamentos!$G:$G,Lançamentos!$J:$J,F$5) -> 0 | G8: =-SUMIFS(Lançamentos!$G:$G,Lançamentos!$J:$J,G$5) -> 0 | H8: =-SUMIFS(Lançamentos!$G:$G,Lançamentos!$J:$J,H$5) -> 0 | I8: =-SUMIFS(Lançamentos!$G:$G,Lançamentos!$J:$J,I$5) -> 0 | ... M8: =-SUMIFS(Lançamentos!$G:$G,Lançamentos!$J:$J,M$5) -> 0 | N8: =SUM(B8:M8) -> -15500
A9: (=) Fluxo do Mês | B9: =B7+B8 -> 11500 | C9: =C7+C8 -> -4000 | D9: =D7+D8 -> 0 | E9: =E7+E8 -> 0 | F9: =F7+F8 -> 25000 | G9: =G7+G8 -> 0 | H9: =H7+H8 -> 0 | I9: =I7+I8 -> 0 | ... M9: =M7+M8 -> 0 | N9: =SUM(B9:M9) -> 32500
A10: (=) Saldo Acumulado | B10: =B6+B9 -> 11500 | C10: =C6+C9 -> 7500 | D10: =D6+D9 -> 7500 | E10: =E6+E9 -> 7500 | F10: =F6+F9 -> 32500 | G10: =G6+G9 -> 32500 | H10: =H6+H9 -> 32500 | I10: =I6+I9 -> 32500 | ... M10: =M6+M9 -> 32500 | N10: =M10 -> 32500
A12: Detalhamento por Banco
A13: =Categorias!E2 -> Banco do Brasil | B13: =Categorias!F2+SUMIFS(Lançamentos!$F:$F,Lançamentos!$I:$I,$A13,Lançamentos!$J:$J,B$5)-SUMIFS(Lançamentos!$G:$G,Lançamentos!$I:$I,$A13,Lançamentos!$J:$J,B$5) -> 15000 | C13: =Categorias!G2+SUMIFS(Lançamentos!$F:$F,Lançamentos!$I:$I,$A13,Lançamentos!$J:$J,C$5)-SUMIFS(Lançamentos!$G:$G,Lançamentos!$I:$I,$A13,Lançamentos!$J:$J,C$5) -> 8000 | D13: =Categorias!H2+SUMIFS(Lançamentos!$F:$F,Lançamentos!$I:$I,$A13,Lançamentos!$J:$J,D$5)-SUMIFS(Lançamentos!$G:$G,Lançamentos!$I:$I,$A13,Lançamentos!$J:$J,D$5) -> 0 | E13: =Categorias!I2+SUMIFS(Lançamentos!$F:$F,Lançamentos!$I:$I,$A13,Lançamentos!$J:$J,E$5)-SUMIFS(Lançamentos!$G:$G,Lançamentos!$I:$I,$A13,Lançamentos!$J:$J,E$5) -> 0 | F13: =Categorias!J2+SUMIFS(Lançamentos!$F:$F,Lançamentos!$I:$I,$A13,Lançamentos!$J:$J,F$5)-SUMIFS(Lançamentos!$G:$G,Lançamentos!$I:$I,$A13,Lançamentos!$J:$J,F$5) -> 25000 | G13: =Categorias!K2+SUMIFS(Lançamentos!$F:$F,Lançamentos!$I:$I,$A13,Lançamentos!$J:$J,G$5)-SUMIFS(Lançamentos!$G:$G,Lançamentos!$I:$I,$A13,Lançamentos!$J:$J,G$5) -> 0 | H13: =Categorias!L2+SUMIFS(Lançamentos!$F:$F,Lançamentos!$I:$I,$A13,Lançamentos!$J:$J,H$5)-SUMIFS(Lançamentos!$G:$G,Lançamentos!$I:$I,$A13,Lançamentos!$J:$J,H$5) -> 0 | I13: =Categorias!M2+SUMIFS(Lançamentos!$F:$F,Lançamentos!$I:$I,$A13,Lançamentos!$J:$J,I$5)-SUMIFS(Lançamentos!$G:$G,Lançamentos!$I:$I,$A13,Lançamentos!$J:$J,I$5) -> 0 | ... M13: =Categorias!Q2+SUMIFS(Lançamentos!$F:$F,Lançamentos!$I:$I,$A13,Lançamentos!$J:$J,M$5)-SUMIFS(Lançamentos!$G:$G,Lançamentos!$I:$I,$A13,Lançamentos!$J:$J,M$5) -> 0 | N13: =M13 -> 0
A14: =Categorias!E3 -> Itaú | B14: =Categorias!F3+SUMIFS(Lançamentos!$F:$F,Lançamentos!$I:$I,$A14,Lançamentos!$J:$J,B$5)-SUMIFS(Lançamentos!$G:$G,Lançamentos!$I:$I,$A14,Lançamentos!$J:$J,B$5) -> -3500 | C14: =Categorias!G3+SUMIFS(Lançamentos!$F:$F,Lançamentos!$I:$I,$A14,Lançamentos!$J:$J,C$5)-SUMIFS(Lançamentos!$G:$G,Lançamentos!$I:$I,$A14,Lançamentos!$J:$J,C$5) -> -12000 | D14: =Categorias!H3+SUMIFS(Lançamentos!$F:$F,Lançamentos!$I:$I,$A14,Lançamentos!$J:$J,D$5)-SUMIFS(Lançamentos!$G:$G,Lançamentos!$I:$I,$A14,Lançamentos!$J:$J,D$5) -> 0 | E14: =Categorias!I3+SUMIFS(Lançamentos!$F:$F,Lançamentos!$I:$I,$A14,Lançamentos!$J:$J,E$5)-SUMIFS(Lançamentos!$G:$G,Lançamentos!$I:$I,$A14,Lançamentos!$J:$J,E$5) -> 0 | F14: =Categorias!J3+SUMIFS(Lançamentos!$F:$F,Lançamentos!$I:$I,$A14,Lançamentos!$J:$J,F$5)-SUMIFS(Lançamentos!$G:$G,Lançamentos!$I:$I,$A14,Lançamentos!$J:$J,F$5) -> 0 | G14: =Categorias!K3+SUMIFS(Lançamentos!$F:$F,Lançamentos!$I:$I,$A14,Lançamentos!$J:$J,G$5)-SUMIFS(Lançamentos!$G:$G,Lançamentos!$I:$I,$A14,Lançamentos!$J:$J,G$5) -> 0 | H14: =Categorias!L3+SUMIFS(Lançamentos!$F:$F,Lançamentos!$I:$I,$A14,Lançamentos!$J:$J,H$5)-SUMIFS(Lançamentos!$G:$G,Lançamentos!$I:$I,$A14,Lançamentos!$J:$J,H$5) -> 0 | I14: =Categorias!M3+SUMIFS(Lançamentos!$F:$F,Lançamentos!$I:$I,$A14,Lançamentos!$J:$J,I$5)-SUMIFS(Lançamentos!$G:$G,Lançamentos!$I:$I,$A14,Lançamentos!$J:$J,I$5) -> 0 | ... M14: =Categorias!Q3+SUMIFS(Lançamentos!$F:$F,Lançamentos!$I:$I,$A14,Lançamentos!$J:$J,M$5)-SUMIFS(Lançamentos!$G:$G,Lançamentos!$I:$I,$A14,Lançamentos!$J:$J,M$5) -> 0 | N14: =M14 -> 0
A15: =Categorias!E4 -> Caixa | B15: =Categorias!F4+SUMIFS(Lançamentos!$F:$F,Lançamentos!$I:$I,$A15,Lançamentos!$J:$J,B$5)-SUMIFS(Lançamentos!$G:$G,Lançamentos!$I:$I,$A15,Lançamentos!$J:$J,B$5) -> 0 | C15: =Categorias!G4+SUMIFS(Lançamentos!$F:$F,Lançamentos!$I:$I,$A15,Lançamentos!$J:$J,C$5)-SUMIFS(Lançamentos!$G:$G,Lançamentos!$I:$I,$A15,Lançamentos!$J:$J,C$5) -> 0 | D15: =Categorias!H4+SUMIFS(Lançamentos!$F:$F,Lançamentos!$I:$I,$A15,Lançamentos!$J:$J,D$5)-SUMIFS(Lançamentos!$G:$G,Lançamentos!$I:$I,$A15,Lançamentos!$J:$J,D$5) -> 0 | E15: =Categorias!I4+SUMIFS(Lançamentos!$F:$F,Lançamentos!$I:$I,$A15,Lançamentos!$J:$J,E$5)-SUMIFS(Lançamentos!$G:$G,Lançamentos!$I:$I,$A15,Lançamentos!$J:$J,E$5) -> 0 | F15: =Categorias!J4+SUMIFS(Lançamentos!$F:$F,Lançamentos!$I:$I,$A15,Lançamentos!$J:$J,F$5)-SUMIFS(Lançamentos!$G:$G,Lançamentos!$I:$I,$A15,Lançamentos!$J:$J,F$5) -> 0 | G15: =Categorias!K4+SUMIFS(Lançamentos!$F:$F,Lançamentos!$I:$I,$A15,Lançamentos!$J:$J,G$5)-SUMIFS(Lançamentos!$G:$G,Lançamentos!$I:$I,$A15,Lançamentos!$J:$J,G$5) -> 0 | H15: =Categorias!L4+SUMIFS(Lançamentos!$F:$F,Lançamentos!$I:$I,$A15,Lançamentos!$J:$J,H$5)-SUMIFS(Lançamentos!$G:$G,Lançamentos!$I:$I,$A15,Lançamentos!$J:$J,H$5) -> 0 | I15: =Categorias!M4+SUMIFS(Lançamentos!$F:$F,Lançamentos!$I:$I,$A15,Lançamentos!$J:$J,I$5)-SUMIFS(Lançamentos!$G:$G,Lançamentos!$I:$I,$A15,Lançamentos!$J:$J,I$5) -> 0 | ... M15: =Categorias!Q4+SUMIFS(Lançamentos!$F:$F,Lançamentos!$I:$I,$A15,Lançamentos!$J:$J,M$5)-SUMIFS(Lançamentos!$G:$G,Lançamentos!$I:$I,$A15,Lançamentos!$J:$J,M$5) -> 0 | N15: =M15 -> 0
A18: FLUXO DE CAIXA DIÁRIO (Mai-Dez)
A19: Data → | B19: =DATE(2026,5,1) -> 46143 | C19: =DATE(2026,5,2) -> 46144 | D19: =DATE(2026,5,3) -> 46145 | E19: =DATE(2026,5,4) -> 46146 | F19: =DATE(2026,5,5) -> 46147 | G19: =DATE(2026,5,6) -> 46148 | H19: =DATE(2026,5,7) -> 46149 | I19: =DATE(2026,5,8) -> 46150 | J19: =DATE(2026,5,9) -> 46151 | K19: =DATE(2026,5,10) -> 46152 | L19: =DATE(2026,5,11) -> 46153 | M19: =DATE(2026,5,12) -> 46154 | N19: =DATE(2026,5,13) -> 46155 | O19: =DATE(2026,5,14) -> 46156 | P19: =DATE(2026,5,15) -> 46157 | Q19: =DATE(2026,5,16) -> 46158 | R19: =DATE(2026,5,17) -> 46159 | S19: =DATE(2026,5,18) -> 46160 | T19: =DATE(2026,5,19) -> 46161 | U19: =DATE(2026,5,20) -> 46162 | V19: =DATE(2026,5,21) -> 46163 | W19: =DATE(2026,5,22) -> 46164 | X19: =DATE(2026,5,23) -> 46165 | Y19: =DATE(2026,5,24) -> 46166 | Z19: =DATE(2026,5,25) -> 46167 | AA19: =DATE(2026,5,26) -> 46168 | AB19: =DATE(2026,5,27) -> 46169 | AC19: =DATE(2026,5,28) -> 46170 | AD19: =DATE(2026,5,29) -> 46171 | AE19: =DATE(2026,5,30) -> 46172 | AF19: =DATE(2026,5,31) -> 46173 | AG19: =DATE(2026,6,1) -> 46174 | AH19: =DATE(2026,6,2) -> 46175 | AI19: =DATE(2026,6,3) -> 46176 | AJ19: =DATE(2026,6,4) -> 46177 | AK19: =DATE(2026,6,5) -> 46178 | AL19: =DATE(2026,6,6) -> 46179 | AM19: =DATE(2026,6,7) -> 46180 | AN19: =DATE(2026,6,8) -> 46181 | AO19: =DATE(2026,6,9) -> 46182 | AP19: =DATE(2026,6,10) -> 46183 | AQ19: =DATE(2026,6,11) -> 46184 | AR19: =DATE(2026,6,12) -> 46185 | AS19: =DATE(2026,6,13) -> 46186 | AT19: =DATE(2026,6,14) -> 46187 | AU19: =DATE(2026,6,15) -> 46188 | AV19: =DATE(2026,6,16) -> 46189 | AW19: =DATE(2026,6,17) -> 46190 | AX19: =DATE(2026,6,18) -> 46191 | AY19: =DATE(2026,6,19) -> 46192 | AZ19: =DATE(2026,6,20) -> 46193 | BA19: =DATE(2026,6,21) -> 46194 | BB19: =DATE(2026,6,22) -> 46195 | BC19: =DATE(2026,6,23) -> 46196 | BD19: =DATE(2026,6,24) -> 46197 | BE19: =DATE(2026,6,25) -> 46198 | BF19: =DATE(2026,6,26) -> 46199 | BG19: =DATE(2026,6,27) -> 46200 | BH19: =DATE(2026,6,28) -> 46201 | BI19: =DATE(2026,6,29) -> 46202 | BJ19: =DATE(2026,6,30) -> 46203 | BK19: =DATE(2026,7,1) -> 46204 | BL19: =DATE(2026,7,2) -> 46205 | BM19: =DATE(2026,7,3) -> 46206 | BN19: =DATE(2026,7,4) -> 46207 | BO19: =DATE(2026,7,5) -> 46208 | BP19: =DATE(2026,7,6) -> 46209 | BQ19: =DATE(2026,7,7) -> 46210 | BR19: =DATE(2026,7,8) -> 46211 | BS19: =DATE(2026,7,9) -> 46212 | BT19: =DATE(2026,7,10) -> 46213 | BU19: =DATE(2026,7,11) -> 46214 | BV19: =DATE(2026,7,12) -> 46215 | BW19: =DATE(2026,7,13) -> 46216 | BX19: =DATE(2026,7,14) -> 46217 | BY19: =DATE(2026,7,15) -> 46218 | BZ19: =DATE(2026,7,16) -> 46219 | CA19: =DATE(2026,7,17) -> 46220 | CB19: =DATE(2026,7,18) -> 46221 | CC19: =DATE(2026,7,19) -> 46222 | CD19: =DATE(2026,7,20) -> 46223 | CE19: =DATE(2026,7,21) -> 46224 | CF19: =DATE(2026,7,22) -> 46225 | CG19: =DATE(2026,7,23) -> 46226 | CH19: =DATE(2026,7,24) -> 46227 | CI19: =DATE(2026,7,25) -> 46228 | CJ19: =DATE(2026,7,26) -> 46229 | CK19: =DATE(2026,7,27) -> 46230 | CL19: =DATE(2026,7,28) -> 46231 | CM19: =DATE(2026,7,29) -> 46232 | CN19: =DATE(2026,7,30) -> 46233 | CO19: =DATE(2026,7,31) -> 46234 | CP19: =DATE(2026,8,1) -> 46235 | CQ19: =DATE(2026,8,2) -> 46236 | CR19: =DATE(2026,8,3) -> 46237 | CS19: =DATE(2026,8,4) -> 46238 | CT19: =DATE(2026,8,5) -> 46239 | CU19: =DATE(2026,8,6) -> 46240 | CV19: =DATE(2026,8,7) -> 46241 | CW19: =DATE(2026,8,8) -> 46242 | CX19: =DATE(2026,8,9) -> 46243 | CY19: =DATE(2026,8,10) -> 46244 | CZ19: =DATE(2026,8,11) -> 46245 | DA19: =DATE(2026,8,12) -> 46246 | DB19: =DATE(2026,8,13) -> 46247 | DC19: =DATE(2026,8,14) -> 46248 | DD19: =DATE(2026,8,15) -> 46249 | DE19: =DATE(2026,8,16) -> 46250 | DF19: =DATE(2026,8,17) -> 46251 | DG19: =DATE(2026,8,18) -> 46252 | DH19: =DATE(2026,8,19) -> 46253 | DI19: =DATE(2026,8,20) -> 46254 | DJ19: =DATE(2026,8,21) -> 46255 | DK19: =DATE(2026,8,22) -> 46256 | DL19: =DATE(2026,8,23) -> 46257 | DM19: =DATE(2026,8,24) -> 46258 | DN19: =DATE(2026,8,25) -> 46259 | DO19: =DATE(2026,8,26) -> 46260 | DP19: =DATE(2026,8,27) -> 46261 | DQ19: =DATE(2026,8,28) -> 46262 | DR19: =DATE(2026,8,29) -> 46263 | DS19: =DATE(2026,8,30) -> 46264 | DT19: =DATE(2026,8,31) -> 46265 | DU19: =DATE(2026,9,1) -> 46266 | DV19: =DATE(2026,9,2) -> 46267 | DW19: =DATE(2026,9,3) -> 46268 | DX19: =DATE(2026,9,4) -> 46269 | DY19: =DATE(2026,9,5) -> 46270 | DZ19: =DATE(2026,9,6) -> 46271 | EA19: =DATE(2026,9,7) -> 46272 | EB19: =DATE(2026,9,8) -> 46273 | EC19: =DATE(2026,9,9) -> 46274 | ED19: =DATE(2026,9,10) -> 46275 | EE19: =DATE(2026,9,11) -> 46276 | EF19: =DATE(2026,9,12) -> 46277 | EG19: =DATE(2026,9,13) -> 46278 | EH19: =DATE(2026,9,14) -> 46279 | EI19: =DATE(2026,9,15) -> 46280 | EJ19: =DATE(2026,9,16) -> 46281 | EK19: =DATE(2026,9,17) -> 46282 | EL19: =DATE(2026,9,18) -> 46283 | EM19: =DATE(2026,9,19) -> 46284 | EN19: =DATE(2026,9,20) -> 46285 | EO19: =DATE(2026,9,21) -> 46286 | EP19: =DATE(2026,9,22) -> 46287 | EQ19: =DATE(2026,9,23) -> 46288 | ER19: =DATE(2026,9,24) -> 46289 | ES19: =DATE(2026,9,25) -> 46290 | ET19: =DATE(2026,9,26) -> 46291 | EU19: =DATE(2026,9,27) -> 46292 | EV19: =DATE(2026,9,28) -> 46293 | EW19: =DATE(2026,9,29) -> 46294 | EX19: =DATE(2026,9,30) -> 46295 | EY19: =DATE(2026,10,1) -> 46296 | EZ19: =DATE(2026,10,2) -> 46297 | FA19: =DATE(2026,10,3) -> 46298 | FB19: =DATE(2026,10,4) -> 46299 | FC19: =DATE(2026,10,5) -> 46300 | FD19: =DATE(2026,10,6) -> 46301 | FE19: =DATE(2026,10,7) -> 46302 | FF19: =DATE(2026,10,8) -> 46303 | FG19: =DATE(2026,10,9) -> 46304 | FH19: =DATE(2026,10,10) -> 46305 | FI19: =DATE(2026,10,11) -> 46306 | FJ19: =DATE(2026,10,12) -> 46307 | FK19: =DATE(2026,10,13) -> 46308 | FL19: =DATE(2026,10,14) -> 46309 | FM19: =DATE(2026,10,15) -> 46310 | FN19: =DATE(2026,10,16) -> 46311 | FO19: =DATE(2026,10,17) -> 46312 | FP19: =DATE(2026,10,18) -> 46313 | FQ19: =DATE(2026,10,19) -> 46314 | FR19: =DATE(2026,10,20) -> 46315 | FS19: =DATE(2026,10,21) -> 46316 | FT19: =DATE(2026,10,22) -> 46317 | FU19: =DATE(2026,10,23) -> 46318 | FV19: =DATE(2026,10,24) -> 46319 | FW19: =DATE(2026,10,25) -> 46320 | FX19: =DATE(2026,10,26) -> 46321 | FY19: =DATE(2026,10,27) -> 46322 | FZ19: =DATE(2026,10,28) -> 46323 | GA19: =DATE(2026,10,29) -> 46324 | GB19: =DATE(2026,10,30) -> 46325 | GC19: =DATE(2026,10,31) -> 46326 | GD19: =DATE(2026,11,1) -> 46327 | GE19: =DATE(2026,11,2) -> 46328 | GF19: =DATE(2026,11,3) -> 46329 | GG19: =DATE(2026,11,4) -> 46330 | GH19: =DATE(2026,11,5) -> 46331 | GI19: =DATE(2026,11,6) -> 46332 | GJ19: =DATE(2026,11,7) -> 46333 | GK19: =DATE(2026,11,8) -> 46334 | GL19: =DATE(2026,11,9) -> 46335 | GM19: =DATE(2026,11,10) -> 46336 | GN19: =DATE(2026,11,11) -> 46337 | GO19: =DATE(2026,11,12) -> 46338 | GP19: =DATE(2026,11,13) -> 46339 | GQ19: =DATE(2026,11,14) -> 46340 | GR19: =DATE(2026,11,15) -> 46341 | GS19: =DATE(2026,11,16) -> 46342 | GT19: =DATE(2026,11,17) -> 46343 | GU19: =DATE(2026,11,18) -> 46344 | GV19: =DATE(2026,11,19) -> 46345 | GW19: =DATE(2026,11,20) -> 46346 | GX19: =DATE(2026,11,21) -> 46347 | GY19: =DATE(2026,11,22) -> 46348 | GZ19: =DATE(2026,11,23) -> 46349 | HA19: =DATE(2026,11,24) -> 46350 | HB19: =DATE(2026,11,25) -> 46351 | HC19: =DATE(2026,11,26) -> 46352 | HD19: =DATE(2026,11,27) -> 46353 | HE19: =DATE(2026,11,28) -> 46354 | HF19: =DATE(2026,11,29) -> 46355 | HG19: =DATE(2026,11,30) -> 46356 | HH19: =DATE(2026,12,1) -> 46357 | HI19: =DATE(2026,12,2) -> 46358 | HJ19: =DATE(2026,12,3) -> 46359 | HK19: =DATE(2026,12,4) -> 46360 | HL19: =DATE(2026,12,5) -> 46361 | HM19: =DATE(2026,12,6) -> 46362 | HN19: =DATE(2026,12,7) -> 46363 | HO19: =DATE(2026,12,8) -> 46364 | HP19: =DATE(2026,12,9) -> 46365 | HQ19: =DATE(2026,12,10) -> 46366 | HR19: =DATE(2026,12,11) -> 46367 | HS19: =DATE(2026,12,12) -> 46368 | HT19: =DATE(2026,12,13) -> 46369 | HU19: =DATE(2026,12,14) -> 46370 | HV19: =DATE(2026,12,15) -> 46371 | HW19: =DATE(2026,12,16) -> 46372 | HX19: =DATE(2026,12,17) -> 46373 | HY19: =DATE(2026,12,18) -> 46374 | HZ19: =DATE(2026,12,19) -> 46375 | IA19: =DATE(2026,12,20) -> 46376 | IB19: =DATE(2026,12,21) -> 46377 | IC19: =DATE(2026,12,22) -> 46378 | ID19: =DATE(2026,12,23) -> 46379 | IE19: =DATE(2026,12,24) -> 46380 | IF19: =DATE(2026,12,25) -> 46381 | IG19: =DATE(2026,12,26) -> 46382 | IH19: =DATE(2026,12,27) -> 46383 | II19: =DATE(2026,12,28) -> 46384 | IJ19: =DATE(2026,12,29) -> 46385 | IK19: =DATE(2026,12,30) -> 46386 | IL19: =DATE(2026,12,31) -> 46387
A20: SALDO INICIAL DO DIA | B20: =SUM(Categorias!$F$2:$F$4)+SUMIFS(Lançamentos!$F:$F,Lançamentos!$A:$A,"<"&B$19)-SUMIFS(Lançamentos!$G:$G,Lançamentos!$A:$A,"<"&B$19) -> 7500 | C20: =B79 -> 7500 | D20: =C79 -> 7500 | E20: =D79 -> 7500 | F20: =E79 -> 7500 | G20: =F79 -> 7500 | H20: =G79 -> 7500 | I20: =H79 -> 7500 | J20: =I79 -> 7500 | ... IL20: =IK79 -> 32500
A21: 💰 RECEITAS
A22: Vendas de Produtos | B22: =SUMIFS(Lançamentos!$F:$F,Lançamentos!$A:$A,B$19,Lançamentos!$C:$C,"Vendas de Produtos") -> 0 | C22: =SUMIFS(Lançamentos!$F:$F,Lançamentos!$A:$A,C$19,Lançamentos!$C:$C,"Vendas de Produtos") -> 0 | D22: =SUMIFS(Lançamentos!$F:$F,Lançamentos!$A:$A,D$19,Lançamentos!$C:$C,"Vendas de Produtos") -> 0 | E22: =SUMIFS(Lançamentos!$F:$F,Lançamentos!$A:$A,E$19,Lançamentos!$C:$C,"Vendas de Produtos") -> 0 | F22: =SUMIFS(Lançamentos!$F:$F,Lançamentos!$A:$A,F$19,Lançamentos!$C:$C,"Vendas de Produtos") -> 0 | G22: =SUMIFS(Lançamentos!$F:$F,Lançamentos!$A:$A,G$19,Lançamentos!$C:$C,"Vendas de Produtos") -> 0 | H22: =SUMIFS(Lançamentos!$F:$F,Lançamentos!$A:$A,H$19,Lançamentos!$C:$C,"Vendas de Produtos") -> 0 | I22: =SUMIFS(Lançamentos!$F:$F,Lançamentos!$A:$A,I$19,Lançamentos!$C:$C,"Vendas de Produtos") -> 0 | ... IL22: =SUMIFS(Lançamentos!$F:$F,Lançamentos!$A:$A,IL$19,Lançamentos!$C:$C,"Vendas de Produtos") -> 0
A23: Vendas de Serviços | B23: =SUMIFS(Lançamentos!$F:$F,Lançamentos!$A:$A,B$19,Lançamentos!$C:$C,"Vendas de Serviços") -> 0 | C23: =SUMIFS(Lançamentos!$F:$F,Lançamentos!$A:$A,C$19,Lançamentos!$C:$C,"Vendas de Serviços") -> 0 | D23: =SUMIFS(Lançamentos!$F:$F,Lançamentos!$A:$A,D$19,Lançamentos!$C:$C,"Vendas de Serviços") -> 0 | E23: =SUMIFS(Lançamentos!$F:$F,Lançamentos!$A:$A,E$19,Lançamentos!$C:$C,"Vendas de Serviços") -> 0 | F23: =SUMIFS(Lançamentos!$F:$F,Lançamentos!$A:$A,F$19,Lançamentos!$C:$C,"Vendas de Serviços") -> 0 | G23: =SUMIFS(Lançamentos!$F:$F,Lançamentos!$A:$A,G$19,Lançamentos!$C:$C,"Vendas de Serviços") -> 0 | H23: =SUMIFS(Lançamentos!$F:$F,Lançamentos!$A:$A,H$19,Lançamentos!$C:$C,"Vendas de Serviços") -> 0 | I23: =SUMIFS(Lançamentos!$F:$F,Lançamentos!$A:$A,I$19,Lançamentos!$C:$C,"Vendas de Serviços") -> 0 | ... IL23: =SUMIFS(Lançamentos!$F:$F,Lançamentos!$A:$A,IL$19,Lançamentos!$C:$C,"Vendas de Serviços") -> 0
A24: Outras Receitas | B24: =SUMIFS(Lançamentos!$F:$F,Lançamentos!$A:$A,B$19,Lançamentos!$C:$C,"Outras Receitas") -> 0 | C24: =SUMIFS(Lançamentos!$F:$F,Lançamentos!$A:$A,C$19,Lançamentos!$C:$C,"Outras Receitas") -> 0 | D24: =SUMIFS(Lançamentos!$F:$F,Lançamentos!$A:$A,D$19,Lançamentos!$C:$C,"Outras Receitas") -> 0 | E24: =SUMIFS(Lançamentos!$F:$F,Lançamentos!$A:$A,E$19,Lançamentos!$C:$C,"Outras Receitas") -> 0 | F24: =SUMIFS(Lançamentos!$F:$F,Lançamentos!$A:$A,F$19,Lançamentos!$C:$C,"Outras Receitas") -> 0 | G24: =SUMIFS(Lançamentos!$F:$F,Lançamentos!$A:$A,G$19,Lançamentos!$C:$C,"Outras Receitas") -> 0 | H24: =SUMIFS(Lançamentos!$F:$F,Lançamentos!$A:$A,H$19,Lançamentos!$C:$C,"Outras Receitas") -> 0 | I24: =SUMIFS(Lançamentos!$F:$F,Lançamentos!$A:$A,I$19,Lançamentos!$C:$C,"Outras Receitas") -> 0 | ... IL24: =SUMIFS(Lançamentos!$F:$F,Lançamentos!$A:$A,IL$19,Lançamentos!$C:$C,"Outras Receitas") -> 0
A25: Receitas Financeiras | B25: =SUMIFS(Lançamentos!$F:$F,Lançamentos!$A:$A,B$19,Lançamentos!$C:$C,"Receitas Financeiras") -> 0 | C25: =SUMIFS(Lançamentos!$F:$F,Lançamentos!$A:$A,C$19,Lançamentos!$C:$C,"Receitas Financeiras") -> 0 | D25: =SUMIFS(Lançamentos!$F:$F,Lançamentos!$A:$A,D$19,Lançamentos!$C:$C,"Receitas Financeiras") -> 0 | E25: =SUMIFS(Lançamentos!$F:$F,Lançamentos!$A:$A,E$19,Lançamentos!$C:$C,"Receitas Financeiras") -> 0 | F25: =SUMIFS(Lançamentos!$F:$F,Lançamentos!$A:$A,F$19,Lançamentos!$C:$C,"Receitas Financeiras") -> 0 | G25: =SUMIFS(Lançamentos!$F:$F,Lançamentos!$A:$A,G$19,Lançamentos!$C:$C,"Receitas Financeiras") -> 0 | H25: =SUMIFS(Lançamentos!$F:$F,Lançamentos!$A:$A,H$19,Lançamentos!$C:$C,"Receitas Financeiras") -> 0 | I25: =SUMIFS(Lançamentos!$F:$F,Lançamentos!$A:$A,I$19,Lançamentos!$C:$C,"Receitas Financeiras") -> 0 | ... IL25: =SUMIFS(Lançamentos!$F:$F,Lançamentos!$A:$A,IL$19,Lançamentos!$C:$C,"Receitas Financeiras") -> 0
A26: Recebimento de Clientes | B26: =SUMIFS(Lançamentos!$F:$F,Lançamentos!$A:$A,B$19,Lançamentos!$C:$C,"Recebimento de Clientes") -> 0 | C26: =SUMIFS(Lançamentos!$F:$F,Lançamentos!$A:$A,C$19,Lançamentos!$C:$C,"Recebimento de Clientes") -> 0 | D26: =SUMIFS(Lançamentos!$F:$F,Lançamentos!$A:$A,D$19,Lançamentos!$C:$C,"Recebimento de Clientes") -> 0 | E26: =SUMIFS(Lançamentos!$F:$F,Lançamentos!$A:$A,E$19,Lançamentos!$C:$C,"Recebimento de Clientes") -> 0 | F26: =SUMIFS(Lançamentos!$F:$F,Lançamentos!$A:$A,F$19,Lançamentos!$C:$C,"Recebimento de Clientes") -> 0 | G26: =SUMIFS(Lançamentos!$F:$F,Lançamentos!$A:$A,G$19,Lançamentos!$C:$C,"Recebimento de Clientes") -> 0 | H26: =SUMIFS(Lançamentos!$F:$F,Lançamentos!$A:$A,H$19,Lançamentos!$C:$C,"Recebimento de Clientes") -> 0 | I26: =SUMIFS(Lançamentos!$F:$F,Lançamentos!$A:$A,I$19,Lançamentos!$C:$C,"Recebimento de Clientes") -> 0 | ... IL26: =SUMIFS(Lançamentos!$F:$F,Lançamentos!$A:$A,IL$19,Lançamentos!$C:$C,"Recebimento de Clientes") -> 0
A27: Vendas Online | B27: =SUMIFS(Lançamentos!$F:$F,Lançamentos!$A:$A,B$19,Lançamentos!$C:$C,"Vendas Online") -> 0 | C27: =SUMIFS(Lançamentos!$F:$F,Lançamentos!$A:$A,C$19,Lançamentos!$C:$C,"Vendas Online") -> 0 | D27: =SUMIFS(Lançamentos!$F:$F,Lançamentos!$A:$A,D$19,Lançamentos!$C:$C,"Vendas Online") -> 0 | E27: =SUMIFS(Lançamentos!$F:$F,Lançamentos!$A:$A,E$19,Lançamentos!$C:$C,"Vendas Online") -> 0 | F27: =SUMIFS(Lançamentos!$F:$F,Lançamentos!$A:$A,F$19,Lançamentos!$C:$C,"Vendas Online") -> 0 | G27: =SUMIFS(Lançamentos!$F:$F,Lançamentos!$A:$A,G$19,Lançamentos!$C:$C,"Vendas Online") -> 0 | H27: =SUMIFS(Lançamentos!$F:$F,Lançamentos!$A:$A,H$19,Lançamentos!$C:$C,"Vendas Online") -> 0 | I27: =SUMIFS(Lançamentos!$F:$F,Lançamentos!$A:$A,I$19,Lançamentos!$C:$C,"Vendas Online") -> 0 | ... IL27: =SUMIFS(Lançamentos!$F:$F,Lançamentos!$A:$A,IL$19,Lançamentos!$C:$C,"Vendas Online") -> 0
A28: Comissões Recebidas | B28: =SUMIFS(Lançamentos!$F:$F,Lançamentos!$A:$A,B$19,Lançamentos!$C:$C,"Comissões Recebidas") -> 0 | C28: =SUMIFS(Lançamentos!$F:$F,Lançamentos!$A:$A,C$19,Lançamentos!$C:$C,"Comissões Recebidas") -> 0 | D28: =SUMIFS(Lançamentos!$F:$F,Lançamentos!$A:$A,D$19,Lançamentos!$C:$C,"Comissões Recebidas") -> 0 | E28: =SUMIFS(Lançamentos!$F:$F,Lançamentos!$A:$A,E$19,Lançamentos!$C:$C,"Comissões Recebidas") -> 0 | F28: =SUMIFS(Lançamentos!$F:$F,Lançamentos!$A:$A,F$19,Lançamentos!$C:$C,"Comissões Recebidas") -> 0 | G28: =SUMIFS(Lançamentos!$F:$F,Lançamentos!$A:$A,G$19,Lançamentos!$C:$C,"Comissões Recebidas") -> 0 | H28: =SUMIFS(Lançamentos!$F:$F,Lançamentos!$A:$A,H$19,Lançamentos!$C:$C,"Comissões Recebidas") -> 0 | I28: =SUMIFS(Lançamentos!$F:$F,Lançamentos!$A:$A,I$19,Lançamentos!$C:$C,"Comissões Recebidas") -> 0 | ... IL28: =SUMIFS(Lançamentos!$F:$F,Lançamentos!$A:$A,IL$19,Lançamentos!$C:$C,"Comissões Recebidas") -> 0
A29: Aluguel Recebido | B29: =SUMIFS(Lançamentos!$F:$F,Lançamentos!$A:$A,B$19,Lançamentos!$C:$C,"Aluguel Recebido") -> 0 | C29: =SUMIFS(Lançamentos!$F:$F,Lançamentos!$A:$A,C$19,Lançamentos!$C:$C,"Aluguel Recebido") -> 0 | D29: =SUMIFS(Lançamentos!$F:$F,Lançamentos!$A:$A,D$19,Lançamentos!$C:$C,"Aluguel Recebido") -> 0 | E29: =SUMIFS(Lançamentos!$F:$F,Lançamentos!$A:$A,E$19,Lançamentos!$C:$C,"Aluguel Recebido") -> 0 | F29: =SUMIFS(Lançamentos!$F:$F,Lançamentos!$A:$A,F$19,Lançamentos!$C:$C,"Aluguel Recebido") -> 0 | G29: =SUMIFS(Lançamentos!$F:$F,Lançamentos!$A:$A,G$19,Lançamentos!$C:$C,"Aluguel Recebido") -> 0 | H29: =SUMIFS(Lançamentos!$F:$F,Lançamentos!$A:$A,H$19,Lançamentos!$C:$C,"Aluguel Recebido") -> 0 | I29: =SUMIFS(Lançamentos!$F:$F,Lançamentos!$A:$A,I$19,Lançamentos!$C:$C,"Aluguel Recebido") -> 0 | ... IL29: =SUMIFS(Lançamentos!$F:$F,Lançamentos!$A:$A,IL$19,Lançamentos!$C:$C,"Aluguel Recebido") -> 0
A30: Reembolsos | B30: =SUMIFS(Lançamentos!$F:$F,Lançamentos!$A:$A,B$19,Lançamentos!$C:$C,"Reembolsos") -> 0 | C30: =SUMIFS(Lançamentos!$F:$F,Lançamentos!$A:$A,C$19,Lançamentos!$C:$C,"Reembolsos") -> 0 | D30: =SUMIFS(Lançamentos!$F:$F,Lançamentos!$A:$A,D$19,Lançamentos!$C:$C,"Reembolsos") -> 0 | E30: =SUMIFS(Lançamentos!$F:$F,Lançamentos!$A:$A,E$19,Lançamentos!$C:$C,"Reembolsos") -> 0 | F30: =SUMIFS(Lançamentos!$F:$F,Lançamentos!$A:$A,F$19,Lançamentos!$C:$C,"Reembolsos") -> 0 | G30: =SUMIFS(Lançamentos!$F:$F,Lançamentos!$A:$A,G$19,Lançamentos!$C:$C,"Reembolsos") -> 0 | H30: =SUMIFS(Lançamentos!$F:$F,Lançamentos!$A:$A,H$19,Lançamentos!$C:$C,"Reembolsos") -> 0 | I30: =SUMIFS(Lançamentos!$F:$F,Lançamentos!$A:$A,I$19,Lançamentos!$C:$C,"Reembolsos") -> 0 | ... IL30: =SUMIFS(Lançamentos!$F:$F,Lançamentos!$A:$A,IL$19,Lançamentos!$C:$C,"Reembolsos") -> 0
A31: Aporte de Sócios | B31: =SUMIFS(Lançamentos!$F:$F,Lançamentos!$A:$A,B$19,Lançamentos!$C:$C,"Aporte de Sócios") -> 0 | C31: =SUMIFS(Lançamentos!$F:$F,Lançamentos!$A:$A,C$19,Lançamentos!$C:$C,"Aporte de Sócios") -> 0 | D31: =SUMIFS(Lançamentos!$F:$F,Lançamentos!$A:$A,D$19,Lançamentos!$C:$C,"Aporte de Sócios") -> 0 | E31: =SUMIFS(Lançamentos!$F:$F,Lançamentos!$A:$A,E$19,Lançamentos!$C:$C,"Aporte de Sócios") -> 0 | F31: =SUMIFS(Lançamentos!$F:$F,Lançamentos!$A:$A,F$19,Lançamentos!$C:$C,"Aporte de Sócios") -> 0 | G31: =SUMIFS(Lançamentos!$F:$F,Lançamentos!$A:$A,G$19,Lançamentos!$C:$C,"Aporte de Sócios") -> 0 | H31: =SUMIFS(Lançamentos!$F:$F,Lançamentos!$A:$A,H$19,Lançamentos!$C:$C,"Aporte de Sócios") -> 0 | I31: =SUMIFS(Lançamentos!$F:$F,Lançamentos!$A:$A,I$19,Lançamentos!$C:$C,"Aporte de Sócios") -> 0 | ... IL31: =SUMIFS(Lançamentos!$F:$F,Lançamentos!$A:$A,IL$19,Lançamentos!$C:$C,"Aporte de Sócios") -> 0
A32: Empréstimo Recebido | B32: =SUMIFS(Lançamentos!$F:$F,Lançamentos!$A:$A,B$19,Lançamentos!$C:$C,"Empréstimo Recebido") -> 0 | C32: =SUMIFS(Lançamentos!$F:$F,Lançamentos!$A:$A,C$19,Lançamentos!$C:$C,"Empréstimo Recebido") -> 0 | D32: =SUMIFS(Lançamentos!$F:$F,Lançamentos!$A:$A,D$19,Lançamentos!$C:$C,"Empréstimo Recebido") -> 0 | E32: =SUMIFS(Lançamentos!$F:$F,Lançamentos!$A:$A,E$19,Lançamentos!$C:$C,"Empréstimo Recebido") -> 0 | F32: =SUMIFS(Lançamentos!$F:$F,Lançamentos!$A:$A,F$19,Lançamentos!$C:$C,"Empréstimo Recebido") -> 0 | G32: =SUMIFS(Lançamentos!$F:$F,Lançamentos!$A:$A,G$19,Lançamentos!$C:$C,"Empréstimo Recebido") -> 0 | H32: =SUMIFS(Lançamentos!$F:$F,Lançamentos!$A:$A,H$19,Lançamentos!$C:$C,"Empréstimo Recebido") -> 0 | I32: =SUMIFS(Lançamentos!$F:$F,Lançamentos!$A:$A,I$19,Lançamentos!$C:$C,"Empréstimo Recebido") -> 0 | ... IL32: =SUMIFS(Lançamentos!$F:$F,Lançamentos!$A:$A,IL$19,Lançamentos!$C:$C,"Empréstimo Recebido") -> 0
A33: TOTAL ENTRADAS | B33: =SUM(B22:B32) -> 0 | C33: =SUM(C22:C32) -> 0 | D33: =SUM(D22:D32) -> 0 | E33: =SUM(E22:E32) -> 0 | F33: =SUM(F22:F32) -> 0 | G33: =SUM(G22:G32) -> 0 | H33: =SUM(H22:H32) -> 0 | I33: =SUM(I22:I32) -> 0 | ... IL33: =SUM(IL22:IL32) -> 0
A34: 💸 DESPESAS
A35: Impostos sobre Vendas | B35: =SUMIFS(Lançamentos!$G:$G,Lançamentos!$A:$A,B$19,Lançamentos!$C:$C,"Impostos sobre Vendas") -> 0 | C35: =SUMIFS(Lançamentos!$G:$G,Lançamentos!$A:$A,C$19,Lançamentos!$C:$C,"Impostos sobre Vendas") -> 0 | D35: =SUMIFS(Lançamentos!$G:$G,Lançamentos!$A:$A,D$19,Lançamentos!$C:$C,"Impostos sobre Vendas") -> 0 | E35: =SUMIFS(Lançamentos!$G:$G,Lançamentos!$A:$A,E$19,Lançamentos!$C:$C,"Impostos sobre Vendas") -> 0 | F35: =SUMIFS(Lançamentos!$G:$G,Lançamentos!$A:$A,F$19,Lançamentos!$C:$C,"Impostos sobre Vendas") -> 0 | G35: =SUMIFS(Lançamentos!$G:$G,Lançamentos!$A:$A,G$19,Lançamentos!$C:$C,"Impostos sobre Vendas") -> 0 | H35: =SUMIFS(Lançamentos!$G:$G,Lançamentos!$A:$A,H$19,Lançamentos!$C:$C,"Impostos sobre Vendas") -> 0 | I35: =SUMIFS(Lançamentos!$G:$G,Lançamentos!$A:$A,I$19,Lançamentos!$C:$C,"Impostos sobre Vendas") -> 0 | ... IL35: =SUMIFS(Lançamentos!$G:$G,Lançamentos!$A:$A,IL$19,Lançamentos!$C:$C,"Impostos sobre Vendas") -> 0
A36: Devoluções | B36: =SUMIFS(Lançamentos!$G:$G,Lançamentos!$A:$A,B$19,Lançamentos!$C:$C,"Devoluções") -> 0 | C36: =SUMIFS(Lançamentos!$G:$G,Lançamentos!$A:$A,C$19,Lançamentos!$C:$C,"Devoluções") -> 0 | D36: =SUMIFS(Lançamentos!$G:$G,Lançamentos!$A:$A,D$19,Lançamentos!$C:$C,"Devoluções") -> 0 | E36: =SUMIFS(Lançamentos!$G:$G,Lançamentos!$A:$A,E$19,Lançamentos!$C:$C,"Devoluções") -> 0 | F36: =SUMIFS(Lançamentos!$G:$G,Lançamentos!$A:$A,F$19,Lançamentos!$C:$C,"Devoluções") -> 0 | G36: =SUMIFS(Lançamentos!$G:$G,Lançamentos!$A:$A,G$19,Lançamentos!$C:$C,"Devoluções") -> 0 | H36: =SUMIFS(Lançamentos!$G:$G,Lançamentos!$A:$A,H$19,Lançamentos!$C:$C,"Devoluções") -> 0 | I36: =SUMIFS(Lançamentos!$G:$G,Lançamentos!$A:$A,I$19,Lançamentos!$C:$C,"Devoluções") -> 0 | ... IL36: =SUMIFS(Lançamentos!$G:$G,Lançamentos!$A:$A,IL$19,Lançamentos!$C:$C,"Devoluções") -> 0
A37: Custo de Mercadoria Vendida | B37: =SUMIFS(Lançamentos!$G:$G,Lançamentos!$A:$A,B$19,Lançamentos!$C:$C,"Custo de Mercadoria Vendida") -> 0 | C37: =SUMIFS(Lançamentos!$G:$G,Lançamentos!$A:$A,C$19,Lançamentos!$C:$C,"Custo de Mercadoria Vendida") -> 0 | D37: =SUMIFS(Lançamentos!$G:$G,Lançamentos!$A:$A,D$19,Lançamentos!$C:$C,"Custo de Mercadoria Vendida") -> 0 | E37: =SUMIFS(Lançamentos!$G:$G,Lançamentos!$A:$A,E$19,Lançamentos!$C:$C,"Custo de Mercadoria Vendida") -> 0 | F37: =SUMIFS(Lançamentos!$G:$G,Lançamentos!$A:$A,F$19,Lançamentos!$C:$C,"Custo de Mercadoria Vendida") -> 0 | G37: =SUMIFS(Lançamentos!$G:$G,Lançamentos!$A:$A,G$19,Lançamentos!$C:$C,"Custo de Mercadoria Vendida") -> 0 | H37: =SUMIFS(Lançamentos!$G:$G,Lançamentos!$A:$A,H$19,Lançamentos!$C:$C,"Custo de Mercadoria Vendida") -> 0 | I37: =SUMIFS(Lançamentos!$G:$G,Lançamentos!$A:$A,I$19,Lançamentos!$C:$C,"Custo de Mercadoria Vendida") -> 0 | ... IL37: =SUMIFS(Lançamentos!$G:$G,Lançamentos!$A:$A,IL$19,Lançamentos!$C:$C,"Custo de Mercadoria Vendida") -> 0
A38: Custo de Serviços Prestados | B38: =SUMIFS(Lançamentos!$G:$G,Lançamentos!$A:$A,B$19,Lançamentos!$C:$C,"Custo de Serviços Prestados") -> 0 | C38: =SUMIFS(Lançamentos!$G:$G,Lançamentos!$A:$A,C$19,Lançamentos!$C:$C,"Custo de Serviços Prestados") -> 0 | D38: =SUMIFS(Lançamentos!$G:$G,Lançamentos!$A:$A,D$19,Lançamentos!$C:$C,"Custo de Serviços Prestados") -> 0 | E38: =SUMIFS(Lançamentos!$G:$G,Lançamentos!$A:$A,E$19,Lançamentos!$C:$C,"Custo de Serviços Prestados") -> 0 | F38: =SUMIFS(Lançamentos!$G:$G,Lançamentos!$A:$A,F$19,Lançamentos!$C:$C,"Custo de Serviços Prestados") -> 0 | G38: =SUMIFS(Lançamentos!$G:$G,Lançamentos!$A:$A,G$19,Lançamentos!$C:$C,"Custo de Serviços Prestados") -> 0 | H38: =SUMIFS(Lançamentos!$G:$G,Lançamentos!$A:$A,H$19,Lançamentos!$C:$C,"Custo de Serviços Prestados") -> 0 | I38: =SUMIFS(Lançamentos!$G:$G,Lançamentos!$A:$A,I$19,Lançamentos!$C:$C,"Custo de Serviços Prestados") -> 0 | ... IL38: =SUMIFS(Lançamentos!$G:$G,Lançamentos!$A:$A,IL$19,Lançamentos!$C:$C,"Custo de Serviços Prestados") -> 0
A39: Salários e Encargos | B39: =SUMIFS(Lançamentos!$G:$G,Lançamentos!$A:$A,B$19,Lançamentos!$C:$C,"Salários e Encargos") -> 0 | C39: =SUMIFS(Lançamentos!$G:$G,Lançamentos!$A:$A,C$19,Lançamentos!$C:$C,"Salários e Encargos") -> 0 | D39: =SUMIFS(Lançamentos!$G:$G,Lançamentos!$A:$A,D$19,Lançamentos!$C:$C,"Salários e Encargos") -> 0 | E39: =SUMIFS(Lançamentos!$G:$G,Lançamentos!$A:$A,E$19,Lançamentos!$C:$C,"Salários e Encargos") -> 0 | F39: =SUMIFS(Lançamentos!$G:$G,Lançamentos!$A:$A,F$19,Lançamentos!$C:$C,"Salários e Encargos") -> 0 | G39: =SUMIFS(Lançamentos!$G:$G,Lançamentos!$A:$A,G$19,Lançamentos!$C:$C,"Salários e Encargos") -> 0 | H39: =SUMIFS(Lançamentos!$G:$G,Lançamentos!$A:$A,H$19,Lançamentos!$C:$C,"Salários e Encargos") -> 0 | I39: =SUMIFS(Lançamentos!$G:$G,Lançamentos!$A:$A,I$19,Lançamentos!$C:$C,"Salários e Encargos") -> 0 | ... IL39: =SUMIFS(Lançamentos!$G:$G,Lançamentos!$A:$A,IL$19,Lançamentos!$C:$C,"Salários e Encargos") -> 0
A40: Aluguel | B40: =SUMIFS(Lançamentos!$G:$G,Lançamentos!$A:$A,B$19,Lançamentos!$C:$C,"Aluguel") -> 0 | C40: =SUMIFS(Lançamentos!$G:$G,Lançamentos!$A:$A,C$19,Lançamentos!$C:$C,"Aluguel") -> 0 | D40: =SUMIFS(Lançamentos!$G:$G,Lançamentos!$A:$A,D$19,Lançamentos!$C:$C,"Aluguel") -> 0 | E40: =SUMIFS(Lançamentos!$G:$G,Lançamentos!$A:$A,E$19,Lançamentos!$C:$C,"Aluguel") -> 0 | F40: =SUMIFS(Lançamentos!$G:$G,Lançamentos!$A:$A,F$19,Lançamentos!$C:$C,"Aluguel") -> 0 | G40: =SUMIFS(Lançamentos!$G:$G,Lançamentos!$A:$A,G$19,Lançamentos!$C:$C,"Aluguel") -> 0 | H40: =SUMIFS(Lançamentos!$G:$G,Lançamentos!$A:$A,H$19,Lançamentos!$C:$C,"Aluguel") -> 0 | I40: =SUMIFS(Lançamentos!$G:$G,Lançamentos!$A:$A,I$19,Lançamentos!$C:$C,"Aluguel") -> 0 | ... IL40: =SUMIFS(Lançamentos!$G:$G,Lançamentos!$A:$A,IL$19,Lançamentos!$C:$C,"Aluguel") -> 0
A41: Água, Luz e Internet | B41: =SUMIFS(Lançamentos!$G:$G,Lançamentos!$A:$A,B$19,Lançamentos!$C:$C,"Água, Luz e Internet") -> 0 | C41: =SUMIFS(Lançamentos!$G:$G,Lançamentos!$A:$A,C$19,Lançamentos!$C:$C,"Água, Luz e Internet") -> 0 | D41: =SUMIFS(Lançamentos!$G:$G,Lançamentos!$A:$A,D$19,Lançamentos!$C:$C,"Água, Luz e Internet") -> 0 | E41: =SUMIFS(Lançamentos!$G:$G,Lançamentos!$A:$A,E$19,Lançamentos!$C:$C,"Água, Luz e Internet") -> 0 | F41: =SUMIFS(Lançamentos!$G:$G,Lançamentos!$A:$A,F$19,Lançamentos!$C:$C,"Água, Luz e Internet") -> 0 | G41: =SUMIFS(Lançamentos!$G:$G,Lançamentos!$A:$A,G$19,Lançamentos!$C:$C,"Água, Luz e Internet") -> 0 | H41: =SUMIFS(Lançamentos!$G:$G,Lançamentos!$A:$A,H$19,Lançamentos!$C:$C,"Água, Luz e Internet") -> 0 | I41: =SUMIFS(Lançamentos!$G:$G,Lançamentos!$A:$A,I$19,Lançamentos!$C:$C,"Água, Luz e Internet") -> 0 | ... IL41: =SUMIFS(Lançamentos!$G:$G,Lançamentos!$A:$A,IL$19,Lançamentos!$C:$C,"Água, Luz e Internet") -> 0
A42: Material de Escritório | B42: =SUMIFS(Lançamentos!$G:$G,Lançamentos!$A:$A,B$19,Lançamentos!$C:$C,"Material de Escritório") -> 0 | C42: =SUMIFS(Lançamentos!$G:$G,Lançamentos!$A:$A,C$19,Lançamentos!$C:$C,"Material de Escritório") -> 0 | D42: =SUMIFS(Lançamentos!$G:$G,Lançamentos!$A:$A,D$19,Lançamentos!$C:$C,"Material de Escritório") -> 0 | E42: =SUMIFS(Lançamentos!$G:$G,Lançamentos!$A:$A,E$19,Lançamentos!$C:$C,"Material de Escritório") -> 0 | F42: =SUMIFS(Lançamentos!$G:$G,Lançamentos!$A:$A,F$19,Lançamentos!$C:$C,"Material de Escritório") -> 0 | G42: =SUMIFS(Lançamentos!$G:$G,Lançamentos!$A:$A,G$19,Lançamentos!$C:$C,"Material de Escritório") -> 0 | H42: =SUMIFS(Lançamentos!$G:$G,Lançamentos!$A:$A,H$19,Lançamentos!$C:$C,"Material de Escritório") -> 0 | I42: =SUMIFS(Lançamentos!$G:$G,Lançamentos!$A:$A,I$19,Lançamentos!$C:$C,"Material de Escritório") -> 0 | ... IL42: =SUMIFS(Lançamentos!$G:$G,Lançamentos!$A:$A,IL$19,Lançamentos!$C:$C,"Material de Escritório") -> 0
A43: Marketing e Publicidade | B43: =SUMIFS(Lançamentos!$G:$G,Lançamentos!$A:$A,B$19,Lançamentos!$C:$C,"Marketing e Publicidade") -> 0 | C43: =SUMIFS(Lançamentos!$G:$G,Lançamentos!$A:$A,C$19,Lançamentos!$C:$C,"Marketing e Publicidade") -> 0 | D43: =SUMIFS(Lançamentos!$G:$G,Lançamentos!$A:$A,D$19,Lançamentos!$C:$C,"Marketing e Publicidade") -> 0 | E43: =SUMIFS(Lançamentos!$G:$G,Lançamentos!$A:$A,E$19,Lançamentos!$C:$C,"Marketing e Publicidade") -> 0 | F43: =SUMIFS(Lançamentos!$G:$G,Lançamentos!$A:$A,F$19,Lançamentos!$C:$C,"Marketing e Publicidade") -> 0 | G43: =SUMIFS(Lançamentos!$G:$G,Lançamentos!$A:$A,G$19,Lançamentos!$C:$C,"Marketing e Publicidade") -> 0 | H43: =SUMIFS(Lançamentos!$G:$G,Lançamentos!$A:$A,H$19,Lançamentos!$C:$C,"Marketing e Publicidade") -> 0 | I43: =SUMIFS(Lançamentos!$G:$G,Lançamentos!$A:$A,I$19,Lançamentos!$C:$C,"Marketing e Publicidade") -> 0 | ... IL43: =SUMIFS(Lançamentos!$G:$G,Lançamentos!$A:$A,IL$19,Lançamentos!$C:$C,"Marketing e Publicidade") -> 0
A44: Manutenção | B44: =SUMIFS(Lançamentos!$G:$G,Lançamentos!$A:$A,B$19,Lançamentos!$C:$C,"Manutenção") -> 0 | C44: =SUMIFS(Lançamentos!$G:$G,Lançamentos!$A:$A,C$19,Lançamentos!$C:$C,"Manutenção") -> 0 | D44: =SUMIFS(Lançamentos!$G:$G,Lançamentos!$A:$A,D$19,Lançamentos!$C:$C,"Manutenção") -> 0 | E44: =SUMIFS(Lançamentos!$G:$G,Lançamentos!$A:$A,E$19,Lançamentos!$C:$C,"Manutenção") -> 0 | F44: =SUMIFS(Lançamentos!$G:$G,Lançamentos!$A:$A,F$19,Lançamentos!$C:$C,"Manutenção") -> 0 | G44: =SUMIFS(Lançamentos!$G:$G,Lançamentos!$A:$A,G$19,Lançamentos!$C:$C,"Manutenção") -> 0 | H44: =SUMIFS(Lançamentos!$G:$G,Lançamentos!$A:$A,H$19,Lançamentos!$C:$C,"Manutenção") -> 0 | I44: =SUMIFS(Lançamentos!$G:$G,Lançamentos!$A:$A,I$19,Lançamentos!$C:$C,"Manutenção") -> 0 | ... IL44: =SUMIFS(Lançamentos!$G:$G,Lançamentos!$A:$A,IL$19,Lançamentos!$C:$C,"Manutenção") -> 0
A45: Transporte e Viagens | B45: =SUMIFS(Lançamentos!$G:$G,Lançamentos!$A:$A,B$19,Lançamentos!$C:$C,"Transporte e Viagens") -> 0 | C45: =SUMIFS(Lançamentos!$G:$G,Lançamentos!$A:$A,C$19,Lançamentos!$C:$C,"Transporte e Viagens") -> 0 | D45: =SUMIFS(Lançamentos!$G:$G,Lançamentos!$A:$A,D$19,Lançamentos!$C:$C,"Transporte e Viagens") -> 0 | E45: =SUMIFS(Lançamentos!$G:$G,Lançamentos!$A:$A,E$19,Lançamentos!$C:$C,"Transporte e Viagens") -> 0 | F45: =SUMIFS(Lançamentos!$G:$G,Lançamentos!$A:$A,F$19,Lançamentos!$C:$C,"Transporte e Viagens") -> 0 | G45: =SUMIFS(Lançamentos!$G:$G,Lançamentos!$A:$A,G$19,Lançamentos!$C:$C,"Transporte e Viagens") -> 0 | H45: =SUMIFS(Lançamentos!$G:$G,Lançamentos!$A:$A,H$19,Lançamentos!$C:$C,"Transporte e Viagens") -> 0 | I45: =SUMIFS(Lançamentos!$G:$G,Lançamentos!$A:$A,I$19,Lançamentos!$C:$C,"Transporte e Viagens") -> 0 | ... IL45: =SUMIFS(Lançamentos!$G:$G,Lançamentos!$A:$A,IL$19,Lançamentos!$C:$C,"Transporte e Viagens") -> 0
A46: Serviços de Terceiros | B46: =SUMIFS(Lançamentos!$G:$G,Lançamentos!$A:$A,B$19,Lançamentos!$C:$C,"Serviços de Terceiros") -> 0 | C46: =SUMIFS(Lançamentos!$G:$G,Lançamentos!$A:$A,C$19,Lançamentos!$C:$C,"Serviços de Terceiros") -> 0 | D46: =SUMIFS(Lançamentos!$G:$G,Lançamentos!$A:$A,D$19,Lançamentos!$C:$C,"Serviços de Terceiros") -> 0 | E46: =SUMIFS(Lançamentos!$G:$G,Lançamentos!$A:$A,E$19,Lançamentos!$C:$C,"Serviços de Terceiros") -> 0 | F46: =SUMIFS(Lançamentos!$G:$G,Lançamentos!$A:$A,F$19,Lançamentos!$C:$C,"Serviços de Terceiros") -> 0 | G46: =SUMIFS(Lançamentos!$G:$G,Lançamentos!$A:$A,G$19,Lançamentos!$C:$C,"Serviços de Terceiros") -> 0 | H46: =SUMIFS(Lançamentos!$G:$G,Lançamentos!$A:$A,H$19,Lançamentos!$C:$C,"Serviços de Terceiros") -> 0 | I46: =SUMIFS(Lançamentos!$G:$G,Lançamentos!$A:$A,I$19,Lançamentos!$C:$C,"Serviços de Terceiros") -> 0 | ... IL46: =SUMIFS(Lançamentos!$G:$G,Lançamentos!$A:$A,IL$19,Lançamentos!$C:$C,"Serviços de Terceiros") -> 0
A47: Juros e Tarifas Bancárias | B47: =SUMIFS(Lançamentos!$G:$G,Lançamentos!$A:$A,B$19,Lançamentos!$C:$C,"Juros e Tarifas Bancárias") -> 0 | C47: =SUMIFS(Lançamentos!$G:$G,Lançamentos!$A:$A,C$19,Lançamentos!$C:$C,"Juros e Tarifas Bancárias") -> 0 | D47: =SUMIFS(Lançamentos!$G:$G,Lançamentos!$A:$A,D$19,Lançamentos!$C:$C,"Juros e Tarifas Bancárias") -> 0 | E47: =SUMIFS(Lançamentos!$G:$G,Lançamentos!$A:$A,E$19,Lançamentos!$C:$C,"Juros e Tarifas Bancárias") -> 0 | F47: =SUMIFS(Lançamentos!$G:$G,Lançamentos!$A:$A,F$19,Lançamentos!$C:$C,"Juros e Tarifas Bancárias") -> 0 | G47: =SUMIFS(Lançamentos!$G:$G,Lançamentos!$A:$A,G$19,Lançamentos!$C:$C,"Juros e Tarifas Bancárias") -> 0 | H47: =SUMIFS(Lançamentos!$G:$G,Lançamentos!$A:$A,H$19,Lançamentos!$C:$C,"Juros e Tarifas Bancárias") -> 0 | I47: =SUMIFS(Lançamentos!$G:$G,Lançamentos!$A:$A,I$19,Lançamentos!$C:$C,"Juros e Tarifas Bancárias") -> 0 | ... IL47: =SUMIFS(Lançamentos!$G:$G,Lançamentos!$A:$A,IL$19,Lançamentos!$C:$C,"Juros e Tarifas Bancárias") -> 0
A48: Empréstimos e Financiamentos | B48: =SUMIFS(Lançamentos!$G:$G,Lançamentos!$A:$A,B$19,Lançamentos!$C:$C,"Empréstimos e Financiamentos") -> 0 | C48: =SUMIFS(Lançamentos!$G:$G,Lançamentos!$A:$A,C$19,Lançamentos!$C:$C,"Empréstimos e Financiamentos") -> 0 | D48: =SUMIFS(Lançamentos!$G:$G,Lançamentos!$A:$A,D$19,Lançamentos!$C:$C,"Empréstimos e Financiamentos") -> 0 | E48: =SUMIFS(Lançamentos!$G:$G,Lançamentos!$A:$A,E$19,Lançamentos!$C:$C,"Empréstimos e Financiamentos") -> 0 | F48: =SUMIFS(Lançamentos!$G:$G,Lançamentos!$A:$A,F$19,Lançamentos!$C:$C,"Empréstimos e Financiamentos") -> 0 | G48: =SUMIFS(Lançamentos!$G:$G,Lançamentos!$A:$A,G$19,Lançamentos!$C:$C,"Empréstimos e Financiamentos") -> 0 | H48: =SUMIFS(Lançamentos!$G:$G,Lançamentos!$A:$A,H$19,Lançamentos!$C:$C,"Empréstimos e Financiamentos") -> 0 | I48: =SUMIFS(Lançamentos!$G:$G,Lançamentos!$A:$A,I$19,Lançamentos!$C:$C,"Empréstimos e Financiamentos") -> 0 | ... IL48: =SUMIFS(Lançamentos!$G:$G,Lançamentos!$A:$A,IL$19,Lançamentos!$C:$C,"Empréstimos e Financiamentos") -> 0
A49: Impostos sobre Lucro | B49: =SUMIFS(Lançamentos!$G:$G,Lançamentos!$A:$A,B$19,Lançamentos!$C:$C,"Impostos sobre Lucro") -> 0 | C49: =SUMIFS(Lançamentos!$G:$G,Lançamentos!$A:$A,C$19,Lançamentos!$C:$C,"Impostos sobre Lucro") -> 0 | D49: =SUMIFS(Lançamentos!$G:$G,Lançamentos!$A:$A,D$19,Lançamentos!$C:$C,"Impostos sobre Lucro") -> 0 | E49: =SUMIFS(Lançamentos!$G:$G,Lançamentos!$A:$A,E$19,Lançamentos!$C:$C,"Impostos sobre Lucro") -> 0 | F49: =SUMIFS(Lançamentos!$G:$G,Lançamentos!$A:$A,F$19,Lançamentos!$C:$C,"Impostos sobre Lucro") -> 0 | G49: =SUMIFS(Lançamentos!$G:$G,Lançamentos!$A:$A,G$19,Lançamentos!$C:$C,"Impostos sobre Lucro") -> 0 | H49: =SUMIFS(Lançamentos!$G:$G,Lançamentos!$A:$A,H$19,Lançamentos!$C:$C,"Impostos sobre Lucro") -> 0 | I49: =SUMIFS(Lançamentos!$G:$G,Lançamentos!$A:$A,I$19,Lançamentos!$C:$C,"Impostos sobre Lucro") -> 0 | ... IL49: =SUMIFS(Lançamentos!$G:$G,Lançamentos!$A:$A,IL$19,Lançamentos!$C:$C,"Impostos sobre Lucro") -> 0
A50: Frete sobre Vendas | B50: =SUMIFS(Lançamentos!$G:$G,Lançamentos!$A:$A,B$19,Lançamentos!$C:$C,"Frete sobre Vendas") -> 0 | C50: =SUMIFS(Lançamentos!$G:$G,Lançamentos!$A:$A,C$19,Lançamentos!$C:$C,"Frete sobre Vendas") -> 0 | D50: =SUMIFS(Lançamentos!$G:$G,Lançamentos!$A:$A,D$19,Lançamentos!$C:$C,"Frete sobre Vendas") -> 0 | E50: =SUMIFS(Lançamentos!$G:$G,Lançamentos!$A:$A,E$19,Lançamentos!$C:$C,"Frete sobre Vendas") -> 0 | F50: =SUMIFS(Lançamentos!$G:$G,Lançamentos!$A:$A,F$19,Lançamentos!$C:$C,"Frete sobre Vendas") -> 0 | G50: =SUMIFS(Lançamentos!$G:$G,Lançamentos!$A:$A,G$19,Lançamentos!$C:$C,"Frete sobre Vendas") -> 0 | H50: =SUMIFS(Lançamentos!$G:$G,Lançamentos!$A:$A,H$19,Lançamentos!$C:$C,"Frete sobre Vendas") -> 0 | I50: =SUMIFS(Lançamentos!$G:$G,Lançamentos!$A:$A,I$19,Lançamentos!$C:$C,"Frete sobre Vendas") -> 0 | ... IL50: =SUMIFS(Lançamentos!$G:$G,Lançamentos!$A:$A,IL$19,Lançamentos!$C:$C,"Frete sobre Vendas") -> 0
A51: Embalagens | B51: =SUMIFS(Lançamentos!$G:$G,Lançamentos!$A:$A,B$19,Lançamentos!$C:$C,"Embalagens") -> 0 | C51: =SUMIFS(Lançamentos!$G:$G,Lançamentos!$A:$A,C$19,Lançamentos!$C:$C,"Embalagens") -> 0 | D51: =SUMIFS(Lançamentos!$G:$G,Lançamentos!$A:$A,D$19,Lançamentos!$C:$C,"Embalagens") -> 0 | E51: =SUMIFS(Lançamentos!$G:$G,Lançamentos!$A:$A,E$19,Lançamentos!$C:$C,"Embalagens") -> 0 | F51: =SUMIFS(Lançamentos!$G:$G,Lançamentos!$A:$A,F$19,Lançamentos!$C:$C,"Embalagens") -> 0 | G51: =SUMIFS(Lançamentos!$G:$G,Lançamentos!$A:$A,G$19,Lançamentos!$C:$C,"Embalagens") -> 0 | H51: =SUMIFS(Lançamentos!$G:$G,Lançamentos!$A:$A,H$19,Lançamentos!$C:$C,"Embalagens") -> 0 | I51: =SUMIFS(Lançamentos!$G:$G,Lançamentos!$A:$A,I$19,Lançamentos!$C:$C,"Embalagens") -> 0 | ... IL51: =SUMIFS(Lançamentos!$G:$G,Lançamentos!$A:$A,IL$19,Lançamentos!$C:$C,"Embalagens") -> 0
A52: Combustível | B52: =SUMIFS(Lançamentos!$G:$G,Lançamentos!$A:$A,B$19,Lançamentos!$C:$C,"Combustível") -> 0 | C52: =SUMIFS(Lançamentos!$G:$G,Lançamentos!$A:$A,C$19,Lançamentos!$C:$C,"Combustível") -> 0 | D52: =SUMIFS(Lançamentos!$G:$G,Lançamentos!$A:$A,D$19,Lançamentos!$C:$C,"Combustível") -> 0 | E52: =SUMIFS(Lançamentos!$G:$G,Lançamentos!$A:$A,E$19,Lançamentos!$C:$C,"Combustível") -> 0 | F52: =SUMIFS(Lançamentos!$G:$G,Lançamentos!$A:$A,F$19,Lançamentos!$C:$C,"Combustível") -> 0 | G52: =SUMIFS(Lançamentos!$G:$G,Lançamentos!$A:$A,G$19,Lançamentos!$C:$C,"Combustível") -> 0 | H52: =SUMIFS(Lançamentos!$G:$G,Lançamentos!$A:$A,H$19,Lançamentos!$C:$C,"Combustível") -> 0 | I52: =SUMIFS(Lançamentos!$G:$G,Lançamentos!$A:$A,I$19,Lançamentos!$C:$C,"Combustível") -> 0 | ... IL52: =SUMIFS(Lançamentos!$G:$G,Lançamentos!$A:$A,IL$19,Lançamentos!$C:$C,"Combustível") -> 0
A53: Pró-labore | B53: =SUMIFS(Lançamentos!$G:$G,Lançamentos!$A:$A,B$19,Lançamentos!$C:$C,"Pró-labore") -> 0 | C53: =SUMIFS(Lançamentos!$G:$G,Lançamentos!$A:$A,C$19,Lançamentos!$C:$C,"Pró-labore") -> 0 | D53: =SUMIFS(Lançamentos!$G:$G,Lançamentos!$A:$A,D$19,Lançamentos!$C:$C,"Pró-labore") -> 0 | E53: =SUMIFS(Lançamentos!$G:$G,Lançamentos!$A:$A,E$19,Lançamentos!$C:$C,"Pró-labore") -> 0 | F53: =SUMIFS(Lançamentos!$G:$G,Lançamentos!$A:$A,F$19,Lançamentos!$C:$C,"Pró-labore") -> 0 | G53: =SUMIFS(Lançamentos!$G:$G,Lançamentos!$A:$A,G$19,Lançamentos!$C:$C,"Pró-labore") -> 0 | H53: =SUMIFS(Lançamentos!$G:$G,Lançamentos!$A:$A,H$19,Lançamentos!$C:$C,"Pró-labore") -> 0 | I53: =SUMIFS(Lançamentos!$G:$G,Lançamentos!$A:$A,I$19,Lançamentos!$C:$C,"Pró-labore") -> 0 | ... IL53: =SUMIFS(Lançamentos!$G:$G,Lançamentos!$A:$A,IL$19,Lançamentos!$C:$C,"Pró-labore") -> 0
A54: Benefícios (VR/VT/Plano) | B54: =SUMIFS(Lançamentos!$G:$G,Lançamentos!$A:$A,B$19,Lançamentos!$C:$C,"Benefícios (VR/VT/Plano)") -> 0 | C54: =SUMIFS(Lançamentos!$G:$G,Lançamentos!$A:$A,C$19,Lançamentos!$C:$C,"Benefícios (VR/VT/Plano)") -> 0 | D54: =SUMIFS(Lançamentos!$G:$G,Lançamentos!$A:$A,D$19,Lançamentos!$C:$C,"Benefícios (VR/VT/Plano)") -> 0 | E54: =SUMIFS(Lançamentos!$G:$G,Lançamentos!$A:$A,E$19,Lançamentos!$C:$C,"Benefícios (VR/VT/Plano)") -> 0 | F54: =SUMIFS(Lançamentos!$G:$G,Lançamentos!$A:$A,F$19,Lançamentos!$C:$C,"Benefícios (VR/VT/Plano)") -> 0 | G54: =SUMIFS(Lançamentos!$G:$G,Lançamentos!$A:$A,G$19,Lançamentos!$C:$C,"Benefícios (VR/VT/Plano)") -> 0 | H54: =SUMIFS(Lançamentos!$G:$G,Lançamentos!$A:$A,H$19,Lançamentos!$C:$C,"Benefícios (VR/VT/Plano)") -> 0 | I54: =SUMIFS(Lançamentos!$G:$G,Lançamentos!$A:$A,I$19,Lançamentos!$C:$C,"Benefícios (VR/VT/Plano)") -> 0 | ... IL54: =SUMIFS(Lançamentos!$G:$G,Lançamentos!$A:$A,IL$19,Lançamentos!$C:$C,"Benefícios (VR/VT/Plano)") -> 0
A55: Software e Assinaturas | B55: =SUMIFS(Lançamentos!$G:$G,Lançamentos!$A:$A,B$19,Lançamentos!$C:$C,"Software e Assinaturas") -> 0 | C55: =SUMIFS(Lançamentos!$G:$G,Lançamentos!$A:$A,C$19,Lançamentos!$C:$C,"Software e Assinaturas") -> 0 | D55: =SUMIFS(Lançamentos!$G:$G,Lançamentos!$A:$A,D$19,Lançamentos!$C:$C,"Software e Assinaturas") -> 0 | E55: =SUMIFS(Lançamentos!$G:$G,Lançamentos!$A:$A,E$19,Lançamentos!$C:$C,"Software e Assinaturas") -> 0 | F55: =SUMIFS(Lançamentos!$G:$G,Lançamentos!$A:$A,F$19,Lançamentos!$C:$C,"Software e Assinaturas") -> 0 | G55: =SUMIFS(Lançamentos!$G:$G,Lançamentos!$A:$A,G$19,Lançamentos!$C:$C,"Software e Assinaturas") -> 0 | H55: =SUMIFS(Lançamentos!$G:$G,Lançamentos!$A:$A,H$19,Lançamentos!$C:$C,"Software e Assinaturas") -> 0 | I55: =SUMIFS(Lançamentos!$G:$G,Lançamentos!$A:$A,I$19,Lançamentos!$C:$C,"Software e Assinaturas") -> 0 | ... IL55: =SUMIFS(Lançamentos!$G:$G,Lançamentos!$A:$A,IL$19,Lançamentos!$C:$C,"Software e Assinaturas") -> 0
A56: Telefone e Celular | B56: =SUMIFS(Lançamentos!$G:$G,Lançamentos!$A:$A,B$19,Lançamentos!$C:$C,"Telefone e Celular") -> 0 | C56: =SUMIFS(Lançamentos!$G:$G,Lançamentos!$A:$A,C$19,Lançamentos!$C:$C,"Telefone e Celular") -> 0 | D56: =SUMIFS(Lançamentos!$G:$G,Lançamentos!$A:$A,D$19,Lançamentos!$C:$C,"Telefone e Celular") -> 0 | E56: =SUMIFS(Lançamentos!$G:$G,Lançamentos!$A:$A,E$19,Lançamentos!$C:$C,"Telefone e Celular") -> 0 | F56: =SUMIFS(Lançamentos!$G:$G,Lançamentos!$A:$A,F$19,Lançamentos!$C:$C,"Telefone e Celular") -> 0 | G56: =SUMIFS(Lançamentos!$G:$G,Lançamentos!$A:$A,G$19,Lançamentos!$C:$C,"Telefone e Celular") -> 0 | H56: =SUMIFS(Lançamentos!$G:$G,Lançamentos!$A:$A,H$19,Lançamentos!$C:$C,"Telefone e Celular") -> 0 | I56: =SUMIFS(Lançamentos!$G:$G,Lançamentos!$A:$A,I$19,Lançamentos!$C:$C,"Telefone e Celular") -> 0 | ... IL56: =SUMIFS(Lançamentos!$G:$G,Lançamentos!$A:$A,IL$19,Lançamentos!$C:$C,"Telefone e Celular") -> 0
A57: Limpeza e Conservação | B57: =SUMIFS(Lançamentos!$G:$G,Lançamentos!$A:$A,B$19,Lançamentos!$C:$C,"Limpeza e Conservação") -> 0 | C57: =SUMIFS(Lançamentos!$G:$G,Lançamentos!$A:$A,C$19,Lançamentos!$C:$C,"Limpeza e Conservação") -> 0 | D57: =SUMIFS(Lançamentos!$G:$G,Lançamentos!$A:$A,D$19,Lançamentos!$C:$C,"Limpeza e Conservação") -> 0 | E57: =SUMIFS(Lançamentos!$G:$G,Lançamentos!$A:$A,E$19,Lançamentos!$C:$C,"Limpeza e Conservação") -> 0 | F57: =SUMIFS(Lançamentos!$G:$G,Lançamentos!$A:$A,F$19,Lançamentos!$C:$C,"Limpeza e Conservação") -> 0 | G57: =SUMIFS(Lançamentos!$G:$G,Lançamentos!$A:$A,G$19,Lançamentos!$C:$C,"Limpeza e Conservação") -> 0 | H57: =SUMIFS(Lançamentos!$G:$G,Lançamentos!$A:$A,H$19,Lançamentos!$C:$C,"Limpeza e Conservação") -> 0 | I57: =SUMIFS(Lançamentos!$G:$G,Lançamentos!$A:$A,I$19,Lançamentos!$C:$C,"Limpeza e Conservação") -> 0 | ... IL57: =SUMIFS(Lançamentos!$G:$G,Lançamentos!$A:$A,IL$19,Lançamentos!$C:$C,"Limpeza e Conservação") -> 0
A58: Seguros | B58: =SUMIFS(Lançamentos!$G:$G,Lançamentos!$A:$A,B$19,Lançamentos!$C:$C,"Seguros") -> 0 | C58: =SUMIFS(Lançamentos!$G:$G,Lançamentos!$A:$A,C$19,Lançamentos!$C:$C,"Seguros") -> 0 | D58: =SUMIFS(Lançamentos!$G:$G,Lançamentos!$A:$A,D$19,Lançamentos!$C:$C,"Seguros") -> 0 | E58: =SUMIFS(Lançamentos!$G:$G,Lançamentos!$A:$A,E$19,Lançamentos!$C:$C,"Seguros") -> 0 | F58: =SUMIFS(Lançamentos!$G:$G,Lançamentos!$A:$A,F$19,Lançamentos!$C:$C,"Seguros") -> 0 | G58: =SUMIFS(Lançamentos!$G:$G,Lançamentos!$A:$A,G$19,Lançamentos!$C:$C,"Seguros") -> 0 | H58: =SUMIFS(Lançamentos!$G:$G,Lançamentos!$A:$A,H$19,Lançamentos!$C:$C,"Seguros") -> 0 | I58: =SUMIFS(Lançamentos!$G:$G,Lançamentos!$A:$A,I$19,Lançamentos!$C:$C,"Seguros") -> 0 | ... IL58: =SUMIFS(Lançamentos!$G:$G,Lançamentos!$A:$A,IL$19,Lançamentos!$C:$C,"Seguros") -> 0
A59: Treinamento e Capacitação | B59: =SUMIFS(Lançamentos!$G:$G,Lançamentos!$A:$A,B$19,Lançamentos!$C:$C,"Treinamento e Capacitação") -> 0 | C59: =SUMIFS(Lançamentos!$G:$G,Lançamentos!$A:$A,C$19,Lançamentos!$C:$C,"Treinamento e Capacitação") -> 0 | D59: =SUMIFS(Lançamentos!$G:$G,Lançamentos!$A:$A,D$19,Lançamentos!$C:$C,"Treinamento e Capacitação") -> 0 | E59: =SUMIFS(Lançamentos!$G:$G,Lançamentos!$A:$A,E$19,Lançamentos!$C:$C,"Treinamento e Capacitação") -> 0 | F59: =SUMIFS(Lançamentos!$G:$G,Lançamentos!$A:$A,F$19,Lançamentos!$C:$C,"Treinamento e Capacitação") -> 0 | G59: =SUMIFS(Lançamentos!$G:$G,Lançamentos!$A:$A,G$19,Lançamentos!$C:$C,"Treinamento e Capacitação") -> 0 | H59: =SUMIFS(Lançamentos!$G:$G,Lançamentos!$A:$A,H$19,Lançamentos!$C:$C,"Treinamento e Capacitação") -> 0 | I59: =SUMIFS(Lançamentos!$G:$G,Lançamentos!$A:$A,I$19,Lançamentos!$C:$C,"Treinamento e Capacitação") -> 0 | ... IL59: =SUMIFS(Lançamentos!$G:$G,Lançamentos!$A:$A,IL$19,Lançamentos!$C:$C,"Treinamento e Capacitação") -> 0
A60: Honorários Contábeis | B60: =SUMIFS(Lançamentos!$G:$G,Lançamentos!$A:$A,B$19,Lançamentos!$C:$C,"Honorários Contábeis") -> 0 | C60: =SUMIFS(Lançamentos!$G:$G,Lançamentos!$A:$A,C$19,Lançamentos!$C:$C,"Honorários Contábeis") -> 0 | D60: =SUMIFS(Lançamentos!$G:$G,Lançamentos!$A:$A,D$19,Lançamentos!$C:$C,"Honorários Contábeis") -> 0 | E60: =SUMIFS(Lançamentos!$G:$G,Lançamentos!$A:$A,E$19,Lançamentos!$C:$C,"Honorários Contábeis") -> 0 | F60: =SUMIFS(Lançamentos!$G:$G,Lançamentos!$A:$A,F$19,Lançamentos!$C:$C,"Honorários Contábeis") -> 0 | G60: =SUMIFS(Lançamentos!$G:$G,Lançamentos!$A:$A,G$19,Lançamentos!$C:$C,"Honorários Contábeis") -> 0 | H60: =SUMIFS(Lançamentos!$G:$G,Lançamentos!$A:$A,H$19,Lançamentos!$C:$C,"Honorários Contábeis") -> 0 | I60: =SUMIFS(Lançamentos!$G:$G,Lançamentos!$A:$A,I$19,Lançamentos!$C:$C,"Honorários Contábeis") -> 0 | ... IL60: =SUMIFS(Lançamentos!$G:$G,Lançamentos!$A:$A,IL$19,Lançamentos!$C:$C,"Honorários Contábeis") -> 0
A61: Honorários Jurídicos | B61: =SUMIFS(Lançamentos!$G:$G,Lançamentos!$A:$A,B$19,Lançamentos!$C:$C,"Honorários Jurídicos") -> 0 | C61: =SUMIFS(Lançamentos!$G:$G,Lançamentos!$A:$A,C$19,Lançamentos!$C:$C,"Honorários Jurídicos") -> 0 | D61: =SUMIFS(Lançamentos!$G:$G,Lançamentos!$A:$A,D$19,Lançamentos!$C:$C,"Honorários Jurídicos") -> 0 | E61: =SUMIFS(Lançamentos!$G:$G,Lançamentos!$A:$A,E$19,Lançamentos!$C:$C,"Honorários Jurídicos") -> 0 | F61: =SUMIFS(Lançamentos!$G:$G,Lançamentos!$A:$A,F$19,Lançamentos!$C:$C,"Honorários Jurídicos") -> 0 | G61: =SUMIFS(Lançamentos!$G:$G,Lançamentos!$A:$A,G$19,Lançamentos!$C:$C,"Honorários Jurídicos") -> 0 | H61: =SUMIFS(Lançamentos!$G:$G,Lançamentos!$A:$A,H$19,Lançamentos!$C:$C,"Honorários Jurídicos") -> 0 | I61: =SUMIFS(Lançamentos!$G:$G,Lançamentos!$A:$A,I$19,Lançamentos!$C:$C,"Honorários Jurídicos") -> 0 | ... IL61: =SUMIFS(Lançamentos!$G:$G,Lançamentos!$A:$A,IL$19,Lançamentos!$C:$C,"Honorários Jurídicos") -> 0
A62: Equipamentos e Informática | B62: =SUMIFS(Lançamentos!$G:$G,Lançamentos!$A:$A,B$19,Lançamentos!$C:$C,"Equipamentos e Informática") -> 0 | C62: =SUMIFS(Lançamentos!$G:$G,Lançamentos!$A:$A,C$19,Lançamentos!$C:$C,"Equipamentos e Informática") -> 0 | D62: =SUMIFS(Lançamentos!$G:$G,Lançamentos!$A:$A,D$19,Lançamentos!$C:$C,"Equipamentos e Informática") -> 0 | E62: =SUMIFS(Lançamentos!$G:$G,Lançamentos!$A:$A,E$19,Lançamentos!$C:$C,"Equipamentos e Informática") -> 0 | F62: =SUMIFS(Lançamentos!$G:$G,Lançamentos!$A:$A,F$19,Lançamentos!$C:$C,"Equipamentos e Informática") -> 0 | G62: =SUMIFS(Lançamentos!$G:$G,Lançamentos!$A:$A,G$19,Lançamentos!$C:$C,"Equipamentos e Informática") -> 0 | H62: =SUMIFS(Lançamentos!$G:$G,Lançamentos!$A:$A,H$19,Lançamentos!$C:$C,"Equipamentos e Informática") -> 0 | I62: =SUMIFS(Lançamentos!$G:$G,Lançamentos!$A:$A,I$19,Lançamentos!$C:$C,"Equipamentos e Informática") -> 0 | ... IL62: =SUMIFS(Lançamentos!$G:$G,Lançamentos!$A:$A,IL$19,Lançamentos!$C:$C,"Equipamentos e Informática") -> 0
A63: Móveis e Utensílios | B63: =SUMIFS(Lançamentos!$G:$G,Lançamentos!$A:$A,B$19,Lançamentos!$C:$C,"Móveis e Utensílios") -> 0 | C63: =SUMIFS(Lançamentos!$G:$G,Lançamentos!$A:$A,C$19,Lançamentos!$C:$C,"Móveis e Utensílios") -> 0 | D63: =SUMIFS(Lançamentos!$G:$G,Lançamentos!$A:$A,D$19,Lançamentos!$C:$C,"Móveis e Utensílios") -> 0 | E63: =SUMIFS(Lançamentos!$G:$G,Lançamentos!$A:$A,E$19,Lançamentos!$C:$C,"Móveis e Utensílios") -> 0 | F63: =SUMIFS(Lançamentos!$G:$G,Lançamentos!$A:$A,F$19,Lançamentos!$C:$C,"Móveis e Utensílios") -> 0 | G63: =SUMIFS(Lançamentos!$G:$G,Lançamentos!$A:$A,G$19,Lançamentos!$C:$C,"Móveis e Utensílios") -> 0 | H63: =SUMIFS(Lançamentos!$G:$G,Lançamentos!$A:$A,H$19,Lançamentos!$C:$C,"Móveis e Utensílios") -> 0 | I63: =SUMIFS(Lançamentos!$G:$G,Lançamentos!$A:$A,I$19,Lançamentos!$C:$C,"Móveis e Utensílios") -> 0 | ... IL63: =SUMIFS(Lançamentos!$G:$G,Lançamentos!$A:$A,IL$19,Lançamentos!$C:$C,"Móveis e Utensílios") -> 0
A64: Refeições e Confraternizações | B64: =SUMIFS(Lançamentos!$G:$G,Lançamentos!$A:$A,B$19,Lançamentos!$C:$C,"Refeições e Confraternizações") -> 0 | C64: =SUMIFS(Lançamentos!$G:$G,Lançamentos!$A:$A,C$19,Lançamentos!$C:$C,"Refeições e Confraternizações") -> 0 | D64: =SUMIFS(Lançamentos!$G:$G,Lançamentos!$A:$A,D$19,Lançamentos!$C:$C,"Refeições e Confraternizações") -> 0 | E64: =SUMIFS(Lançamentos!$G:$G,Lançamentos!$A:$A,E$19,Lançamentos!$C:$C,"Refeições e Confraternizações") -> 0 | F64: =SUMIFS(Lançamentos!$G:$G,Lançamentos!$A:$A,F$19,Lançamentos!$C:$C,"Refeições e Confraternizações") -> 0 | G64: =SUMIFS(Lançamentos!$G:$G,Lançamentos!$A:$A,G$19,Lançamentos!$C:$C,"Refeições e Confraternizações") -> 0 | H64: =SUMIFS(Lançamentos!$G:$G,Lançamentos!$A:$A,H$19,Lançamentos!$C:$C,"Refeições e Confraternizações") -> 0 | I64: =SUMIFS(Lançamentos!$G:$G,Lançamentos!$A:$A,I$19,Lançamentos!$C:$C,"Refeições e Confraternizações") -> 0 | ... IL64: =SUMIFS(Lançamentos!$G:$G,Lançamentos!$A:$A,IL$19,Lançamentos!$C:$C,"Refeições e Confraternizações") -> 0
A65: Correios e Entregas | B65: =SUMIFS(Lançamentos!$G:$G,Lançamentos!$A:$A,B$19,Lançamentos!$C:$C,"Correios e Entregas") -> 0 | C65: =SUMIFS(Lançamentos!$G:$G,Lançamentos!$A:$A,C$19,Lançamentos!$C:$C,"Correios e Entregas") -> 0 | D65: =SUMIFS(Lançamentos!$G:$G,Lançamentos!$A:$A,D$19,Lançamentos!$C:$C,"Correios e Entregas") -> 0 | E65: =SUMIFS(Lançamentos!$G:$G,Lançamentos!$A:$A,E$19,Lançamentos!$C:$C,"Correios e Entregas") -> 0 | F65: =SUMIFS(Lançamentos!$G:$G,Lançamentos!$A:$A,F$19,Lançamentos!$C:$C,"Correios e Entregas") -> 0 | G65: =SUMIFS(Lançamentos!$G:$G,Lançamentos!$A:$A,G$19,Lançamentos!$C:$C,"Correios e Entregas") -> 0 | H65: =SUMIFS(Lançamentos!$G:$G,Lançamentos!$A:$A,H$19,Lançamentos!$C:$C,"Correios e Entregas") -> 0 | I65: =SUMIFS(Lançamentos!$G:$G,Lançamentos!$A:$A,I$19,Lançamentos!$C:$C,"Correios e Entregas") -> 0 | ... IL65: =SUMIFS(Lançamentos!$G:$G,Lançamentos!$A:$A,IL$19,Lançamentos!$C:$C,"Correios e Entregas") -> 0
A66: Taxas e Anuidades | B66: =SUMIFS(Lançamentos!$G:$G,Lançamentos!$A:$A,B$19,Lançamentos!$C:$C,"Taxas e Anuidades") -> 0 | C66: =SUMIFS(Lançamentos!$G:$G,Lançamentos!$A:$A,C$19,Lançamentos!$C:$C,"Taxas e Anuidades") -> 0 | D66: =SUMIFS(Lançamentos!$G:$G,Lançamentos!$A:$A,D$19,Lançamentos!$C:$C,"Taxas e Anuidades") -> 0 | E66: =SUMIFS(Lançamentos!$G:$G,Lançamentos!$A:$A,E$19,Lançamentos!$C:$C,"Taxas e Anuidades") -> 0 | F66: =SUMIFS(Lançamentos!$G:$G,Lançamentos!$A:$A,F$19,Lançamentos!$C:$C,"Taxas e Anuidades") -> 0 | G66: =SUMIFS(Lançamentos!$G:$G,Lançamentos!$A:$A,G$19,Lançamentos!$C:$C,"Taxas e Anuidades") -> 0 | H66: =SUMIFS(Lançamentos!$G:$G,Lançamentos!$A:$A,H$19,Lançamentos!$C:$C,"Taxas e Anuidades") -> 0 | I66: =SUMIFS(Lançamentos!$G:$G,Lançamentos!$A:$A,I$19,Lançamentos!$C:$C,"Taxas e Anuidades") -> 0 | ... IL66: =SUMIFS(Lançamentos!$G:$G,Lançamentos!$A:$A,IL$19,Lançamentos!$C:$C,"Taxas e Anuidades") -> 0
A67: IOF | B67: =SUMIFS(Lançamentos!$G:$G,Lançamentos!$A:$A,B$19,Lançamentos!$C:$C,"IOF") -> 0 | C67: =SUMIFS(Lançamentos!$G:$G,Lançamentos!$A:$A,C$19,Lançamentos!$C:$C,"IOF") -> 0 | D67: =SUMIFS(Lançamentos!$G:$G,Lançamentos!$A:$A,D$19,Lançamentos!$C:$C,"IOF") -> 0 | E67: =SUMIFS(Lançamentos!$G:$G,Lançamentos!$A:$A,E$19,Lançamentos!$C:$C,"IOF") -> 0 | F67: =SUMIFS(Lançamentos!$G:$G,Lançamentos!$A:$A,F$19,Lançamentos!$C:$C,"IOF") -> 0 | G67: =SUMIFS(Lançamentos!$G:$G,Lançamentos!$A:$A,G$19,Lançamentos!$C:$C,"IOF") -> 0 | H67: =SUMIFS(Lançamentos!$G:$G,Lançamentos!$A:$A,H$19,Lançamentos!$C:$C,"IOF") -> 0 | I67: =SUMIFS(Lançamentos!$G:$G,Lançamentos!$A:$A,I$19,Lançamentos!$C:$C,"IOF") -> 0 | ... IL67: =SUMIFS(Lançamentos!$G:$G,Lançamentos!$A:$A,IL$19,Lançamentos!$C:$C,"IOF") -> 0
A68: Cartão de Crédito | B68: =SUMIFS(Lançamentos!$G:$G,Lançamentos!$A:$A,B$19,Lançamentos!$C:$C,"Cartão de Crédito") -> 0 | C68: =SUMIFS(Lançamentos!$G:$G,Lançamentos!$A:$A,C$19,Lançamentos!$C:$C,"Cartão de Crédito") -> 0 | D68: =SUMIFS(Lançamentos!$G:$G,Lançamentos!$A:$A,D$19,Lançamentos!$C:$C,"Cartão de Crédito") -> 0 | E68: =SUMIFS(Lançamentos!$G:$G,Lançamentos!$A:$A,E$19,Lançamentos!$C:$C,"Cartão de Crédito") -> 0 | F68: =SUMIFS(Lançamentos!$G:$G,Lançamentos!$A:$A,F$19,Lançamentos!$C:$C,"Cartão de Crédito") -> 0 | G68: =SUMIFS(Lançamentos!$G:$G,Lançamentos!$A:$A,G$19,Lançamentos!$C:$C,"Cartão de Crédito") -> 0 | H68: =SUMIFS(Lançamentos!$G:$G,Lançamentos!$A:$A,H$19,Lançamentos!$C:$C,"Cartão de Crédito") -> 0 | I68: =SUMIFS(Lançamentos!$G:$G,Lançamentos!$A:$A,I$19,Lançamentos!$C:$C,"Cartão de Crédito") -> 0 | ... IL68: =SUMIFS(Lançamentos!$G:$G,Lançamentos!$A:$A,IL$19,Lançamentos!$C:$C,"Cartão de Crédito") -> 0
A69: Multas e Juros | B69: =SUMIFS(Lançamentos!$G:$G,Lançamentos!$A:$A,B$19,Lançamentos!$C:$C,"Multas e Juros") -> 0 | C69: =SUMIFS(Lançamentos!$G:$G,Lançamentos!$A:$A,C$19,Lançamentos!$C:$C,"Multas e Juros") -> 0 | D69: =SUMIFS(Lançamentos!$G:$G,Lançamentos!$A:$A,D$19,Lançamentos!$C:$C,"Multas e Juros") -> 0 | E69: =SUMIFS(Lançamentos!$G:$G,Lançamentos!$A:$A,E$19,Lançamentos!$C:$C,"Multas e Juros") -> 0 | F69: =SUMIFS(Lançamentos!$G:$G,Lançamentos!$A:$A,F$19,Lançamentos!$C:$C,"Multas e Juros") -> 0 | G69: =SUMIFS(Lançamentos!$G:$G,Lançamentos!$A:$A,G$19,Lançamentos!$C:$C,"Multas e Juros") -> 0 | H69: =SUMIFS(Lançamentos!$G:$G,Lançamentos!$A:$A,H$19,Lançamentos!$C:$C,"Multas e Juros") -> 0 | I69: =SUMIFS(Lançamentos!$G:$G,Lançamentos!$A:$A,I$19,Lançamentos!$C:$C,"Multas e Juros") -> 0 | ... IL69: =SUMIFS(Lançamentos!$G:$G,Lançamentos!$A:$A,IL$19,Lançamentos!$C:$C,"Multas e Juros") -> 0
A70: Pagamento de Fornecedores | B70: =SUMIFS(Lançamentos!$G:$G,Lançamentos!$A:$A,B$19,Lançamentos!$C:$C,"Pagamento de Fornecedores") -> 0 | C70: =SUMIFS(Lançamentos!$G:$G,Lançamentos!$A:$A,C$19,Lançamentos!$C:$C,"Pagamento de Fornecedores") -> 0 | D70: =SUMIFS(Lançamentos!$G:$G,Lançamentos!$A:$A,D$19,Lançamentos!$C:$C,"Pagamento de Fornecedores") -> 0 | E70: =SUMIFS(Lançamentos!$G:$G,Lançamentos!$A:$A,E$19,Lançamentos!$C:$C,"Pagamento de Fornecedores") -> 0 | F70: =SUMIFS(Lançamentos!$G:$G,Lançamentos!$A:$A,F$19,Lançamentos!$C:$C,"Pagamento de Fornecedores") -> 0 | G70: =SUMIFS(Lançamentos!$G:$G,Lançamentos!$A:$A,G$19,Lançamentos!$C:$C,"Pagamento de Fornecedores") -> 0 | H70: =SUMIFS(Lançamentos!$G:$G,Lançamentos!$A:$A,H$19,Lançamentos!$C:$C,"Pagamento de Fornecedores") -> 0 | I70: =SUMIFS(Lançamentos!$G:$G,Lançamentos!$A:$A,I$19,Lançamentos!$C:$C,"Pagamento de Fornecedores") -> 0 | ... IL70: =SUMIFS(Lançamentos!$G:$G,Lançamentos!$A:$A,IL$19,Lançamentos!$C:$C,"Pagamento de Fornecedores") -> 0
A71: Retirada de Sócios | B71: =SUMIFS(Lançamentos!$G:$G,Lançamentos!$A:$A,B$19,Lançamentos!$C:$C,"Retirada de Sócios") -> 0 | C71: =SUMIFS(Lançamentos!$G:$G,Lançamentos!$A:$A,C$19,Lançamentos!$C:$C,"Retirada de Sócios") -> 0 | D71: =SUMIFS(Lançamentos!$G:$G,Lançamentos!$A:$A,D$19,Lançamentos!$C:$C,"Retirada de Sócios") -> 0 | E71: =SUMIFS(Lançamentos!$G:$G,Lançamentos!$A:$A,E$19,Lançamentos!$C:$C,"Retirada de Sócios") -> 0 | F71: =SUMIFS(Lançamentos!$G:$G,Lançamentos!$A:$A,F$19,Lançamentos!$C:$C,"Retirada de Sócios") -> 0 | G71: =SUMIFS(Lançamentos!$G:$G,Lançamentos!$A:$A,G$19,Lançamentos!$C:$C,"Retirada de Sócios") -> 0 | H71: =SUMIFS(Lançamentos!$G:$G,Lançamentos!$A:$A,H$19,Lançamentos!$C:$C,"Retirada de Sócios") -> 0 | I71: =SUMIFS(Lançamentos!$G:$G,Lançamentos!$A:$A,I$19,Lançamentos!$C:$C,"Retirada de Sócios") -> 0 | ... IL71: =SUMIFS(Lançamentos!$G:$G,Lançamentos!$A:$A,IL$19,Lançamentos!$C:$C,"Retirada de Sócios") -> 0
A72: INSS / FGTS | B72: =SUMIFS(Lançamentos!$G:$G,Lançamentos!$A:$A,B$19,Lançamentos!$C:$C,"INSS / FGTS") -> 0 | C72: =SUMIFS(Lançamentos!$G:$G,Lançamentos!$A:$A,C$19,Lançamentos!$C:$C,"INSS / FGTS") -> 0 | D72: =SUMIFS(Lançamentos!$G:$G,Lançamentos!$A:$A,D$19,Lançamentos!$C:$C,"INSS / FGTS") -> 0 | E72: =SUMIFS(Lançamentos!$G:$G,Lançamentos!$A:$A,E$19,Lançamentos!$C:$C,"INSS / FGTS") -> 0 | F72: =SUMIFS(Lançamentos!$G:$G,Lançamentos!$A:$A,F$19,Lançamentos!$C:$C,"INSS / FGTS") -> 0 | G72: =SUMIFS(Lançamentos!$G:$G,Lançamentos!$A:$A,G$19,Lançamentos!$C:$C,"INSS / FGTS") -> 0 | H72: =SUMIFS(Lançamentos!$G:$G,Lançamentos!$A:$A,H$19,Lançamentos!$C:$C,"INSS / FGTS") -> 0 | I72: =SUMIFS(Lançamentos!$G:$G,Lançamentos!$A:$A,I$19,Lançamentos!$C:$C,"INSS / FGTS") -> 0 | ... IL72: =SUMIFS(Lançamentos!$G:$G,Lançamentos!$A:$A,IL$19,Lançamentos!$C:$C,"INSS / FGTS") -> 0
A73: Simples Nacional / DAS | B73: =SUMIFS(Lançamentos!$G:$G,Lançamentos!$A:$A,B$19,Lançamentos!$C:$C,"Simples Nacional / DAS") -> 0 | C73: =SUMIFS(Lançamentos!$G:$G,Lançamentos!$A:$A,C$19,Lançamentos!$C:$C,"Simples Nacional / DAS") -> 0 | D73: =SUMIFS(Lançamentos!$G:$G,Lançamentos!$A:$A,D$19,Lançamentos!$C:$C,"Simples Nacional / DAS") -> 0 | E73: =SUMIFS(Lançamentos!$G:$G,Lançamentos!$A:$A,E$19,Lançamentos!$C:$C,"Simples Nacional / DAS") -> 0 | F73: =SUMIFS(Lançamentos!$G:$G,Lançamentos!$A:$A,F$19,Lançamentos!$C:$C,"Simples Nacional / DAS") -> 0 | G73: =SUMIFS(Lançamentos!$G:$G,Lançamentos!$A:$A,G$19,Lançamentos!$C:$C,"Simples Nacional / DAS") -> 0 | H73: =SUMIFS(Lançamentos!$G:$G,Lançamentos!$A:$A,H$19,Lançamentos!$C:$C,"Simples Nacional / DAS") -> 0 | I73: =SUMIFS(Lançamentos!$G:$G,Lançamentos!$A:$A,I$19,Lançamentos!$C:$C,"Simples Nacional / DAS") -> 0 | ... IL73: =SUMIFS(Lançamentos!$G:$G,Lançamentos!$A:$A,IL$19,Lançamentos!$C:$C,"Simples Nacional / DAS") -> 0
A74: ISS | B74: =SUMIFS(Lançamentos!$G:$G,Lançamentos!$A:$A,B$19,Lançamentos!$C:$C,"ISS") -> 0 | C74: =SUMIFS(Lançamentos!$G:$G,Lançamentos!$A:$A,C$19,Lançamentos!$C:$C,"ISS") -> 0 | D74: =SUMIFS(Lançamentos!$G:$G,Lançamentos!$A:$A,D$19,Lançamentos!$C:$C,"ISS") -> 0 | E74: =SUMIFS(Lançamentos!$G:$G,Lançamentos!$A:$A,E$19,Lançamentos!$C:$C,"ISS") -> 0 | F74: =SUMIFS(Lançamentos!$G:$G,Lançamentos!$A:$A,F$19,Lançamentos!$C:$C,"ISS") -> 0 | G74: =SUMIFS(Lançamentos!$G:$G,Lançamentos!$A:$A,G$19,Lançamentos!$C:$C,"ISS") -> 0 | H74: =SUMIFS(Lançamentos!$G:$G,Lançamentos!$A:$A,H$19,Lançamentos!$C:$C,"ISS") -> 0 | I74: =SUMIFS(Lançamentos!$G:$G,Lançamentos!$A:$A,I$19,Lançamentos!$C:$C,"ISS") -> 0 | ... IL74: =SUMIFS(Lançamentos!$G:$G,Lançamentos!$A:$A,IL$19,Lançamentos!$C:$C,"ISS") -> 0
A75: ICMS | B75: =SUMIFS(Lançamentos!$G:$G,Lançamentos!$A:$A,B$19,Lançamentos!$C:$C,"ICMS") -> 0 | C75: =SUMIFS(Lançamentos!$G:$G,Lançamentos!$A:$A,C$19,Lançamentos!$C:$C,"ICMS") -> 0 | D75: =SUMIFS(Lançamentos!$G:$G,Lançamentos!$A:$A,D$19,Lançamentos!$C:$C,"ICMS") -> 0 | E75: =SUMIFS(Lançamentos!$G:$G,Lançamentos!$A:$A,E$19,Lançamentos!$C:$C,"ICMS") -> 0 | F75: =SUMIFS(Lançamentos!$G:$G,Lançamentos!$A:$A,F$19,Lançamentos!$C:$C,"ICMS") -> 0 | G75: =SUMIFS(Lançamentos!$G:$G,Lançamentos!$A:$A,G$19,Lançamentos!$C:$C,"ICMS") -> 0 | H75: =SUMIFS(Lançamentos!$G:$G,Lançamentos!$A:$A,H$19,Lançamentos!$C:$C,"ICMS") -> 0 | I75: =SUMIFS(Lançamentos!$G:$G,Lançamentos!$A:$A,I$19,Lançamentos!$C:$C,"ICMS") -> 0 | ... IL75: =SUMIFS(Lançamentos!$G:$G,Lançamentos!$A:$A,IL$19,Lançamentos!$C:$C,"ICMS") -> 0
A76: PIS/COFINS | B76: =SUMIFS(Lançamentos!$G:$G,Lançamentos!$A:$A,B$19,Lançamentos!$C:$C,"PIS/COFINS") -> 0 | C76: =SUMIFS(Lançamentos!$G:$G,Lançamentos!$A:$A,C$19,Lançamentos!$C:$C,"PIS/COFINS") -> 0 | D76: =SUMIFS(Lançamentos!$G:$G,Lançamentos!$A:$A,D$19,Lançamentos!$C:$C,"PIS/COFINS") -> 0 | E76: =SUMIFS(Lançamentos!$G:$G,Lançamentos!$A:$A,E$19,Lançamentos!$C:$C,"PIS/COFINS") -> 0 | F76: =SUMIFS(Lançamentos!$G:$G,Lançamentos!$A:$A,F$19,Lançamentos!$C:$C,"PIS/COFINS") -> 0 | G76: =SUMIFS(Lançamentos!$G:$G,Lançamentos!$A:$A,G$19,Lançamentos!$C:$C,"PIS/COFINS") -> 0 | H76: =SUMIFS(Lançamentos!$G:$G,Lançamentos!$A:$A,H$19,Lançamentos!$C:$C,"PIS/COFINS") -> 0 | I76: =SUMIFS(Lançamentos!$G:$G,Lançamentos!$A:$A,I$19,Lançamentos!$C:$C,"PIS/COFINS") -> 0 | ... IL76: =SUMIFS(Lançamentos!$G:$G,Lançamentos!$A:$A,IL$19,Lançamentos!$C:$C,"PIS/COFINS") -> 0
A77: TOTAL SAÍDAS | B77: =SUM(B35:B76) -> 0 | C77: =SUM(C35:C76) -> 0 | D77: =SUM(D35:D76) -> 0 | E77: =SUM(E35:E76) -> 0 | F77: =SUM(F35:F76) -> 0 | G77: =SUM(G35:G76) -> 0 | H77: =SUM(H35:H76) -> 0 | I77: =SUM(I35:I76) -> 0 | ... IL77: =SUM(IL35:IL76) -> 0
A78: FLUXO DO DIA | B78: =B33-B77 -> 0 | C78: =C33-C77 -> 0 | D78: =D33-D77 -> 0 | E78: =E33-E77 -> 0 | F78: =F33-F77 -> 0 | G78: =G33-G77 -> 0 | H78: =H33-H77 -> 0 | I78: =I33-I77 -> 0 | ... IL78: =IL33-IL77 -> 0
A79: SALDO FINAL DO DIA | B79: =B20+B78 -> 7500 | C79: =C20+C78 -> 7500 | D79: =D20+D78 -> 7500 | E79: =E20+E78 -> 7500 | F79: =F20+F78 -> 7500 | G79: =G20+G78 -> 7500 | H79: =H20+H78 -> 7500 | I79: =I20+I78 -> 7500 | ... IL79: =IL20+IL78 -> 32500
A81: FORECAST DIÁRIO (Mai-Dez)
A82: Data → | B82: =B19 -> 46143 | C82: =C19 -> 46144 | D82: =D19 -> 46145 | E82: =E19 -> 46146 | F82: =F19 -> 46147 | G82: =G19 -> 46148 | H82: =H19 -> 46149 | I82: =I19 -> 46150 | ... IL82: =IL19 -> 46387
A83: SALDO INICIAL DO DIA (Forecast) | B83: =SUM(Categorias!$F$2:$F$4) -> 0 | C83: =B142 -> 9416.23 | D83: =C142 -> 9416.23 | E83: =D142 -> 9416.23 | F83: =E142 -> 18824.82 | G83: =F142 -> 27634.34 | H83: =G142 -> 37202.84 | I83: =H142 -> 46329.45 | J83: =I142 -> 56035.15 | ... IL83: =IK142 -> 1622793.8
A84: 💰 RECEITAS PREVISTAS
A85: Vendas de Produtos | B85: =IF(WEEKDAY(B$82,2)>5,0,1584.93) -> 1584.93 | C85: =IF(WEEKDAY(C$82,2)>5,0,1369.05) -> 0 | D85: =IF(WEEKDAY(D$82,2)>5,0,1632.77) -> 0 | E85: =IF(WEEKDAY(E$82,2)>5,0,1690.81) -> 1690.81 | F85: =IF(WEEKDAY(F$82,2)>5,0,1386.73) -> 1386.73 | G85: =IF(WEEKDAY(G$82,2)>5,0,1513.7) -> 1513.7 | H85: =IF(WEEKDAY(H$82,2)>5,0,1604.25) -> 1604.25 | I85: =IF(WEEKDAY(I$82,2)>5,0,1664.58) -> 1664.58 | J85: =IF(WEEKDAY(J$82,2)>5,0,1467.26) -> 0 | K85: =IF(WEEKDAY(K$82,2)>5,0,1514.78) -> 0 | L85: =IF(WEEKDAY(L$82,2)>5,0,1433.47) -> 1433.47 | M85: =IF(WEEKDAY(M$82,2)>5,0,1666.25) -> 1666.25 | N85: =IF(WEEKDAY(N$82,2)>5,0,1350.33) -> 1350.33 | O85: =IF(WEEKDAY(O$82,2)>5,0,1413.89) -> 1413.89 | P85: =IF(WEEKDAY(P$82,2)>5,0,1528.32) -> 1528.32 | Q85: =IF(WEEKDAY(Q$82,2)>5,0,1573.35) -> 0 | R85: =IF(WEEKDAY(R$82,2)>5,0,1579.46) -> 0 | S85: =IF(WEEKDAY(S$82,2)>5,0,1481.71) -> 1481.71 | T85: =IF(WEEKDAY(T$82,2)>5,0,1694.24) -> 1694.24 | U85: =IF(WEEKDAY(U$82,2)>5,0,1372.19) -> 1372.19 | V85: =IF(WEEKDAY(V$82,2)>5,0,1625.55) -> 1625.55 | W85: =IF(WEEKDAY(W$82,2)>5,0,1599.95) -> 1599.95 | X85: =IF(WEEKDAY(X$82,2)>5,0,1499.52) -> 0 | Y85: =IF(WEEKDAY(Y$82,2)>5,0,1658.97) -> 0 | Z85: =IF(WEEKDAY(Z$82,2)>5,0,1677.1) -> 1677.1 | AA85: =IF(WEEKDAY(AA$82,2)>5,0,1682.39) -> 1682.39 | AB85: =IF(WEEKDAY(AB$82,2)>5,0,1675.17) -> 1675.17 | AC85: =IF(WEEKDAY(AC$82,2)>5,0,1444.51) -> 1444.51 | AD85: =IF(WEEKDAY(AD$82,2)>5,0,1277.2) -> 1277.2 | AE85: =IF(WEEKDAY(AE$82,2)>5,0,1519.18) -> 0 | AF85: =IF(WEEKDAY(AF$82,2)>5,0,1587.97) -> 0 | AG85: =IF(WEEKDAY(AG$82,2)>5,0,1470.53) -> 1470.53 | AH85: =IF(WEEKDAY(AH$82,2)>5,0,1645.32) -> 1645.32 | AI85: =IF(WEEKDAY(AI$82,2)>5,0,1378.3) -> 1378.3 | AJ85: =IF(WEEKDAY(AJ$82,2)>5,0,1648.66) -> 1648.66 | AK85: =IF(WEEKDAY(AK$82,2)>5,0,1723.58) -> 1723.58 | AL85: =IF(WEEKDAY(AL$82,2)>5,0,1318.98) -> 0 | AM85: =IF(WEEKDAY(AM$82,2)>5,0,1536.97) -> 0 | AN85: =IF(WEEKDAY(AN$82,2)>5,0,1366.22) -> 1366.22 | AO85: =IF(WEEKDAY(AO$82,2)>5,0,1473.33) -> 1473.33 | AP85: =IF(WEEKDAY(AP$82,2)>5,0,1671.58) -> 1671.58 | AQ85: =IF(WEEKDAY(AQ$82,2)>5,0,1469.33) -> 1469.33 | AR85: =IF(WEEKDAY(AR$82,2)>5,0,1681.94) -> 1681.94 | AS85: =IF(WEEKDAY(AS$82,2)>5,0,1689.94) -> 0 | AT85: =IF(WEEKDAY(AT$82,2)>5,0,1537.34) -> 0 | AU85: =IF(WEEKDAY(AU$82,2)>5,0,1541.55) -> 1541.55 | AV85: =IF(WEEKDAY(AV$82,2)>5,0,1521.04) -> 1521.04 | AW85: =IF(WEEKDAY(AW$82,2)>5,0,1521.92) -> 1521.92 | AX85: =IF(WEEKDAY(AX$82,2)>5,0,1508.25) -> 1508.25 | AY85: =IF(WEEKDAY(AY$82,2)>5,0,1567.09) -> 1567.09 | AZ85: =IF(WEEKDAY(AZ$82,2)>5,0,1699.55) -> 0 | BA85: =IF(WEEKDAY(BA$82,2)>5,0,1667.75) -> 0 | BB85: =IF(WEEKDAY(BB$82,2)>5,0,1449.25) -> 1449.25 | BC85: =IF(WEEKDAY(BC$82,2)>5,0,1531.81) -> 1531.81 | BD85: =IF(WEEKDAY(BD$82,2)>5,0,1522.93) -> 1522.93 | BE85: =IF(WEEKDAY(BE$82,2)>5,0,1295.28) -> 1295.28 | BF85: =IF(WEEKDAY(BF$82,2)>5,0,1460.11) -> 1460.11 | BG85: =IF(WEEKDAY(BG$82,2)>5,0,1572.98) -> 0 | BH85: =IF(WEEKDAY(BH$82,2)>5,0,1562.48) -> 0 | BI85: =IF(WEEKDAY(BI$82,2)>5,0,1602.92) -> 1602.92 | BJ85: =IF(WEEKDAY(BJ$82,2)>5,0,1298.76) -> 1298.76 | BK85: =IF(WEEKDAY(BK$82,2)>5,0,1595.31) -> 1595.31 | BL85: =IF(WEEKDAY(BL$82,2)>5,0,1559.13) -> 1559.13 | BM85: =IF(WEEKDAY(BM$82,2)>5,0,1384.88) -> 1384.88 | BN85: =IF(WEEKDAY(BN$82,2)>5,0,1455.53) -> 0 | BO85: =IF(WEEKDAY(BO$82,2)>5,0,1385.17) -> 0 | BP85: =IF(WEEKDAY(BP$82,2)>5,0,1415.15) -> 1415.15 | BQ85: =IF(WEEKDAY(BQ$82,2)>5,0,1431.67) -> 1431.67 | BR85: =IF(WEEKDAY(BR$82,2)>5,0,1522.53) -> 1522.53 | BS85: =IF(WEEKDAY(BS$82,2)>5,0,1307.48) -> 1307.48 | BT85: =IF(WEEKDAY(BT$82,2)>5,0,1484.77) -> 1484.77 | BU85: =IF(WEEKDAY(BU$82,2)>5,0,1447.52) -> 0 | BV85: =IF(WEEKDAY(BV$82,2)>5,0,1603.84) -> 0 | BW85: =IF(WEEKDAY(BW$82,2)>5,0,1366.52) -> 1366.52 | BX85: =IF(WEEKDAY(BX$82,2)>5,0,1485.04) -> 1485.04 | BY85: =IF(WEEKDAY(BY$82,2)>5,0,1474.79) -> 1474.79 | BZ85: =IF(WEEKDAY(BZ$82,2)>5,0,1569.51) -> 1569.51 | CA85: =IF(WEEKDAY(CA$82,2)>5,0,1606.92) -> 1606.92 | CB85: =IF(WEEKDAY(CB$82,2)>5,0,1356.23) -> 0 | CC85: =IF(WEEKDAY(CC$82,2)>5,0,1467.84) -> 0 | CD85: =IF(WEEKDAY(CD$82,2)>5,0,1692.33) -> 1692.33 | CE85: =IF(WEEKDAY(CE$82,2)>5,0,1313.02) -> 1313.02 | CF85: =IF(WEEKDAY(CF$82,2)>5,0,1384.95) -> 1384.95 | CG85: =IF(WEEKDAY(CG$82,2)>5,0,1537.76) -> 1537.76 | CH85: =IF(WEEKDAY(CH$82,2)>5,0,1540.12) -> 1540.12 | CI85: =IF(WEEKDAY(CI$82,2)>5,0,1621.79) -> 0 | CJ85: =IF(WEEKDAY(CJ$82,2)>5,0,1685.13) -> 0 | CK85: =IF(WEEKDAY(CK$82,2)>5,0,1406.92) -> 1406.92 | CL85: =IF(WEEKDAY(CL$82,2)>5,0,1676.31) -> 1676.31 | CM85: =IF(WEEKDAY(CM$82,2)>5,0,1432.75) -> 1432.75 | CN85: =IF(WEEKDAY(CN$82,2)>5,0,1585.31) -> 1585.31 | CO85: =IF(WEEKDAY(CO$82,2)>5,0,1712.47) -> 1712.47 | CP85: =IF(WEEKDAY(CP$82,2)>5,0,1314.62) -> 0 | CQ85: =IF(WEEKDAY(CQ$82,2)>5,0,1412.61) -> 0 | CR85: =IF(WEEKDAY(CR$82,2)>5,0,1591.54) -> 1591.54 | CS85: =IF(WEEKDAY(CS$82,2)>5,0,1398.73) -> 1398.73 | CT85: =IF(WEEKDAY(CT$82,2)>5,0,1421.58) -> 1421.58 | CU85: =IF(WEEKDAY(CU$82,2)>5,0,1438.14) -> 1438.14 | CV85: =IF(WEEKDAY(CV$82,2)>5,0,1538.92) -> 1538.92 | CW85: =IF(WEEKDAY(CW$82,2)>5,0,1623.55) -> 0 | CX85: =IF(WEEKDAY(CX$82,2)>5,0,1700.98) -> 0 | CY85: =IF(WEEKDAY(CY$82,2)>5,0,1467.54) -> 1467.54 | CZ85: =IF(WEEKDAY(CZ$82,2)>5,0,1329.3) -> 1329.3 | DA85: =IF(WEEKDAY(DA$82,2)>5,0,1340.82) -> 1340.82 | DB85: =IF(WEEKDAY(DB$82,2)>5,0,1575.27) -> 1575.27 | DC85: =IF(WEEKDAY(DC$82,2)>5,0,1596.05) -> 1596.05 | DD85: =IF(WEEKDAY(DD$82,2)>5,0,1413.35) -> 0 | DE85: =IF(WEEKDAY(DE$82,2)>5,0,1663.6) -> 0 | DF85: =IF(WEEKDAY(DF$82,2)>5,0,1692.6) -> 1692.6 | DG85: =IF(WEEKDAY(DG$82,2)>5,0,1448.29) -> 1448.29 | DH85: =IF(WEEKDAY(DH$82,2)>5,0,1297.17) -> 1297.17 | DI85: =IF(WEEKDAY(DI$82,2)>5,0,1533.34) -> 1533.34 | DJ85: =IF(WEEKDAY(DJ$82,2)>5,0,1393.57) -> 1393.57 | DK85: =IF(WEEKDAY(DK$82,2)>5,0,1481.14) -> 0 | DL85: =IF(WEEKDAY(DL$82,2)>5,0,1594.5) -> 0 | DM85: =IF(WEEKDAY(DM$82,2)>5,0,1679.24) -> 1679.24 | DN85: =IF(WEEKDAY(DN$82,2)>5,0,1672.84) -> 1672.84 | DO85: =IF(WEEKDAY(DO$82,2)>5,0,1362.59) -> 1362.59 | DP85: =IF(WEEKDAY(DP$82,2)>5,0,1306.87) -> 1306.87 | DQ85: =IF(WEEKDAY(DQ$82,2)>5,0,1576.86) -> 1576.86 | DR85: =IF(WEEKDAY(DR$82,2)>5,0,1450.87) -> 0 | DS85: =IF(WEEKDAY(DS$82,2)>5,0,1594.43) -> 0 | DT85: =IF(WEEKDAY(DT$82,2)>5,0,1418.32) -> 1418.32 | DU85: =IF(WEEKDAY(DU$82,2)>5,0,1600.36) -> 1600.36 | DV85: =IF(WEEKDAY(DV$82,2)>5,0,1614.24) -> 1614.24 | DW85: =IF(WEEKDAY(DW$82,2)>5,0,1673.47) -> 1673.47 | DX85: =IF(WEEKDAY(DX$82,2)>5,0,1512.93) -> 1512.93 | DY85: =IF(WEEKDAY(DY$82,2)>5,0,1535.13) -> 0 | DZ85: =IF(WEEKDAY(DZ$82,2)>5,0,1631.7) -> 0 | EA85: =IF(WEEKDAY(EA$82,2)>5,0,1662.86) -> 1662.86 | EB85: =IF(WEEKDAY(EB$82,2)>5,0,1381.42) -> 1381.42 | EC85: =IF(WEEKDAY(EC$82,2)>5,0,1619.35) -> 1619.35 | ED85: =IF(WEEKDAY(ED$82,2)>5,0,1549.46) -> 1549.46 | EE85: =IF(WEEKDAY(EE$82,2)>5,0,1557.18) -> 1557.18 | EF85: =IF(WEEKDAY(EF$82,2)>5,0,1639.14) -> 0 | EG85: =IF(WEEKDAY(EG$82,2)>5,0,1674.75) -> 0 | EH85: =IF(WEEKDAY(EH$82,2)>5,0,1646.58) -> 1646.58 | EI85: =IF(WEEKDAY(EI$82,2)>5,0,1559.68) -> 1559.68 | EJ85: =IF(WEEKDAY(EJ$82,2)>5,0,1301.58) -> 1301.58 | EK85: =IF(WEEKDAY(EK$82,2)>5,0,1447.78) -> 1447.78 | EL85: =IF(WEEKDAY(EL$82,2)>5,0,1445.4) -> 1445.4 | EM85: =IF(WEEKDAY(EM$82,2)>5,0,1506.08) -> 0 | EN85: =IF(WEEKDAY(EN$82,2)>5,0,1711.57) -> 0 | EO85: =IF(WEEKDAY(EO$82,2)>5,0,1530.02) -> 1530.02 | EP85: =IF(WEEKDAY(EP$82,2)>5,0,1422.9) -> 1422.9 | EQ85: =IF(WEEKDAY(EQ$82,2)>5,0,1681.89) -> 1681.89 | ER85: =IF(WEEKDAY(ER$82,2)>5,0,1461.08) -> 1461.08 | ES85: =IF(WEEKDAY(ES$82,2)>5,0,1497.55) -> 1497.55 | ET85: =IF(WEEKDAY(ET$82,2)>5,0,1700.28) -> 0 | EU85: =IF(WEEKDAY(EU$82,2)>5,0,1483.18) -> 0 | EV85: =IF(WEEKDAY(EV$82,2)>5,0,1373.22) -> 1373.22 | EW85: =IF(WEEKDAY(EW$82,2)>5,0,1290.1) -> 1290.1 | EX85: =IF(WEEKDAY(EX$82,2)>5,0,1690.52) -> 1690.52 | EY85: =IF(WEEKDAY(EY$82,2)>5,0,1356.63) -> 1356.63 | EZ85: =IF(WEEKDAY(EZ$82,2)>5,0,1589.55) -> 1589.55 | FA85: =IF(WEEKDAY(FA$82,2)>5,0,1586.02) -> 0 | FB85: =IF(WEEKDAY(FB$82,2)>5,0,1722.73) -> 0 | FC85: =IF(WEEKDAY(FC$82,2)>5,0,1551.66) -> 1551.66 | FD85: =IF(WEEKDAY(FD$82,2)>5,0,1506) -> 1506 | FE85: =IF(WEEKDAY(FE$82,2)>5,0,1576.09) -> 1576.09 | FF85: =IF(WEEKDAY(FF$82,2)>5,0,1716.6) -> 1716.6 | FG85: =IF(WEEKDAY(FG$82,2)>5,0,1371.87) -> 1371.87 | FH85: =IF(WEEKDAY(FH$82,2)>5,0,1539.49) -> 0 | FI85: =IF(WEEKDAY(FI$82,2)>5,0,1425.46) -> 0 | FJ85: =IF(WEEKDAY(FJ$82,2)>5,0,1289) -> 1289 | FK85: =IF(WEEKDAY(FK$82,2)>5,0,1696.04) -> 1696.04 | FL85: =IF(WEEKDAY(FL$82,2)>5,0,1447.36) -> 1447.36 | FM85: =IF(WEEKDAY(FM$82,2)>5,0,1279.17) -> 1279.17 | FN85: =IF(WEEKDAY(FN$82,2)>5,0,1337.5) -> 1337.5 | FO85: =IF(WEEKDAY(FO$82,2)>5,0,1611.08) -> 0 | FP85: =IF(WEEKDAY(FP$82,2)>5,0,1612.97) -> 0 | FQ85: =IF(WEEKDAY(FQ$82,2)>5,0,1638.45) -> 1638.45 | FR85: =IF(WEEKDAY(FR$82,2)>5,0,1349.04) -> 1349.04 | FS85: =IF(WEEKDAY(FS$82,2)>5,0,1388.75) -> 1388.75 | FT85: =IF(WEEKDAY(FT$82,2)>5,0,1453.89) -> 1453.89 | FU85: =IF(WEEKDAY(FU$82,2)>5,0,1418.74) -> 1418.74 | FV85: =IF(WEEKDAY(FV$82,2)>5,0,1448.44) -> 0 | FW85: =IF(WEEKDAY(FW$82,2)>5,0,1623.38) -> 0 | FX85: =IF(WEEKDAY(FX$82,2)>5,0,1457.56) -> 1457.56 | FY85: =IF(WEEKDAY(FY$82,2)>5,0,1299.98) -> 1299.98 | FZ85: =IF(WEEKDAY(FZ$82,2)>5,0,1308.48) -> 1308.48 | GA85: =IF(WEEKDAY(GA$82,2)>5,0,1632.68) -> 1632.68 | GB85: =IF(WEEKDAY(GB$82,2)>5,0,1365.8) -> 1365.8 | GC85: =IF(WEEKDAY(GC$82,2)>5,0,1561.6) -> 0 | GD85: =IF(WEEKDAY(GD$82,2)>5,0,1723.13) -> 0 | GE85: =IF(WEEKDAY(GE$82,2)>5,0,1687.31) -> 1687.31 | GF85: =IF(WEEKDAY(GF$82,2)>5,0,1464.93) -> 1464.93 | GG85: =IF(WEEKDAY(GG$82,2)>5,0,1534.18) -> 1534.18 | GH85: =IF(WEEKDAY(GH$82,2)>5,0,1481.86) -> 1481.86 | GI85: =IF(WEEKDAY(GI$82,2)>5,0,1404.3) -> 1404.3 | GJ85: =IF(WEEKDAY(GJ$82,2)>5,0,1301.66) -> 0 | GK85: =IF(WEEKDAY(GK$82,2)>5,0,1472.1) -> 0 | GL85: =IF(WEEKDAY(GL$82,2)>5,0,1354.64) -> 1354.64 | GM85: =IF(WEEKDAY(GM$82,2)>5,0,1715.15) -> 1715.15 | GN85: =IF(WEEKDAY(GN$82,2)>5,0,1661.11) -> 1661.11 | GO85: =IF(WEEKDAY(GO$82,2)>5,0,1524.72) -> 1524.72 | GP85: =IF(WEEKDAY(GP$82,2)>5,0,1484) -> 1484 | GQ85: =IF(WEEKDAY(GQ$82,2)>5,0,1652.98) -> 0 | GR85: =IF(WEEKDAY(GR$82,2)>5,0,1318.84) -> 0 | GS85: =IF(WEEKDAY(GS$82,2)>5,0,1435.54) -> 1435.54 | GT85: =IF(WEEKDAY(GT$82,2)>5,0,1307.97) -> 1307.97 | GU85: =IF(WEEKDAY(GU$82,2)>5,0,1487.53) -> 1487.53 | GV85: =IF(WEEKDAY(GV$82,2)>5,0,1603.18) -> 1603.18 | GW85: =IF(WEEKDAY(GW$82,2)>5,0,1436.98) -> 1436.98 | GX85: =IF(WEEKDAY(GX$82,2)>5,0,1487.96) -> 0 | GY85: =IF(WEEKDAY(GY$82,2)>5,0,1287.66) -> 0 | GZ85: =IF(WEEKDAY(GZ$82,2)>5,0,1555.08) -> 1555.08 | HA85: =IF(WEEKDAY(HA$82,2)>5,0,1295.3) -> 1295.3 | HB85: =IF(WEEKDAY(HB$82,2)>5,0,1663.22) -> 1663.22 | HC85: =IF(WEEKDAY(HC$82,2)>5,0,1328.29) -> 1328.29 | HD85: =IF(WEEKDAY(HD$82,2)>5,0,1716.25) -> 1716.25 | HE85: =IF(WEEKDAY(HE$82,2)>5,0,1549.68) -> 0 | HF85: =IF(WEEKDAY(HF$82,2)>5,0,1394.75) -> 0 | HG85: =IF(WEEKDAY(HG$82,2)>5,0,1606.39) -> 1606.39 | HH85: =IF(WEEKDAY(HH$82,2)>5,0,1298.63) -> 1298.63 | HI85: =IF(WEEKDAY(HI$82,2)>5,0,1280.88) -> 1280.88 | HJ85: =IF(WEEKDAY(HJ$82,2)>5,0,1367.52) -> 1367.52 | HK85: =IF(WEEKDAY(HK$82,2)>5,0,1379.5) -> 1379.5 | HL85: =IF(WEEKDAY(HL$82,2)>5,0,1410.71) -> 0 | HM85: =IF(WEEKDAY(HM$82,2)>5,0,1468.95) -> 0 | HN85: =IF(WEEKDAY(HN$82,2)>5,0,1442.67) -> 1442.67 | HO85: =IF(WEEKDAY(HO$82,2)>5,0,1718.79) -> 1718.79 | HP85: =IF(WEEKDAY(HP$82,2)>5,0,1651.99) -> 1651.99 | HQ85: =IF(WEEKDAY(HQ$82,2)>5,0,1657.96) -> 1657.96 | HR85: =IF(WEEKDAY(HR$82,2)>5,0,1495.59) -> 1495.59 | HS85: =IF(WEEKDAY(HS$82,2)>5,0,1514.66) -> 0 | HT85: =IF(WEEKDAY(HT$82,2)>5,0,1383.09) -> 0 | HU85: =IF(WEEKDAY(HU$82,2)>5,0,1663.66) -> 1663.66 | HV85: =IF(WEEKDAY(HV$82,2)>5,0,1484.89) -> 1484.89 | HW85: =IF(WEEKDAY(HW$82,2)>5,0,1350.71) -> 1350.71 | HX85: =IF(WEEKDAY(HX$82,2)>5,0,1475) -> 1475 | HY85: =IF(WEEKDAY(HY$82,2)>5,0,1664.79) -> 1664.79 | HZ85: =IF(WEEKDAY(HZ$82,2)>5,0,1551.58) -> 0 | IA85: =IF(WEEKDAY(IA$82,2)>5,0,1332.88) -> 0 | IB85: =IF(WEEKDAY(IB$82,2)>5,0,1605.8) -> 1605.8 | IC85: =IF(WEEKDAY(IC$82,2)>5,0,1488.78) -> 1488.78 | ID85: =IF(WEEKDAY(ID$82,2)>5,0,1287.86) -> 1287.86 | IE85: =IF(WEEKDAY(IE$82,2)>5,0,1560.3) -> 1560.3 | IF85: =IF(WEEKDAY(IF$82,2)>5,0,1331.88) -> 1331.88 | IG85: =IF(WEEKDAY(IG$82,2)>5,0,1418.76) -> 0 | IH85: =IF(WEEKDAY(IH$82,2)>5,0,1453) -> 0 | II85: =IF(WEEKDAY(II$82,2)>5,0,1432.94) -> 1432.94 | IJ85: =IF(WEEKDAY(IJ$82,2)>5,0,1438.06) -> 1438.06 | IK85: =IF(WEEKDAY(IK$82,2)>5,0,1719.61) -> 1719.61 | IL85: =IF(WEEKDAY(IL$82,2)>5,0,1282.16) -> 1282.16
A86: Vendas de Serviços | B86: =IF(WEEKDAY(B$82,2)>5,0,841.7) -> 841.7 | C86: =IF(WEEKDAY(C$82,2)>5,0,887.11) -> 0 | D86: =IF(WEEKDAY(D$82,2)>5,0,865.84) -> 0 | E86: =IF(WEEKDAY(E$82,2)>5,0,840.02) -> 840.02 | F86: =IF(WEEKDAY(F$82,2)>5,0,738.66) -> 738.66 | G86: =IF(WEEKDAY(G$82,2)>5,0,855.87) -> 855.87 | H86: =IF(WEEKDAY(H$82,2)>5,0,698.04) -> 698.04 | I86: =IF(WEEKDAY(I$82,2)>5,0,845.1) -> 845.1 | J86: =IF(WEEKDAY(J$82,2)>5,0,703.35) -> 0 | K86: =IF(WEEKDAY(K$82,2)>5,0,856.53) -> 0 | L86: =IF(WEEKDAY(L$82,2)>5,0,909.66) -> 909.66 | M86: =IF(WEEKDAY(M$82,2)>5,0,846.08) -> 846.08 | N86: =IF(WEEKDAY(N$82,2)>5,0,688.69) -> 688.69 | O86: =IF(WEEKDAY(O$82,2)>5,0,772.06) -> 772.06 | P86: =IF(WEEKDAY(P$82,2)>5,0,889.96) -> 889.96 | Q86: =IF(WEEKDAY(Q$82,2)>5,0,766.2) -> 0 | R86: =IF(WEEKDAY(R$82,2)>5,0,706.64) -> 0 | S86: =IF(WEEKDAY(S$82,2)>5,0,840.55) -> 840.55 | T86: =IF(WEEKDAY(T$82,2)>5,0,827.77) -> 827.77 | U86: =IF(WEEKDAY(U$82,2)>5,0,812.34) -> 812.34 | V86: =IF(WEEKDAY(V$82,2)>5,0,892.46) -> 892.46 | W86: =IF(WEEKDAY(W$82,2)>5,0,746.21) -> 746.21 | X86: =IF(WEEKDAY(X$82,2)>5,0,849.7) -> 0 | Y86: =IF(WEEKDAY(Y$82,2)>5,0,747.35) -> 0 | Z86: =IF(WEEKDAY(Z$82,2)>5,0,789.97) -> 789.97 | AA86: =IF(WEEKDAY(AA$82,2)>5,0,780.98) -> 780.98 | AB86: =IF(WEEKDAY(AB$82,2)>5,0,875.92) -> 875.92 | AC86: =IF(WEEKDAY(AC$82,2)>5,0,914.88) -> 914.88 | AD86: =IF(WEEKDAY(AD$82,2)>5,0,709.09) -> 709.09 | AE86: =IF(WEEKDAY(AE$82,2)>5,0,821.32) -> 0 | AF86: =IF(WEEKDAY(AF$82,2)>5,0,778.29) -> 0 | AG86: =IF(WEEKDAY(AG$82,2)>5,0,767.31) -> 767.31 | AH86: =IF(WEEKDAY(AH$82,2)>5,0,905.85) -> 905.85 | AI86: =IF(WEEKDAY(AI$82,2)>5,0,825.79) -> 825.79 | AJ86: =IF(WEEKDAY(AJ$82,2)>5,0,892.13) -> 892.13 | AK86: =IF(WEEKDAY(AK$82,2)>5,0,793.36) -> 793.36 | AL86: =IF(WEEKDAY(AL$82,2)>5,0,754.13) -> 0 | AM86: =IF(WEEKDAY(AM$82,2)>5,0,854.4) -> 0 | AN86: =IF(WEEKDAY(AN$82,2)>5,0,883.7) -> 883.7 | AO86: =IF(WEEKDAY(AO$82,2)>5,0,873.38) -> 873.38 | AP86: =IF(WEEKDAY(AP$82,2)>5,0,866.81) -> 866.81 | AQ86: =IF(WEEKDAY(AQ$82,2)>5,0,821.58) -> 821.58 | AR86: =IF(WEEKDAY(AR$82,2)>5,0,700.02) -> 700.02 | AS86: =IF(WEEKDAY(AS$82,2)>5,0,843.67) -> 0 | AT86: =IF(WEEKDAY(AT$82,2)>5,0,817.25) -> 0 | AU86: =IF(WEEKDAY(AU$82,2)>5,0,842.59) -> 842.59 | AV86: =IF(WEEKDAY(AV$82,2)>5,0,872.34) -> 872.34 | AW86: =IF(WEEKDAY(AW$82,2)>5,0,784.96) -> 784.96 | AX86: =IF(WEEKDAY(AX$82,2)>5,0,789.24) -> 789.24 | AY86: =IF(WEEKDAY(AY$82,2)>5,0,733.24) -> 733.24 | AZ86: =IF(WEEKDAY(AZ$82,2)>5,0,757.97) -> 0 | BA86: =IF(WEEKDAY(BA$82,2)>5,0,813.1) -> 0 | BB86: =IF(WEEKDAY(BB$82,2)>5,0,806.53) -> 806.53 | BC86: =IF(WEEKDAY(BC$82,2)>5,0,833.81) -> 833.81 | BD86: =IF(WEEKDAY(BD$82,2)>5,0,712.85) -> 712.85 | BE86: =IF(WEEKDAY(BE$82,2)>5,0,838.42) -> 838.42 | BF86: =IF(WEEKDAY(BF$82,2)>5,0,838.2) -> 838.2 | BG86: =IF(WEEKDAY(BG$82,2)>5,0,913.15) -> 0 | BH86: =IF(WEEKDAY(BH$82,2)>5,0,906.15) -> 0 | BI86: =IF(WEEKDAY(BI$82,2)>5,0,724.59) -> 724.59 | BJ86: =IF(WEEKDAY(BJ$82,2)>5,0,751.23) -> 751.23 | BK86: =IF(WEEKDAY(BK$82,2)>5,0,910.3) -> 910.3 | BL86: =IF(WEEKDAY(BL$82,2)>5,0,862.24) -> 862.24 | BM86: =IF(WEEKDAY(BM$82,2)>5,0,892.3) -> 892.3 | BN86: =IF(WEEKDAY(BN$82,2)>5,0,752.48) -> 0 | BO86: =IF(WEEKDAY(BO$82,2)>5,0,771.56) -> 0 | BP86: =IF(WEEKDAY(BP$82,2)>5,0,884.38) -> 884.38 | BQ86: =IF(WEEKDAY(BQ$82,2)>5,0,829.91) -> 829.91 | BR86: =IF(WEEKDAY(BR$82,2)>5,0,687.68) -> 687.68 | BS86: =IF(WEEKDAY(BS$82,2)>5,0,724.1) -> 724.1 | BT86: =IF(WEEKDAY(BT$82,2)>5,0,742.64) -> 742.64 | BU86: =IF(WEEKDAY(BU$82,2)>5,0,691.2) -> 0 | BV86: =IF(WEEKDAY(BV$82,2)>5,0,753.4) -> 0 | BW86: =IF(WEEKDAY(BW$82,2)>5,0,867.25) -> 867.25 | BX86: =IF(WEEKDAY(BX$82,2)>5,0,874.71) -> 874.71 | BY86: =IF(WEEKDAY(BY$82,2)>5,0,723.29) -> 723.29 | BZ86: =IF(WEEKDAY(BZ$82,2)>5,0,782.92) -> 782.92 | CA86: =IF(WEEKDAY(CA$82,2)>5,0,827.08) -> 827.08 | CB86: =IF(WEEKDAY(CB$82,2)>5,0,852.66) -> 0 | CC86: =IF(WEEKDAY(CC$82,2)>5,0,865.92) -> 0 | CD86: =IF(WEEKDAY(CD$82,2)>5,0,748.29) -> 748.29 | CE86: =IF(WEEKDAY(CE$82,2)>5,0,842.79) -> 842.79 | CF86: =IF(WEEKDAY(CF$82,2)>5,0,888.8) -> 888.8 | CG86: =IF(WEEKDAY(CG$82,2)>5,0,891.67) -> 891.67 | CH86: =IF(WEEKDAY(CH$82,2)>5,0,890.77) -> 890.77 | CI86: =IF(WEEKDAY(CI$82,2)>5,0,842.82) -> 0 | CJ86: =IF(WEEKDAY(CJ$82,2)>5,0,723.66) -> 0 | CK86: =IF(WEEKDAY(CK$82,2)>5,0,849.41) -> 849.41 | CL86: =IF(WEEKDAY(CL$82,2)>5,0,866.16) -> 866.16 | CM86: =IF(WEEKDAY(CM$82,2)>5,0,902.46) -> 902.46 | CN86: =IF(WEEKDAY(CN$82,2)>5,0,728.31) -> 728.31 | CO86: =IF(WEEKDAY(CO$82,2)>5,0,882.81) -> 882.81 | CP86: =IF(WEEKDAY(CP$82,2)>5,0,781.27) -> 0 | CQ86: =IF(WEEKDAY(CQ$82,2)>5,0,681.18) -> 0 | CR86: =IF(WEEKDAY(CR$82,2)>5,0,813.95) -> 813.95 | CS86: =IF(WEEKDAY(CS$82,2)>5,0,899.96) -> 899.96 | CT86: =IF(WEEKDAY(CT$82,2)>5,0,732.24) -> 732.24 | CU86: =IF(WEEKDAY(CU$82,2)>5,0,790.54) -> 790.54 | CV86: =IF(WEEKDAY(CV$82,2)>5,0,860.29) -> 860.29 | CW86: =IF(WEEKDAY(CW$82,2)>5,0,759.81) -> 0 | CX86: =IF(WEEKDAY(CX$82,2)>5,0,767.28) -> 0 | CY86: =IF(WEEKDAY(CY$82,2)>5,0,905.78) -> 905.78 | CZ86: =IF(WEEKDAY(CZ$82,2)>5,0,721.37) -> 721.37 | DA86: =IF(WEEKDAY(DA$82,2)>5,0,793.92) -> 793.92 | DB86: =IF(WEEKDAY(DB$82,2)>5,0,710.8) -> 710.8 | DC86: =IF(WEEKDAY(DC$82,2)>5,0,810.41) -> 810.41 | DD86: =IF(WEEKDAY(DD$82,2)>5,0,882.28) -> 0 | DE86: =IF(WEEKDAY(DE$82,2)>5,0,877.15) -> 0 | DF86: =IF(WEEKDAY(DF$82,2)>5,0,749.22) -> 749.22 | DG86: =IF(WEEKDAY(DG$82,2)>5,0,728.49) -> 728.49 | DH86: =IF(WEEKDAY(DH$82,2)>5,0,752.38) -> 752.38 | DI86: =IF(WEEKDAY(DI$82,2)>5,0,707.17) -> 707.17 | DJ86: =IF(WEEKDAY(DJ$82,2)>5,0,892.74) -> 892.74 | DK86: =IF(WEEKDAY(DK$82,2)>5,0,918.63) -> 0 | DL86: =IF(WEEKDAY(DL$82,2)>5,0,836.45) -> 0 | DM86: =IF(WEEKDAY(DM$82,2)>5,0,704.76) -> 704.76 | DN86: =IF(WEEKDAY(DN$82,2)>5,0,723.11) -> 723.11 | DO86: =IF(WEEKDAY(DO$82,2)>5,0,772.04) -> 772.04 | DP86: =IF(WEEKDAY(DP$82,2)>5,0,836.48) -> 836.48 | DQ86: =IF(WEEKDAY(DQ$82,2)>5,0,883.02) -> 883.02 | DR86: =IF(WEEKDAY(DR$82,2)>5,0,819.44) -> 0 | DS86: =IF(WEEKDAY(DS$82,2)>5,0,720.8) -> 0 | DT86: =IF(WEEKDAY(DT$82,2)>5,0,744.74) -> 744.74 | DU86: =IF(WEEKDAY(DU$82,2)>5,0,893.81) -> 893.81 | DV86: =IF(WEEKDAY(DV$82,2)>5,0,866.04) -> 866.04 | DW86: =IF(WEEKDAY(DW$82,2)>5,0,721.74) -> 721.74 | DX86: =IF(WEEKDAY(DX$82,2)>5,0,836.91) -> 836.91 | DY86: =IF(WEEKDAY(DY$82,2)>5,0,880.87) -> 0 | DZ86: =IF(WEEKDAY(DZ$82,2)>5,0,700.59) -> 0 | EA86: =IF(WEEKDAY(EA$82,2)>5,0,718.07) -> 718.07 | EB86: =IF(WEEKDAY(EB$82,2)>5,0,833.01) -> 833.01 | EC86: =IF(WEEKDAY(EC$82,2)>5,0,849.83) -> 849.83 | ED86: =IF(WEEKDAY(ED$82,2)>5,0,736.13) -> 736.13 | EE86: =IF(WEEKDAY(EE$82,2)>5,0,820.44) -> 820.44 | EF86: =IF(WEEKDAY(EF$82,2)>5,0,859.5) -> 0 | EG86: =IF(WEEKDAY(EG$82,2)>5,0,811.17) -> 0 | EH86: =IF(WEEKDAY(EH$82,2)>5,0,878.86) -> 878.86 | EI86: =IF(WEEKDAY(EI$82,2)>5,0,800.48) -> 800.48 | EJ86: =IF(WEEKDAY(EJ$82,2)>5,0,864.74) -> 864.74 | EK86: =IF(WEEKDAY(EK$82,2)>5,0,813.25) -> 813.25 | EL86: =IF(WEEKDAY(EL$82,2)>5,0,725.94) -> 725.94 | EM86: =IF(WEEKDAY(EM$82,2)>5,0,894.03) -> 0 | EN86: =IF(WEEKDAY(EN$82,2)>5,0,901.1) -> 0 | EO86: =IF(WEEKDAY(EO$82,2)>5,0,769.43) -> 769.43 | EP86: =IF(WEEKDAY(EP$82,2)>5,0,681.66) -> 681.66 | EQ86: =IF(WEEKDAY(EQ$82,2)>5,0,745.11) -> 745.11 | ER86: =IF(WEEKDAY(ER$82,2)>5,0,820.54) -> 820.54 | ES86: =IF(WEEKDAY(ES$82,2)>5,0,790.97) -> 790.97 | ET86: =IF(WEEKDAY(ET$82,2)>5,0,863.04) -> 0 | EU86: =IF(WEEKDAY(EU$82,2)>5,0,848.11) -> 0 | EV86: =IF(WEEKDAY(EV$82,2)>5,0,752.58) -> 752.58 | EW86: =IF(WEEKDAY(EW$82,2)>5,0,833.11) -> 833.11 | EX86: =IF(WEEKDAY(EX$82,2)>5,0,862.69) -> 862.69 | EY86: =IF(WEEKDAY(EY$82,2)>5,0,829.24) -> 829.24 | EZ86: =IF(WEEKDAY(EZ$82,2)>5,0,802.51) -> 802.51 | FA86: =IF(WEEKDAY(FA$82,2)>5,0,758.04) -> 0 | FB86: =IF(WEEKDAY(FB$82,2)>5,0,716.14) -> 0 | FC86: =IF(WEEKDAY(FC$82,2)>5,0,741.48) -> 741.48 | FD86: =IF(WEEKDAY(FD$82,2)>5,0,773.42) -> 773.42 | FE86: =IF(WEEKDAY(FE$82,2)>5,0,757.66) -> 757.66 | FF86: =IF(WEEKDAY(FF$82,2)>5,0,749.58) -> 749.58 | FG86: =IF(WEEKDAY(FG$82,2)>5,0,872.79) -> 872.79 | FH86: =IF(WEEKDAY(FH$82,2)>5,0,800.74) -> 0 | FI86: =IF(WEEKDAY(FI$82,2)>5,0,763.42) -> 0 | FJ86: =IF(WEEKDAY(FJ$82,2)>5,0,828.9) -> 828.9 | FK86: =IF(WEEKDAY(FK$82,2)>5,0,715.58) -> 715.58 | FL86: =IF(WEEKDAY(FL$82,2)>5,0,839.05) -> 839.05 | FM86: =IF(WEEKDAY(FM$82,2)>5,0,698.94) -> 698.94 | FN86: =IF(WEEKDAY(FN$82,2)>5,0,811.29) -> 811.29 | FO86: =IF(WEEKDAY(FO$82,2)>5,0,737.4) -> 0 | FP86: =IF(WEEKDAY(FP$82,2)>5,0,840.48) -> 0 | FQ86: =IF(WEEKDAY(FQ$82,2)>5,0,876.76) -> 876.76 | FR86: =IF(WEEKDAY(FR$82,2)>5,0,753.02) -> 753.02 | FS86: =IF(WEEKDAY(FS$82,2)>5,0,690.49) -> 690.49 | FT86: =IF(WEEKDAY(FT$82,2)>5,0,700.82) -> 700.82 | FU86: =IF(WEEKDAY(FU$82,2)>5,0,825.71) -> 825.71 | FV86: =IF(WEEKDAY(FV$82,2)>5,0,798.16) -> 0 | FW86: =IF(WEEKDAY(FW$82,2)>5,0,799.73) -> 0 | FX86: =IF(WEEKDAY(FX$82,2)>5,0,766.04) -> 766.04 | FY86: =IF(WEEKDAY(FY$82,2)>5,0,820.32) -> 820.32 | FZ86: =IF(WEEKDAY(FZ$82,2)>5,0,763.04) -> 763.04 | GA86: =IF(WEEKDAY(GA$82,2)>5,0,831.37) -> 831.37 | GB86: =IF(WEEKDAY(GB$82,2)>5,0,812.51) -> 812.51 | GC86: =IF(WEEKDAY(GC$82,2)>5,0,809.73) -> 0 | GD86: =IF(WEEKDAY(GD$82,2)>5,0,755.49) -> 0 | GE86: =IF(WEEKDAY(GE$82,2)>5,0,892.31) -> 892.31 | GF86: =IF(WEEKDAY(GF$82,2)>5,0,812.87) -> 812.87 | GG86: =IF(WEEKDAY(GG$82,2)>5,0,855.65) -> 855.65 | GH86: =IF(WEEKDAY(GH$82,2)>5,0,724.76) -> 724.76 | GI86: =IF(WEEKDAY(GI$82,2)>5,0,829.09) -> 829.09 | GJ86: =IF(WEEKDAY(GJ$82,2)>5,0,812.15) -> 0 | GK86: =IF(WEEKDAY(GK$82,2)>5,0,711.69) -> 0 | GL86: =IF(WEEKDAY(GL$82,2)>5,0,826.06) -> 826.06 | GM86: =IF(WEEKDAY(GM$82,2)>5,0,861.84) -> 861.84 | GN86: =IF(WEEKDAY(GN$82,2)>5,0,726.05) -> 726.05 | GO86: =IF(WEEKDAY(GO$82,2)>5,0,798.79) -> 798.79 | GP86: =IF(WEEKDAY(GP$82,2)>5,0,814.84) -> 814.84 | GQ86: =IF(WEEKDAY(GQ$82,2)>5,0,823.83) -> 0 | GR86: =IF(WEEKDAY(GR$82,2)>5,0,782.46) -> 0 | GS86: =IF(WEEKDAY(GS$82,2)>5,0,706.53) -> 706.53 | GT86: =IF(WEEKDAY(GT$82,2)>5,0,769.11) -> 769.11 | GU86: =IF(WEEKDAY(GU$82,2)>5,0,832.54) -> 832.54 | GV86: =IF(WEEKDAY(GV$82,2)>5,0,802.26) -> 802.26 | GW86: =IF(WEEKDAY(GW$82,2)>5,0,734.46) -> 734.46 | GX86: =IF(WEEKDAY(GX$82,2)>5,0,837.98) -> 0 | GY86: =IF(WEEKDAY(GY$82,2)>5,0,863.19) -> 0 | GZ86: =IF(WEEKDAY(GZ$82,2)>5,0,899.82) -> 899.82 | HA86: =IF(WEEKDAY(HA$82,2)>5,0,832.53) -> 832.53 | HB86: =IF(WEEKDAY(HB$82,2)>5,0,762.69) -> 762.69 | HC86: =IF(WEEKDAY(HC$82,2)>5,0,778.05) -> 778.05 | HD86: =IF(WEEKDAY(HD$82,2)>5,0,695.82) -> 695.82 | HE86: =IF(WEEKDAY(HE$82,2)>5,0,808.59) -> 0 | HF86: =IF(WEEKDAY(HF$82,2)>5,0,846.67) -> 0 | HG86: =IF(WEEKDAY(HG$82,2)>5,0,837.92) -> 837.92 | HH86: =IF(WEEKDAY(HH$82,2)>5,0,696.79) -> 696.79 | HI86: =IF(WEEKDAY(HI$82,2)>5,0,889.7) -> 889.7 | HJ86: =IF(WEEKDAY(HJ$82,2)>5,0,855.96) -> 855.96 | HK86: =IF(WEEKDAY(HK$82,2)>5,0,808.08) -> 808.08 | HL86: =IF(WEEKDAY(HL$82,2)>5,0,712.52) -> 0 | HM86: =IF(WEEKDAY(HM$82,2)>5,0,828.29) -> 0 | HN86: =IF(WEEKDAY(HN$82,2)>5,0,694.44) -> 694.44 | HO86: =IF(WEEKDAY(HO$82,2)>5,0,904.23) -> 904.23 | HP86: =IF(WEEKDAY(HP$82,2)>5,0,841.82) -> 841.82 | HQ86: =IF(WEEKDAY(HQ$82,2)>5,0,816.6) -> 816.6 | HR86: =IF(WEEKDAY(HR$82,2)>5,0,779.92) -> 779.92 | HS86: =IF(WEEKDAY(HS$82,2)>5,0,718.14) -> 0 | HT86: =IF(WEEKDAY(HT$82,2)>5,0,837.35) -> 0 | HU86: =IF(WEEKDAY(HU$82,2)>5,0,786.3) -> 786.3 | HV86: =IF(WEEKDAY(HV$82,2)>5,0,682.17) -> 682.17 | HW86: =IF(WEEKDAY(HW$82,2)>5,0,681.81) -> 681.81 | HX86: =IF(WEEKDAY(HX$82,2)>5,0,740.59) -> 740.59 | HY86: =IF(WEEKDAY(HY$82,2)>5,0,776.31) -> 776.31 | HZ86: =IF(WEEKDAY(HZ$82,2)>5,0,745.73) -> 0 | IA86: =IF(WEEKDAY(IA$82,2)>5,0,905.74) -> 0 | IB86: =IF(WEEKDAY(IB$82,2)>5,0,730.43) -> 730.43 | IC86: =IF(WEEKDAY(IC$82,2)>5,0,743.04) -> 743.04 | ID86: =IF(WEEKDAY(ID$82,2)>5,0,711.9) -> 711.9 | IE86: =IF(WEEKDAY(IE$82,2)>5,0,871.77) -> 871.77 | IF86: =IF(WEEKDAY(IF$82,2)>5,0,733.88) -> 733.88 | IG86: =IF(WEEKDAY(IG$82,2)>5,0,742.93) -> 0 | IH86: =IF(WEEKDAY(IH$82,2)>5,0,758.13) -> 0 | II86: =IF(WEEKDAY(II$82,2)>5,0,689.14) -> 689.14 | IJ86: =IF(WEEKDAY(IJ$82,2)>5,0,725.97) -> 725.97 | IK86: =IF(WEEKDAY(IK$82,2)>5,0,818.89) -> 818.89 | IL86: =IF(WEEKDAY(IL$82,2)>5,0,686.13) -> 686.13
A87: Outras Receitas | B87: =IF(WEEKDAY(B$82,2)>5,0,52.41) -> 52.41 | C87: =IF(WEEKDAY(C$82,2)>5,0,55.89) -> 0 | D87: =IF(WEEKDAY(D$82,2)>5,0,55.02) -> 0 | E87: =IF(WEEKDAY(E$82,2)>5,0,44.72) -> 44.72 | F87: =IF(WEEKDAY(F$82,2)>5,0,45.5) -> 45.5 | G87: =IF(WEEKDAY(G$82,2)>5,0,46.36) -> 46.36 | H87: =IF(WEEKDAY(H$82,2)>5,0,44.6) -> 44.6 | I87: =IF(WEEKDAY(I$82,2)>5,0,46.1) -> 46.1 | J87: =IF(WEEKDAY(J$82,2)>5,0,56.91) -> 0 | K87: =IF(WEEKDAY(K$82,2)>5,0,47.62) -> 0 | L87: =IF(WEEKDAY(L$82,2)>5,0,47.04) -> 47.04 | M87: =IF(WEEKDAY(M$82,2)>5,0,49.86) -> 49.86 | N87: =IF(WEEKDAY(N$82,2)>5,0,45.34) -> 45.34 | O87: =IF(WEEKDAY(O$82,2)>5,0,51.13) -> 51.13 | P87: =IF(WEEKDAY(P$82,2)>5,0,48.11) -> 48.11 | Q87: =IF(WEEKDAY(Q$82,2)>5,0,46.62) -> 0 | R87: =IF(WEEKDAY(R$82,2)>5,0,43.99) -> 0 | S87: =IF(WEEKDAY(S$82,2)>5,0,46.78) -> 46.78 | T87: =IF(WEEKDAY(T$82,2)>5,0,47.54) -> 47.54 | U87: =IF(WEEKDAY(U$82,2)>5,0,55.33) -> 55.33 | V87: =IF(WEEKDAY(V$82,2)>5,0,47.27) -> 47.27 | W87: =IF(WEEKDAY(W$82,2)>5,0,47.45) -> 47.45 | X87: =IF(WEEKDAY(X$82,2)>5,0,46.88) -> 0 | Y87: =IF(WEEKDAY(Y$82,2)>5,0,43.19) -> 0 | Z87: =IF(WEEKDAY(Z$82,2)>5,0,46.68) -> 46.68 | AA87: =IF(WEEKDAY(AA$82,2)>5,0,45.28) -> 45.28 | AB87: =IF(WEEKDAY(AB$82,2)>5,0,48.09) -> 48.09 | AC87: =IF(WEEKDAY(AC$82,2)>5,0,50.06) -> 50.06 | AD87: =IF(WEEKDAY(AD$82,2)>5,0,53.61) -> 53.61 | AE87: =IF(WEEKDAY(AE$82,2)>5,0,51.75) -> 0 | AF87: =IF(WEEKDAY(AF$82,2)>5,0,54.01) -> 0 | AG87: =IF(WEEKDAY(AG$82,2)>5,0,45.98) -> 45.98 | AH87: =IF(WEEKDAY(AH$82,2)>5,0,44.3) -> 44.3 | AI87: =IF(WEEKDAY(AI$82,2)>5,0,55.58) -> 55.58 | AJ87: =IF(WEEKDAY(AJ$82,2)>5,0,51.31) -> 51.31 | AK87: =IF(WEEKDAY(AK$82,2)>5,0,45.96) -> 45.96 | AL87: =IF(WEEKDAY(AL$82,2)>5,0,47.02) -> 0 | AM87: =IF(WEEKDAY(AM$82,2)>5,0,44.21) -> 0 | AN87: =IF(WEEKDAY(AN$82,2)>5,0,56.5) -> 56.5 | AO87: =IF(WEEKDAY(AO$82,2)>5,0,53.03) -> 53.03 | AP87: =IF(WEEKDAY(AP$82,2)>5,0,42.88) -> 42.88 | AQ87: =IF(WEEKDAY(AQ$82,2)>5,0,55.23) -> 55.23 | AR87: =IF(WEEKDAY(AR$82,2)>5,0,43.05) -> 43.05 | AS87: =IF(WEEKDAY(AS$82,2)>5,0,45.21) -> 0 | AT87: =IF(WEEKDAY(AT$82,2)>5,0,55.59) -> 0 | AU87: =IF(WEEKDAY(AU$82,2)>5,0,49.54) -> 49.54 | AV87: =IF(WEEKDAY(AV$82,2)>5,0,50.34) -> 50.34 | AW87: =IF(WEEKDAY(AW$82,2)>5,0,52.45) -> 52.45 | AX87: =IF(WEEKDAY(AX$82,2)>5,0,44.38) -> 44.38 | AY87: =IF(WEEKDAY(AY$82,2)>5,0,54.35) -> 54.35 | AZ87: =IF(WEEKDAY(AZ$82,2)>5,0,48.62) -> 0 | BA87: =IF(WEEKDAY(BA$82,2)>5,0,49.15) -> 0 | BB87: =IF(WEEKDAY(BB$82,2)>5,0,50.89) -> 50.89 | BC87: =IF(WEEKDAY(BC$82,2)>5,0,45.43) -> 45.43 | BD87: =IF(WEEKDAY(BD$82,2)>5,0,52.4) -> 52.4 | BE87: =IF(WEEKDAY(BE$82,2)>5,0,44.57) -> 44.57 | BF87: =IF(WEEKDAY(BF$82,2)>5,0,46.09) -> 46.09 | BG87: =IF(WEEKDAY(BG$82,2)>5,0,56.43) -> 0 | BH87: =IF(WEEKDAY(BH$82,2)>5,0,43.62) -> 0 | BI87: =IF(WEEKDAY(BI$82,2)>5,0,54.69) -> 54.69 | BJ87: =IF(WEEKDAY(BJ$82,2)>5,0,42.79) -> 42.79 | BK87: =IF(WEEKDAY(BK$82,2)>5,0,55.08) -> 55.08 | BL87: =IF(WEEKDAY(BL$82,2)>5,0,51.47) -> 51.47 | BM87: =IF(WEEKDAY(BM$82,2)>5,0,56.98) -> 56.98 | BN87: =IF(WEEKDAY(BN$82,2)>5,0,54.34) -> 0 | BO87: =IF(WEEKDAY(BO$82,2)>5,0,52.55) -> 0 | BP87: =IF(WEEKDAY(BP$82,2)>5,0,46.18) -> 46.18 | BQ87: =IF(WEEKDAY(BQ$82,2)>5,0,43.74) -> 43.74 | BR87: =IF(WEEKDAY(BR$82,2)>5,0,45.26) -> 45.26 | BS87: =IF(WEEKDAY(BS$82,2)>5,0,45.99) -> 45.99 | BT87: =IF(WEEKDAY(BT$82,2)>5,0,56.54) -> 56.54 | BU87: =IF(WEEKDAY(BU$82,2)>5,0,47.25) -> 0 | BV87: =IF(WEEKDAY(BV$82,2)>5,0,44.41) -> 0 | BW87: =IF(WEEKDAY(BW$82,2)>5,0,49.47) -> 49.47 | BX87: =IF(WEEKDAY(BX$82,2)>5,0,54.3) -> 54.3 | BY87: =IF(WEEKDAY(BY$82,2)>5,0,49.94) -> 49.94 | BZ87: =IF(WEEKDAY(BZ$82,2)>5,0,43.52) -> 43.52 | CA87: =IF(WEEKDAY(CA$82,2)>5,0,56.04) -> 56.04 | CB87: =IF(WEEKDAY(CB$82,2)>5,0,53.38) -> 0 | CC87: =IF(WEEKDAY(CC$82,2)>5,0,50.58) -> 0 | CD87: =IF(WEEKDAY(CD$82,2)>5,0,53.91) -> 53.91 | CE87: =IF(WEEKDAY(CE$82,2)>5,0,51.68) -> 51.68 | CF87: =IF(WEEKDAY(CF$82,2)>5,0,48.02) -> 48.02 | CG87: =IF(WEEKDAY(CG$82,2)>5,0,54.4) -> 54.4 | CH87: =IF(WEEKDAY(CH$82,2)>5,0,53.57) -> 53.57 | CI87: =IF(WEEKDAY(CI$82,2)>5,0,44.66) -> 0 | CJ87: =IF(WEEKDAY(CJ$82,2)>5,0,55.86) -> 0 | CK87: =IF(WEEKDAY(CK$82,2)>5,0,55.13) -> 55.13 | CL87: =IF(WEEKDAY(CL$82,2)>5,0,51.54) -> 51.54 | CM87: =IF(WEEKDAY(CM$82,2)>5,0,54.98) -> 54.98 | CN87: =IF(WEEKDAY(CN$82,2)>5,0,48.44) -> 48.44 | CO87: =IF(WEEKDAY(CO$82,2)>5,0,50.94) -> 50.94 | CP87: =IF(WEEKDAY(CP$82,2)>5,0,53.66) -> 0 | CQ87: =IF(WEEKDAY(CQ$82,2)>5,0,52.68) -> 0 | CR87: =IF(WEEKDAY(CR$82,2)>5,0,45.69) -> 45.69 | CS87: =IF(WEEKDAY(CS$82,2)>5,0,55.41) -> 55.41 | CT87: =IF(WEEKDAY(CT$82,2)>5,0,45.98) -> 45.98 | CU87: =IF(WEEKDAY(CU$82,2)>5,0,50.88) -> 50.88 | CV87: =IF(WEEKDAY(CV$82,2)>5,0,52.16) -> 52.16 | CW87: =IF(WEEKDAY(CW$82,2)>5,0,46.32) -> 0 | CX87: =IF(WEEKDAY(CX$82,2)>5,0,56.64) -> 0 | CY87: =IF(WEEKDAY(CY$82,2)>5,0,45.4) -> 45.4 | CZ87: =IF(WEEKDAY(CZ$82,2)>5,0,47.2) -> 47.2 | DA87: =IF(WEEKDAY(DA$82,2)>5,0,48.47) -> 48.47 | DB87: =IF(WEEKDAY(DB$82,2)>5,0,43.89) -> 43.89 | DC87: =IF(WEEKDAY(DC$82,2)>5,0,42.98) -> 42.98 | DD87: =IF(WEEKDAY(DD$82,2)>5,0,51.78) -> 0 | DE87: =IF(WEEKDAY(DE$82,2)>5,0,53.07) -> 0 | DF87: =IF(WEEKDAY(DF$82,2)>5,0,53.76) -> 53.76 | DG87: =IF(WEEKDAY(DG$82,2)>5,0,45.41) -> 45.41 | DH87: =IF(WEEKDAY(DH$82,2)>5,0,52.7) -> 52.7 | DI87: =IF(WEEKDAY(DI$82,2)>5,0,55.61) -> 55.61 | DJ87: =IF(WEEKDAY(DJ$82,2)>5,0,50.86) -> 50.86 | DK87: =IF(WEEKDAY(DK$82,2)>5,0,44.61) -> 0 | DL87: =IF(WEEKDAY(DL$82,2)>5,0,54.99) -> 0 | DM87: =IF(WEEKDAY(DM$82,2)>5,0,49.45) -> 49.45 | DN87: =IF(WEEKDAY(DN$82,2)>5,0,52.83) -> 52.83 | DO87: =IF(WEEKDAY(DO$82,2)>5,0,43.92) -> 43.92 | DP87: =IF(WEEKDAY(DP$82,2)>5,0,55.59) -> 55.59 | DQ87: =IF(WEEKDAY(DQ$82,2)>5,0,52.14) -> 52.14 | DR87: =IF(WEEKDAY(DR$82,2)>5,0,54.27) -> 0 | DS87: =IF(WEEKDAY(DS$82,2)>5,0,52.98) -> 0 | DT87: =IF(WEEKDAY(DT$82,2)>5,0,52.16) -> 52.16 | DU87: =IF(WEEKDAY(DU$82,2)>5,0,57.15) -> 57.15 | DV87: =IF(WEEKDAY(DV$82,2)>5,0,50.42) -> 50.42 | DW87: =IF(WEEKDAY(DW$82,2)>5,0,44.49) -> 44.49 | DX87: =IF(WEEKDAY(DX$82,2)>5,0,51.28) -> 51.28 | DY87: =IF(WEEKDAY(DY$82,2)>5,0,51.84) -> 0 | DZ87: =IF(WEEKDAY(DZ$82,2)>5,0,43.62) -> 0 | EA87: =IF(WEEKDAY(EA$82,2)>5,0,43.55) -> 43.55 | EB87: =IF(WEEKDAY(EB$82,2)>5,0,53.96) -> 53.96 | EC87: =IF(WEEKDAY(EC$82,2)>5,0,55.82) -> 55.82 | ED87: =IF(WEEKDAY(ED$82,2)>5,0,54.68) -> 54.68 | EE87: =IF(WEEKDAY(EE$82,2)>5,0,47.21) -> 47.21 | EF87: =IF(WEEKDAY(EF$82,2)>5,0,55.48) -> 0 | EG87: =IF(WEEKDAY(EG$82,2)>5,0,51.69) -> 0 | EH87: =IF(WEEKDAY(EH$82,2)>5,0,47.81) -> 47.81 | EI87: =IF(WEEKDAY(EI$82,2)>5,0,51.82) -> 51.82 | EJ87: =IF(WEEKDAY(EJ$82,2)>5,0,46.9) -> 46.9 | EK87: =IF(WEEKDAY(EK$82,2)>5,0,54.52) -> 54.52 | EL87: =IF(WEEKDAY(EL$82,2)>5,0,55.75) -> 55.75 | EM87: =IF(WEEKDAY(EM$82,2)>5,0,49.89) -> 0 | EN87: =IF(WEEKDAY(EN$82,2)>5,0,44.26) -> 0 | EO87: =IF(WEEKDAY(EO$82,2)>5,0,45.61) -> 45.61 | EP87: =IF(WEEKDAY(EP$82,2)>5,0,44.14) -> 44.14 | EQ87: =IF(WEEKDAY(EQ$82,2)>5,0,42.92) -> 42.92 | ER87: =IF(WEEKDAY(ER$82,2)>5,0,48.53) -> 48.53 | ES87: =IF(WEEKDAY(ES$82,2)>5,0,47.78) -> 47.78 | ET87: =IF(WEEKDAY(ET$82,2)>5,0,53.62) -> 0 | EU87: =IF(WEEKDAY(EU$82,2)>5,0,44.12) -> 0 | EV87: =IF(WEEKDAY(EV$82,2)>5,0,48.52) -> 48.52 | EW87: =IF(WEEKDAY(EW$82,2)>5,0,44.29) -> 44.29 | EX87: =IF(WEEKDAY(EX$82,2)>5,0,47.98) -> 47.98 | EY87: =IF(WEEKDAY(EY$82,2)>5,0,55.62) -> 55.62 | EZ87: =IF(WEEKDAY(EZ$82,2)>5,0,46.96) -> 46.96 | FA87: =IF(WEEKDAY(FA$82,2)>5,0,47.04) -> 0 | FB87: =IF(WEEKDAY(FB$82,2)>5,0,44.73) -> 0 | FC87: =IF(WEEKDAY(FC$82,2)>5,0,47.37) -> 47.37 | FD87: =IF(WEEKDAY(FD$82,2)>5,0,55.51) -> 55.51 | FE87: =IF(WEEKDAY(FE$82,2)>5,0,49.05) -> 49.05 | FF87: =IF(WEEKDAY(FF$82,2)>5,0,43.42) -> 43.42 | FG87: =IF(WEEKDAY(FG$82,2)>5,0,47.07) -> 47.07 | FH87: =IF(WEEKDAY(FH$82,2)>5,0,50.04) -> 0 | FI87: =IF(WEEKDAY(FI$82,2)>5,0,54.08) -> 0 | FJ87: =IF(WEEKDAY(FJ$82,2)>5,0,44.06) -> 44.06 | FK87: =IF(WEEKDAY(FK$82,2)>5,0,55.6) -> 55.6 | FL87: =IF(WEEKDAY(FL$82,2)>5,0,50.83) -> 50.83 | FM87: =IF(WEEKDAY(FM$82,2)>5,0,42.76) -> 42.76 | FN87: =IF(WEEKDAY(FN$82,2)>5,0,44.94) -> 44.94 | FO87: =IF(WEEKDAY(FO$82,2)>5,0,43.71) -> 0 | FP87: =IF(WEEKDAY(FP$82,2)>5,0,46.34) -> 0 | FQ87: =IF(WEEKDAY(FQ$82,2)>5,0,44.53) -> 44.53 | FR87: =IF(WEEKDAY(FR$82,2)>5,0,43.09) -> 43.09 | FS87: =IF(WEEKDAY(FS$82,2)>5,0,45.22) -> 45.22 | FT87: =IF(WEEKDAY(FT$82,2)>5,0,49.25) -> 49.25 | FU87: =IF(WEEKDAY(FU$82,2)>5,0,43.98) -> 43.98 | FV87: =IF(WEEKDAY(FV$82,2)>5,0,44.78) -> 0 | FW87: =IF(WEEKDAY(FW$82,2)>5,0,44.42) -> 0 | FX87: =IF(WEEKDAY(FX$82,2)>5,0,52.76) -> 52.76 | FY87: =IF(WEEKDAY(FY$82,2)>5,0,42.76) -> 42.76 | FZ87: =IF(WEEKDAY(FZ$82,2)>5,0,56.81) -> 56.81 | GA87: =IF(WEEKDAY(GA$82,2)>5,0,44.73) -> 44.73 | GB87: =IF(WEEKDAY(GB$82,2)>5,0,45.82) -> 45.82 | GC87: =IF(WEEKDAY(GC$82,2)>5,0,44.87) -> 0 | GD87: =IF(WEEKDAY(GD$82,2)>5,0,55.86) -> 0 | GE87: =IF(WEEKDAY(GE$82,2)>5,0,49.91) -> 49.91 | GF87: =IF(WEEKDAY(GF$82,2)>5,0,56.7) -> 56.7 | GG87: =IF(WEEKDAY(GG$82,2)>5,0,55.47) -> 55.47 | GH87: =IF(WEEKDAY(GH$82,2)>5,0,54.2) -> 54.2 | GI87: =IF(WEEKDAY(GI$82,2)>5,0,49.15) -> 49.15 | GJ87: =IF(WEEKDAY(GJ$82,2)>5,0,51.34) -> 0 | GK87: =IF(WEEKDAY(GK$82,2)>5,0,45.27) -> 0 | GL87: =IF(WEEKDAY(GL$82,2)>5,0,52.11) -> 52.11 | GM87: =IF(WEEKDAY(GM$82,2)>5,0,54.62) -> 54.62 | GN87: =IF(WEEKDAY(GN$82,2)>5,0,49.48) -> 49.48 | GO87: =IF(WEEKDAY(GO$82,2)>5,0,43.19) -> 43.19 | GP87: =IF(WEEKDAY(GP$82,2)>5,0,46.29) -> 46.29 | GQ87: =IF(WEEKDAY(GQ$82,2)>5,0,46.58) -> 0 | GR87: =IF(WEEKDAY(GR$82,2)>5,0,55.04) -> 0 | GS87: =IF(WEEKDAY(GS$82,2)>5,0,49.28) -> 49.28 | GT87: =IF(WEEKDAY(GT$82,2)>5,0,45.37) -> 45.37 | GU87: =IF(WEEKDAY(GU$82,2)>5,0,43.83) -> 43.83 | GV87: =IF(WEEKDAY(GV$82,2)>5,0,49.11) -> 49.11 | GW87: =IF(WEEKDAY(GW$82,2)>5,0,44.79) -> 44.79 | GX87: =IF(WEEKDAY(GX$82,2)>5,0,48.15) -> 0 | GY87: =IF(WEEKDAY(GY$82,2)>5,0,53.68) -> 0 | GZ87: =IF(WEEKDAY(GZ$82,2)>5,0,45.36) -> 45.36 | HA87: =IF(WEEKDAY(HA$82,2)>5,0,51.55) -> 51.55 | HB87: =IF(WEEKDAY(HB$82,2)>5,0,53.3) -> 53.3 | HC87: =IF(WEEKDAY(HC$82,2)>5,0,47.33) -> 47.33 | HD87: =IF(WEEKDAY(HD$82,2)>5,0,55.7) -> 55.7 | HE87: =IF(WEEKDAY(HE$82,2)>5,0,54.77) -> 0 | HF87: =IF(WEEKDAY(HF$82,2)>5,0,55.7) -> 0 | HG87: =IF(WEEKDAY(HG$82,2)>5,0,50.99) -> 50.99 | HH87: =IF(WEEKDAY(HH$82,2)>5,0,49.41) -> 49.41 | HI87: =IF(WEEKDAY(HI$82,2)>5,0,47.52) -> 47.52 | HJ87: =IF(WEEKDAY(HJ$82,2)>5,0,47.27) -> 47.27 | HK87: =IF(WEEKDAY(HK$82,2)>5,0,44.97) -> 44.97 | HL87: =IF(WEEKDAY(HL$82,2)>5,0,47.28) -> 0 | HM87: =IF(WEEKDAY(HM$82,2)>5,0,43.24) -> 0 | HN87: =IF(WEEKDAY(HN$82,2)>5,0,52.62) -> 52.62 | HO87: =IF(WEEKDAY(HO$82,2)>5,0,45.15) -> 45.15 | HP87: =IF(WEEKDAY(HP$82,2)>5,0,55.72) -> 55.72 | HQ87: =IF(WEEKDAY(HQ$82,2)>5,0,56.08) -> 56.08 | HR87: =IF(WEEKDAY(HR$82,2)>5,0,43.27) -> 43.27 | HS87: =IF(WEEKDAY(HS$82,2)>5,0,45.04) -> 0 | HT87: =IF(WEEKDAY(HT$82,2)>5,0,43.99) -> 0 | HU87: =IF(WEEKDAY(HU$82,2)>5,0,52.5) -> 52.5 | HV87: =IF(WEEKDAY(HV$82,2)>5,0,53.68) -> 53.68 | HW87: =IF(WEEKDAY(HW$82,2)>5,0,55.16) -> 55.16 | HX87: =IF(WEEKDAY(HX$82,2)>5,0,48.72) -> 48.72 | HY87: =IF(WEEKDAY(HY$82,2)>5,0,53.04) -> 53.04 | HZ87: =IF(WEEKDAY(HZ$82,2)>5,0,46.3) -> 0 | IA87: =IF(WEEKDAY(IA$82,2)>5,0,57.14) -> 0 | IB87: =IF(WEEKDAY(IB$82,2)>5,0,47.4) -> 47.4 | IC87: =IF(WEEKDAY(IC$82,2)>5,0,56.04) -> 56.04 | ID87: =IF(WEEKDAY(ID$82,2)>5,0,43.37) -> 43.37 | IE87: =IF(WEEKDAY(IE$82,2)>5,0,51.4) -> 51.4 | IF87: =IF(WEEKDAY(IF$82,2)>5,0,46.98) -> 46.98 | IG87: =IF(WEEKDAY(IG$82,2)>5,0,56.3) -> 0 | IH87: =IF(WEEKDAY(IH$82,2)>5,0,50.17) -> 0 | II87: =IF(WEEKDAY(II$82,2)>5,0,56.17) -> 56.17 | IJ87: =IF(WEEKDAY(IJ$82,2)>5,0,57.32) -> 57.32 | IK87: =IF(WEEKDAY(IK$82,2)>5,0,54.3) -> 54.3 | IL87: =IF(WEEKDAY(IL$82,2)>5,0,49.31) -> 49.31
A88: Receitas Financeiras | B88: =IF(WEEKDAY(B$82,2)>5,0,34.32) -> 34.32 | C88: =IF(WEEKDAY(C$82,2)>5,0,29.04) -> 0 | D88: =IF(WEEKDAY(D$82,2)>5,0,29.91) -> 0 | E88: =IF(WEEKDAY(E$82,2)>5,0,31.69) -> 31.69 | F88: =IF(WEEKDAY(F$82,2)>5,0,29.29) -> 29.29 | G88: =IF(WEEKDAY(G$82,2)>5,0,34.11) -> 34.11 | H88: =IF(WEEKDAY(H$82,2)>5,0,34.06) -> 34.06 | I88: =IF(WEEKDAY(I$82,2)>5,0,29.41) -> 29.41 | J88: =IF(WEEKDAY(J$82,2)>5,0,31.22) -> 0 | K88: =IF(WEEKDAY(K$82,2)>5,0,26.43) -> 0 | L88: =IF(WEEKDAY(L$82,2)>5,0,28.97) -> 28.97 | M88: =IF(WEEKDAY(M$82,2)>5,0,33.16) -> 33.16 | N88: =IF(WEEKDAY(N$82,2)>5,0,28.97) -> 28.97 | O88: =IF(WEEKDAY(O$82,2)>5,0,30.84) -> 30.84 | P88: =IF(WEEKDAY(P$82,2)>5,0,27.13) -> 27.13 | Q88: =IF(WEEKDAY(Q$82,2)>5,0,34.14) -> 0 | R88: =IF(WEEKDAY(R$82,2)>5,0,27.54) -> 0 | S88: =IF(WEEKDAY(S$82,2)>5,0,29.17) -> 29.17 | T88: =IF(WEEKDAY(T$82,2)>5,0,26.65) -> 26.65 | U88: =IF(WEEKDAY(U$82,2)>5,0,26.29) -> 26.29 | V88: =IF(WEEKDAY(V$82,2)>5,0,29.82) -> 29.82 | W88: =IF(WEEKDAY(W$82,2)>5,0,30.8) -> 30.8 | X88: =IF(WEEKDAY(X$82,2)>5,0,30.42) -> 0 | Y88: =IF(WEEKDAY(Y$82,2)>5,0,28.18) -> 0 | Z88: =IF(WEEKDAY(Z$82,2)>5,0,28.58) -> 28.58 | AA88: =IF(WEEKDAY(AA$82,2)>5,0,31.83) -> 31.83 | AB88: =IF(WEEKDAY(AB$82,2)>5,0,33.75) -> 33.75 | AC88: =IF(WEEKDAY(AC$82,2)>5,0,34.21) -> 34.21 | AD88: =IF(WEEKDAY(AD$82,2)>5,0,31.68) -> 31.68 | AE88: =IF(WEEKDAY(AE$82,2)>5,0,30.8) -> 0 | AF88: =IF(WEEKDAY(AF$82,2)>5,0,31.13) -> 0 | AG88: =IF(WEEKDAY(AG$82,2)>5,0,25.81) -> 25.81 | AH88: =IF(WEEKDAY(AH$82,2)>5,0,27) -> 27 | AI88: =IF(WEEKDAY(AI$82,2)>5,0,30.52) -> 30.52 | AJ88: =IF(WEEKDAY(AJ$82,2)>5,0,30.07) -> 30.07 | AK88: =IF(WEEKDAY(AK$82,2)>5,0,29.74) -> 29.74 | AL88: =IF(WEEKDAY(AL$82,2)>5,0,30.91) -> 0 | AM88: =IF(WEEKDAY(AM$82,2)>5,0,27.57) -> 0 | AN88: =IF(WEEKDAY(AN$82,2)>5,0,29.14) -> 29.14 | AO88: =IF(WEEKDAY(AO$82,2)>5,0,28.07) -> 28.07 | AP88: =IF(WEEKDAY(AP$82,2)>5,0,26.66) -> 26.66 | AQ88: =IF(WEEKDAY(AQ$82,2)>5,0,31.04) -> 31.04 | AR88: =IF(WEEKDAY(AR$82,2)>5,0,28.15) -> 28.15 | AS88: =IF(WEEKDAY(AS$82,2)>5,0,27.09) -> 0 | AT88: =IF(WEEKDAY(AT$82,2)>5,0,25.51) -> 0 | AU88: =IF(WEEKDAY(AU$82,2)>5,0,28.55) -> 28.55 | AV88: =IF(WEEKDAY(AV$82,2)>5,0,32.47) -> 32.47 | AW88: =IF(WEEKDAY(AW$82,2)>5,0,28.79) -> 28.79 | AX88: =IF(WEEKDAY(AX$82,2)>5,0,29.54) -> 29.54 | AY88: =IF(WEEKDAY(AY$82,2)>5,0,26.47) -> 26.47 | AZ88: =IF(WEEKDAY(AZ$82,2)>5,0,30.96) -> 0 | BA88: =IF(WEEKDAY(BA$82,2)>5,0,27.99) -> 0 | BB88: =IF(WEEKDAY(BB$82,2)>5,0,29.9) -> 29.9 | BC88: =IF(WEEKDAY(BC$82,2)>5,0,26.18) -> 26.18 | BD88: =IF(WEEKDAY(BD$82,2)>5,0,29.31) -> 29.31 | BE88: =IF(WEEKDAY(BE$82,2)>5,0,28.21) -> 28.21 | BF88: =IF(WEEKDAY(BF$82,2)>5,0,33.32) -> 33.32 | BG88: =IF(WEEKDAY(BG$82,2)>5,0,31.73) -> 0 | BH88: =IF(WEEKDAY(BH$82,2)>5,0,30.63) -> 0 | BI88: =IF(WEEKDAY(BI$82,2)>5,0,26.65) -> 26.65 | BJ88: =IF(WEEKDAY(BJ$82,2)>5,0,26.69) -> 26.69 | BK88: =IF(WEEKDAY(BK$82,2)>5,0,26.49) -> 26.49 | BL88: =IF(WEEKDAY(BL$82,2)>5,0,30.4) -> 30.4 | BM88: =IF(WEEKDAY(BM$82,2)>5,0,34.26) -> 34.26 | BN88: =IF(WEEKDAY(BN$82,2)>5,0,33.35) -> 0 | BO88: =IF(WEEKDAY(BO$82,2)>5,0,27.55) -> 0 | BP88: =IF(WEEKDAY(BP$82,2)>5,0,27.01) -> 27.01 | BQ88: =IF(WEEKDAY(BQ$82,2)>5,0,29.42) -> 29.42 | BR88: =IF(WEEKDAY(BR$82,2)>5,0,30.02) -> 30.02 | BS88: =IF(WEEKDAY(BS$82,2)>5,0,30.97) -> 30.97 | BT88: =IF(WEEKDAY(BT$82,2)>5,0,26.15) -> 26.15 | BU88: =IF(WEEKDAY(BU$82,2)>5,0,26.58) -> 0 | BV88: =IF(WEEKDAY(BV$82,2)>5,0,32.18) -> 0 | BW88: =IF(WEEKDAY(BW$82,2)>5,0,33.08) -> 33.08 | BX88: =IF(WEEKDAY(BX$82,2)>5,0,33.33) -> 33.33 | BY88: =IF(WEEKDAY(BY$82,2)>5,0,33) -> 33 | BZ88: =IF(WEEKDAY(BZ$82,2)>5,0,26.89) -> 26.89 | CA88: =IF(WEEKDAY(CA$82,2)>5,0,26.91) -> 26.91 | CB88: =IF(WEEKDAY(CB$82,2)>5,0,27.96) -> 0 | CC88: =IF(WEEKDAY(CC$82,2)>5,0,26.67) -> 0 | CD88: =IF(WEEKDAY(CD$82,2)>5,0,27.18) -> 27.18 | CE88: =IF(WEEKDAY(CE$82,2)>5,0,25.64) -> 25.64 | CF88: =IF(WEEKDAY(CF$82,2)>5,0,30.88) -> 30.88 | CG88: =IF(WEEKDAY(CG$82,2)>5,0,27.84) -> 27.84 | CH88: =IF(WEEKDAY(CH$82,2)>5,0,26.52) -> 26.52 | CI88: =IF(WEEKDAY(CI$82,2)>5,0,32.23) -> 0 | CJ88: =IF(WEEKDAY(CJ$82,2)>5,0,31.72) -> 0 | CK88: =IF(WEEKDAY(CK$82,2)>5,0,31.09) -> 31.09 | CL88: =IF(WEEKDAY(CL$82,2)>5,0,32.11) -> 32.11 | CM88: =IF(WEEKDAY(CM$82,2)>5,0,27.62) -> 27.62 | CN88: =IF(WEEKDAY(CN$82,2)>5,0,29.85) -> 29.85 | CO88: =IF(WEEKDAY(CO$82,2)>5,0,31.35) -> 31.35 | CP88: =IF(WEEKDAY(CP$82,2)>5,0,29.63) -> 0 | CQ88: =IF(WEEKDAY(CQ$82,2)>5,0,29.58) -> 0 | CR88: =IF(WEEKDAY(CR$82,2)>5,0,34.21) -> 34.21 | CS88: =IF(WEEKDAY(CS$82,2)>5,0,33.82) -> 33.82 | CT88: =IF(WEEKDAY(CT$82,2)>5,0,29.75) -> 29.75 | CU88: =IF(WEEKDAY(CU$82,2)>5,0,26.49) -> 26.49 | CV88: =IF(WEEKDAY(CV$82,2)>5,0,31.37) -> 31.37 | CW88: =IF(WEEKDAY(CW$82,2)>5,0,30.92) -> 0 | CX88: =IF(WEEKDAY(CX$82,2)>5,0,27.81) -> 0 | CY88: =IF(WEEKDAY(CY$82,2)>5,0,29.29) -> 29.29 | CZ88: =IF(WEEKDAY(CZ$82,2)>5,0,27.78) -> 27.78 | DA88: =IF(WEEKDAY(DA$82,2)>5,0,33.29) -> 33.29 | DB88: =IF(WEEKDAY(DB$82,2)>5,0,31.16) -> 31.16 | DC88: =IF(WEEKDAY(DC$82,2)>5,0,34.47) -> 34.47 | DD88: =IF(WEEKDAY(DD$82,2)>5,0,27.03) -> 0 | DE88: =IF(WEEKDAY(DE$82,2)>5,0,33.08) -> 0 | DF88: =IF(WEEKDAY(DF$82,2)>5,0,32.99) -> 32.99 | DG88: =IF(WEEKDAY(DG$82,2)>5,0,28.68) -> 28.68 | DH88: =IF(WEEKDAY(DH$82,2)>5,0,32.48) -> 32.48 | DI88: =IF(WEEKDAY(DI$82,2)>5,0,28.63) -> 28.63 | DJ88: =IF(WEEKDAY(DJ$82,2)>5,0,31.7) -> 31.7 | DK88: =IF(WEEKDAY(DK$82,2)>5,0,31.64) -> 0 | DL88: =IF(WEEKDAY(DL$82,2)>5,0,26.43) -> 0 | DM88: =IF(WEEKDAY(DM$82,2)>5,0,34.25) -> 34.25 | DN88: =IF(WEEKDAY(DN$82,2)>5,0,27.52) -> 27.52 | DO88: =IF(WEEKDAY(DO$82,2)>5,0,27.36) -> 27.36 | DP88: =IF(WEEKDAY(DP$82,2)>5,0,28.52) -> 28.52 | DQ88: =IF(WEEKDAY(DQ$82,2)>5,0,31.27) -> 31.27 | DR88: =IF(WEEKDAY(DR$82,2)>5,0,29.1) -> 0 | DS88: =IF(WEEKDAY(DS$82,2)>5,0,26.47) -> 0 | DT88: =IF(WEEKDAY(DT$82,2)>5,0,26.29) -> 26.29 | DU88: =IF(WEEKDAY(DU$82,2)>5,0,27.35) -> 27.35 | DV88: =IF(WEEKDAY(DV$82,2)>5,0,31.25) -> 31.25 | DW88: =IF(WEEKDAY(DW$82,2)>5,0,33.18) -> 33.18 | DX88: =IF(WEEKDAY(DX$82,2)>5,0,29.26) -> 29.26 | DY88: =IF(WEEKDAY(DY$82,2)>5,0,28.58) -> 0 | DZ88: =IF(WEEKDAY(DZ$82,2)>5,0,28.07) -> 0 | EA88: =IF(WEEKDAY(EA$82,2)>5,0,26.73) -> 26.73 | EB88: =IF(WEEKDAY(EB$82,2)>5,0,31.29) -> 31.29 | EC88: =IF(WEEKDAY(EC$82,2)>5,0,30.1) -> 30.1 | ED88: =IF(WEEKDAY(ED$82,2)>5,0,29.26) -> 29.26 | EE88: =IF(WEEKDAY(EE$82,2)>5,0,28.98) -> 28.98 | EF88: =IF(WEEKDAY(EF$82,2)>5,0,28.27) -> 0 | EG88: =IF(WEEKDAY(EG$82,2)>5,0,27.77) -> 0 | EH88: =IF(WEEKDAY(EH$82,2)>5,0,31.19) -> 31.19 | EI88: =IF(WEEKDAY(EI$82,2)>5,0,28.04) -> 28.04 | EJ88: =IF(WEEKDAY(EJ$82,2)>5,0,30.79) -> 30.79 | EK88: =IF(WEEKDAY(EK$82,2)>5,0,28.42) -> 28.42 | EL88: =IF(WEEKDAY(EL$82,2)>5,0,25.91) -> 25.91 | EM88: =IF(WEEKDAY(EM$82,2)>5,0,30.26) -> 0 | EN88: =IF(WEEKDAY(EN$82,2)>5,0,28.19) -> 0 | EO88: =IF(WEEKDAY(EO$82,2)>5,0,31.34) -> 31.34 | EP88: =IF(WEEKDAY(EP$82,2)>5,0,28.45) -> 28.45 | EQ88: =IF(WEEKDAY(EQ$82,2)>5,0,28.18) -> 28.18 | ER88: =IF(WEEKDAY(ER$82,2)>5,0,32.41) -> 32.41 | ES88: =IF(WEEKDAY(ES$82,2)>5,0,28.84) -> 28.84 | ET88: =IF(WEEKDAY(ET$82,2)>5,0,25.52) -> 0 | EU88: =IF(WEEKDAY(EU$82,2)>5,0,30.32) -> 0 | EV88: =IF(WEEKDAY(EV$82,2)>5,0,33.76) -> 33.76 | EW88: =IF(WEEKDAY(EW$82,2)>5,0,29.27) -> 29.27 | EX88: =IF(WEEKDAY(EX$82,2)>5,0,26.3) -> 26.3 | EY88: =IF(WEEKDAY(EY$82,2)>5,0,25.98) -> 25.98 | EZ88: =IF(WEEKDAY(EZ$82,2)>5,0,26.19) -> 26.19 | FA88: =IF(WEEKDAY(FA$82,2)>5,0,33.91) -> 0 | FB88: =IF(WEEKDAY(FB$82,2)>5,0,30.55) -> 0 | FC88: =IF(WEEKDAY(FC$82,2)>5,0,34.36) -> 34.36 | FD88: =IF(WEEKDAY(FD$82,2)>5,0,34.11) -> 34.11 | FE88: =IF(WEEKDAY(FE$82,2)>5,0,30.59) -> 30.59 | FF88: =IF(WEEKDAY(FF$82,2)>5,0,32.06) -> 32.06 | FG88: =IF(WEEKDAY(FG$82,2)>5,0,32.87) -> 32.87 | FH88: =IF(WEEKDAY(FH$82,2)>5,0,32.48) -> 0 | FI88: =IF(WEEKDAY(FI$82,2)>5,0,32.13) -> 0 | FJ88: =IF(WEEKDAY(FJ$82,2)>5,0,31.64) -> 31.64 | FK88: =IF(WEEKDAY(FK$82,2)>5,0,26.13) -> 26.13 | FL88: =IF(WEEKDAY(FL$82,2)>5,0,30.73) -> 30.73 | FM88: =IF(WEEKDAY(FM$82,2)>5,0,33.14) -> 33.14 | FN88: =IF(WEEKDAY(FN$82,2)>5,0,30.2) -> 30.2 | FO88: =IF(WEEKDAY(FO$82,2)>5,0,25.56) -> 0 | FP88: =IF(WEEKDAY(FP$82,2)>5,0,33.49) -> 0 | FQ88: =IF(WEEKDAY(FQ$82,2)>5,0,28.98) -> 28.98 | FR88: =IF(WEEKDAY(FR$82,2)>5,0,27.72) -> 27.72 | FS88: =IF(WEEKDAY(FS$82,2)>5,0,29.7) -> 29.7 | FT88: =IF(WEEKDAY(FT$82,2)>5,0,26.59) -> 26.59 | FU88: =IF(WEEKDAY(FU$82,2)>5,0,33.86) -> 33.86 | FV88: =IF(WEEKDAY(FV$82,2)>5,0,33.77) -> 0 | FW88: =IF(WEEKDAY(FW$82,2)>5,0,26.38) -> 0 | FX88: =IF(WEEKDAY(FX$82,2)>5,0,32.61) -> 32.61 | FY88: =IF(WEEKDAY(FY$82,2)>5,0,30.36) -> 30.36 | FZ88: =IF(WEEKDAY(FZ$82,2)>5,0,30.76) -> 30.76 | GA88: =IF(WEEKDAY(GA$82,2)>5,0,32.25) -> 32.25 | GB88: =IF(WEEKDAY(GB$82,2)>5,0,30.03) -> 30.03 | GC88: =IF(WEEKDAY(GC$82,2)>5,0,29.26) -> 0 | GD88: =IF(WEEKDAY(GD$82,2)>5,0,33.65) -> 0 | GE88: =IF(WEEKDAY(GE$82,2)>5,0,28.64) -> 28.64 | GF88: =IF(WEEKDAY(GF$82,2)>5,0,26.88) -> 26.88 | GG88: =IF(WEEKDAY(GG$82,2)>5,0,27.03) -> 27.03 | GH88: =IF(WEEKDAY(GH$82,2)>5,0,28.27) -> 28.27 | GI88: =IF(WEEKDAY(GI$82,2)>5,0,30.56) -> 30.56 | GJ88: =IF(WEEKDAY(GJ$82,2)>5,0,33.49) -> 0 | GK88: =IF(WEEKDAY(GK$82,2)>5,0,26.61) -> 0 | GL88: =IF(WEEKDAY(GL$82,2)>5,0,30.98) -> 30.98 | GM88: =IF(WEEKDAY(GM$82,2)>5,0,32.78) -> 32.78 | GN88: =IF(WEEKDAY(GN$82,2)>5,0,31.76) -> 31.76 | GO88: =IF(WEEKDAY(GO$82,2)>5,0,29.69) -> 29.69 | GP88: =IF(WEEKDAY(GP$82,2)>5,0,25.53) -> 25.53 | GQ88: =IF(WEEKDAY(GQ$82,2)>5,0,32.9) -> 0 | GR88: =IF(WEEKDAY(GR$82,2)>5,0,33.4) -> 0 | GS88: =IF(WEEKDAY(GS$82,2)>5,0,29.42) -> 29.42 | GT88: =IF(WEEKDAY(GT$82,2)>5,0,25.63) -> 25.63 | GU88: =IF(WEEKDAY(GU$82,2)>5,0,30.58) -> 30.58 | GV88: =IF(WEEKDAY(GV$82,2)>5,0,26.67) -> 26.67 | GW88: =IF(WEEKDAY(GW$82,2)>5,0,26.09) -> 26.09 | GX88: =IF(WEEKDAY(GX$82,2)>5,0,32.61) -> 0 | GY88: =IF(WEEKDAY(GY$82,2)>5,0,31.17) -> 0 | GZ88: =IF(WEEKDAY(GZ$82,2)>5,0,30.29) -> 30.29 | HA88: =IF(WEEKDAY(HA$82,2)>5,0,30.66) -> 30.66 | HB88: =IF(WEEKDAY(HB$82,2)>5,0,31.89) -> 31.89 | HC88: =IF(WEEKDAY(HC$82,2)>5,0,26.67) -> 26.67 | HD88: =IF(WEEKDAY(HD$82,2)>5,0,26.64) -> 26.64 | HE88: =IF(WEEKDAY(HE$82,2)>5,0,31.53) -> 0 | HF88: =IF(WEEKDAY(HF$82,2)>5,0,26.59) -> 0 | HG88: =IF(WEEKDAY(HG$82,2)>5,0,31.36) -> 31.36 | HH88: =IF(WEEKDAY(HH$82,2)>5,0,29.37) -> 29.37 | HI88: =IF(WEEKDAY(HI$82,2)>5,0,28.26) -> 28.26 | HJ88: =IF(WEEKDAY(HJ$82,2)>5,0,27.7) -> 27.7 | HK88: =IF(WEEKDAY(HK$82,2)>5,0,27.15) -> 27.15 | HL88: =IF(WEEKDAY(HL$82,2)>5,0,31.21) -> 0 | HM88: =IF(WEEKDAY(HM$82,2)>5,0,30.96) -> 0 | HN88: =IF(WEEKDAY(HN$82,2)>5,0,28.91) -> 28.91 | HO88: =IF(WEEKDAY(HO$82,2)>5,0,28.72) -> 28.72 | HP88: =IF(WEEKDAY(HP$82,2)>5,0,27.41) -> 27.41 | HQ88: =IF(WEEKDAY(HQ$82,2)>5,0,32.72) -> 32.72 | HR88: =IF(WEEKDAY(HR$82,2)>5,0,25.96) -> 25.96 | HS88: =IF(WEEKDAY(HS$82,2)>5,0,26.82) -> 0 | HT88: =IF(WEEKDAY(HT$82,2)>5,0,27.76) -> 0 | HU88: =IF(WEEKDAY(HU$82,2)>5,0,27.58) -> 27.58 | HV88: =IF(WEEKDAY(HV$82,2)>5,0,31.26) -> 31.26 | HW88: =IF(WEEKDAY(HW$82,2)>5,0,29.94) -> 29.94 | HX88: =IF(WEEKDAY(HX$82,2)>5,0,30.8) -> 30.8 | HY88: =IF(WEEKDAY(HY$82,2)>5,0,33.3) -> 33.3 | HZ88: =IF(WEEKDAY(HZ$82,2)>5,0,32.41) -> 0 | IA88: =IF(WEEKDAY(IA$82,2)>5,0,30) -> 0 | IB88: =IF(WEEKDAY(IB$82,2)>5,0,30) -> 30 | IC88: =IF(WEEKDAY(IC$82,2)>5,0,33) -> 33 | ID88: =IF(WEEKDAY(ID$82,2)>5,0,26.11) -> 26.11 | IE88: =IF(WEEKDAY(IE$82,2)>5,0,27.36) -> 27.36 | IF88: =IF(WEEKDAY(IF$82,2)>5,0,31.49) -> 31.49 | IG88: =IF(WEEKDAY(IG$82,2)>5,0,26.98) -> 0 | IH88: =IF(WEEKDAY(IH$82,2)>5,0,32.81) -> 0 | II88: =IF(WEEKDAY(II$82,2)>5,0,28.29) -> 28.29 | IJ88: =IF(WEEKDAY(IJ$82,2)>5,0,30.46) -> 30.46 | IK88: =IF(WEEKDAY(IK$82,2)>5,0,29.93) -> 29.93 | IL88: =IF(WEEKDAY(IL$82,2)>5,0,31.17) -> 31.17
A89: Recebimento de Clientes | B89: =IF(WEEKDAY(B$82,2)>5,0,1914.15) -> 1914.15 | C89: =IF(WEEKDAY(C$82,2)>5,0,2038.34) -> 0 | D89: =IF(WEEKDAY(D$82,2)>5,0,2242.84) -> 0 | E89: =IF(WEEKDAY(E$82,2)>5,0,1917.6) -> 1917.6 | F89: =IF(WEEKDAY(F$82,2)>5,0,1790.81) -> 1790.81 | G89: =IF(WEEKDAY(G$82,2)>5,0,2014.72) -> 2014.72 | H89: =IF(WEEKDAY(H$82,2)>5,0,1888.69) -> 1888.69 | I89: =IF(WEEKDAY(I$82,2)>5,0,2183.39) -> 2183.39 | J89: =IF(WEEKDAY(J$82,2)>5,0,1736.92) -> 0 | K89: =IF(WEEKDAY(K$82,2)>5,0,1815.58) -> 0 | L89: =IF(WEEKDAY(L$82,2)>5,0,2191.06) -> 2191.06 | M89: =IF(WEEKDAY(M$82,2)>5,0,1781.59) -> 1781.59 | N89: =IF(WEEKDAY(N$82,2)>5,0,1868.56) -> 1868.56 | O89: =IF(WEEKDAY(O$82,2)>5,0,2109.72) -> 2109.72 | P89: =IF(WEEKDAY(P$82,2)>5,0,1917.66) -> 1917.66 | Q89: =IF(WEEKDAY(Q$82,2)>5,0,2136.02) -> 0 | R89: =IF(WEEKDAY(R$82,2)>5,0,2204.07) -> 0 | S89: =IF(WEEKDAY(S$82,2)>5,0,2149.18) -> 2149.18 | T89: =IF(WEEKDAY(T$82,2)>5,0,1923.45) -> 1923.45 | U89: =IF(WEEKDAY(U$82,2)>5,0,2266.75) -> 2266.75 | V89: =IF(WEEKDAY(V$82,2)>5,0,2170.92) -> 2170.92 | W89: =IF(WEEKDAY(W$82,2)>5,0,1989.79) -> 1989.79 | X89: =IF(WEEKDAY(X$82,2)>5,0,2237.91) -> 0 | Y89: =IF(WEEKDAY(Y$82,2)>5,0,2236.61) -> 0 | Z89: =IF(WEEKDAY(Z$82,2)>5,0,2222.68) -> 2222.68 | AA89: =IF(WEEKDAY(AA$82,2)>5,0,2145) -> 2145 | AB89: =IF(WEEKDAY(AB$82,2)>5,0,1829.95) -> 1829.95 | AC89: =IF(WEEKDAY(AC$82,2)>5,0,1986.07) -> 1986.07 | AD89: =IF(WEEKDAY(AD$82,2)>5,0,2094.36) -> 2094.36 | AE89: =IF(WEEKDAY(AE$82,2)>5,0,2220.82) -> 0 | AF89: =IF(WEEKDAY(AF$82,2)>5,0,2200.22) -> 0 | AG89: =IF(WEEKDAY(AG$82,2)>5,0,1825.64) -> 1825.64 | AH89: =IF(WEEKDAY(AH$82,2)>5,0,1996.72) -> 1996.72 | AI89: =IF(WEEKDAY(AI$82,2)>5,0,1721.41) -> 1721.41 | AJ89: =IF(WEEKDAY(AJ$82,2)>5,0,2113.55) -> 2113.55 | AK89: =IF(WEEKDAY(AK$82,2)>5,0,1819.05) -> 1819.05 | AL89: =IF(WEEKDAY(AL$82,2)>5,0,2044.72) -> 0 | AM89: =IF(WEEKDAY(AM$82,2)>5,0,1840.82) -> 0 | AN89: =IF(WEEKDAY(AN$82,2)>5,0,1924.82) -> 1924.82 | AO89: =IF(WEEKDAY(AO$82,2)>5,0,2081.79) -> 2081.79 | AP89: =IF(WEEKDAY(AP$82,2)>5,0,2028.4) -> 2028.4 | AQ89: =IF(WEEKDAY(AQ$82,2)>5,0,1815.4) -> 1815.4 | AR89: =IF(WEEKDAY(AR$82,2)>5,0,2105.5) -> 2105.5 | AS89: =IF(WEEKDAY(AS$82,2)>5,0,1715.71) -> 0 | AT89: =IF(WEEKDAY(AT$82,2)>5,0,2004.33) -> 0 | AU89: =IF(WEEKDAY(AU$82,2)>5,0,2093.93) -> 2093.93 | AV89: =IF(WEEKDAY(AV$82,2)>5,0,1815.79) -> 1815.79 | AW89: =IF(WEEKDAY(AW$82,2)>5,0,1971.68) -> 1971.68 | AX89: =IF(WEEKDAY(AX$82,2)>5,0,1971.9) -> 1971.9 | AY89: =IF(WEEKDAY(AY$82,2)>5,0,2106.19) -> 2106.19 | AZ89: =IF(WEEKDAY(AZ$82,2)>5,0,2262.74) -> 0 | BA89: =IF(WEEKDAY(BA$82,2)>5,0,1866.53) -> 0 | BB89: =IF(WEEKDAY(BB$82,2)>5,0,2106.31) -> 2106.31 | BC89: =IF(WEEKDAY(BC$82,2)>5,0,2023.58) -> 2023.58 | BD89: =IF(WEEKDAY(BD$82,2)>5,0,2213.24) -> 2213.24 | BE89: =IF(WEEKDAY(BE$82,2)>5,0,2032.55) -> 2032.55 | BF89: =IF(WEEKDAY(BF$82,2)>5,0,2298.69) -> 2298.69 | BG89: =IF(WEEKDAY(BG$82,2)>5,0,2012.66) -> 0 | BH89: =IF(WEEKDAY(BH$82,2)>5,0,2090.2) -> 0 | BI89: =IF(WEEKDAY(BI$82,2)>5,0,1880.88) -> 1880.88 | BJ89: =IF(WEEKDAY(BJ$82,2)>5,0,1826.78) -> 1826.78 | BK89: =IF(WEEKDAY(BK$82,2)>5,0,2272.05) -> 2272.05 | BL89: =IF(WEEKDAY(BL$82,2)>5,0,2155.55) -> 2155.55 | BM89: =IF(WEEKDAY(BM$82,2)>5,0,1709.41) -> 1709.41 | BN89: =IF(WEEKDAY(BN$82,2)>5,0,2236.06) -> 0 | BO89: =IF(WEEKDAY(BO$82,2)>5,0,1860.34) -> 0 | BP89: =IF(WEEKDAY(BP$82,2)>5,0,1750.31) -> 1750.31 | BQ89: =IF(WEEKDAY(BQ$82,2)>5,0,1775.16) -> 1775.16 | BR89: =IF(WEEKDAY(BR$82,2)>5,0,2280.75) -> 2280.75 | BS89: =IF(WEEKDAY(BS$82,2)>5,0,2251.15) -> 2251.15 | BT89: =IF(WEEKDAY(BT$82,2)>5,0,1854.58) -> 1854.58 | BU89: =IF(WEEKDAY(BU$82,2)>5,0,1860.59) -> 0 | BV89: =IF(WEEKDAY(BV$82,2)>5,0,1995.55) -> 0 | BW89: =IF(WEEKDAY(BW$82,2)>5,0,1781.76) -> 1781.76 | BX89: =IF(WEEKDAY(BX$82,2)>5,0,1732.32) -> 1732.32 | BY89: =IF(WEEKDAY(BY$82,2)>5,0,1906.66) -> 1906.66 | BZ89: =IF(WEEKDAY(BZ$82,2)>5,0,2233.37) -> 2233.37 | CA89: =IF(WEEKDAY(CA$82,2)>5,0,2183.65) -> 2183.65 | CB89: =IF(WEEKDAY(CB$82,2)>5,0,1761.21) -> 0 | CC89: =IF(WEEKDAY(CC$82,2)>5,0,2185.69) -> 0 | CD89: =IF(WEEKDAY(CD$82,2)>5,0,1988.31) -> 1988.31 | CE89: =IF(WEEKDAY(CE$82,2)>5,0,1705.5) -> 1705.5 | CF89: =IF(WEEKDAY(CF$82,2)>5,0,2061.66) -> 2061.66 | CG89: =IF(WEEKDAY(CG$82,2)>5,0,1915.84) -> 1915.84 | CH89: =IF(WEEKDAY(CH$82,2)>5,0,1779.02) -> 1779.02 | CI89: =IF(WEEKDAY(CI$82,2)>5,0,2282.29) -> 0 | CJ89: =IF(WEEKDAY(CJ$82,2)>5,0,2136.97) -> 0 | CK89: =IF(WEEKDAY(CK$82,2)>5,0,1843.13) -> 1843.13 | CL89: =IF(WEEKDAY(CL$82,2)>5,0,1946.07) -> 1946.07 | CM89: =IF(WEEKDAY(CM$82,2)>5,0,1966.13) -> 1966.13 | CN89: =IF(WEEKDAY(CN$82,2)>5,0,2127.47) -> 2127.47 | CO89: =IF(WEEKDAY(CO$82,2)>5,0,2051.35) -> 2051.35 | CP89: =IF(WEEKDAY(CP$82,2)>5,0,1988.71) -> 0 | CQ89: =IF(WEEKDAY(CQ$82,2)>5,0,2029.55) -> 0 | CR89: =IF(WEEKDAY(CR$82,2)>5,0,1750.39) -> 1750.39 | CS89: =IF(WEEKDAY(CS$82,2)>5,0,1871.62) -> 1871.62 | CT89: =IF(WEEKDAY(CT$82,2)>5,0,2280.84) -> 2280.84 | CU89: =IF(WEEKDAY(CU$82,2)>5,0,1872.41) -> 1872.41 | CV89: =IF(WEEKDAY(CV$82,2)>5,0,1797.67) -> 1797.67 | CW89: =IF(WEEKDAY(CW$82,2)>5,0,1805.39) -> 0 | CX89: =IF(WEEKDAY(CX$82,2)>5,0,2239.03) -> 0 | CY89: =IF(WEEKDAY(CY$82,2)>5,0,1874.04) -> 1874.04 | CZ89: =IF(WEEKDAY(CZ$82,2)>5,0,2084.4) -> 2084.4 | DA89: =IF(WEEKDAY(DA$82,2)>5,0,2193.31) -> 2193.31 | DB89: =IF(WEEKDAY(DB$82,2)>5,0,2188.59) -> 2188.59 | DC89: =IF(WEEKDAY(DC$82,2)>5,0,1945.28) -> 1945.28 | DD89: =IF(WEEKDAY(DD$82,2)>5,0,2046.28) -> 0 | DE89: =IF(WEEKDAY(DE$82,2)>5,0,1954.93) -> 0 | DF89: =IF(WEEKDAY(DF$82,2)>5,0,1981.2) -> 1981.2 | DG89: =IF(WEEKDAY(DG$82,2)>5,0,1749.43) -> 1749.43 | DH89: =IF(WEEKDAY(DH$82,2)>5,0,2039.14) -> 2039.14 | DI89: =IF(WEEKDAY(DI$82,2)>5,0,1878.73) -> 1878.73 | DJ89: =IF(WEEKDAY(DJ$82,2)>5,0,2164.08) -> 2164.08 | DK89: =IF(WEEKDAY(DK$82,2)>5,0,1742.64) -> 0 | DL89: =IF(WEEKDAY(DL$82,2)>5,0,2254.28) -> 0 | DM89: =IF(WEEKDAY(DM$82,2)>5,0,2131.68) -> 2131.68 | DN89: =IF(WEEKDAY(DN$82,2)>5,0,1751.62) -> 1751.62 | DO89: =IF(WEEKDAY(DO$82,2)>5,0,2159.39) -> 2159.39 | DP89: =IF(WEEKDAY(DP$82,2)>5,0,2027.1) -> 2027.1 | DQ89: =IF(WEEKDAY(DQ$82,2)>5,0,1718.43) -> 1718.43 | DR89: =IF(WEEKDAY(DR$82,2)>5,0,2173.49) -> 0 | DS89: =IF(WEEKDAY(DS$82,2)>5,0,2107.43) -> 0 | DT89: =IF(WEEKDAY(DT$82,2)>5,0,2040.71) -> 2040.71 | DU89: =IF(WEEKDAY(DU$82,2)>5,0,1875.65) -> 1875.65 | DV89: =IF(WEEKDAY(DV$82,2)>5,0,1954.81) -> 1954.81 | DW89: =IF(WEEKDAY(DW$82,2)>5,0,2104.49) -> 2104.49 | DX89: =IF(WEEKDAY(DX$82,2)>5,0,2124.58) -> 2124.58 | DY89: =IF(WEEKDAY(DY$82,2)>5,0,1748.05) -> 0 | DZ89: =IF(WEEKDAY(DZ$82,2)>5,0,2200.8) -> 0 | EA89: =IF(WEEKDAY(EA$82,2)>5,0,1938.45) -> 1938.45 | EB89: =IF(WEEKDAY(EB$82,2)>5,0,2073.31) -> 2073.31 | EC89: =IF(WEEKDAY(EC$82,2)>5,0,2039.17) -> 2039.17 | ED89: =IF(WEEKDAY(ED$82,2)>5,0,1807.46) -> 1807.46 | EE89: =IF(WEEKDAY(EE$82,2)>5,0,2281.52) -> 2281.52 | EF89: =IF(WEEKDAY(EF$82,2)>5,0,2046.98) -> 0 | EG89: =IF(WEEKDAY(EG$82,2)>5,0,2013.95) -> 0 | EH89: =IF(WEEKDAY(EH$82,2)>5,0,1948.91) -> 1948.91 | EI89: =IF(WEEKDAY(EI$82,2)>5,0,2059.38) -> 2059.38 | EJ89: =IF(WEEKDAY(EJ$82,2)>5,0,1944.92) -> 1944.92 | EK89: =IF(WEEKDAY(EK$82,2)>5,0,1914.86) -> 1914.86 | EL89: =IF(WEEKDAY(EL$82,2)>5,0,2087.56) -> 2087.56 | EM89: =IF(WEEKDAY(EM$82,2)>5,0,2092.76) -> 0 | EN89: =IF(WEEKDAY(EN$82,2)>5,0,1724.73) -> 0 | EO89: =IF(WEEKDAY(EO$82,2)>5,0,1993.43) -> 1993.43 | EP89: =IF(WEEKDAY(EP$82,2)>5,0,1975.08) -> 1975.08 | EQ89: =IF(WEEKDAY(EQ$82,2)>5,0,2121.11) -> 2121.11 | ER89: =IF(WEEKDAY(ER$82,2)>5,0,2217.68) -> 2217.68 | ES89: =IF(WEEKDAY(ES$82,2)>5,0,2128.33) -> 2128.33 | ET89: =IF(WEEKDAY(ET$82,2)>5,0,2257.04) -> 0 | EU89: =IF(WEEKDAY(EU$82,2)>5,0,2247.66) -> 0 | EV89: =IF(WEEKDAY(EV$82,2)>5,0,1981.92) -> 1981.92 | EW89: =IF(WEEKDAY(EW$82,2)>5,0,1822.85) -> 1822.85 | EX89: =IF(WEEKDAY(EX$82,2)>5,0,2292.13) -> 2292.13 | EY89: =IF(WEEKDAY(EY$82,2)>5,0,2250.57) -> 2250.57 | EZ89: =IF(WEEKDAY(EZ$82,2)>5,0,2251.67) -> 2251.67 | FA89: =IF(WEEKDAY(FA$82,2)>5,0,1847.58) -> 0 | FB89: =IF(WEEKDAY(FB$82,2)>5,0,1943.43) -> 0 | FC89: =IF(WEEKDAY(FC$82,2)>5,0,1998.51) -> 1998.51 | FD89: =IF(WEEKDAY(FD$82,2)>5,0,2269.31) -> 2269.31 | FE89: =IF(WEEKDAY(FE$82,2)>5,0,1981.17) -> 1981.17 | FF89: =IF(WEEKDAY(FF$82,2)>5,0,2084.55) -> 2084.55 | FG89: =IF(WEEKDAY(FG$82,2)>5,0,2149.38) -> 2149.38 | FH89: =IF(WEEKDAY(FH$82,2)>5,0,1737.42) -> 0 | FI89: =IF(WEEKDAY(FI$82,2)>5,0,2184.14) -> 0 | FJ89: =IF(WEEKDAY(FJ$82,2)>5,0,2042.63) -> 2042.63 | FK89: =IF(WEEKDAY(FK$82,2)>5,0,2136.44) -> 2136.44 | FL89: =IF(WEEKDAY(FL$82,2)>5,0,2235.26) -> 2235.26 | FM89: =IF(WEEKDAY(FM$82,2)>5,0,1912.84) -> 1912.84 | FN89: =IF(WEEKDAY(FN$82,2)>5,0,2240.02) -> 2240.02 | FO89: =IF(WEEKDAY(FO$82,2)>5,0,1943.06) -> 0 | FP89: =IF(WEEKDAY(FP$82,2)>5,0,2101.43) -> 0 | FQ89: =IF(WEEKDAY(FQ$82,2)>5,0,1924.1) -> 1924.1 | FR89: =IF(WEEKDAY(FR$82,2)>5,0,2073.16) -> 2073.16 | FS89: =IF(WEEKDAY(FS$82,2)>5,0,1818.92) -> 1818.92 | FT89: =IF(WEEKDAY(FT$82,2)>5,0,1971.22) -> 1971.22 | FU89: =IF(WEEKDAY(FU$82,2)>5,0,2287.16) -> 2287.16 | FV89: =IF(WEEKDAY(FV$82,2)>5,0,1738.07) -> 0 | FW89: =IF(WEEKDAY(FW$82,2)>5,0,2201.97) -> 0 | FX89: =IF(WEEKDAY(FX$82,2)>5,0,2182.17) -> 2182.17 | FY89: =IF(WEEKDAY(FY$82,2)>5,0,1760.89) -> 1760.89 | FZ89: =IF(WEEKDAY(FZ$82,2)>5,0,2215.81) -> 2215.81 | GA89: =IF(WEEKDAY(GA$82,2)>5,0,1908.12) -> 1908.12 | GB89: =IF(WEEKDAY(GB$82,2)>5,0,1760.72) -> 1760.72 | GC89: =IF(WEEKDAY(GC$82,2)>5,0,1931.68) -> 0 | GD89: =IF(WEEKDAY(GD$82,2)>5,0,1865.62) -> 0 | GE89: =IF(WEEKDAY(GE$82,2)>5,0,2095.63) -> 2095.63 | GF89: =IF(WEEKDAY(GF$82,2)>5,0,2177.9) -> 2177.9 | GG89: =IF(WEEKDAY(GG$82,2)>5,0,2149.99) -> 2149.99 | GH89: =IF(WEEKDAY(GH$82,2)>5,0,2174.69) -> 2174.69 | GI89: =IF(WEEKDAY(GI$82,2)>5,0,1996.44) -> 1996.44 | GJ89: =IF(WEEKDAY(GJ$82,2)>5,0,2209.68) -> 0 | GK89: =IF(WEEKDAY(GK$82,2)>5,0,2244.32) -> 0 | GL89: =IF(WEEKDAY(GL$82,2)>5,0,1728.17) -> 1728.17 | GM89: =IF(WEEKDAY(GM$82,2)>5,0,1944.55) -> 1944.55 | GN89: =IF(WEEKDAY(GN$82,2)>5,0,2059.81) -> 2059.81 | GO89: =IF(WEEKDAY(GO$82,2)>5,0,1942.42) -> 1942.42 | GP89: =IF(WEEKDAY(GP$82,2)>5,0,1955.3) -> 1955.3 | GQ89: =IF(WEEKDAY(GQ$82,2)>5,0,2215.37) -> 0 | GR89: =IF(WEEKDAY(GR$82,2)>5,0,2134.1) -> 0 | GS89: =IF(WEEKDAY(GS$82,2)>5,0,1933.49) -> 1933.49 | GT89: =IF(WEEKDAY(GT$82,2)>5,0,2181.61) -> 2181.61 | GU89: =IF(WEEKDAY(GU$82,2)>5,0,1948.11) -> 1948.11 | GV89: =IF(WEEKDAY(GV$82,2)>5,0,1864.68) -> 1864.68 | GW89: =IF(WEEKDAY(GW$82,2)>5,0,1742.44) -> 1742.44 | GX89: =IF(WEEKDAY(GX$82,2)>5,0,1730.92) -> 0 | GY89: =IF(WEEKDAY(GY$82,2)>5,0,1738.31) -> 0 | GZ89: =IF(WEEKDAY(GZ$82,2)>5,0,2083.89) -> 2083.89 | HA89: =IF(WEEKDAY(HA$82,2)>5,0,2179.89) -> 2179.89 | HB89: =IF(WEEKDAY(HB$82,2)>5,0,2036.92) -> 2036.92 | HC89: =IF(WEEKDAY(HC$82,2)>5,0,2128.7) -> 2128.7 | HD89: =IF(WEEKDAY(HD$82,2)>5,0,2022.93) -> 2022.93 | HE89: =IF(WEEKDAY(HE$82,2)>5,0,1885.23) -> 0 | HF89: =IF(WEEKDAY(HF$82,2)>5,0,1992.96) -> 0 | HG89: =IF(WEEKDAY(HG$82,2)>5,0,2039.61) -> 2039.61 | HH89: =IF(WEEKDAY(HH$82,2)>5,0,1790.4) -> 1790.4 | HI89: =IF(WEEKDAY(HI$82,2)>5,0,1875.09) -> 1875.09 | HJ89: =IF(WEEKDAY(HJ$82,2)>5,0,2071.84) -> 2071.84 | HK89: =IF(WEEKDAY(HK$82,2)>5,0,2238.54) -> 2238.54 | HL89: =IF(WEEKDAY(HL$82,2)>5,0,2106.94) -> 0 | HM89: =IF(WEEKDAY(HM$82,2)>5,0,2249.07) -> 0 | HN89: =IF(WEEKDAY(HN$82,2)>5,0,2198.11) -> 2198.11 | HO89: =IF(WEEKDAY(HO$82,2)>5,0,1748.47) -> 1748.47 | HP89: =IF(WEEKDAY(HP$82,2)>5,0,2242.67) -> 2242.67 | HQ89: =IF(WEEKDAY(HQ$82,2)>5,0,2299.18) -> 2299.18 | HR89: =IF(WEEKDAY(HR$82,2)>5,0,2295.49) -> 2295.49 | HS89: =IF(WEEKDAY(HS$82,2)>5,0,2168.97) -> 0 | HT89: =IF(WEEKDAY(HT$82,2)>5,0,1998.8) -> 0 | HU89: =IF(WEEKDAY(HU$82,2)>5,0,2268.14) -> 2268.14 | HV89: =IF(WEEKDAY(HV$82,2)>5,0,2192.11) -> 2192.11 | HW89: =IF(WEEKDAY(HW$82,2)>5,0,1845.8) -> 1845.8 | HX89: =IF(WEEKDAY(HX$82,2)>5,0,2033.19) -> 2033.19 | HY89: =IF(WEEKDAY(HY$82,2)>5,0,2292.48) -> 2292.48 | HZ89: =IF(WEEKDAY(HZ$82,2)>5,0,2092.79) -> 0 | IA89: =IF(WEEKDAY(IA$82,2)>5,0,1757.17) -> 0 | IB89: =IF(WEEKDAY(IB$82,2)>5,0,2073.03) -> 2073.03 | IC89: =IF(WEEKDAY(IC$82,2)>5,0,1738.36) -> 1738.36 | ID89: =IF(WEEKDAY(ID$82,2)>5,0,1746.06) -> 1746.06 | IE89: =IF(WEEKDAY(IE$82,2)>5,0,1799.94) -> 1799.94 | IF89: =IF(WEEKDAY(IF$82,2)>5,0,2251.9) -> 2251.9 | IG89: =IF(WEEKDAY(IG$82,2)>5,0,1813.39) -> 0 | IH89: =IF(WEEKDAY(IH$82,2)>5,0,1769.73) -> 0 | II89: =IF(WEEKDAY(II$82,2)>5,0,1958.11) -> 1958.11 | IJ89: =IF(WEEKDAY(IJ$82,2)>5,0,2075.47) -> 2075.47 | IK89: =IF(WEEKDAY(IK$82,2)>5,0,1798.7) -> 1798.7 | IL89: =IF(WEEKDAY(IL$82,2)>5,0,2243.85) -> 2243.85
A90: Vendas Online | B90: =IF(WEEKDAY(B$82,2)>5,0,571.01) -> 571.01 | C90: =IF(WEEKDAY(C$82,2)>5,0,615.17) -> 0 | D90: =IF(WEEKDAY(D$82,2)>5,0,670.57) -> 0 | E90: =IF(WEEKDAY(E$82,2)>5,0,641.29) -> 641.29 | F90: =IF(WEEKDAY(F$82,2)>5,0,561.18) -> 561.18 | G90: =IF(WEEKDAY(G$82,2)>5,0,649.58) -> 649.58 | H90: =IF(WEEKDAY(H$82,2)>5,0,610.54) -> 610.54 | I90: =IF(WEEKDAY(I$82,2)>5,0,605.08) -> 605.08 | J90: =IF(WEEKDAY(J$82,2)>5,0,555.83) -> 0 | K90: =IF(WEEKDAY(K$82,2)>5,0,606.46) -> 0 | L90: =IF(WEEKDAY(L$82,2)>5,0,544.23) -> 544.23 | M90: =IF(WEEKDAY(M$82,2)>5,0,530.37) -> 530.37 | N90: =IF(WEEKDAY(N$82,2)>5,0,687.47) -> 687.47 | O90: =IF(WEEKDAY(O$82,2)>5,0,652.39) -> 652.39 | P90: =IF(WEEKDAY(P$82,2)>5,0,544.26) -> 544.26 | Q90: =IF(WEEKDAY(Q$82,2)>5,0,661.32) -> 0 | R90: =IF(WEEKDAY(R$82,2)>5,0,663.81) -> 0 | S90: =IF(WEEKDAY(S$82,2)>5,0,597.65) -> 597.65 | T90: =IF(WEEKDAY(T$82,2)>5,0,510.62) -> 510.62 | U90: =IF(WEEKDAY(U$82,2)>5,0,642.94) -> 642.94 | V90: =IF(WEEKDAY(V$82,2)>5,0,533.77) -> 533.77 | W90: =IF(WEEKDAY(W$82,2)>5,0,580.12) -> 580.12 | X90: =IF(WEEKDAY(X$82,2)>5,0,528.17) -> 0 | Y90: =IF(WEEKDAY(Y$82,2)>5,0,578.46) -> 0 | Z90: =IF(WEEKDAY(Z$82,2)>5,0,536.43) -> 536.43 | AA90: =IF(WEEKDAY(AA$82,2)>5,0,536.72) -> 536.72 | AB90: =IF(WEEKDAY(AB$82,2)>5,0,573.17) -> 573.17 | AC90: =IF(WEEKDAY(AC$82,2)>5,0,560.72) -> 560.72 | AD90: =IF(WEEKDAY(AD$82,2)>5,0,608.39) -> 608.39 | AE90: =IF(WEEKDAY(AE$82,2)>5,0,557.08) -> 0 | AF90: =IF(WEEKDAY(AF$82,2)>5,0,673.95) -> 0 | AG90: =IF(WEEKDAY(AG$82,2)>5,0,680.26) -> 680.26 | AH90: =IF(WEEKDAY(AH$82,2)>5,0,628.49) -> 628.49 | AI90: =IF(WEEKDAY(AI$82,2)>5,0,511.63) -> 511.63 | AJ90: =IF(WEEKDAY(AJ$82,2)>5,0,629.55) -> 629.55 | AK90: =IF(WEEKDAY(AK$82,2)>5,0,685.37) -> 685.37 | AL90: =IF(WEEKDAY(AL$82,2)>5,0,684.51) -> 0 | AM90: =IF(WEEKDAY(AM$82,2)>5,0,538.27) -> 0 | AN90: =IF(WEEKDAY(AN$82,2)>5,0,671.19) -> 671.19 | AO90: =IF(WEEKDAY(AO$82,2)>5,0,678.54) -> 678.54 | AP90: =IF(WEEKDAY(AP$82,2)>5,0,689.29) -> 689.29 | AQ90: =IF(WEEKDAY(AQ$82,2)>5,0,516.18) -> 516.18 | AR90: =IF(WEEKDAY(AR$82,2)>5,0,624.09) -> 624.09 | AS90: =IF(WEEKDAY(AS$82,2)>5,0,591.18) -> 0 | AT90: =IF(WEEKDAY(AT$82,2)>5,0,675.64) -> 0 | AU90: =IF(WEEKDAY(AU$82,2)>5,0,561.4) -> 561.4 | AV90: =IF(WEEKDAY(AV$82,2)>5,0,682.31) -> 682.31 | AW90: =IF(WEEKDAY(AW$82,2)>5,0,577.37) -> 577.37 | AX90: =IF(WEEKDAY(AX$82,2)>5,0,584.3) -> 584.3 | AY90: =IF(WEEKDAY(AY$82,2)>5,0,520.99) -> 520.99 | AZ90: =IF(WEEKDAY(AZ$82,2)>5,0,511) -> 0 | BA90: =IF(WEEKDAY(BA$82,2)>5,0,649.18) -> 0 | BB90: =IF(WEEKDAY(BB$82,2)>5,0,662.94) -> 662.94 | BC90: =IF(WEEKDAY(BC$82,2)>5,0,619.04) -> 619.04 | BD90: =IF(WEEKDAY(BD$82,2)>5,0,629.87) -> 629.87 | BE90: =IF(WEEKDAY(BE$82,2)>5,0,521.01) -> 521.01 | BF90: =IF(WEEKDAY(BF$82,2)>5,0,514.13) -> 514.13 | BG90: =IF(WEEKDAY(BG$82,2)>5,0,574.63) -> 0 | BH90: =IF(WEEKDAY(BH$82,2)>5,0,624.15) -> 0 | BI90: =IF(WEEKDAY(BI$82,2)>5,0,595.92) -> 595.92 | BJ90: =IF(WEEKDAY(BJ$82,2)>5,0,537.34) -> 537.34 | BK90: =IF(WEEKDAY(BK$82,2)>5,0,574.57) -> 574.57 | BL90: =IF(WEEKDAY(BL$82,2)>5,0,586.15) -> 586.15 | BM90: =IF(WEEKDAY(BM$82,2)>5,0,521.44) -> 521.44 | BN90: =IF(WEEKDAY(BN$82,2)>5,0,677.81) -> 0 | BO90: =IF(WEEKDAY(BO$82,2)>5,0,644.55) -> 0 | BP90: =IF(WEEKDAY(BP$82,2)>5,0,623.52) -> 623.52 | BQ90: =IF(WEEKDAY(BQ$82,2)>5,0,540.54) -> 540.54 | BR90: =IF(WEEKDAY(BR$82,2)>5,0,635.15) -> 635.15 | BS90: =IF(WEEKDAY(BS$82,2)>5,0,599.04) -> 599.04 | BT90: =IF(WEEKDAY(BT$82,2)>5,0,648.55) -> 648.55 | BU90: =IF(WEEKDAY(BU$82,2)>5,0,671.13) -> 0 | BV90: =IF(WEEKDAY(BV$82,2)>5,0,684.07) -> 0 | BW90: =IF(WEEKDAY(BW$82,2)>5,0,644.5) -> 644.5 | BX90: =IF(WEEKDAY(BX$82,2)>5,0,535.64) -> 535.64 | BY90: =IF(WEEKDAY(BY$82,2)>5,0,585.4) -> 585.4 | BZ90: =IF(WEEKDAY(BZ$82,2)>5,0,651.82) -> 651.82 | CA90: =IF(WEEKDAY(CA$82,2)>5,0,594.07) -> 594.07 | CB90: =IF(WEEKDAY(CB$82,2)>5,0,590.01) -> 0 | CC90: =IF(WEEKDAY(CC$82,2)>5,0,608.59) -> 0 | CD90: =IF(WEEKDAY(CD$82,2)>5,0,640.06) -> 640.06 | CE90: =IF(WEEKDAY(CE$82,2)>5,0,656.1) -> 656.1 | CF90: =IF(WEEKDAY(CF$82,2)>5,0,665.22) -> 665.22 | CG90: =IF(WEEKDAY(CG$82,2)>5,0,565.11) -> 565.11 | CH90: =IF(WEEKDAY(CH$82,2)>5,0,596.17) -> 596.17 | CI90: =IF(WEEKDAY(CI$82,2)>5,0,641.25) -> 0 | CJ90: =IF(WEEKDAY(CJ$82,2)>5,0,639.6) -> 0 | CK90: =IF(WEEKDAY(CK$82,2)>5,0,511.09) -> 511.09 | CL90: =IF(WEEKDAY(CL$82,2)>5,0,579.91) -> 579.91 | CM90: =IF(WEEKDAY(CM$82,2)>5,0,647.51) -> 647.51 | CN90: =IF(WEEKDAY(CN$82,2)>5,0,650.12) -> 650.12 | CO90: =IF(WEEKDAY(CO$82,2)>5,0,572.67) -> 572.67 | CP90: =IF(WEEKDAY(CP$82,2)>5,0,526.97) -> 0 | CQ90: =IF(WEEKDAY(CQ$82,2)>5,0,558.13) -> 0 | CR90: =IF(WEEKDAY(CR$82,2)>5,0,599.49) -> 599.49 | CS90: =IF(WEEKDAY(CS$82,2)>5,0,515.79) -> 515.79 | CT90: =IF(WEEKDAY(CT$82,2)>5,0,573.35) -> 573.35 | CU90: =IF(WEEKDAY(CU$82,2)>5,0,684.22) -> 684.22 | CV90: =IF(WEEKDAY(CV$82,2)>5,0,636.02) -> 636.02 | CW90: =IF(WEEKDAY(CW$82,2)>5,0,581) -> 0 | CX90: =IF(WEEKDAY(CX$82,2)>5,0,537.8) -> 0 | CY90: =IF(WEEKDAY(CY$82,2)>5,0,556.17) -> 556.17 | CZ90: =IF(WEEKDAY(CZ$82,2)>5,0,511.28) -> 511.28 | DA90: =IF(WEEKDAY(DA$82,2)>5,0,553.51) -> 553.51 | DB90: =IF(WEEKDAY(DB$82,2)>5,0,689.11) -> 689.11 | DC90: =IF(WEEKDAY(DC$82,2)>5,0,626.52) -> 626.52 | DD90: =IF(WEEKDAY(DD$82,2)>5,0,605.37) -> 0 | DE90: =IF(WEEKDAY(DE$82,2)>5,0,674.68) -> 0 | DF90: =IF(WEEKDAY(DF$82,2)>5,0,587.81) -> 587.81 | DG90: =IF(WEEKDAY(DG$82,2)>5,0,585.22) -> 585.22 | DH90: =IF(WEEKDAY(DH$82,2)>5,0,551.82) -> 551.82 | DI90: =IF(WEEKDAY(DI$82,2)>5,0,686.05) -> 686.05 | DJ90: =IF(WEEKDAY(DJ$82,2)>5,0,604.81) -> 604.81 | DK90: =IF(WEEKDAY(DK$82,2)>5,0,549.28) -> 0 | DL90: =IF(WEEKDAY(DL$82,2)>5,0,563.17) -> 0 | DM90: =IF(WEEKDAY(DM$82,2)>5,0,676.68) -> 676.68 | DN90: =IF(WEEKDAY(DN$82,2)>5,0,551.9) -> 551.9 | DO90: =IF(WEEKDAY(DO$82,2)>5,0,579.92) -> 579.92 | DP90: =IF(WEEKDAY(DP$82,2)>5,0,643.86) -> 643.86 | DQ90: =IF(WEEKDAY(DQ$82,2)>5,0,526.71) -> 526.71 | DR90: =IF(WEEKDAY(DR$82,2)>5,0,570.73) -> 0 | DS90: =IF(WEEKDAY(DS$82,2)>5,0,590.8) -> 0 | DT90: =IF(WEEKDAY(DT$82,2)>5,0,525.58) -> 525.58 | DU90: =IF(WEEKDAY(DU$82,2)>5,0,620.81) -> 620.81 | DV90: =IF(WEEKDAY(DV$82,2)>5,0,656.33) -> 656.33 | DW90: =IF(WEEKDAY(DW$82,2)>5,0,672.47) -> 672.47 | DX90: =IF(WEEKDAY(DX$82,2)>5,0,598.5) -> 598.5 | DY90: =IF(WEEKDAY(DY$82,2)>5,0,677.17) -> 0 | DZ90: =IF(WEEKDAY(DZ$82,2)>5,0,640.42) -> 0 | EA90: =IF(WEEKDAY(EA$82,2)>5,0,527.37) -> 527.37 | EB90: =IF(WEEKDAY(EB$82,2)>5,0,580.49) -> 580.49 | EC90: =IF(WEEKDAY(EC$82,2)>5,0,549.53) -> 549.53 | ED90: =IF(WEEKDAY(ED$82,2)>5,0,558.81) -> 558.81 | EE90: =IF(WEEKDAY(EE$82,2)>5,0,525.96) -> 525.96 | EF90: =IF(WEEKDAY(EF$82,2)>5,0,597.69) -> 0 | EG90: =IF(WEEKDAY(EG$82,2)>5,0,576.86) -> 0 | EH90: =IF(WEEKDAY(EH$82,2)>5,0,527.76) -> 527.76 | EI90: =IF(WEEKDAY(EI$82,2)>5,0,603.81) -> 603.81 | EJ90: =IF(WEEKDAY(EJ$82,2)>5,0,551.26) -> 551.26 | EK90: =IF(WEEKDAY(EK$82,2)>5,0,659.31) -> 659.31 | EL90: =IF(WEEKDAY(EL$82,2)>5,0,602.84) -> 602.84 | EM90: =IF(WEEKDAY(EM$82,2)>5,0,653.69) -> 0 | EN90: =IF(WEEKDAY(EN$82,2)>5,0,541.04) -> 0 | EO90: =IF(WEEKDAY(EO$82,2)>5,0,580.73) -> 580.73 | EP90: =IF(WEEKDAY(EP$82,2)>5,0,627.88) -> 627.88 | EQ90: =IF(WEEKDAY(EQ$82,2)>5,0,648.98) -> 648.98 | ER90: =IF(WEEKDAY(ER$82,2)>5,0,564.21) -> 564.21 | ES90: =IF(WEEKDAY(ES$82,2)>5,0,580.84) -> 580.84 | ET90: =IF(WEEKDAY(ET$82,2)>5,0,654.57) -> 0 | EU90: =IF(WEEKDAY(EU$82,2)>5,0,611.82) -> 0 | EV90: =IF(WEEKDAY(EV$82,2)>5,0,533.71) -> 533.71 | EW90: =IF(WEEKDAY(EW$82,2)>5,0,653.46) -> 653.46 | EX90: =IF(WEEKDAY(EX$82,2)>5,0,547.63) -> 547.63 | EY90: =IF(WEEKDAY(EY$82,2)>5,0,515.18) -> 515.18 | EZ90: =IF(WEEKDAY(EZ$82,2)>5,0,569.49) -> 569.49 | FA90: =IF(WEEKDAY(FA$82,2)>5,0,561.49) -> 0 | FB90: =IF(WEEKDAY(FB$82,2)>5,0,614.02) -> 0 | FC90: =IF(WEEKDAY(FC$82,2)>5,0,546.14) -> 546.14 | FD90: =IF(WEEKDAY(FD$82,2)>5,0,593.9) -> 593.9 | FE90: =IF(WEEKDAY(FE$82,2)>5,0,616.68) -> 616.68 | FF90: =IF(WEEKDAY(FF$82,2)>5,0,605.62) -> 605.62 | FG90: =IF(WEEKDAY(FG$82,2)>5,0,520.19) -> 520.19 | FH90: =IF(WEEKDAY(FH$82,2)>5,0,568.29) -> 0 | FI90: =IF(WEEKDAY(FI$82,2)>5,0,561.72) -> 0 | FJ90: =IF(WEEKDAY(FJ$82,2)>5,0,618.43) -> 618.43 | FK90: =IF(WEEKDAY(FK$82,2)>5,0,658.54) -> 658.54 | FL90: =IF(WEEKDAY(FL$82,2)>5,0,644.36) -> 644.36 | FM90: =IF(WEEKDAY(FM$82,2)>5,0,675.99) -> 675.99 | FN90: =IF(WEEKDAY(FN$82,2)>5,0,523.6) -> 523.6 | FO90: =IF(WEEKDAY(FO$82,2)>5,0,615.79) -> 0 | FP90: =IF(WEEKDAY(FP$82,2)>5,0,640.53) -> 0 | FQ90: =IF(WEEKDAY(FQ$82,2)>5,0,529.7) -> 529.7 | FR90: =IF(WEEKDAY(FR$82,2)>5,0,650.11) -> 650.11 | FS90: =IF(WEEKDAY(FS$82,2)>5,0,526.45) -> 526.45 | FT90: =IF(WEEKDAY(FT$82,2)>5,0,674.22) -> 674.22 | FU90: =IF(WEEKDAY(FU$82,2)>5,0,649.52) -> 649.52 | FV90: =IF(WEEKDAY(FV$82,2)>5,0,529.13) -> 0 | FW90: =IF(WEEKDAY(FW$82,2)>5,0,568.05) -> 0 | FX90: =IF(WEEKDAY(FX$82,2)>5,0,523.14) -> 523.14 | FY90: =IF(WEEKDAY(FY$82,2)>5,0,653.85) -> 653.85 | FZ90: =IF(WEEKDAY(FZ$82,2)>5,0,539.99) -> 539.99 | GA90: =IF(WEEKDAY(GA$82,2)>5,0,566.78) -> 566.78 | GB90: =IF(WEEKDAY(GB$82,2)>5,0,627.52) -> 627.52 | GC90: =IF(WEEKDAY(GC$82,2)>5,0,582.64) -> 0 | GD90: =IF(WEEKDAY(GD$82,2)>5,0,598.16) -> 0 | GE90: =IF(WEEKDAY(GE$82,2)>5,0,633.2) -> 633.2 | GF90: =IF(WEEKDAY(GF$82,2)>5,0,600.84) -> 600.84 | GG90: =IF(WEEKDAY(GG$82,2)>5,0,659.51) -> 659.51 | GH90: =IF(WEEKDAY(GH$82,2)>5,0,582.94) -> 582.94 | GI90: =IF(WEEKDAY(GI$82,2)>5,0,680.74) -> 680.74 | GJ90: =IF(WEEKDAY(GJ$82,2)>5,0,556.23) -> 0 | GK90: =IF(WEEKDAY(GK$82,2)>5,0,595.5) -> 0 | GL90: =IF(WEEKDAY(GL$82,2)>5,0,555.24) -> 555.24 | GM90: =IF(WEEKDAY(GM$82,2)>5,0,622.51) -> 622.51 | GN90: =IF(WEEKDAY(GN$82,2)>5,0,645.55) -> 645.55 | GO90: =IF(WEEKDAY(GO$82,2)>5,0,534.86) -> 534.86 | GP90: =IF(WEEKDAY(GP$82,2)>5,0,516.03) -> 516.03 | GQ90: =IF(WEEKDAY(GQ$82,2)>5,0,659.12) -> 0 | GR90: =IF(WEEKDAY(GR$82,2)>5,0,590.22) -> 0 | GS90: =IF(WEEKDAY(GS$82,2)>5,0,552.81) -> 552.81 | GT90: =IF(WEEKDAY(GT$82,2)>5,0,578.22) -> 578.22 | GU90: =IF(WEEKDAY(GU$82,2)>5,0,521.27) -> 521.27 | GV90: =IF(WEEKDAY(GV$82,2)>5,0,599.94) -> 599.94 | GW90: =IF(WEEKDAY(GW$82,2)>5,0,686.14) -> 686.14 | GX90: =IF(WEEKDAY(GX$82,2)>5,0,675.54) -> 0 | GY90: =IF(WEEKDAY(GY$82,2)>5,0,633.3) -> 0 | GZ90: =IF(WEEKDAY(GZ$82,2)>5,0,628.42) -> 628.42 | HA90: =IF(WEEKDAY(HA$82,2)>5,0,636.93) -> 636.93 | HB90: =IF(WEEKDAY(HB$82,2)>5,0,650.39) -> 650.39 | HC90: =IF(WEEKDAY(HC$82,2)>5,0,529.42) -> 529.42 | HD90: =IF(WEEKDAY(HD$82,2)>5,0,656.74) -> 656.74 | HE90: =IF(WEEKDAY(HE$82,2)>5,0,537.93) -> 0 | HF90: =IF(WEEKDAY(HF$82,2)>5,0,559.86) -> 0 | HG90: =IF(WEEKDAY(HG$82,2)>5,0,670.98) -> 670.98 | HH90: =IF(WEEKDAY(HH$82,2)>5,0,535.69) -> 535.69 | HI90: =IF(WEEKDAY(HI$82,2)>5,0,620.68) -> 620.68 | HJ90: =IF(WEEKDAY(HJ$82,2)>5,0,517.75) -> 517.75 | HK90: =IF(WEEKDAY(HK$82,2)>5,0,615.31) -> 615.31 | HL90: =IF(WEEKDAY(HL$82,2)>5,0,525.01) -> 0 | HM90: =IF(WEEKDAY(HM$82,2)>5,0,541.98) -> 0 | HN90: =IF(WEEKDAY(HN$82,2)>5,0,642.63) -> 642.63 | HO90: =IF(WEEKDAY(HO$82,2)>5,0,521) -> 521 | HP90: =IF(WEEKDAY(HP$82,2)>5,0,661.5) -> 661.5 | HQ90: =IF(WEEKDAY(HQ$82,2)>5,0,596.33) -> 596.33 | HR90: =IF(WEEKDAY(HR$82,2)>5,0,644.62) -> 644.62 | HS90: =IF(WEEKDAY(HS$82,2)>5,0,565.14) -> 0 | HT90: =IF(WEEKDAY(HT$82,2)>5,0,574.92) -> 0 | HU90: =IF(WEEKDAY(HU$82,2)>5,0,632) -> 632 | HV90: =IF(WEEKDAY(HV$82,2)>5,0,645.67) -> 645.67 | HW90: =IF(WEEKDAY(HW$82,2)>5,0,664.94) -> 664.94 | HX90: =IF(WEEKDAY(HX$82,2)>5,0,534.15) -> 534.15 | HY90: =IF(WEEKDAY(HY$82,2)>5,0,678.49) -> 678.49 | HZ90: =IF(WEEKDAY(HZ$82,2)>5,0,601.57) -> 0 | IA90: =IF(WEEKDAY(IA$82,2)>5,0,574.24) -> 0 | IB90: =IF(WEEKDAY(IB$82,2)>5,0,653.81) -> 653.81 | IC90: =IF(WEEKDAY(IC$82,2)>5,0,623.42) -> 623.42 | ID90: =IF(WEEKDAY(ID$82,2)>5,0,580.42) -> 580.42 | IE90: =IF(WEEKDAY(IE$82,2)>5,0,599.98) -> 599.98 | IF90: =IF(WEEKDAY(IF$82,2)>5,0,570.28) -> 570.28 | IG90: =IF(WEEKDAY(IG$82,2)>5,0,530.86) -> 0 | IH90: =IF(WEEKDAY(IH$82,2)>5,0,625.7) -> 0 | II90: =IF(WEEKDAY(II$82,2)>5,0,689.08) -> 689.08 | IJ90: =IF(WEEKDAY(IJ$82,2)>5,0,529.33) -> 529.33 | IK90: =IF(WEEKDAY(IK$82,2)>5,0,628.34) -> 628.34 | IL90: =IF(WEEKDAY(IL$82,2)>5,0,650.78) -> 650.78
A91: Comissões Recebidas | B91: =IF(WEEKDAY(B$82,2)>5,0,94.54) -> 94.54 | C91: =IF(WEEKDAY(C$82,2)>5,0,114.97) -> 0 | D91: =IF(WEEKDAY(D$82,2)>5,0,96.66) -> 0 | E91: =IF(WEEKDAY(E$82,2)>5,0,102.7) -> 102.7 | F91: =IF(WEEKDAY(F$82,2)>5,0,98.86) -> 98.86 | G91: =IF(WEEKDAY(G$82,2)>5,0,96.78) -> 96.78 | H91: =IF(WEEKDAY(H$82,2)>5,0,99.65) -> 99.65 | I91: =IF(WEEKDAY(I$82,2)>5,0,87.21) -> 87.21 | J91: =IF(WEEKDAY(J$82,2)>5,0,110.39) -> 0 | K91: =IF(WEEKDAY(K$82,2)>5,0,87.72) -> 0 | L91: =IF(WEEKDAY(L$82,2)>5,0,103.94) -> 103.94 | M91: =IF(WEEKDAY(M$82,2)>5,0,91.65) -> 91.65 | N91: =IF(WEEKDAY(N$82,2)>5,0,114.53) -> 114.53 | O91: =IF(WEEKDAY(O$82,2)>5,0,114.04) -> 114.04 | P91: =IF(WEEKDAY(P$82,2)>5,0,112.31) -> 112.31 | Q91: =IF(WEEKDAY(Q$82,2)>5,0,111.33) -> 0 | R91: =IF(WEEKDAY(R$82,2)>5,0,112.03) -> 0 | S91: =IF(WEEKDAY(S$82,2)>5,0,103.09) -> 103.09 | T91: =IF(WEEKDAY(T$82,2)>5,0,110.09) -> 110.09 | U91: =IF(WEEKDAY(U$82,2)>5,0,110.16) -> 110.16 | V91: =IF(WEEKDAY(V$82,2)>5,0,85.98) -> 85.98 | W91: =IF(WEEKDAY(W$82,2)>5,0,96.32) -> 96.32 | X91: =IF(WEEKDAY(X$82,2)>5,0,110.84) -> 0 | Y91: =IF(WEEKDAY(Y$82,2)>5,0,104.09) -> 0 | Z91: =IF(WEEKDAY(Z$82,2)>5,0,102.29) -> 102.29 | AA91: =IF(WEEKDAY(AA$82,2)>5,0,113.12) -> 113.12 | AB91: =IF(WEEKDAY(AB$82,2)>5,0,89.06) -> 89.06 | AC91: =IF(WEEKDAY(AC$82,2)>5,0,100.17) -> 100.17 | AD91: =IF(WEEKDAY(AD$82,2)>5,0,112.35) -> 112.35 | AE91: =IF(WEEKDAY(AE$82,2)>5,0,91.59) -> 0 | AF91: =IF(WEEKDAY(AF$82,2)>5,0,96.82) -> 0 | AG91: =IF(WEEKDAY(AG$82,2)>5,0,113.29) -> 113.29 | AH91: =IF(WEEKDAY(AH$82,2)>5,0,90.84) -> 90.84 | AI91: =IF(WEEKDAY(AI$82,2)>5,0,86.45) -> 86.45 | AJ91: =IF(WEEKDAY(AJ$82,2)>5,0,101.3) -> 101.3 | AK91: =IF(WEEKDAY(AK$82,2)>5,0,87.68) -> 87.68 | AL91: =IF(WEEKDAY(AL$82,2)>5,0,86.3) -> 0 | AM91: =IF(WEEKDAY(AM$82,2)>5,0,111.78) -> 0 | AN91: =IF(WEEKDAY(AN$82,2)>5,0,90.6) -> 90.6 | AO91: =IF(WEEKDAY(AO$82,2)>5,0,95.81) -> 95.81 | AP91: =IF(WEEKDAY(AP$82,2)>5,0,96.07) -> 96.07 | AQ91: =IF(WEEKDAY(AQ$82,2)>5,0,89.13) -> 89.13 | AR91: =IF(WEEKDAY(AR$82,2)>5,0,101.7) -> 101.7 | AS91: =IF(WEEKDAY(AS$82,2)>5,0,114.63) -> 0 | AT91: =IF(WEEKDAY(AT$82,2)>5,0,99.81) -> 0 | AU91: =IF(WEEKDAY(AU$82,2)>5,0,96.45) -> 96.45 | AV91: =IF(WEEKDAY(AV$82,2)>5,0,91.97) -> 91.97 | AW91: =IF(WEEKDAY(AW$82,2)>5,0,100.83) -> 100.83 | AX91: =IF(WEEKDAY(AX$82,2)>5,0,98.53) -> 98.53 | AY91: =IF(WEEKDAY(AY$82,2)>5,0,97.3) -> 97.3 | AZ91: =IF(WEEKDAY(AZ$82,2)>5,0,88.65) -> 0 | BA91: =IF(WEEKDAY(BA$82,2)>5,0,102.93) -> 0 | BB91: =IF(WEEKDAY(BB$82,2)>5,0,106.71) -> 106.71 | BC91: =IF(WEEKDAY(BC$82,2)>5,0,104) -> 104 | BD91: =IF(WEEKDAY(BD$82,2)>5,0,111.24) -> 111.24 | BE91: =IF(WEEKDAY(BE$82,2)>5,0,95.64) -> 95.64 | BF91: =IF(WEEKDAY(BF$82,2)>5,0,106.72) -> 106.72 | BG91: =IF(WEEKDAY(BG$82,2)>5,0,87.76) -> 0 | BH91: =IF(WEEKDAY(BH$82,2)>5,0,105.47) -> 0 | BI91: =IF(WEEKDAY(BI$82,2)>5,0,96.76) -> 96.76 | BJ91: =IF(WEEKDAY(BJ$82,2)>5,0,106.7) -> 106.7 | BK91: =IF(WEEKDAY(BK$82,2)>5,0,110.61) -> 110.61 | BL91: =IF(WEEKDAY(BL$82,2)>5,0,85.61) -> 85.61 | BM91: =IF(WEEKDAY(BM$82,2)>5,0,110.42) -> 110.42 | BN91: =IF(WEEKDAY(BN$82,2)>5,0,98.71) -> 0 | BO91: =IF(WEEKDAY(BO$82,2)>5,0,97.93) -> 0 | BP91: =IF(WEEKDAY(BP$82,2)>5,0,106.52) -> 106.52 | BQ91: =IF(WEEKDAY(BQ$82,2)>5,0,114.39) -> 114.39 | BR91: =IF(WEEKDAY(BR$82,2)>5,0,99.58) -> 99.58 | BS91: =IF(WEEKDAY(BS$82,2)>5,0,103.86) -> 103.86 | BT91: =IF(WEEKDAY(BT$82,2)>5,0,98.19) -> 98.19 | BU91: =IF(WEEKDAY(BU$82,2)>5,0,111.62) -> 0 | BV91: =IF(WEEKDAY(BV$82,2)>5,0,89.72) -> 0 | BW91: =IF(WEEKDAY(BW$82,2)>5,0,112.4) -> 112.4 | BX91: =IF(WEEKDAY(BX$82,2)>5,0,107.26) -> 107.26 | BY91: =IF(WEEKDAY(BY$82,2)>5,0,106.21) -> 106.21 | BZ91: =IF(WEEKDAY(BZ$82,2)>5,0,109.74) -> 109.74 | CA91: =IF(WEEKDAY(CA$82,2)>5,0,86.08) -> 86.08 | CB91: =IF(WEEKDAY(CB$82,2)>5,0,101.44) -> 0 | CC91: =IF(WEEKDAY(CC$82,2)>5,0,88.95) -> 0 | CD91: =IF(WEEKDAY(CD$82,2)>5,0,103.2) -> 103.2 | CE91: =IF(WEEKDAY(CE$82,2)>5,0,90.15) -> 90.15 | CF91: =IF(WEEKDAY(CF$82,2)>5,0,100.96) -> 100.96 | CG91: =IF(WEEKDAY(CG$82,2)>5,0,92.79) -> 92.79 | CH91: =IF(WEEKDAY(CH$82,2)>5,0,98.86) -> 98.86 | CI91: =IF(WEEKDAY(CI$82,2)>5,0,108.9) -> 0 | CJ91: =IF(WEEKDAY(CJ$82,2)>5,0,114.64) -> 0 | CK91: =IF(WEEKDAY(CK$82,2)>5,0,109.5) -> 109.5 | CL91: =IF(WEEKDAY(CL$82,2)>5,0,96.21) -> 96.21 | CM91: =IF(WEEKDAY(CM$82,2)>5,0,106.43) -> 106.43 | CN91: =IF(WEEKDAY(CN$82,2)>5,0,113.16) -> 113.16 | CO91: =IF(WEEKDAY(CO$82,2)>5,0,94.76) -> 94.76 | CP91: =IF(WEEKDAY(CP$82,2)>5,0,87.67) -> 0 | CQ91: =IF(WEEKDAY(CQ$82,2)>5,0,86.53) -> 0 | CR91: =IF(WEEKDAY(CR$82,2)>5,0,86.2) -> 86.2 | CS91: =IF(WEEKDAY(CS$82,2)>5,0,100.77) -> 100.77 | CT91: =IF(WEEKDAY(CT$82,2)>5,0,99.35) -> 99.35 | CU91: =IF(WEEKDAY(CU$82,2)>5,0,85.75) -> 85.75 | CV91: =IF(WEEKDAY(CV$82,2)>5,0,102.15) -> 102.15 | CW91: =IF(WEEKDAY(CW$82,2)>5,0,86.93) -> 0 | CX91: =IF(WEEKDAY(CX$82,2)>5,0,86.57) -> 0 | CY91: =IF(WEEKDAY(CY$82,2)>5,0,88.64) -> 88.64 | CZ91: =IF(WEEKDAY(CZ$82,2)>5,0,105.02) -> 105.02 | DA91: =IF(WEEKDAY(DA$82,2)>5,0,111.62) -> 111.62 | DB91: =IF(WEEKDAY(DB$82,2)>5,0,108.99) -> 108.99 | DC91: =IF(WEEKDAY(DC$82,2)>5,0,111.45) -> 111.45 | DD91: =IF(WEEKDAY(DD$82,2)>5,0,113.85) -> 0 | DE91: =IF(WEEKDAY(DE$82,2)>5,0,94.26) -> 0 | DF91: =IF(WEEKDAY(DF$82,2)>5,0,98.04) -> 98.04 | DG91: =IF(WEEKDAY(DG$82,2)>5,0,113.05) -> 113.05 | DH91: =IF(WEEKDAY(DH$82,2)>5,0,107.67) -> 107.67 | DI91: =IF(WEEKDAY(DI$82,2)>5,0,106.65) -> 106.65 | DJ91: =IF(WEEKDAY(DJ$82,2)>5,0,97.4) -> 97.4 | DK91: =IF(WEEKDAY(DK$82,2)>5,0,106.44) -> 0 | DL91: =IF(WEEKDAY(DL$82,2)>5,0,98.67) -> 0 | DM91: =IF(WEEKDAY(DM$82,2)>5,0,113.62) -> 113.62 | DN91: =IF(WEEKDAY(DN$82,2)>5,0,97.76) -> 97.76 | DO91: =IF(WEEKDAY(DO$82,2)>5,0,94.86) -> 94.86 | DP91: =IF(WEEKDAY(DP$82,2)>5,0,91.97) -> 91.97 | DQ91: =IF(WEEKDAY(DQ$82,2)>5,0,102.31) -> 102.31 | DR91: =IF(WEEKDAY(DR$82,2)>5,0,104.63) -> 0 | DS91: =IF(WEEKDAY(DS$82,2)>5,0,104.21) -> 0 | DT91: =IF(WEEKDAY(DT$82,2)>5,0,90.87) -> 90.87 | DU91: =IF(WEEKDAY(DU$82,2)>5,0,97.15) -> 97.15 | DV91: =IF(WEEKDAY(DV$82,2)>5,0,113.89) -> 113.89 | DW91: =IF(WEEKDAY(DW$82,2)>5,0,94.76) -> 94.76 | DX91: =IF(WEEKDAY(DX$82,2)>5,0,103.24) -> 103.24 | DY91: =IF(WEEKDAY(DY$82,2)>5,0,90.34) -> 0 | DZ91: =IF(WEEKDAY(DZ$82,2)>5,0,91.98) -> 0 | EA91: =IF(WEEKDAY(EA$82,2)>5,0,110.84) -> 110.84 | EB91: =IF(WEEKDAY(EB$82,2)>5,0,94.9) -> 94.9 | EC91: =IF(WEEKDAY(EC$82,2)>5,0,85.01) -> 85.01 | ED91: =IF(WEEKDAY(ED$82,2)>5,0,109.02) -> 109.02 | EE91: =IF(WEEKDAY(EE$82,2)>5,0,89.2) -> 89.2 | EF91: =IF(WEEKDAY(EF$82,2)>5,0,110.4) -> 0 | EG91: =IF(WEEKDAY(EG$82,2)>5,0,103.68) -> 0 | EH91: =IF(WEEKDAY(EH$82,2)>5,0,105.54) -> 105.54 | EI91: =IF(WEEKDAY(EI$82,2)>5,0,104.65) -> 104.65 | EJ91: =IF(WEEKDAY(EJ$82,2)>5,0,96.13) -> 96.13 | EK91: =IF(WEEKDAY(EK$82,2)>5,0,92.55) -> 92.55 | EL91: =IF(WEEKDAY(EL$82,2)>5,0,103.04) -> 103.04 | EM91: =IF(WEEKDAY(EM$82,2)>5,0,104.23) -> 0 | EN91: =IF(WEEKDAY(EN$82,2)>5,0,97.92) -> 0 | EO91: =IF(WEEKDAY(EO$82,2)>5,0,104.01) -> 104.01 | EP91: =IF(WEEKDAY(EP$82,2)>5,0,102.44) -> 102.44 | EQ91: =IF(WEEKDAY(EQ$82,2)>5,0,113.47) -> 113.47 | ER91: =IF(WEEKDAY(ER$82,2)>5,0,96.05) -> 96.05 | ES91: =IF(WEEKDAY(ES$82,2)>5,0,101.39) -> 101.39 | ET91: =IF(WEEKDAY(ET$82,2)>5,0,106.92) -> 0 | EU91: =IF(WEEKDAY(EU$82,2)>5,0,109.51) -> 0 | EV91: =IF(WEEKDAY(EV$82,2)>5,0,112.56) -> 112.56 | EW91: =IF(WEEKDAY(EW$82,2)>5,0,94.92) -> 94.92 | EX91: =IF(WEEKDAY(EX$82,2)>5,0,111.41) -> 111.41 | EY91: =IF(WEEKDAY(EY$82,2)>5,0,86.23) -> 86.23 | EZ91: =IF(WEEKDAY(EZ$82,2)>5,0,88.76) -> 88.76 | FA91: =IF(WEEKDAY(FA$82,2)>5,0,86.89) -> 0 | FB91: =IF(WEEKDAY(FB$82,2)>5,0,97.58) -> 0 | FC91: =IF(WEEKDAY(FC$82,2)>5,0,88.34) -> 88.34 | FD91: =IF(WEEKDAY(FD$82,2)>5,0,100.62) -> 100.62 | FE91: =IF(WEEKDAY(FE$82,2)>5,0,98.55) -> 98.55 | FF91: =IF(WEEKDAY(FF$82,2)>5,0,113.6) -> 113.6 | FG91: =IF(WEEKDAY(FG$82,2)>5,0,99.69) -> 99.69 | FH91: =IF(WEEKDAY(FH$82,2)>5,0,107.12) -> 0 | FI91: =IF(WEEKDAY(FI$82,2)>5,0,99.98) -> 0 | FJ91: =IF(WEEKDAY(FJ$82,2)>5,0,114) -> 114 | FK91: =IF(WEEKDAY(FK$82,2)>5,0,109.97) -> 109.97 | FL91: =IF(WEEKDAY(FL$82,2)>5,0,99.19) -> 99.19 | FM91: =IF(WEEKDAY(FM$82,2)>5,0,88.26) -> 88.26 | FN91: =IF(WEEKDAY(FN$82,2)>5,0,106.66) -> 106.66 | FO91: =IF(WEEKDAY(FO$82,2)>5,0,85.3) -> 0 | FP91: =IF(WEEKDAY(FP$82,2)>5,0,103.34) -> 0 | FQ91: =IF(WEEKDAY(FQ$82,2)>5,0,88.82) -> 88.82 | FR91: =IF(WEEKDAY(FR$82,2)>5,0,113.7) -> 113.7 | FS91: =IF(WEEKDAY(FS$82,2)>5,0,102.16) -> 102.16 | FT91: =IF(WEEKDAY(FT$82,2)>5,0,110.99) -> 110.99 | FU91: =IF(WEEKDAY(FU$82,2)>5,0,98.61) -> 98.61 | FV91: =IF(WEEKDAY(FV$82,2)>5,0,96.14) -> 0 | FW91: =IF(WEEKDAY(FW$82,2)>5,0,92.55) -> 0 | FX91: =IF(WEEKDAY(FX$82,2)>5,0,102.12) -> 102.12 | FY91: =IF(WEEKDAY(FY$82,2)>5,0,101.91) -> 101.91 | FZ91: =IF(WEEKDAY(FZ$82,2)>5,0,92.54) -> 92.54 | GA91: =IF(WEEKDAY(GA$82,2)>5,0,91.71) -> 91.71 | GB91: =IF(WEEKDAY(GB$82,2)>5,0,98.82) -> 98.82 | GC91: =IF(WEEKDAY(GC$82,2)>5,0,86.89) -> 0 | GD91: =IF(WEEKDAY(GD$82,2)>5,0,98.93) -> 0 | GE91: =IF(WEEKDAY(GE$82,2)>5,0,107.94) -> 107.94 | GF91: =IF(WEEKDAY(GF$82,2)>5,0,100.9) -> 100.9 | GG91: =IF(WEEKDAY(GG$82,2)>5,0,95.86) -> 95.86 | GH91: =IF(WEEKDAY(GH$82,2)>5,0,86) -> 86 | GI91: =IF(WEEKDAY(GI$82,2)>5,0,92.71) -> 92.71 | GJ91: =IF(WEEKDAY(GJ$82,2)>5,0,95.74) -> 0 | GK91: =IF(WEEKDAY(GK$82,2)>5,0,95.77) -> 0 | GL91: =IF(WEEKDAY(GL$82,2)>5,0,93.16) -> 93.16 | GM91: =IF(WEEKDAY(GM$82,2)>5,0,88.84) -> 88.84 | GN91: =IF(WEEKDAY(GN$82,2)>5,0,108.44) -> 108.44 | GO91: =IF(WEEKDAY(GO$82,2)>5,0,107.95) -> 107.95 | GP91: =IF(WEEKDAY(GP$82,2)>5,0,89.18) -> 89.18 | GQ91: =IF(WEEKDAY(GQ$82,2)>5,0,111.87) -> 0 | GR91: =IF(WEEKDAY(GR$82,2)>5,0,113.05) -> 0 | GS91: =IF(WEEKDAY(GS$82,2)>5,0,114.45) -> 114.45 | GT91: =IF(WEEKDAY(GT$82,2)>5,0,109.08) -> 109.08 | GU91: =IF(WEEKDAY(GU$82,2)>5,0,90.72) -> 90.72 | GV91: =IF(WEEKDAY(GV$82,2)>5,0,91.17) -> 91.17 | GW91: =IF(WEEKDAY(GW$82,2)>5,0,103.43) -> 103.43 | GX91: =IF(WEEKDAY(GX$82,2)>5,0,105) -> 0 | GY91: =IF(WEEKDAY(GY$82,2)>5,0,109.89) -> 0 | GZ91: =IF(WEEKDAY(GZ$82,2)>5,0,93.88) -> 93.88 | HA91: =IF(WEEKDAY(HA$82,2)>5,0,114.31) -> 114.31 | HB91: =IF(WEEKDAY(HB$82,2)>5,0,90.99) -> 90.99 | HC91: =IF(WEEKDAY(HC$82,2)>5,0,98.31) -> 98.31 | HD91: =IF(WEEKDAY(HD$82,2)>5,0,87.13) -> 87.13 | HE91: =IF(WEEKDAY(HE$82,2)>5,0,109.95) -> 0 | HF91: =IF(WEEKDAY(HF$82,2)>5,0,102.89) -> 0 | HG91: =IF(WEEKDAY(HG$82,2)>5,0,96.26) -> 96.26 | HH91: =IF(WEEKDAY(HH$82,2)>5,0,113.08) -> 113.08 | HI91: =IF(WEEKDAY(HI$82,2)>5,0,110.36) -> 110.36 | HJ91: =IF(WEEKDAY(HJ$82,2)>5,0,90.79) -> 90.79 | HK91: =IF(WEEKDAY(HK$82,2)>5,0,85.29) -> 85.29 | HL91: =IF(WEEKDAY(HL$82,2)>5,0,89.31) -> 0 | HM91: =IF(WEEKDAY(HM$82,2)>5,0,106.26) -> 0 | HN91: =IF(WEEKDAY(HN$82,2)>5,0,96.4) -> 96.4 | HO91: =IF(WEEKDAY(HO$82,2)>5,0,98.23) -> 98.23 | HP91: =IF(WEEKDAY(HP$82,2)>5,0,98.57) -> 98.57 | HQ91: =IF(WEEKDAY(HQ$82,2)>5,0,85.16) -> 85.16 | HR91: =IF(WEEKDAY(HR$82,2)>5,0,88.22) -> 88.22 | HS91: =IF(WEEKDAY(HS$82,2)>5,0,102.24) -> 0 | HT91: =IF(WEEKDAY(HT$82,2)>5,0,107.19) -> 0 | HU91: =IF(WEEKDAY(HU$82,2)>5,0,88.19) -> 88.19 | HV91: =IF(WEEKDAY(HV$82,2)>5,0,89.88) -> 89.88 | HW91: =IF(WEEKDAY(HW$82,2)>5,0,91.43) -> 91.43 | HX91: =IF(WEEKDAY(HX$82,2)>5,0,114.14) -> 114.14 | HY91: =IF(WEEKDAY(HY$82,2)>5,0,98.43) -> 98.43 | HZ91: =IF(WEEKDAY(HZ$82,2)>5,0,100.04) -> 0 | IA91: =IF(WEEKDAY(IA$82,2)>5,0,85.14) -> 0 | IB91: =IF(WEEKDAY(IB$82,2)>5,0,95.02) -> 95.02 | IC91: =IF(WEEKDAY(IC$82,2)>5,0,89.34) -> 89.34 | ID91: =IF(WEEKDAY(ID$82,2)>5,0,111.96) -> 111.96 | IE91: =IF(WEEKDAY(IE$82,2)>5,0,97.46) -> 97.46 | IF91: =IF(WEEKDAY(IF$82,2)>5,0,90.61) -> 90.61 | IG91: =IF(WEEKDAY(IG$82,2)>5,0,93.58) -> 0 | IH91: =IF(WEEKDAY(IH$82,2)>5,0,110.31) -> 0 | II91: =IF(WEEKDAY(II$82,2)>5,0,95.48) -> 95.48 | IJ91: =IF(WEEKDAY(IJ$82,2)>5,0,100.15) -> 100.15 | IK91: =IF(WEEKDAY(IK$82,2)>5,0,86.68) -> 86.68 | IL91: =IF(WEEKDAY(IL$82,2)>5,0,111.43) -> 111.43
A92: Aluguel Recebido | B92: 0 | C92: 0 | D92: 0 | E92: 0 | F92: 0 | G92: 0 | H92: 0 | I92: 0 | J92: 0 | K92: 0 | L92: 0 | M92: 0 | N92: 0 | O92: 0 | P92: 0 | Q92: 0 | R92: 0 | S92: 0 | T92: 0 | U92: 0 | V92: 0 | W92: 0 | X92: 0 | Y92: 0 | Z92: 0 | AA92: 0 | AB92: 0 | AC92: 0 | AD92: 0 | AE92: 0 | AF92: 0 | AG92: 0 | AH92: 0 | AI92: 0 | AJ92: 0 | AK92: 0 | AL92: 0 | AM92: 0 | AN92: 0 | AO92: 0 | AP92: 0 | AQ92: 0 | AR92: 0 | AS92: 0 | AT92: 0 | AU92: 0 | AV92: 0 | AW92: 0 | AX92: 0 | AY92: 0 | AZ92: 0 | BA92: 0 | BB92: 0 | BC92: 0 | BD92: 0 | BE92: 0 | BF92: 0 | BG92: 0 | BH92: 0 | BI92: 0 | BJ92: 0 | BK92: 0 | BL92: 0 | BM92: 0 | BN92: 0 | BO92: 0 | BP92: 0 | BQ92: 0 | BR92: 0 | BS92: 0 | BT92: 0 | BU92: 0 | BV92: 0 | BW92: 0 | BX92: 0 | BY92: 0 | BZ92: 0 | CA92: 0 | CB92: 0 | CC92: 0 | CD92: 0 | CE92: 0 | CF92: 0 | CG92: 0 | CH92: 0 | CI92: 0 | CJ92: 0 | CK92: 0 | CL92: 0 | CM92: 0 | CN92: 0 | CO92: 0 | CP92: 0 | CQ92: 0 | CR92: 0 | CS92: 0 | CT92: 0 | CU92: 0 | CV92: 0 | CW92: 0 | CX92: 0 | CY92: 0 | CZ92: 0 | DA92: 0 | DB92: 0 | DC92: 0 | DD92: 0 | DE92: 0 | DF92: 0 | DG92: 0 | DH92: 0 | DI92: 0 | DJ92: 0 | DK92: 0 | DL92: 0 | DM92: 0 | DN92: 0 | DO92: 0 | DP92: 0 | DQ92: 0 | DR92: 0 | DS92: 0 | DT92: 0 | DU92: 0 | DV92: 0 | DW92: 0 | DX92: 0 | DY92: 0 | DZ92: 0 | EA92: 0 | EB92: 0 | EC92: 0 | ED92: 0 | EE92: 0 | EF92: 0 | EG92: 0 | EH92: 0 | EI92: 0 | EJ92: 0 | EK92: 0 | EL92: 0 | EM92: 0 | EN92: 0 | EO92: 0 | EP92: 0 | EQ92: 0 | ER92: 0 | ES92: 0 | ET92: 0 | EU92: 0 | EV92: 0 | EW92: 0 | EX92: 0 | EY92: 0 | EZ92: 0 | FA92: 0 | FB92: 0 | FC92: 0 | FD92: 0 | FE92: 0 | FF92: 0 | FG92: 0 | FH92: 0 | FI92: 0 | FJ92: 0 | FK92: 0 | FL92: 0 | FM92: 0 | FN92: 0 | FO92: 0 | FP92: 0 | FQ92: 0 | FR92: 0 | FS92: 0 | FT92: 0 | FU92: 0 | FV92: 0 | FW92: 0 | FX92: 0 | FY92: 0 | FZ92: 0 | GA92: 0 | GB92: 0 | GC92: 0 | GD92: 0 | GE92: 0 | GF92: 0 | GG92: 0 | GH92: 0 | GI92: 0 | GJ92: 0 | GK92: 0 | GL92: 0 | GM92: 0 | GN92: 0 | GO92: 0 | GP92: 0 | GQ92: 0 | GR92: 0 | GS92: 0 | GT92: 0 | GU92: 0 | GV92: 0 | GW92: 0 | GX92: 0 | GY92: 0 | GZ92: 0 | HA92: 0 | HB92: 0 | HC92: 0 | HD92: 0 | HE92: 0 | HF92: 0 | HG92: 0 | HH92: 0 | HI92: 0 | HJ92: 0 | HK92: 0 | HL92: 0 | HM92: 0 | HN92: 0 | HO92: 0 | HP92: 0 | HQ92: 0 | HR92: 0 | HS92: 0 | HT92: 0 | HU92: 0 | HV92: 0 | HW92: 0 | HX92: 0 | HY92: 0 | HZ92: 0 | IA92: 0 | IB92: 0 | IC92: 0 | ID92: 0 | IE92: 0 | IF92: 0 | IG92: 0 | IH92: 0 | II92: 0 | IJ92: 0 | IK92: 0 | IL92: 0
A93: Reembolsos | B93: =IF(WEEKDAY(B$82,2)>5,0,18.67) -> 18.67 | C93: =IF(WEEKDAY(C$82,2)>5,0,19.53) -> 0 | D93: =IF(WEEKDAY(D$82,2)>5,0,20.48) -> 0 | E93: =IF(WEEKDAY(E$82,2)>5,0,21.35) -> 21.35 | F93: =IF(WEEKDAY(F$82,2)>5,0,19.66) -> 19.66 | G93: =IF(WEEKDAY(G$82,2)>5,0,17.93) -> 17.93 | H93: =IF(WEEKDAY(H$82,2)>5,0,19.59) -> 19.59 | I93: =IF(WEEKDAY(I$82,2)>5,0,20.33) -> 20.33 | J93: =IF(WEEKDAY(J$82,2)>5,0,21.66) -> 0 | K93: =IF(WEEKDAY(K$82,2)>5,0,20.43) -> 0 | L93: =IF(WEEKDAY(L$82,2)>5,0,20.82) -> 20.82 | M93: =IF(WEEKDAY(M$82,2)>5,0,17.77) -> 17.77 | N93: =IF(WEEKDAY(N$82,2)>5,0,17.37) -> 17.37 | O93: =IF(WEEKDAY(O$82,2)>5,0,22.28) -> 22.28 | P93: =IF(WEEKDAY(P$82,2)>5,0,20.57) -> 20.57 | Q93: =IF(WEEKDAY(Q$82,2)>5,0,22.47) -> 0 | R93: =IF(WEEKDAY(R$82,2)>5,0,20.91) -> 0 | S93: =IF(WEEKDAY(S$82,2)>5,0,21.72) -> 21.72 | T93: =IF(WEEKDAY(T$82,2)>5,0,22.39) -> 22.39 | U93: =IF(WEEKDAY(U$82,2)>5,0,18.03) -> 18.03 | V93: =IF(WEEKDAY(V$82,2)>5,0,17.41) -> 17.41 | W93: =IF(WEEKDAY(W$82,2)>5,0,20.8) -> 20.8 | X93: =IF(WEEKDAY(X$82,2)>5,0,19.62) -> 0 | Y93: =IF(WEEKDAY(Y$82,2)>5,0,18.64) -> 0 | Z93: =IF(WEEKDAY(Z$82,2)>5,0,17.83) -> 17.83 | AA93: =IF(WEEKDAY(AA$82,2)>5,0,20.22) -> 20.22 | AB93: =IF(WEEKDAY(AB$82,2)>5,0,22.88) -> 22.88 | AC93: =IF(WEEKDAY(AC$82,2)>5,0,18.8) -> 18.8 | AD93: =IF(WEEKDAY(AD$82,2)>5,0,18.22) -> 18.22 | AE93: =IF(WEEKDAY(AE$82,2)>5,0,18.91) -> 0 | AF93: =IF(WEEKDAY(AF$82,2)>5,0,18.31) -> 0 | AG93: =IF(WEEKDAY(AG$82,2)>5,0,20.94) -> 20.94 | AH93: =IF(WEEKDAY(AH$82,2)>5,0,21.31) -> 21.31 | AI93: =IF(WEEKDAY(AI$82,2)>5,0,22.36) -> 22.36 | AJ93: =IF(WEEKDAY(AJ$82,2)>5,0,18.88) -> 18.88 | AK93: =IF(WEEKDAY(AK$82,2)>5,0,21.42) -> 21.42 | AL93: =IF(WEEKDAY(AL$82,2)>5,0,18.7) -> 0 | AM93: =IF(WEEKDAY(AM$82,2)>5,0,19.11) -> 0 | AN93: =IF(WEEKDAY(AN$82,2)>5,0,17.13) -> 17.13 | AO93: =IF(WEEKDAY(AO$82,2)>5,0,20.73) -> 20.73 | AP93: =IF(WEEKDAY(AP$82,2)>5,0,20.43) -> 20.43 | AQ93: =IF(WEEKDAY(AQ$82,2)>5,0,19) -> 19 | AR93: =IF(WEEKDAY(AR$82,2)>5,0,18.61) -> 18.61 | AS93: =IF(WEEKDAY(AS$82,2)>5,0,21.65) -> 0 | AT93: =IF(WEEKDAY(AT$82,2)>5,0,22.83) -> 0 | AU93: =IF(WEEKDAY(AU$82,2)>5,0,18.01) -> 18.01 | AV93: =IF(WEEKDAY(AV$82,2)>5,0,22.79) -> 22.79 | AW93: =IF(WEEKDAY(AW$82,2)>5,0,21.36) -> 21.36 | AX93: =IF(WEEKDAY(AX$82,2)>5,0,21.58) -> 21.58 | AY93: =IF(WEEKDAY(AY$82,2)>5,0,18.85) -> 18.85 | AZ93: =IF(WEEKDAY(AZ$82,2)>5,0,17.23) -> 0 | BA93: =IF(WEEKDAY(BA$82,2)>5,0,22.28) -> 0 | BB93: =IF(WEEKDAY(BB$82,2)>5,0,22.75) -> 22.75 | BC93: =IF(WEEKDAY(BC$82,2)>5,0,19.87) -> 19.87 | BD93: =IF(WEEKDAY(BD$82,2)>5,0,19.37) -> 19.37 | BE93: =IF(WEEKDAY(BE$82,2)>5,0,21.34) -> 21.34 | BF93: =IF(WEEKDAY(BF$82,2)>5,0,20.98) -> 20.98 | BG93: =IF(WEEKDAY(BG$82,2)>5,0,20.14) -> 0 | BH93: =IF(WEEKDAY(BH$82,2)>5,0,22.36) -> 0 | BI93: =IF(WEEKDAY(BI$82,2)>5,0,17.41) -> 17.41 | BJ93: =IF(WEEKDAY(BJ$82,2)>5,0,21.46) -> 21.46 | BK93: =IF(WEEKDAY(BK$82,2)>5,0,22.26) -> 22.26 | BL93: =IF(WEEKDAY(BL$82,2)>5,0,21.51) -> 21.51 | BM93: =IF(WEEKDAY(BM$82,2)>5,0,17.71) -> 17.71 | BN93: =IF(WEEKDAY(BN$82,2)>5,0,18.9) -> 0 | BO93: =IF(WEEKDAY(BO$82,2)>5,0,18.15) -> 0 | BP93: =IF(WEEKDAY(BP$82,2)>5,0,17.53) -> 17.53 | BQ93: =IF(WEEKDAY(BQ$82,2)>5,0,18.78) -> 18.78 | BR93: =IF(WEEKDAY(BR$82,2)>5,0,21.58) -> 21.58 | BS93: =IF(WEEKDAY(BS$82,2)>5,0,21.48) -> 21.48 | BT93: =IF(WEEKDAY(BT$82,2)>5,0,17.08) -> 17.08 | BU93: =IF(WEEKDAY(BU$82,2)>5,0,17.75) -> 0 | BV93: =IF(WEEKDAY(BV$82,2)>5,0,18.16) -> 0 | BW93: =IF(WEEKDAY(BW$82,2)>5,0,20.95) -> 20.95 | BX93: =IF(WEEKDAY(BX$82,2)>5,0,21.8) -> 21.8 | BY93: =IF(WEEKDAY(BY$82,2)>5,0,17.43) -> 17.43 | BZ93: =IF(WEEKDAY(BZ$82,2)>5,0,17.59) -> 17.59 | CA93: =IF(WEEKDAY(CA$82,2)>5,0,20.63) -> 20.63 | CB93: =IF(WEEKDAY(CB$82,2)>5,0,20.44) -> 0 | CC93: =IF(WEEKDAY(CC$82,2)>5,0,17.83) -> 0 | CD93: =IF(WEEKDAY(CD$82,2)>5,0,18.94) -> 18.94 | CE93: =IF(WEEKDAY(CE$82,2)>5,0,22.5) -> 22.5 | CF93: =IF(WEEKDAY(CF$82,2)>5,0,22.09) -> 22.09 | CG93: =IF(WEEKDAY(CG$82,2)>5,0,22.96) -> 22.96 | CH93: =IF(WEEKDAY(CH$82,2)>5,0,21.61) -> 21.61 | CI93: =IF(WEEKDAY(CI$82,2)>5,0,17.28) -> 0 | CJ93: =IF(WEEKDAY(CJ$82,2)>5,0,18.49) -> 0 | CK93: =IF(WEEKDAY(CK$82,2)>5,0,22.46) -> 22.46 | CL93: =IF(WEEKDAY(CL$82,2)>5,0,22.98) -> 22.98 | CM93: =IF(WEEKDAY(CM$82,2)>5,0,20.74) -> 20.74 | CN93: =IF(WEEKDAY(CN$82,2)>5,0,18.7) -> 18.7 | CO93: =IF(WEEKDAY(CO$82,2)>5,0,17.78) -> 17.78 | CP93: =IF(WEEKDAY(CP$82,2)>5,0,17.96) -> 0 | CQ93: =IF(WEEKDAY(CQ$82,2)>5,0,18.43) -> 0 | CR93: =IF(WEEKDAY(CR$82,2)>5,0,22.47) -> 22.47 | CS93: =IF(WEEKDAY(CS$82,2)>5,0,20.32) -> 20.32 | CT93: =IF(WEEKDAY(CT$82,2)>5,0,21.28) -> 21.28 | CU93: =IF(WEEKDAY(CU$82,2)>5,0,22.37) -> 22.37 | CV93: =IF(WEEKDAY(CV$82,2)>5,0,21.15) -> 21.15 | CW93: =IF(WEEKDAY(CW$82,2)>5,0,20.22) -> 0 | CX93: =IF(WEEKDAY(CX$82,2)>5,0,19.19) -> 0 | CY93: =IF(WEEKDAY(CY$82,2)>5,0,22.03) -> 22.03 | CZ93: =IF(WEEKDAY(CZ$82,2)>5,0,20.58) -> 20.58 | DA93: =IF(WEEKDAY(DA$82,2)>5,0,22.26) -> 22.26 | DB93: =IF(WEEKDAY(DB$82,2)>5,0,21.38) -> 21.38 | DC93: =IF(WEEKDAY(DC$82,2)>5,0,19.74) -> 19.74 | DD93: =IF(WEEKDAY(DD$82,2)>5,0,20.1) -> 0 | DE93: =IF(WEEKDAY(DE$82,2)>5,0,19.13) -> 0 | DF93: =IF(WEEKDAY(DF$82,2)>5,0,22.67) -> 22.67 | DG93: =IF(WEEKDAY(DG$82,2)>5,0,19.97) -> 19.97 | DH93: =IF(WEEKDAY(DH$82,2)>5,0,21.39) -> 21.39 | DI93: =IF(WEEKDAY(DI$82,2)>5,0,19.79) -> 19.79 | DJ93: =IF(WEEKDAY(DJ$82,2)>5,0,17.43) -> 17.43 | DK93: =IF(WEEKDAY(DK$82,2)>5,0,17.67) -> 0 | DL93: =IF(WEEKDAY(DL$82,2)>5,0,22.54) -> 0 | DM93: =IF(WEEKDAY(DM$82,2)>5,0,18.98) -> 18.98 | DN93: =IF(WEEKDAY(DN$82,2)>5,0,18.9) -> 18.9 | DO93: =IF(WEEKDAY(DO$82,2)>5,0,20.13) -> 20.13 | DP93: =IF(WEEKDAY(DP$82,2)>5,0,22.31) -> 22.31 | DQ93: =IF(WEEKDAY(DQ$82,2)>5,0,19.19) -> 19.19 | DR93: =IF(WEEKDAY(DR$82,2)>5,0,22.58) -> 0 | DS93: =IF(WEEKDAY(DS$82,2)>5,0,19.8) -> 0 | DT93: =IF(WEEKDAY(DT$82,2)>5,0,20.37) -> 20.37 | DU93: =IF(WEEKDAY(DU$82,2)>5,0,19.32) -> 19.32 | DV93: =IF(WEEKDAY(DV$82,2)>5,0,22.74) -> 22.74 | DW93: =IF(WEEKDAY(DW$82,2)>5,0,18.88) -> 18.88 | DX93: =IF(WEEKDAY(DX$82,2)>5,0,19.44) -> 19.44 | DY93: =IF(WEEKDAY(DY$82,2)>5,0,19.08) -> 0 | DZ93: =IF(WEEKDAY(DZ$82,2)>5,0,18.12) -> 0 | EA93: =IF(WEEKDAY(EA$82,2)>5,0,18.23) -> 18.23 | EB93: =IF(WEEKDAY(EB$82,2)>5,0,19.5) -> 19.5 | EC93: =IF(WEEKDAY(EC$82,2)>5,0,21.24) -> 21.24 | ED93: =IF(WEEKDAY(ED$82,2)>5,0,21.52) -> 21.52 | EE93: =IF(WEEKDAY(EE$82,2)>5,0,18.82) -> 18.82 | EF93: =IF(WEEKDAY(EF$82,2)>5,0,22.22) -> 0 | EG93: =IF(WEEKDAY(EG$82,2)>5,0,18.55) -> 0 | EH93: =IF(WEEKDAY(EH$82,2)>5,0,22.44) -> 22.44 | EI93: =IF(WEEKDAY(EI$82,2)>5,0,21.09) -> 21.09 | EJ93: =IF(WEEKDAY(EJ$82,2)>5,0,18.8) -> 18.8 | EK93: =IF(WEEKDAY(EK$82,2)>5,0,20.37) -> 20.37 | EL93: =IF(WEEKDAY(EL$82,2)>5,0,19.02) -> 19.02 | EM93: =IF(WEEKDAY(EM$82,2)>5,0,21.45) -> 0 | EN93: =IF(WEEKDAY(EN$82,2)>5,0,21.26) -> 0 | EO93: =IF(WEEKDAY(EO$82,2)>5,0,19.08) -> 19.08 | EP93: =IF(WEEKDAY(EP$82,2)>5,0,21.59) -> 21.59 | EQ93: =IF(WEEKDAY(EQ$82,2)>5,0,19.3) -> 19.3 | ER93: =IF(WEEKDAY(ER$82,2)>5,0,18.31) -> 18.31 | ES93: =IF(WEEKDAY(ES$82,2)>5,0,21.27) -> 21.27 | ET93: =IF(WEEKDAY(ET$82,2)>5,0,21.34) -> 0 | EU93: =IF(WEEKDAY(EU$82,2)>5,0,22.96) -> 0 | EV93: =IF(WEEKDAY(EV$82,2)>5,0,20.76) -> 20.76 | EW93: =IF(WEEKDAY(EW$82,2)>5,0,18.13) -> 18.13 | EX93: =IF(WEEKDAY(EX$82,2)>5,0,18.71) -> 18.71 | EY93: =IF(WEEKDAY(EY$82,2)>5,0,20.11) -> 20.11 | EZ93: =IF(WEEKDAY(EZ$82,2)>5,0,17.89) -> 17.89 | FA93: =IF(WEEKDAY(FA$82,2)>5,0,22.54) -> 0 | FB93: =IF(WEEKDAY(FB$82,2)>5,0,22.6) -> 0 | FC93: =IF(WEEKDAY(FC$82,2)>5,0,21.08) -> 21.08 | FD93: =IF(WEEKDAY(FD$82,2)>5,0,21.83) -> 21.83 | FE93: =IF(WEEKDAY(FE$82,2)>5,0,17.4) -> 17.4 | FF93: =IF(WEEKDAY(FF$82,2)>5,0,17.88) -> 17.88 | FG93: =IF(WEEKDAY(FG$82,2)>5,0,20.21) -> 20.21 | FH93: =IF(WEEKDAY(FH$82,2)>5,0,19.53) -> 0 | FI93: =IF(WEEKDAY(FI$82,2)>5,0,19.93) -> 0 | FJ93: =IF(WEEKDAY(FJ$82,2)>5,0,20.42) -> 20.42 | FK93: =IF(WEEKDAY(FK$82,2)>5,0,17.16) -> 17.16 | FL93: =IF(WEEKDAY(FL$82,2)>5,0,18.83) -> 18.83 | FM93: =IF(WEEKDAY(FM$82,2)>5,0,18.3) -> 18.3 | FN93: =IF(WEEKDAY(FN$82,2)>5,0,19.85) -> 19.85 | FO93: =IF(WEEKDAY(FO$82,2)>5,0,18.21) -> 0 | FP93: =IF(WEEKDAY(FP$82,2)>5,0,19.62) -> 0 | FQ93: =IF(WEEKDAY(FQ$82,2)>5,0,20.2) -> 20.2 | FR93: =IF(WEEKDAY(FR$82,2)>5,0,19.24) -> 19.24 | FS93: =IF(WEEKDAY(FS$82,2)>5,0,20.9) -> 20.9 | FT93: =IF(WEEKDAY(FT$82,2)>5,0,19.92) -> 19.92 | FU93: =IF(WEEKDAY(FU$82,2)>5,0,22.87) -> 22.87 | FV93: =IF(WEEKDAY(FV$82,2)>5,0,21.87) -> 0 | FW93: =IF(WEEKDAY(FW$82,2)>5,0,17.82) -> 0 | FX93: =IF(WEEKDAY(FX$82,2)>5,0,17.68) -> 17.68 | FY93: =IF(WEEKDAY(FY$82,2)>5,0,20.91) -> 20.91 | FZ93: =IF(WEEKDAY(FZ$82,2)>5,0,17.79) -> 17.79 | GA93: =IF(WEEKDAY(GA$82,2)>5,0,17.36) -> 17.36 | GB93: =IF(WEEKDAY(GB$82,2)>5,0,22.57) -> 22.57 | GC93: =IF(WEEKDAY(GC$82,2)>5,0,21.74) -> 0 | GD93: =IF(WEEKDAY(GD$82,2)>5,0,18.99) -> 0 | GE93: =IF(WEEKDAY(GE$82,2)>5,0,18.82) -> 18.82 | GF93: =IF(WEEKDAY(GF$82,2)>5,0,18.38) -> 18.38 | GG93: =IF(WEEKDAY(GG$82,2)>5,0,18.08) -> 18.08 | GH93: =IF(WEEKDAY(GH$82,2)>5,0,18.29) -> 18.29 | GI93: =IF(WEEKDAY(GI$82,2)>5,0,19.68) -> 19.68 | GJ93: =IF(WEEKDAY(GJ$82,2)>5,0,19.26) -> 0 | GK93: =IF(WEEKDAY(GK$82,2)>5,0,22.71) -> 0 | GL93: =IF(WEEKDAY(GL$82,2)>5,0,19.13) -> 19.13 | GM93: =IF(WEEKDAY(GM$82,2)>5,0,21.19) -> 21.19 | GN93: =IF(WEEKDAY(GN$82,2)>5,0,20.48) -> 20.48 | GO93: =IF(WEEKDAY(GO$82,2)>5,0,17.92) -> 17.92 | GP93: =IF(WEEKDAY(GP$82,2)>5,0,22.19) -> 22.19 | GQ93: =IF(WEEKDAY(GQ$82,2)>5,0,19.53) -> 0 | GR93: =IF(WEEKDAY(GR$82,2)>5,0,21.91) -> 0 | GS93: =IF(WEEKDAY(GS$82,2)>5,0,18.05) -> 18.05 | GT93: =IF(WEEKDAY(GT$82,2)>5,0,18.86) -> 18.86 | GU93: =IF(WEEKDAY(GU$82,2)>5,0,19.38) -> 19.38 | GV93: =IF(WEEKDAY(GV$82,2)>5,0,21.46) -> 21.46 | GW93: =IF(WEEKDAY(GW$82,2)>5,0,17.93) -> 17.93 | GX93: =IF(WEEKDAY(GX$82,2)>5,0,17.67) -> 0 | GY93: =IF(WEEKDAY(GY$82,2)>5,0,20.2) -> 0 | GZ93: =IF(WEEKDAY(GZ$82,2)>5,0,22.72) -> 22.72 | HA93: =IF(WEEKDAY(HA$82,2)>5,0,21.91) -> 21.91 | HB93: =IF(WEEKDAY(HB$82,2)>5,0,18.33) -> 18.33 | HC93: =IF(WEEKDAY(HC$82,2)>5,0,21.95) -> 21.95 | HD93: =IF(WEEKDAY(HD$82,2)>5,0,22.36) -> 22.36 | HE93: =IF(WEEKDAY(HE$82,2)>5,0,17.08) -> 0 | HF93: =IF(WEEKDAY(HF$82,2)>5,0,22.6) -> 0 | HG93: =IF(WEEKDAY(HG$82,2)>5,0,17.9) -> 17.9 | HH93: =IF(WEEKDAY(HH$82,2)>5,0,19.1) -> 19.1 | HI93: =IF(WEEKDAY(HI$82,2)>5,0,21.18) -> 21.18 | HJ93: =IF(WEEKDAY(HJ$82,2)>5,0,21.45) -> 21.45 | HK93: =IF(WEEKDAY(HK$82,2)>5,0,22.21) -> 22.21 | HL93: =IF(WEEKDAY(HL$82,2)>5,0,17.24) -> 0 | HM93: =IF(WEEKDAY(HM$82,2)>5,0,18.8) -> 0 | HN93: =IF(WEEKDAY(HN$82,2)>5,0,18.33) -> 18.33 | HO93: =IF(WEEKDAY(HO$82,2)>5,0,18.02) -> 18.02 | HP93: =IF(WEEKDAY(HP$82,2)>5,0,20.41) -> 20.41 | HQ93: =IF(WEEKDAY(HQ$82,2)>5,0,17.52) -> 17.52 | HR93: =IF(WEEKDAY(HR$82,2)>5,0,17.15) -> 17.15 | HS93: =IF(WEEKDAY(HS$82,2)>5,0,17.97) -> 0 | HT93: =IF(WEEKDAY(HT$82,2)>5,0,21.18) -> 0 | HU93: =IF(WEEKDAY(HU$82,2)>5,0,21.08) -> 21.08 | HV93: =IF(WEEKDAY(HV$82,2)>5,0,22.71) -> 22.71 | HW93: =IF(WEEKDAY(HW$82,2)>5,0,20.83) -> 20.83 | HX93: =IF(WEEKDAY(HX$82,2)>5,0,21.01) -> 21.01 | HY93: =IF(WEEKDAY(HY$82,2)>5,0,22.86) -> 22.86 | HZ93: =IF(WEEKDAY(HZ$82,2)>5,0,21.7) -> 0 | IA93: =IF(WEEKDAY(IA$82,2)>5,0,17.52) -> 0 | IB93: =IF(WEEKDAY(IB$82,2)>5,0,22.39) -> 22.39 | IC93: =IF(WEEKDAY(IC$82,2)>5,0,22.02) -> 22.02 | ID93: =IF(WEEKDAY(ID$82,2)>5,0,17.96) -> 17.96 | IE93: =IF(WEEKDAY(IE$82,2)>5,0,21.24) -> 21.24 | IF93: =IF(WEEKDAY(IF$82,2)>5,0,21.64) -> 21.64 | IG93: =IF(WEEKDAY(IG$82,2)>5,0,18.56) -> 0 | IH93: =IF(WEEKDAY(IH$82,2)>5,0,19.69) -> 0 | II93: =IF(WEEKDAY(II$82,2)>5,0,19.09) -> 19.09 | IJ93: =IF(WEEKDAY(IJ$82,2)>5,0,21.36) -> 21.36 | IK93: =IF(WEEKDAY(IK$82,2)>5,0,22.31) -> 22.31 | IL93: =IF(WEEKDAY(IL$82,2)>5,0,22.04) -> 22.04
A94: Aporte de Sócios | B94: 0 | C94: 0 | D94: 0 | E94: 0 | F94: 0 | G94: 0 | H94: 0 | I94: 0 | J94: 0 | K94: 0 | L94: 0 | M94: 0 | N94: 0 | O94: 0 | P94: 0 | Q94: 0 | R94: 0 | S94: 0 | T94: 0 | U94: 0 | V94: 0 | W94: 0 | X94: 0 | Y94: 0 | Z94: 0 | AA94: 0 | AB94: 0 | AC94: 0 | AD94: 0 | AE94: 0 | AF94: 0 | AG94: 0 | AH94: 0 | AI94: 0 | AJ94: 0 | AK94: 0 | AL94: 0 | AM94: 0 | AN94: 0 | AO94: 0 | AP94: 0 | AQ94: 0 | AR94: 0 | AS94: 0 | AT94: 0 | AU94: 0 | AV94: 0 | AW94: 0 | AX94: 0 | AY94: 0 | AZ94: 0 | BA94: 0 | BB94: 0 | BC94: 0 | BD94: 0 | BE94: 0 | BF94: 0 | BG94: 0 | BH94: 0 | BI94: 0 | BJ94: 0 | BK94: 0 | BL94: 0 | BM94: 0 | BN94: 0 | BO94: 0 | BP94: 0 | BQ94: 0 | BR94: 0 | BS94: 0 | BT94: 0 | BU94: 0 | BV94: 0 | BW94: 0 | BX94: 0 | BY94: 0 | BZ94: 0 | CA94: 0 | CB94: 0 | CC94: 0 | CD94: 0 | CE94: 0 | CF94: 0 | CG94: 0 | CH94: 0 | CI94: 0 | CJ94: 0 | CK94: 0 | CL94: 0 | CM94: 0 | CN94: 0 | CO94: 0 | CP94: 0 | CQ94: 0 | CR94: 0 | CS94: 0 | CT94: 0 | CU94: 0 | CV94: 0 | CW94: 0 | CX94: 0 | CY94: 0 | CZ94: 0 | DA94: 0 | DB94: 0 | DC94: 0 | DD94: 0 | DE94: 0 | DF94: 0 | DG94: 0 | DH94: 0 | DI94: 0 | DJ94: 0 | DK94: 0 | DL94: 0 | DM94: 0 | DN94: 0 | DO94: 0 | DP94: 0 | DQ94: 0 | DR94: 0 | DS94: 0 | DT94: 0 | DU94: 0 | DV94: 0 | DW94: 0 | DX94: 0 | DY94: 0 | DZ94: 0 | EA94: 0 | EB94: 0 | EC94: 0 | ED94: 0 | EE94: 0 | EF94: 0 | EG94: 0 | EH94: 0 | EI94: 0 | EJ94: 0 | EK94: 0 | EL94: 0 | EM94: 0 | EN94: 0 | EO94: 0 | EP94: 0 | EQ94: 0 | ER94: 0 | ES94: 0 | ET94: 0 | EU94: 0 | EV94: 0 | EW94: 0 | EX94: 0 | EY94: 0 | EZ94: 0 | FA94: 0 | FB94: 0 | FC94: 0 | FD94: 0 | FE94: 0 | FF94: 0 | FG94: 0 | FH94: 0 | FI94: 0 | FJ94: 0 | FK94: 0 | FL94: 0 | FM94: 0 | FN94: 0 | FO94: 0 | FP94: 0 | FQ94: 0 | FR94: 0 | FS94: 0 | FT94: 0 | FU94: 0 | FV94: 0 | FW94: 0 | FX94: 0 | FY94: 0 | FZ94: 0 | GA94: 0 | GB94: 0 | GC94: 0 | GD94: 0 | GE94: 0 | GF94: 0 | GG94: 0 | GH94: 0 | GI94: 0 | GJ94: 0 | GK94: 0 | GL94: 0 | GM94: 0 | GN94: 0 | GO94: 0 | GP94: 0 | GQ94: 0 | GR94: 0 | GS94: 0 | GT94: 0 | GU94: 0 | GV94: 0 | GW94: 0 | GX94: 0 | GY94: 0 | GZ94: 0 | HA94: 0 | HB94: 0 | HC94: 0 | HD94: 0 | HE94: 0 | HF94: 0 | HG94: 0 | HH94: 0 | HI94: 0 | HJ94: 0 | HK94: 0 | HL94: 0 | HM94: 0 | HN94: 0 | HO94: 0 | HP94: 0 | HQ94: 0 | HR94: 0 | HS94: 0 | HT94: 0 | HU94: 0 | HV94: 0 | HW94: 0 | HX94: 0 | HY94: 0 | HZ94: 0 | IA94: 0 | IB94: 0 | IC94: 0 | ID94: 0 | IE94: 0 | IF94: 0 | IG94: 0 | IH94: 0 | II94: 0 | IJ94: 0 | IK94: 0 | IL94: 0
A95: Empréstimo Recebido | B95: 0 | C95: 0 | D95: 0 | E95: 0 | F95: 0 | G95: 0 | H95: 0 | I95: 0 | J95: 0 | K95: 0 | L95: 0 | M95: 0 | N95: 0 | O95: 0 | P95: 0 | Q95: 0 | R95: 0 | S95: 0 | T95: 0 | U95: 0 | V95: 0 | W95: 0 | X95: 0 | Y95: 0 | Z95: 0 | AA95: 0 | AB95: 0 | AC95: 0 | AD95: 0 | AE95: 0 | AF95: 0 | AG95: 0 | AH95: 0 | AI95: 0 | AJ95: 0 | AK95: 0 | AL95: 0 | AM95: 0 | AN95: 0 | AO95: 0 | AP95: 0 | AQ95: 0 | AR95: 0 | AS95: 0 | AT95: 0 | AU95: 0 | AV95: 0 | AW95: 0 | AX95: 0 | AY95: 0 | AZ95: 0 | BA95: 0 | BB95: 0 | BC95: 0 | BD95: 0 | BE95: 0 | BF95: 0 | BG95: 0 | BH95: 0 | BI95: 0 | BJ95: 0 | BK95: 0 | BL95: 0 | BM95: 0 | BN95: 0 | BO95: 0 | BP95: 0 | BQ95: 0 | BR95: 0 | BS95: 0 | BT95: 0 | BU95: 0 | BV95: 0 | BW95: 0 | BX95: 0 | BY95: 0 | BZ95: 0 | CA95: 0 | CB95: 0 | CC95: 0 | CD95: 0 | CE95: 0 | CF95: 0 | CG95: 0 | CH95: 0 | CI95: 0 | CJ95: 0 | CK95: 0 | CL95: 0 | CM95: 0 | CN95: 0 | CO95: 0 | CP95: 0 | CQ95: 0 | CR95: 0 | CS95: 0 | CT95: 0 | CU95: 0 | CV95: 0 | CW95: 0 | CX95: 0 | CY95: 0 | CZ95: 0 | DA95: 0 | DB95: 0 | DC95: 0 | DD95: 0 | DE95: 0 | DF95: 0 | DG95: 0 | DH95: 0 | DI95: 0 | DJ95: 0 | DK95: 0 | DL95: 0 | DM95: 0 | DN95: 0 | DO95: 0 | DP95: 0 | DQ95: 0 | DR95: 0 | DS95: 0 | DT95: 0 | DU95: 0 | DV95: 0 | DW95: 0 | DX95: 0 | DY95: 0 | DZ95: 0 | EA95: 0 | EB95: 0 | EC95: 0 | ED95: 0 | EE95: 0 | EF95: 0 | EG95: 0 | EH95: 0 | EI95: 0 | EJ95: 0 | EK95: 0 | EL95: 0 | EM95: 0 | EN95: 0 | EO95: 0 | EP95: 0 | EQ95: 0 | ER95: 0 | ES95: 0 | ET95: 0 | EU95: 0 | EV95: 0 | EW95: 0 | EX95: 0 | EY95: 0 | EZ95: 0 | FA95: 0 | FB95: 0 | FC95: 0 | FD95: 0 | FE95: 0 | FF95: 0 | FG95: 0 | FH95: 0 | FI95: 0 | FJ95: 0 | FK95: 0 | FL95: 0 | FM95: 0 | FN95: 0 | FO95: 0 | FP95: 0 | FQ95: 0 | FR95: 0 | FS95: 0 | FT95: 0 | FU95: 0 | FV95: 0 | FW95: 0 | FX95: 0 | FY95: 0 | FZ95: 0 | GA95: 0 | GB95: 0 | GC95: 0 | GD95: 0 | GE95: 0 | GF95: 0 | GG95: 0 | GH95: 0 | GI95: 0 | GJ95: 0 | GK95: 0 | GL95: 0 | GM95: 0 | GN95: 0 | GO95: 0 | GP95: 0 | GQ95: 0 | GR95: 0 | GS95: 0 | GT95: 0 | GU95: 0 | GV95: 0 | GW95: 0 | GX95: 0 | GY95: 0 | GZ95: 0 | HA95: 0 | HB95: 0 | HC95: 0 | HD95: 0 | HE95: 0 | HF95: 0 | HG95: 0 | HH95: 0 | HI95: 0 | HJ95: 0 | HK95: 0 | HL95: 0 | HM95: 0 | HN95: 0 | HO95: 0 | HP95: 0 | HQ95: 0 | HR95: 0 | HS95: 0 | HT95: 0 | HU95: 0 | HV95: 0 | HW95: 0 | HX95: 0 | HY95: 0 | HZ95: 0 | IA95: 0 | IB95: 0 | IC95: 0 | ID95: 0 | IE95: 0 | IF95: 0 | IG95: 0 | IH95: 0 | II95: 0 | IJ95: 0 | IK95: 0 | IL95: 0
A96: TOTAL ENTRADAS PREVISTAS | B96: =SUM(B85:B95) -> 5111.73 | C96: =SUM(C85:C95) -> 0 | D96: =SUM(D85:D95) -> 0 | E96: =SUM(E85:E95) -> 5290.18 | F96: =SUM(F85:F95) -> 4670.69 | G96: =SUM(G85:G95) -> 5229.05 | H96: =SUM(H85:H95) -> 4999.42 | I96: =SUM(I85:I95) -> 5481.2 | ... IL96: =SUM(IL85:IL95) -> 5076.87
A97: 💸 DESPESAS PREVISTAS
A98: Impostos sobre Vendas | B98: =(IF(WEEKDAY(B$82,2)>5,0,155.47))*-1 -> -155.47 | C98: =(IF(WEEKDAY(C$82,2)>5,0,143.63))*-1 -> 0 | D98: =(IF(WEEKDAY(D$82,2)>5,0,151.18))*-1 -> 0 | E98: =(IF(WEEKDAY(E$82,2)>5,0,130.15))*-1 -> -130.15 | F98: =(IF(WEEKDAY(F$82,2)>5,0,135.69))*-1 -> -135.69 | G98: =(IF(WEEKDAY(G$82,2)>5,0,132.81))*-1 -> -132.81 | H98: =(IF(WEEKDAY(H$82,2)>5,0,152.94))*-1 -> -152.94 | I98: =(IF(WEEKDAY(I$82,2)>5,0,132.3))*-1 -> -132.3 | J98: =(IF(WEEKDAY(J$82,2)>5,0,161.57))*-1 -> 0 | K98: =(IF(WEEKDAY(K$82,2)>5,0,156.64))*-1 -> 0 | L98: =(IF(WEEKDAY(L$82,2)>5,0,170.63))*-1 -> -170.63 | M98: =(IF(WEEKDAY(M$82,2)>5,0,158.21))*-1 -> -158.21 | N98: =(IF(WEEKDAY(N$82,2)>5,0,170.63))*-1 -> -170.63 | O98: =(IF(WEEKDAY(O$82,2)>5,0,164.31))*-1 -> -164.31 | P98: =(IF(WEEKDAY(P$82,2)>5,0,128.17))*-1 -> -128.17 | Q98: =(IF(WEEKDAY(Q$82,2)>5,0,139.62))*-1 -> 0 | R98: =(IF(WEEKDAY(R$82,2)>5,0,131.5))*-1 -> 0 | S98: =(IF(WEEKDAY(S$82,2)>5,0,128.95))*-1 -> -128.95 | T98: =(IF(WEEKDAY(T$82,2)>5,0,165.04))*-1 -> -165.04 | U98: =(IF(WEEKDAY(U$82,2)>5,0,138.33))*-1 -> -138.33 | V98: =(IF(WEEKDAY(V$82,2)>5,0,161.08))*-1 -> -161.08 | W98: =(IF(WEEKDAY(W$82,2)>5,0,150.01))*-1 -> -150.01 | X98: =(IF(WEEKDAY(X$82,2)>5,0,146.46))*-1 -> 0 | Y98: =(IF(WEEKDAY(Y$82,2)>5,0,148.1))*-1 -> 0 | Z98: =(IF(WEEKDAY(Z$82,2)>5,0,150.5))*-1 -> -150.5 | AA98: =(IF(WEEKDAY(AA$82,2)>5,0,151.34))*-1 -> -151.34 | AB98: =(IF(WEEKDAY(AB$82,2)>5,0,159.27))*-1 -> -159.27 | AC98: =(IF(WEEKDAY(AC$82,2)>5,0,136.79))*-1 -> -136.79 | AD98: =(IF(WEEKDAY(AD$82,2)>5,0,171.69))*-1 -> -171.69 | AE98: =(IF(WEEKDAY(AE$82,2)>5,0,172.46))*-1 -> 0 | AF98: =(IF(WEEKDAY(AF$82,2)>5,0,153.99))*-1 -> 0 | AG98: =(IF(WEEKDAY(AG$82,2)>5,0,169.45))*-1 -> -169.45 | AH98: =(IF(WEEKDAY(AH$82,2)>5,0,129.69))*-1 -> -129.69 | AI98: =(IF(WEEKDAY(AI$82,2)>5,0,164.32))*-1 -> -164.32 | AJ98: =(IF(WEEKDAY(AJ$82,2)>5,0,167.55))*-1 -> -167.55 | AK98: =(IF(WEEKDAY(AK$82,2)>5,0,150.74))*-1 -> -150.74 | AL98: =(IF(WEEKDAY(AL$82,2)>5,0,147.56))*-1 -> 0 | AM98: =(IF(WEEKDAY(AM$82,2)>5,0,130.53))*-1 -> 0 | AN98: =(IF(WEEKDAY(AN$82,2)>5,0,162.25))*-1 -> -162.25 | AO98: =(IF(WEEKDAY(AO$82,2)>5,0,172.41))*-1 -> -172.41 | AP98: =(IF(WEEKDAY(AP$82,2)>5,0,131.34))*-1 -> -131.34 | AQ98: =(IF(WEEKDAY(AQ$82,2)>5,0,139.31))*-1 -> -139.31 | AR98: =(IF(WEEKDAY(AR$82,2)>5,0,162.77))*-1 -> -162.77 | AS98: =(IF(WEEKDAY(AS$82,2)>5,0,135.45))*-1 -> 0 | AT98: =(IF(WEEKDAY(AT$82,2)>5,0,152.66))*-1 -> 0 | AU98: =(IF(WEEKDAY(AU$82,2)>5,0,159.6))*-1 -> -159.6 | AV98: =(IF(WEEKDAY(AV$82,2)>5,0,154.09))*-1 -> -154.09 | AW98: =(IF(WEEKDAY(AW$82,2)>5,0,147.77))*-1 -> -147.77 | AX98: =(IF(WEEKDAY(AX$82,2)>5,0,149.64))*-1 -> -149.64 | AY98: =(IF(WEEKDAY(AY$82,2)>5,0,170.08))*-1 -> -170.08 | AZ98: =(IF(WEEKDAY(AZ$82,2)>5,0,127.9))*-1 -> 0 | BA98: =(IF(WEEKDAY(BA$82,2)>5,0,162.51))*-1 -> 0 | BB98: =(IF(WEEKDAY(BB$82,2)>5,0,168.24))*-1 -> -168.24 | BC98: =(IF(WEEKDAY(BC$82,2)>5,0,144.92))*-1 -> -144.92 | BD98: =(IF(WEEKDAY(BD$82,2)>5,0,164.83))*-1 -> -164.83 | BE98: =(IF(WEEKDAY(BE$82,2)>5,0,150.89))*-1 -> -150.89 | BF98: =(IF(WEEKDAY(BF$82,2)>5,0,144.16))*-1 -> -144.16 | BG98: =(IF(WEEKDAY(BG$82,2)>5,0,156.75))*-1 -> 0 | BH98: =(IF(WEEKDAY(BH$82,2)>5,0,167.48))*-1 -> 0 | BI98: =(IF(WEEKDAY(BI$82,2)>5,0,144.64))*-1 -> -144.64 | BJ98: =(IF(WEEKDAY(BJ$82,2)>5,0,146.64))*-1 -> -146.64 | BK98: =(IF(WEEKDAY(BK$82,2)>5,0,149))*-1 -> -149 | BL98: =(IF(WEEKDAY(BL$82,2)>5,0,130.22))*-1 -> -130.22 | BM98: =(IF(WEEKDAY(BM$82,2)>5,0,172.48))*-1 -> -172.48 | BN98: =(IF(WEEKDAY(BN$82,2)>5,0,165.94))*-1 -> 0 | BO98: =(IF(WEEKDAY(BO$82,2)>5,0,144.89))*-1 -> 0 | BP98: =(IF(WEEKDAY(BP$82,2)>5,0,130.09))*-1 -> -130.09 | BQ98: =(IF(WEEKDAY(BQ$82,2)>5,0,168.67))*-1 -> -168.67 | BR98: =(IF(WEEKDAY(BR$82,2)>5,0,135.38))*-1 -> -135.38 | BS98: =(IF(WEEKDAY(BS$82,2)>5,0,152.8))*-1 -> -152.8 | BT98: =(IF(WEEKDAY(BT$82,2)>5,0,162.68))*-1 -> -162.68 | BU98: =(IF(WEEKDAY(BU$82,2)>5,0,128.09))*-1 -> 0 | BV98: =(IF(WEEKDAY(BV$82,2)>5,0,168.24))*-1 -> 0 | BW98: =(IF(WEEKDAY(BW$82,2)>5,0,159.36))*-1 -> -159.36 | BX98: =(IF(WEEKDAY(BX$82,2)>5,0,134.9))*-1 -> -134.9 | BY98: =(IF(WEEKDAY(BY$82,2)>5,0,162.06))*-1 -> -162.06 | BZ98: =(IF(WEEKDAY(BZ$82,2)>5,0,166.95))*-1 -> -166.95 | CA98: =(IF(WEEKDAY(CA$82,2)>5,0,169.74))*-1 -> -169.74 | CB98: =(IF(WEEKDAY(CB$82,2)>5,0,149.11))*-1 -> 0 | CC98: =(IF(WEEKDAY(CC$82,2)>5,0,169.71))*-1 -> 0 | CD98: =(IF(WEEKDAY(CD$82,2)>5,0,135.9))*-1 -> -135.9 | CE98: =(IF(WEEKDAY(CE$82,2)>5,0,146.07))*-1 -> -146.07 | CF98: =(IF(WEEKDAY(CF$82,2)>5,0,137.98))*-1 -> -137.98 | CG98: =(IF(WEEKDAY(CG$82,2)>5,0,171.2))*-1 -> -171.2 | CH98: =(IF(WEEKDAY(CH$82,2)>5,0,130.22))*-1 -> -130.22 | CI98: =(IF(WEEKDAY(CI$82,2)>5,0,167.84))*-1 -> 0 | CJ98: =(IF(WEEKDAY(CJ$82,2)>5,0,131.94))*-1 -> 0 | CK98: =(IF(WEEKDAY(CK$82,2)>5,0,137.09))*-1 -> -137.09 | CL98: =(IF(WEEKDAY(CL$82,2)>5,0,131))*-1 -> -131 | CM98: =(IF(WEEKDAY(CM$82,2)>5,0,127.84))*-1 -> -127.84 | CN98: =(IF(WEEKDAY(CN$82,2)>5,0,145.35))*-1 -> -145.35 | CO98: =(IF(WEEKDAY(CO$82,2)>5,0,161.18))*-1 -> -161.18 | CP98: =(IF(WEEKDAY(CP$82,2)>5,0,159.3))*-1 -> 0 | CQ98: =(IF(WEEKDAY(CQ$82,2)>5,0,161.23))*-1 -> 0 | CR98: =(IF(WEEKDAY(CR$82,2)>5,0,163.17))*-1 -> -163.17 | CS98: =(IF(WEEKDAY(CS$82,2)>5,0,149.29))*-1 -> -149.29 | CT98: =(IF(WEEKDAY(CT$82,2)>5,0,156.67))*-1 -> -156.67 | CU98: =(IF(WEEKDAY(CU$82,2)>5,0,158.73))*-1 -> -158.73 | CV98: =(IF(WEEKDAY(CV$82,2)>5,0,155.19))*-1 -> -155.19 | CW98: =(IF(WEEKDAY(CW$82,2)>5,0,154.97))*-1 -> 0 | CX98: =(IF(WEEKDAY(CX$82,2)>5,0,139.92))*-1 -> 0 | CY98: =(IF(WEEKDAY(CY$82,2)>5,0,136.94))*-1 -> -136.94 | CZ98: =(IF(WEEKDAY(CZ$82,2)>5,0,137.18))*-1 -> -137.18 | DA98: =(IF(WEEKDAY(DA$82,2)>5,0,150.65))*-1 -> -150.65 | DB98: =(IF(WEEKDAY(DB$82,2)>5,0,160.75))*-1 -> -160.75 | DC98: =(IF(WEEKDAY(DC$82,2)>5,0,152.63))*-1 -> -152.63 | DD98: =(IF(WEEKDAY(DD$82,2)>5,0,145.76))*-1 -> 0 | DE98: =(IF(WEEKDAY(DE$82,2)>5,0,161.92))*-1 -> 0 | DF98: =(IF(WEEKDAY(DF$82,2)>5,0,136.08))*-1 -> -136.08 | DG98: =(IF(WEEKDAY(DG$82,2)>5,0,167.58))*-1 -> -167.58 | DH98: =(IF(WEEKDAY(DH$82,2)>5,0,138.32))*-1 -> -138.32 | DI98: =(IF(WEEKDAY(DI$82,2)>5,0,153.57))*-1 -> -153.57 | DJ98: =(IF(WEEKDAY(DJ$82,2)>5,0,144.98))*-1 -> -144.98 | DK98: =(IF(WEEKDAY(DK$82,2)>5,0,143.94))*-1 -> 0 | DL98: =(IF(WEEKDAY(DL$82,2)>5,0,143.65))*-1 -> 0 | DM98: =(IF(WEEKDAY(DM$82,2)>5,0,153.17))*-1 -> -153.17 | DN98: =(IF(WEEKDAY(DN$82,2)>5,0,166.38))*-1 -> -166.38 | DO98: =(IF(WEEKDAY(DO$82,2)>5,0,153.78))*-1 -> -153.78 | DP98: =(IF(WEEKDAY(DP$82,2)>5,0,136.97))*-1 -> -136.97 | DQ98: =(IF(WEEKDAY(DQ$82,2)>5,0,139.78))*-1 -> -139.78 | DR98: =(IF(WEEKDAY(DR$82,2)>5,0,159.65))*-1 -> 0 | DS98: =(IF(WEEKDAY(DS$82,2)>5,0,158.75))*-1 -> 0 | DT98: =(IF(WEEKDAY(DT$82,2)>5,0,144.35))*-1 -> -144.35 | DU98: =(IF(WEEKDAY(DU$82,2)>5,0,136.78))*-1 -> -136.78 | DV98: =(IF(WEEKDAY(DV$82,2)>5,0,138.29))*-1 -> -138.29 | DW98: =(IF(WEEKDAY(DW$82,2)>5,0,140.23))*-1 -> -140.23 | DX98: =(IF(WEEKDAY(DX$82,2)>5,0,170.07))*-1 -> -170.07 | DY98: =(IF(WEEKDAY(DY$82,2)>5,0,131.63))*-1 -> 0 | DZ98: =(IF(WEEKDAY(DZ$82,2)>5,0,128.62))*-1 -> 0 | EA98: =(IF(WEEKDAY(EA$82,2)>5,0,172.07))*-1 -> -172.07 | EB98: =(IF(WEEKDAY(EB$82,2)>5,0,164.74))*-1 -> -164.74 | EC98: =(IF(WEEKDAY(EC$82,2)>5,0,164.97))*-1 -> -164.97 | ED98: =(IF(WEEKDAY(ED$82,2)>5,0,130.19))*-1 -> -130.19 | EE98: =(IF(WEEKDAY(EE$82,2)>5,0,144.86))*-1 -> -144.86 | EF98: =(IF(WEEKDAY(EF$82,2)>5,0,171.26))*-1 -> 0 | EG98: =(IF(WEEKDAY(EG$82,2)>5,0,146.63))*-1 -> 0 | EH98: =(IF(WEEKDAY(EH$82,2)>5,0,154.76))*-1 -> -154.76 | EI98: =(IF(WEEKDAY(EI$82,2)>5,0,152.83))*-1 -> -152.83 | EJ98: =(IF(WEEKDAY(EJ$82,2)>5,0,163.02))*-1 -> -163.02 | EK98: =(IF(WEEKDAY(EK$82,2)>5,0,149.16))*-1 -> -149.16 | EL98: =(IF(WEEKDAY(EL$82,2)>5,0,140.65))*-1 -> -140.65 | EM98: =(IF(WEEKDAY(EM$82,2)>5,0,132.17))*-1 -> 0 | EN98: =(IF(WEEKDAY(EN$82,2)>5,0,141.57))*-1 -> 0 | EO98: =(IF(WEEKDAY(EO$82,2)>5,0,141.03))*-1 -> -141.03 | EP98: =(IF(WEEKDAY(EP$82,2)>5,0,139.32))*-1 -> -139.32 | EQ98: =(IF(WEEKDAY(EQ$82,2)>5,0,161.7))*-1 -> -161.7 | ER98: =(IF(WEEKDAY(ER$82,2)>5,0,155.26))*-1 -> -155.26 | ES98: =(IF(WEEKDAY(ES$82,2)>5,0,170.1))*-1 -> -170.1 | ET98: =(IF(WEEKDAY(ET$82,2)>5,0,159.94))*-1 -> 0 | EU98: =(IF(WEEKDAY(EU$82,2)>5,0,131.28))*-1 -> 0 | EV98: =(IF(WEEKDAY(EV$82,2)>5,0,144.36))*-1 -> -144.36 | EW98: =(IF(WEEKDAY(EW$82,2)>5,0,140.24))*-1 -> -140.24 | EX98: =(IF(WEEKDAY(EX$82,2)>5,0,140.72))*-1 -> -140.72 | EY98: =(IF(WEEKDAY(EY$82,2)>5,0,128.95))*-1 -> -128.95 | EZ98: =(IF(WEEKDAY(EZ$82,2)>5,0,139.38))*-1 -> -139.38 | FA98: =(IF(WEEKDAY(FA$82,2)>5,0,131.18))*-1 -> 0 | FB98: =(IF(WEEKDAY(FB$82,2)>5,0,136.93))*-1 -> 0 | FC98: =(IF(WEEKDAY(FC$82,2)>5,0,130.76))*-1 -> -130.76 | FD98: =(IF(WEEKDAY(FD$82,2)>5,0,153.68))*-1 -> -153.68 | FE98: =(IF(WEEKDAY(FE$82,2)>5,0,148.1))*-1 -> -148.1 | FF98: =(IF(WEEKDAY(FF$82,2)>5,0,153.55))*-1 -> -153.55 | FG98: =(IF(WEEKDAY(FG$82,2)>5,0,145.17))*-1 -> -145.17 | FH98: =(IF(WEEKDAY(FH$82,2)>5,0,130.06))*-1 -> 0 | FI98: =(IF(WEEKDAY(FI$82,2)>5,0,167.85))*-1 -> 0 | FJ98: =(IF(WEEKDAY(FJ$82,2)>5,0,142.24))*-1 -> -142.24 | FK98: =(IF(WEEKDAY(FK$82,2)>5,0,128.87))*-1 -> -128.87 | FL98: =(IF(WEEKDAY(FL$82,2)>5,0,134.1))*-1 -> -134.1 | FM98: =(IF(WEEKDAY(FM$82,2)>5,0,136.1))*-1 -> -136.1 | FN98: =(IF(WEEKDAY(FN$82,2)>5,0,149.52))*-1 -> -149.52 | FO98: =(IF(WEEKDAY(FO$82,2)>5,0,132.06))*-1 -> 0 | FP98: =(IF(WEEKDAY(FP$82,2)>5,0,166.31))*-1 -> 0 | FQ98: =(IF(WEEKDAY(FQ$82,2)>5,0,136.51))*-1 -> -136.51 | FR98: =(IF(WEEKDAY(FR$82,2)>5,0,149.34))*-1 -> -149.34 | FS98: =(IF(WEEKDAY(FS$82,2)>5,0,146.1))*-1 -> -146.1 | FT98: =(IF(WEEKDAY(FT$82,2)>5,0,170.06))*-1 -> -170.06 | FU98: =(IF(WEEKDAY(FU$82,2)>5,0,168.89))*-1 -> -168.89 | FV98: =(IF(WEEKDAY(FV$82,2)>5,0,150.53))*-1 -> 0 | FW98: =(IF(WEEKDAY(FW$82,2)>5,0,135.06))*-1 -> 0 | FX98: =(IF(WEEKDAY(FX$82,2)>5,0,154.02))*-1 -> -154.02 | FY98: =(IF(WEEKDAY(FY$82,2)>5,0,135.97))*-1 -> -135.97 | FZ98: =(IF(WEEKDAY(FZ$82,2)>5,0,152.83))*-1 -> -152.83 | GA98: =(IF(WEEKDAY(GA$82,2)>5,0,145.81))*-1 -> -145.81 | GB98: =(IF(WEEKDAY(GB$82,2)>5,0,143.23))*-1 -> -143.23 | GC98: =(IF(WEEKDAY(GC$82,2)>5,0,168.71))*-1 -> 0 | GD98: =(IF(WEEKDAY(GD$82,2)>5,0,171.57))*-1 -> 0 | GE98: =(IF(WEEKDAY(GE$82,2)>5,0,141.12))*-1 -> -141.12 | GF98: =(IF(WEEKDAY(GF$82,2)>5,0,163.48))*-1 -> -163.48 | GG98: =(IF(WEEKDAY(GG$82,2)>5,0,141.62))*-1 -> -141.62 | GH98: =(IF(WEEKDAY(GH$82,2)>5,0,170.15))*-1 -> -170.15 | GI98: =(IF(WEEKDAY(GI$82,2)>5,0,169.09))*-1 -> -169.09 | GJ98: =(IF(WEEKDAY(GJ$82,2)>5,0,132.29))*-1 -> 0 | GK98: =(IF(WEEKDAY(GK$82,2)>5,0,162.47))*-1 -> 0 | GL98: =(IF(WEEKDAY(GL$82,2)>5,0,142.36))*-1 -> -142.36 | GM98: =(IF(WEEKDAY(GM$82,2)>5,0,159.48))*-1 -> -159.48 | GN98: =(IF(WEEKDAY(GN$82,2)>5,0,152.91))*-1 -> -152.91 | GO98: =(IF(WEEKDAY(GO$82,2)>5,0,157.64))*-1 -> -157.64 | GP98: =(IF(WEEKDAY(GP$82,2)>5,0,145.74))*-1 -> -145.74 | GQ98: =(IF(WEEKDAY(GQ$82,2)>5,0,133.55))*-1 -> 0 | GR98: =(IF(WEEKDAY(GR$82,2)>5,0,127.61))*-1 -> 0 | GS98: =(IF(WEEKDAY(GS$82,2)>5,0,171.54))*-1 -> -171.54 | GT98: =(IF(WEEKDAY(GT$82,2)>5,0,161.8))*-1 -> -161.8 | GU98: =(IF(WEEKDAY(GU$82,2)>5,0,159.16))*-1 -> -159.16 | GV98: =(IF(WEEKDAY(GV$82,2)>5,0,161.24))*-1 -> -161.24 | GW98: =(IF(WEEKDAY(GW$82,2)>5,0,159.92))*-1 -> -159.92 | GX98: =(IF(WEEKDAY(GX$82,2)>5,0,165.6))*-1 -> 0 | GY98: =(IF(WEEKDAY(GY$82,2)>5,0,161.47))*-1 -> 0 | GZ98: =(IF(WEEKDAY(GZ$82,2)>5,0,153.5))*-1 -> -153.5 | HA98: =(IF(WEEKDAY(HA$82,2)>5,0,158))*-1 -> -158 | HB98: =(IF(WEEKDAY(HB$82,2)>5,0,168.33))*-1 -> -168.33 | HC98: =(IF(WEEKDAY(HC$82,2)>5,0,134.2))*-1 -> -134.2 | HD98: =(IF(WEEKDAY(HD$82,2)>5,0,149.02))*-1 -> -149.02 | HE98: =(IF(WEEKDAY(HE$82,2)>5,0,167.41))*-1 -> 0 | HF98: =(IF(WEEKDAY(HF$82,2)>5,0,148.38))*-1 -> 0 | HG98: =(IF(WEEKDAY(HG$82,2)>5,0,147.79))*-1 -> -147.79 | HH98: =(IF(WEEKDAY(HH$82,2)>5,0,149.77))*-1 -> -149.77 | HI98: =(IF(WEEKDAY(HI$82,2)>5,0,163.6))*-1 -> -163.6 | HJ98: =(IF(WEEKDAY(HJ$82,2)>5,0,166.42))*-1 -> -166.42 | HK98: =(IF(WEEKDAY(HK$82,2)>5,0,138.92))*-1 -> -138.92 | HL98: =(IF(WEEKDAY(HL$82,2)>5,0,133.7))*-1 -> 0 | HM98: =(IF(WEEKDAY(HM$82,2)>5,0,163.95))*-1 -> 0 | HN98: =(IF(WEEKDAY(HN$82,2)>5,0,156.64))*-1 -> -156.64 | HO98: =(IF(WEEKDAY(HO$82,2)>5,0,128.94))*-1 -> -128.94 | HP98: =(IF(WEEKDAY(HP$82,2)>5,0,152.05))*-1 -> -152.05 | HQ98: =(IF(WEEKDAY(HQ$82,2)>5,0,153.74))*-1 -> -153.74 | HR98: =(IF(WEEKDAY(HR$82,2)>5,0,165.08))*-1 -> -165.08 | HS98: =(IF(WEEKDAY(HS$82,2)>5,0,147.14))*-1 -> 0 | HT98: =(IF(WEEKDAY(HT$82,2)>5,0,129.16))*-1 -> 0 | HU98: =(IF(WEEKDAY(HU$82,2)>5,0,160.73))*-1 -> -160.73 | HV98: =(IF(WEEKDAY(HV$82,2)>5,0,144.5))*-1 -> -144.5 | HW98: =(IF(WEEKDAY(HW$82,2)>5,0,148.25))*-1 -> -148.25 | HX98: =(IF(WEEKDAY(HX$82,2)>5,0,148.47))*-1 -> -148.47 | HY98: =(IF(WEEKDAY(HY$82,2)>5,0,140.07))*-1 -> -140.07 | HZ98: =(IF(WEEKDAY(HZ$82,2)>5,0,128.47))*-1 -> 0 | IA98: =(IF(WEEKDAY(IA$82,2)>5,0,130.84))*-1 -> 0 | IB98: =(IF(WEEKDAY(IB$82,2)>5,0,133.53))*-1 -> -133.53 | IC98: =(IF(WEEKDAY(IC$82,2)>5,0,128.97))*-1 -> -128.97 | ID98: =(IF(WEEKDAY(ID$82,2)>5,0,170.64))*-1 -> -170.64 | IE98: =(IF(WEEKDAY(IE$82,2)>5,0,154.91))*-1 -> -154.91 | IF98: =(IF(WEEKDAY(IF$82,2)>5,0,137))*-1 -> -137 | IG98: =(IF(WEEKDAY(IG$82,2)>5,0,159.12))*-1 -> 0 | IH98: =(IF(WEEKDAY(IH$82,2)>5,0,162.39))*-1 -> 0 | II98: =(IF(WEEKDAY(II$82,2)>5,0,164.05))*-1 -> -164.05 | IJ98: =(IF(WEEKDAY(IJ$82,2)>5,0,158.54))*-1 -> -158.54 | IK98: =(IF(WEEKDAY(IK$82,2)>5,0,164.6))*-1 -> -164.6 | IL98: =(IF(WEEKDAY(IL$82,2)>5,0,169.59))*-1 -> -169.59
